Workbook

Sheet Inputs
A1: BANK OF AMERICA - BROOMFIELD, CO | METAL FRAMING & DRYWALL TAKEOFF
A2: Permit / Bid Set, 95 sheets. Every quantity below is driven by a live formula. Edit ONLY the yellow cells: the whole workbook recalculates.
A4: PARAMETER | B4: VALUE | C4: NOTE / SOURCE
A5: Waste - ALL METAL, any type | B5: 0.15 | C5: Estimator standing rule, 11-Oct-2026: 15% on everything that is metal, whatever type it is - stud, track, channel, clip, hanger wire, metal trim. No type-by-type exceptions.
A6: Waste - EVERYTHING THAT IS NOT METAL | B6: 0.06 | C6: Estimator standing rule, 11-Oct-2026: everything that is not metal takes the SAME figure as drywall / gypsum board, 6%. That covers board of every type, plywood, FRP, substrates, FRT wood blocking and non-metal trim. This cell is the single source of the 6%; nothing else carries its own copy.
A7: Board sheet width (ft) | B7: 4 | C7: Sheet size is a PARAMETER, never fixed at 4x8 - buy the size that wastes least.
A8: Board sheet length (ft) | B8: 12 | C8: Change it and every piece count below re-rounds up.
A9: SF per board sheet | B9: =B7*B8 -> 48 | C9: Width x length.
A10: Stud stock length (ft) | B10: 20 | C10: Stud is bought in sticks; pieces are converted to sticks in Material Summary.
A11: Track stock length (ft) | B11: 10 | C11: Track is bought in 10 ft runs unless the supplier says otherwise.
A12: Floor plan scale (pt/ft) | B12: 18 | C12: A02.01 at 1/4"=1'-0" -> 18.0 pt/ft, 1.5 pt per real inch. Every length came from vector geometry at this scale.
A13: B.O. Deck north of grid B (ft) | B13: 15.375 | C13: S2.20: T/STEEL 15'-4 1/2", NO SLOPE north of grid B.
A14: T.O. Parapet 1 (ft) | B14: 17.75 | C14: Exterior elevations A09.01 / A09.02 datum T.O. PARAPET 1 = 17'-9".
A15: Sealant coverage (LF per tube) | B15: 25 | C15: Acoustical sealant yield per tube - set your supplier's figure.
A16: C.R. channel stock length (ft) | B16: 16 | C16: 1-1/2" cold-rolled channel ships in 16 ft and 20 ft - NOT in 10 ft track lengths.
A17: Hat / furring channel stock (ft) | B17: 12 | C17: 7/8" hat furring channel ships in 12 ft.
A18: Trim stick length (ft) | B18: 10 | C18: Corner bead, casing bead and shadow molding ship in 8 ft and 10 ft sticks - NOT in 20 ft stud lengths.
A19: Wood blocking waste - SUPERSEDED, do not use | C19: SUPERSEDED 11-Oct-2026. This used to be its own parameter, left at 0 because FRT wood blocking was neither metal nor board and the old 15%/6% rule had no row for it. The rule now covers it: everything that is not metal takes the same figure as board, so wood blocking reads the 'EVERYTHING THAT IS NOT METAL' cell above like every other non-metal material. The cell is left empty on purpose - two cells meaning the same 6% is a second source of truth, which is how the figures drift apart.
A20: Drywall screws per SF of board | B20: 1.2 | C20: YIELD, not a drawing quantity. GA-216: field 12" O.C., perimeter 8" O.C. over framing at 16" O.C. Set your own figure.
A21: Framing screws per stud piece | B21: 4 | C21: YIELD: 2 per stud-to-track connection at each end. Clips and bracing are counted separately.
A22: Power-driven pin spacing (ft) | B22: 2 | C22: YIELD: 4/A12.01 calls POWER DRIVEN FASTENERS @ 2'-0" O.C. alternating sides on the bottom track.
A23: Joint compound (lb per SF) | B23: 0.072 | C23: YIELD: 72 lb per 1,000 SF, typical level 4 finish. Set your supplier's figure.
A24: Joint tape (LF per SF) | B24: 0.37 | C24: YIELD: 370 LF per 1,000 SF.
A26: LEGEND
A27: Blue text on yellow fill = input you may edit
A28: Black text = live formula, do not overwrite
A29: Green text = pulled from another sheet
A31: EXAMPLE ROW (format reference, not part of the takeoff)
A32: A1 #1 | Corridor 111 / Break Room 118 | L 16.42 LF | H 15.375 FT | Layers 2 | 3-5/8" 362S137-33 MST @ 16" O.C., 33 mil | 1 layer 5/8" gyp per face

Sheet Partition Takeoff
A1: ORGANIZED PARTITION TAKEOFF ESTIMATOR - BANK OF AMERICA, BROOMFIELD CO
A2: Grouped by partition type, longest first inside each type. Stud columns are in LF of MATERIAL (pieces x height) and never mix two stud sizes. Quantities are NET - waste lives in its own cells on Material Summary.
A4: Partition / Scope | B4: Wall # | C4: Length (LF) | D4: Height (FT) | E4: Layers | F4: Stud Size | G4: Stud (pcs) | H4: 6" Metal Stud (LF) | I4: 3-5/8" Metal Stud (LF) | J4: 1-5/8" Metal Stud (LF) | K4: 5/8" Gyp Board (SF) | L4: FRP-1 (SF) | M4: FRP-2 (SF) | N4: Durock / Cement Bd (SF) | O4: Demolition (SF) | P4: Labor (Hrs) | Q4: Bottom Track (LF) | R4: Top / Deflection Track (LF) | S4: Bracing (LF) | T4: Clips (pcs) | U4: Blocking (LF) | V4: Insulation (SF) | W4: Ext. Gypsum Sheathing, deck to parapet (SF) | X4: Ext. Sheathing FRT+Polyiso (SF) | Y4: Ballistic Panel 3/8" UL752 (SF) | Z4: 3/8" Gyp Board (SF) | AA4: FRT Plywood Substrate (SF) | AB4: Level 5 Finish (SF) | AC4: Trim - corner/casing/shadow (LF) | AD4: Extra Framing - sistered, furring, MEP (LF) | AE4: Fasteners (pcs) | AF4: Sealant (LF) | AG4: Header / Box Beam (LF) | AH4: Sill Track (LF) | AI4: Openings | AJ4: Status | AK4: Source / Seal | AL4: Stud (LF of material) | AM4: Addl Head Track >4'-0" opening (LF) | AN4: Ext. Glass Mat Sheathing at stud face (SF) | AO4: Gypsum Board Jamb Return (SF) | AP4: Detail sequence (plan → section → detail → schedule)
A5: TYPE A1
A6: A1 #8 - Corridor 111 / Break Room 118 + Electrical 120 + NER 121 - the long wall (tags #8 and #10). Stud 3-5/8" 362S137-33 MST @ 16" O.C.; bracing 1-1/2" C.R. channel @ 48" O.C. Corridor 111: 1 layer(s) 5/8 GYP @ 9.000 FT | Break Room 118: 1 layer(s) 5/8 GYP @ 9.000 FT | Electrical 120: 1 layer(s) 5/8 GYP @ 12.820 FT | NER 121: 1 layer(s) 5/8 GYP @ 12.690 FT (1 instance) | B6: 8 | C6: 17.06 | D6: 12.89 | E6: 1.95 | F6: 3-5/8" | G6: 21 | H6: =IF($F6="6""",$AL6,0) -> 0 | I6: =IF($F6="3-5/8""",$AL6,0) -> 270.69 | J6: =IF($F6="1-5/8""",$AL6,0) -> 0 | K6: =SUMIFS('Board by Face'!$I$5:$I$115,'Board by Face'!$A$5:$A$115,$B6) -> 349.6456 | Q6: 17.06 | R6: 17.06 | S6: 51.18 | U6: 21.97 | AA6: 106.66 | AF6: 34.12 | AG6: 3.33 | AI6: door 118B 3.33 x 7.00 | AJ6: CLOSED | AK6: seal f6f3ebf997a3f559 | AL6: 270.69 | AP6: A02.01 → A04.01 → S2.20 → 2/A11.03 → 3/A11.03 → 4/A11.03 → 5/A11.03 → 7/A11.03 → 1/A12.01 → 3/A12.01 → 4/A12.01 → A09.01 → 10/A12.02 → 11/A12.02 → 1/S5.20 → 2/S5.20 → 4/S5.20 → 7/S5.20 → 9/S5.20 → A00.01 → A00.30 → A09.27 → A09.33 → E02.01 → M01.01 → P01.01 → P01.02
A7: A1 #1 - Central Zone 103 / Calling Cubes 122 - north wall of Calling Cubes. Stud 3-5/8" 362S137-33 MST @ 16" O.C.; bracing 1-1/2" C.R. channel @ 48" O.C. Central Zone 103: 1 layer(s) 5/8 GYP @ 12.000 FT | Calling Cubes 122: 1 layer(s) 5/8 GYP @ 9.000 FT (1 instance) | B7: 1 | C7: 16.42 | D7: 15.375 | E7: 2 | F7: 3-5/8" | G7: 16 | H7: =IF($F7="6""",$AL7,0) -> 0 | I7: =IF($F7="3-5/8""",$AL7,0) -> 246 | J7: =IF($F7="1-5/8""",$AL7,0) -> 0 | K7: =SUMIFS('Board by Face'!$I$5:$I$115,'Board by Face'!$A$5:$A$115,$B7) -> 344.82 | Q7: 16.42 | R7: 16.42 | S7: 49.26 | U7: 32.84 | AF7: 32.84 | AI7: none | AJ7: CLOSED | AK7: seal 0b6d1dcbcf676ced | AL7: 246 | AP7: A02.01 → A04.01 → S2.20 → 1/A12.01 → 3/A12.01 → 4/A12.01 → A09.01 → 10/A12.02 → 11/A12.02 → 1/S5.20 → 4/S5.20 → 7/S5.20 → A00.01 → A00.30 → A09.27 → A09.33 → E02.01 → M01.01 → P01.01 → P01.02
A8: A1 #5 - Calling Cubes 122 / Break Room 118 - carries MW21 on the south face. Stud 3-5/8" 362S137-33 MST @ 16" O.C.; bracing 1-1/2" C.R. channel @ 48" O.C. Calling Cubes 122: 1 layer(s) 5/8 GYP @ 9.000 FT | Break Room 118: 1 layer(s) 5/8 GYP @ 9.000 FT (1 instance) | B8: 5 | C8: 15.23 | D8: 12.971 | E8: 2 | F8: 3-5/8" | G8: 14 | H8: =IF($F8="6""",$AL8,0) -> 0 | I8: =IF($F8="3-5/8""",$AL8,0) -> 181.59 | J8: =IF($F8="1-5/8""",$AL8,0) -> 0 | K8: =SUMIFS('Board by Face'!$I$5:$I$115,'Board by Face'!$A$5:$A$115,$B8) -> 274.14 | Q8: 15.23 | R8: 15.23 | S8: 45.69 | U8: 40.46 | AF8: 30.46 | AI8: none | AJ8: CLOSED | AK8: seal b142fb73ec3b93d8 | AL8: 181.59 | AP8: A02.01 → A04.01 → S2.20 → 1/A12.01 → 3/A12.01 → 4/A12.01 → A09.01 → 10/A12.02 → 11/A12.02 → 1/S5.20 → 4/S5.20 → 7/S5.20 → A00.01 → A00.30 → A09.27 → A09.33 → A12.04 → A12.06 → E02.01 → M01.01 → P01.01 → P01.02
A9: A1 #9 - Cash Window 116 / Work Room 119 - north wall of the Work Room, carries MW12 and door 119. Stud 3-5/8" 362S137-33 MST @ 16" O.C.; bracing 1-1/2" C.R. channel @ 48" O.C. Cash Window 116: 1 layer(s) 5/8 GYP @ 9.500 FT | Work Room 119: 1 layer(s) 5/8 GYP @ 9.000 FT (1 instance) | B9: 9 | C9: 11.667 | D9: 12.775 | E9: 2 | F9: 3-5/8" | G9: 23 | H9: =IF($F9="6""",$AL9,0) -> 0 | I9: =IF($F9="3-5/8""",$AL9,0) -> 293.82 | J9: =IF($F9="1-5/8""",$AL9,0) -> 0 | K9: =SUMIFS('Board by Face'!$I$5:$I$115,'Board by Face'!$A$5:$A$115,$B9) -> 169.235 | Q9: 11.667 | R9: 11.667 | S9: 35 | U9: 46.27 | AF9: 23.33 | AG9: 5.33 | AH9: 2 | AI9: door 119 3.33 x 7.00 + framed opening 8" duct M01.01 (solid run) 1.00 x 1.00 + framed opening 8" duct M01.01 (over the 119 header) 1.00 x 1.00 | AJ9: CLOSED | AK9: seal 5ae93fd71c06450b | AL9: 293.82 | AP9: A02.01 → A04.01 → S2.20 → 1/A12.01 → 3/A12.01 → 4/A12.01 → A09.01 → 10/A12.02 → 11/A12.02 → 1/S5.20 → 2/S5.20 → 4/S5.20 → 6/S5.20 → 7/S5.20 → 9/S5.20 → A00.01 → A00.30 → A09.27 → A09.33 → A12.05 → E02.01 → M01.01 → P01.01 → P01.02
A10: A1 #6 - Break Room 118 / Future FCAM - carries door 118A. Stud 3-5/8" 362S137-33 MST @ 16" O.C.; bracing 1-1/2" C.R. channel @ 48" O.C. Cash Window 116: 1 layer(s) 5/8 GYP @ 9.500 FT | Break Room 118: 1 layer(s) 5/8 GYP @ 9.000 FT (1 instance) | B10: 6 | C10: 5.5 | D10: 12.927 | E10: 2 | F10: 3-5/8" | G10: 11 | H10: =IF($F10="6""",$AL10,0) -> 0 | I10: =IF($F10="3-5/8""",$AL10,0) -> 142.2 | J10: =IF($F10="1-5/8""",$AL10,0) -> 0 | K10: =SUMIFS('Board by Face'!$I$5:$I$115,'Board by Face'!$A$5:$A$115,$B10) -> 48.43 | Q10: 5.5 | R10: 5.5 | S10: 16.5 | U10: 13 | AF10: 11 | AG10: 3.33 | AI10: door 118A 3.33 x 8.00 | AJ10: CLOSED | AK10: seal 330ea163b4a7954b | AL10: 142.2 | AP10: A02.01 → A04.01 → S2.20 → 1/A12.01 → 3/A12.01 → 4/A12.01 → A09.01 → 10/A12.02 → 11/A12.02 → 1/S5.20 → 2/S5.20 → 4/S5.20 → 7/S5.20 → 9/S5.20 → A00.01 → A00.30 → A09.27 → A09.33 → E02.01 → M01.01 → P01.01 → P01.02
A11: A1 #4 - Corridor 111 - jambs of door 111, entry from Central Zone. Stud 3-5/8" 362S137-33 MST @ 16" O.C.; bracing 1-1/2" C.R. channel @ 48" O.C. Corridor 111: 1 layer(s) 5/8 GYP @ 9.000 FT | Corridor 111 (face 2): 1 layer(s) 5/8 GYP @ 9.000 FT (1 instance) | B11: 4 | C11: 5 | D11: 15.375 | E11: 2 | F11: 3-5/8" | G11: 10 | H11: =IF($F11="6""",$AL11,0) -> 0 | I11: =IF($F11="3-5/8""",$AL11,0) -> 153.75 | J11: =IF($F11="1-5/8""",$AL11,0) -> 0 | K11: =SUMIFS('Board by Face'!$I$5:$I$115,'Board by Face'!$A$5:$A$115,$B11) -> 36.68 | Q11: 5 | R11: 5 | S11: 15 | U11: 12 | AF11: 10 | AG11: 3.33 | AI11: door 111 3.33 x 8.00 | AJ11: CLOSED | AK11: seal bad128ab97504e87 | AL11: 153.75 | AP11: A02.01 → A04.01 → S2.20 → 1/A12.01 → 3/A12.01 → 4/A12.01 → A09.01 → 10/A12.02 → 11/A12.02 → 1/S5.20 → 2/S5.20 → 4/S5.20 → 7/S5.20 → 9/S5.20 → A00.01 → A00.30 → A09.27 → A09.33 → E02.01 → M01.01 → P01.01 → P01.02
A12: A1 #2 - MW01 niche / Calling Cubes 122 - back of the printer cabinet. Stud 3-5/8" 362S137-33 MST @ 16" O.C.; bracing 1-1/2" C.R. channel @ 48" O.C. Calling Cubes 122: 1 layer(s) 5/8 GYP @ 9.000 FT | MW01 niche: 1 layer(s) 5/8 GYP @ 9.000 FT (1 instance) | B12: 2 | C12: 3.13 | D12: 15.375 | E12: 2 | F12: 3-5/8" | G12: 5 | H12: =IF($F12="6""",$AL12,0) -> 0 | I12: =IF($F12="3-5/8""",$AL12,0) -> 76.88 | J12: =IF($F12="1-5/8""",$AL12,0) -> 0 | K12: =SUMIFS('Board by Face'!$I$5:$I$115,'Board by Face'!$A$5:$A$115,$B12) -> 56.34 | Q12: 3.13 | R12: 3.13 | S12: 9.39 | U12: 12.52 | AF12: 6.26 | AI12: none | AJ12: CLOSED | AK12: seal f9459712ac3d5e8f | AL12: 76.88 | AP12: A02.01 → A04.01 → S2.20 → 1/A12.01 → 3/A12.01 → 4/A12.01 → A09.01 → 10/A12.02 → 11/A12.02 → 1/S5.20 → 4/S5.20 → 7/S5.20 → A00.01 → A00.30 → A09.27 → A09.33 → A12.03 → A12.04 → A12.05 → E02.01 → M01.01 → P01.01 → P01.02
A13: A1 #3 - MW01 niche / Calling Cubes 122 - south close of the niche. Stud 3-5/8" 362S137-33 MST @ 16" O.C.; bracing 1-1/2" C.R. channel @ 48" O.C. Calling Cubes 122: 1 layer(s) 5/8 GYP @ 9.000 FT | MW01 niche: 1 layer(s) 5/8 GYP @ 9.000 FT (1 instance) | B13: 3 | C13: 2.63 | D13: 15.375 | E13: 2 | F13: 3-5/8" | G13: 4 | H13: =IF($F13="6""",$AL13,0) -> 0 | I13: =IF($F13="3-5/8""",$AL13,0) -> 61.5 | J13: =IF($F13="1-5/8""",$AL13,0) -> 0 | K13: =SUMIFS('Board by Face'!$I$5:$I$115,'Board by Face'!$A$5:$A$115,$B13) -> 47.34 | Q13: 2.63 | R13: 2.63 | S13: 7.89 | U13: 5.26 | AF13: 5.26 | AI13: none | AJ13: CLOSED | AK13: seal de2d6c733839b704 | AL13: 61.5 | AP13: A02.01 → A04.01 → S2.20 → 1/A12.01 → 3/A12.01 → 4/A12.01 → A09.01 → 10/A12.02 → 11/A12.02 → 7/A12.04 → 1/S5.20 → 4/S5.20 → 7/S5.20 → A00.01 → A00.30 → A09.27 → A09.33 → E02.01 → M01.01 → P01.01 → P01.02
A14: A1 #7 - Break Room 118 / Cash Window 116 - vertical return between walls A1-5 and A1-6. Stud 3-5/8" 362S137-33 MST @ 16" O.C.; bracing 1-1/2" C.R. channel @ 48" O.C. Break Room 118: 1 layer(s) 5/8 GYP @ 9.000 FT | Cash Window 116: 1 layer(s) 5/8 GYP @ 9.500 FT (1 instance) | B14: 7 | C14: 1.73 | D14: 12.963 | E14: 2 | F14: 3-5/8" | G14: 4 | H14: =IF($F14="6""",$AL14,0) -> 0 | I14: =IF($F14="3-5/8""",$AL14,0) -> 51.85 | J14: =IF($F14="1-5/8""",$AL14,0) -> 0 | K14: =SUMIFS('Board by Face'!$I$5:$I$115,'Board by Face'!$A$5:$A$115,$B14) -> 32.005 | Q14: 1.73 | R14: 1.73 | S14: 5.19 | U14: 3.46 | AF14: 3.46 | AI14: none | AJ14: CLOSED | AK14: seal 59b6ae489514c65f | AL14: 51.85 | AP14: A02.01 → A04.01 → S2.20 → 1/A12.01 → 3/A12.01 → 4/A12.01 → A09.01 → 10/A12.02 → 11/A12.02 → 1/S5.20 → 4/S5.20 → 7/S5.20 → A00.01 → A00.30 → A09.27 → A09.33 → E02.01 → M01.01 → P01.01 → P01.02
A15: TYPE A1K
A16: A1K #11 - NORTH head of Cash Window 116 / CSR line (banda y 1120.68/1128.48). Stud 3-5/8" 362S137-68 MST @ 24" O.C.; bracing 1-1/2" C.R. channel @ 48" O.C. Lado norte (linea de teller, contra el wall G-47): 1 layer(s) 5/8 GYP 1 layer @ 15.375 FT | Cash Window 116: 1 layer(s) 5/8 GYP 1 layer @ 15.375 FT (1 instance) | B16: 11 | C16: 3.417 | D16: 15.375 | E16: 2 | F16: 3-5/8" | G16: 4 | H16: =IF($F16="6""",$AL16,0) -> 0 | I16: =IF($F16="3-5/8""",$AL16,0) -> 61.5 | J16: =IF($F16="1-5/8""",$AL16,0) -> 0 | K16: =SUMIFS('Board by Face'!$I$5:$I$115,'Board by Face'!$A$5:$A$115,$B16) -> 105.07275 | Q16: 3.42 | R16: 3.42 | S16: 10.25 | Y16: 27.34 | Z16: 25.2 | AC16: 6.83 | AE16: 6 | AF16: 13.67 | AI16: none | AJ16: CLOSED | AK16: seal 55ac0f1c5756bccf | AL16: 61.5 | AP16: A02.01 → S2.20 → 4/A12.01 → 1/S5.20 → 7/S5.20 → A09.01 → A00.01 → A09.27 → A09.33
A17: A1K #12 - SOUTH head of Cash Window 116 (banda y 1344.72/1352.64). Stud 3-5/8" 362S137-68 MST @ 24" O.C.; bracing 1-1/2" C.R. channel @ 48" O.C. Cash Window 116: 1 layer(s) 5/8 GYP 1 layer @ 12.933 FT | Lado sur (zona del FUTURE FCAM): 1 layer(s) 5/8 GYP 1 layer @ 12.933 FT (1 instance) | B17: 12 | C17: 3.413 | D17: 12.933 | E17: 2 | F17: 3-5/8" | G17: 4 | H17: =IF($F17="6""",$AL17,0) -> 0 | I17: =IF($F17="3-5/8""",$AL17,0) -> 51.73 | J17: =IF($F17="1-5/8""",$AL17,0) -> 0 | K17: =SUMIFS('Board by Face'!$I$5:$I$115,'Board by Face'!$A$5:$A$115,$B17) -> 88.280658 | Q17: 3.41 | R17: 3.41 | S17: 10.24 | Y17: 27.3 | Z17: 16.84 | AC17: 6.83 | AE17: 6 | AF17: 13.65 | AI17: none | AJ17: CLOSED | AK17: seal 7fa175fb06948b14 | AL17: 51.73 | AP17: A02.01 → S2.20 → 4/A12.01 → 1/S5.20 → 7/S5.20 → A09.01 → A00.01 → A09.27 → A09.33
A18: A1K #13 - Southwest return at Cash Window 116 (banda y 1355.28/1363.08). Stud 3-5/8" 362S137-68 MST @ 24" O.C.; bracing 1-1/2" C.R. channel @ 48" O.C. Lado norte: 1 layer(s) 5/8 GYP 1 layer @ 12.921 FT | Lado sur (zona del FUTURE FCAM): 1 layer(s) 5/8 GYP 1 layer @ 12.921 FT (1 instance) | B18: 13 | C18: 1.16 | D18: 12.921 | E18: 2 | F18: 3-5/8" | G18: 3 | H18: =IF($F18="6""",$AL18,0) -> 0 | I18: =IF($F18="3-5/8""",$AL18,0) -> 38.76 | J18: =IF($F18="1-5/8""",$AL18,0) -> 0 | K18: =SUMIFS('Board by Face'!$I$5:$I$115,'Board by Face'!$A$5:$A$115,$B18) -> 29.97672 | Q18: 1.16 | R18: 1.16 | S18: 3.48 | Y18: 9.28 | Z18: 5.71 | AC18: 2.32 | AE18: 4 | AF18: 4.64 | AI18: none | AJ18: CLOSED | AK18: seal e3169842073623f7 | AL18: 38.76 | AP18: A02.01 → S2.20 → 4/A12.01 → 1/S5.20 → 7/S5.20 → A09.01 → A00.01 → A09.27 → A09.33
A19: TYPE A5
A20: A5 #14 - Calling Cubes 122 / Office 4 CB 108. Stud 6" 600S137-33 MST @ 16" O.C.; bracing 1-1/2" C.R. channel @ 48" O.C. Calling Cubes 122: 1 layer(s) 5/8 GYP @ 9.000 FT | Office 4 CB 108: 1 layer(s) 5/8 GYP @ 9.500 FT (1 instance) | B20: 14 | C20: 19 | D20: 15.375 | E20: 2 | F20: 6" | G20: 15 | H20: =IF($F20="6""",$AL20,0) -> 223.66 | I20: =IF($F20="3-5/8""",$AL20,0) -> 0 | J20: =IF($F20="1-5/8""",$AL20,0) -> 0 | K20: =SUMIFS('Board by Face'!$I$5:$I$115,'Board by Face'!$A$5:$A$115,$B20) -> 351.5 | Q20: 19 | R20: 19 | S20: 57 | U20: 38 | AF20: 38 | AI20: none | AJ20: CLOSED | AK20: seal 95c67946c0f7261d | AL20: 223.66 | AP20: A02.01 → A04.01 → 3/A12.01 → 1/S5.20 → 4/S5.20 → 7/S5.20 → A09.01 → A00.30 → A09.27 → A09.33
A21: A5 #15 - Calling Cubes 122 / Corridor 111. Stud 6" 600S137-33 MST @ 16" O.C.; bracing 1-1/2" C.R. channel @ 48" O.C. Calling Cubes 122: 1 layer(s) 5/8 GYP @ 9.000 FT | Corridor 111: 1 layer(s) 5/8 GYP @ 9.000 FT (1 instance) | B21: 15 | C21: 11 | D21: 15.375 | E21: 2 | F21: 6" | G21: 9 | H21: =IF($F21="6""",$AL21,0) -> 138.38 | I21: =IF($F21="3-5/8""",$AL21,0) -> 0 | J21: =IF($F21="1-5/8""",$AL21,0) -> 0 | K21: =SUMIFS('Board by Face'!$I$5:$I$115,'Board by Face'!$A$5:$A$115,$B21) -> 198 | Q21: 11 | R21: 11 | S21: 33 | U21: 41.88 | AF21: 22 | AI21: none | AJ21: CLOSED | AK21: seal 4742d9e4779e1bab | AL21: 138.38 | AP21: A02.01 → A04.01 → S2.20 → 3/A12.01 → 1/S5.20 → 4/S5.20 → 7/S5.20 → A09.01 → A00.30 → A09.27 → A09.33 → A12.05
A22: A5 #16 - Corridor 111 / Calling Cubes 122. Stud 6" 600S137-33 MST @ 16" O.C.; bracing 1-1/2" C.R. channel @ 48" O.C. Corridor 111: 1 layer(s) 5/8 GYP @ 9.000 FT | Calling Cubes 122: 1 layer(s) 5/8 GYP @ 9.000 FT (1 instance) | B22: 16 | C22: 5.41 | D22: 13.052 | E22: 2 | F22: 6" | G22: 9 | H22: =IF($F22="6""",$AL22,0) -> 119.79 | I22: =IF($F22="3-5/8""",$AL22,0) -> 0 | J22: =IF($F22="1-5/8""",$AL22,0) -> 0 | K22: =SUMIFS('Board by Face'!$I$5:$I$115,'Board by Face'!$A$5:$A$115,$B22) -> 50.76 | Q22: 5.41 | R22: 5.41 | S22: 16.23 | U22: 10.82 | AF22: 10.82 | AG22: 3.33 | AI22: door 122 3.33 x 7.00 | AJ22: CLOSED | AK22: seal 33f26d5ec19f564f | AL22: 119.79 | AP22: A02.01 → A04.01 → 3/A12.01 → A09.01 → 10/A12.02 → 1/S5.20 → 4/S5.20 → 7/S5.20 → 9/S5.20 → A00.30 → A09.27 → A09.33
A23: A5 #17 - Break Room 118 / Cash Window 116. Stud 6" 600S137-33 MST @ 16" O.C.; bracing 1-1/2" C.R. channel @ 48" O.C. Break Room 118: 1 layer(s) 5/8 GYP @ 9.000 FT | Cash Window 116: 1 layer(s) 5/8 GYP @ 9.500 FT (1 instance) | B23: 17 | C23: 3.71 | D23: 12.927 | E23: 2 | F23: 6" | G23: 3 | H23: =IF($F23="6""",$AL23,0) -> 38.78 | I23: =IF($F23="3-5/8""",$AL23,0) -> 0 | J23: =IF($F23="1-5/8""",$AL23,0) -> 0 | K23: =SUMIFS('Board by Face'!$I$5:$I$115,'Board by Face'!$A$5:$A$115,$B23) -> 68.635 | Q23: 3.71 | R23: 3.71 | S23: 11.13 | U23: 7.42 | AF23: 7.42 | AI23: none | AJ23: CLOSED | AK23: seal e3797658ed2d6b14 | AL23: 38.78 | AP23: A02.01 → A04.01 → S2.20 → 3/A12.01 → 1/S5.20 → 4/S5.20 → 7/S5.20 → A09.01 → A00.30 → A09.27 → A09.33
A24: TYPE B
A25: B #23 - Electrical 120 + NER 121 / Break Room 118 (east wall). Stud 3-5/8" 362S137-33 MST @ 16" O.C.; bracing 1-1/2" C.R. channel @ 48" O.C. Electrical 120: 1 layer(s) 5/8 GYP @ 12.831 FT | NER 121: 1 layer(s) 5/8 GYP @ 12.831 FT | Break Room 118: 1 layer(s) 5/8 GYP @ 12.831 FT (1 instance) | B25: 23 | C25: 14.15 | D25: 12.831 | E25: 2 | F25: 3-5/8" | G25: 19 | H25: =IF($F25="6""",$AL25,0) -> 0 | I25: =IF($F25="3-5/8""",$AL25,0) -> 243.79 | J25: =IF($F25="1-5/8""",$AL25,0) -> 0 | K25: =SUMIFS('Board by Face'!$I$5:$I$115,'Board by Face'!$A$5:$A$115,$B25) -> 269.74899 | Q25: 14.15 | R25: 14.15 | S25: 42.45 | AF25: 56.6 | AG25: 6.66 | AI25: door 120 3.33 x 7.00 + door 121 3.33 x 7.00 | AJ25: CLOSED | AK25: seal 94fc9636f6965f50 | AL25: 243.79 | AP25: A02.01 → S2.20 → 1/A12.01 → A09.01 → 10/A12.02 → 11/A12.02 → 1/S5.20 → 4/S5.20 → 7/S5.20 → 9/S5.20 → A00.30 → A09.27 → A09.33
A26: B #20 - Janitor Closet 112 / Storage 117 (horizontal wall, with door 112). Stud 3-5/8" 362S137-33 MST @ 16" O.C.; bracing 1-1/2" C.R. channel @ 48" O.C. Janitor Closet 112: 1 layer(s) 5/8 GYP @ 12.748 FT | Storage 117: 1 layer(s) 5/8 GYP @ 12.748 FT (1 instance) | B26: 20 | C26: 11.83 | D26: 12.748 | E26: 2 | F26: 3-5/8" | G26: 13 | H26: =IF($F26="6""",$AL26,0) -> 0 | I26: =IF($F26="3-5/8""",$AL26,0) -> 165.72 | J26: =IF($F26="1-5/8""",$AL26,0) -> 0 | K26: =SUMIFS('Board by Face'!$I$5:$I$115,'Board by Face'!$A$5:$A$115,$B26) -> 259.61768 | Q26: 11.83 | R26: 11.83 | S26: 35.49 | AF26: 47.32 | AG26: 3 | AI26: door 112 3.00 x 7.00 | AJ26: CLOSED | AK26: seal cf6621bf33cfc512 | AL26: 165.72 | AP26: A02.01 → S2.20 → 1/A12.01 → A09.01 → 10/A12.02 → 11/A12.02 → 1/S5.20 → 4/S5.20 → 7/S5.20 → 9/S5.20 → A00.30 → A09.27 → A09.33
A27: B #21 - Janitor Closet 112 + Storage 117 / Wellness 115. Stud 3-5/8" 362S137-33 MST @ 16" O.C.; bracing 1-1/2" C.R. channel @ 48" O.C. Wellness 115: 1 layer(s) 5/8 GYP @ 12.666 FT | Janitor Closet 112: 1 layer(s) 5/8 GYP @ 12.666 FT | Storage 117: 1 layer(s) 5/8 GYP @ 12.666 FT (1 instance) | B27: 21 | C27: 11.73 | D27: 12.666 | E27: 2 | F27: 3-5/8" | G27: 9 | H27: =IF($F27="6""",$AL27,0) -> 0 | I27: =IF($F27="3-5/8""",$AL27,0) -> 113.99 | J27: =IF($F27="1-5/8""",$AL27,0) -> 0 | K27: =SUMIFS('Board by Face'!$I$5:$I$115,'Board by Face'!$A$5:$A$115,$B27) -> 297.14436 | Q27: 11.73 | R27: 11.73 | S27: 35.19 | AF27: 46.92 | AI27: none | AJ27: CLOSED | AK27: seal 97c412d53363891c | AL27: 113.99 | AP27: A02.01 → S2.20 → 1/A12.01 → 1/S5.20 → 4/S5.20 → 7/S5.20 → A09.01 → A00.30 → A09.27 → A09.33
A28: B #18 - Electrical 120 / Break Room 118 (north wall of Electrical). Stud 3-5/8" 362S137-33 MST @ 16" O.C.; bracing 1-1/2" C.R. channel @ 48" O.C. Break Room 118: 1 layer(s) 5/8 GYP @ 12.827 FT | Electrical 120: 1 layer(s) 5/8 GYP @ 12.827 FT (1 instance) | B28: 18 | C28: 9.99 | D28: 12.827 | E28: 2 | F28: 3-5/8" | G28: 8 | H28: =IF($F28="6""",$AL28,0) -> 0 | I28: =IF($F28="3-5/8""",$AL28,0) -> 102.62 | J28: =IF($F28="1-5/8""",$AL28,0) -> 0 | K28: =SUMIFS('Board by Face'!$I$5:$I$115,'Board by Face'!$A$5:$A$115,$B28) -> 256.28346 | Q28: 9.99 | R28: 9.99 | S28: 29.97 | AA28: 76.32 | AF28: 39.96 | AI28: none | AJ28: CLOSED | AK28: seal 22cceb27f4d24f0a | AL28: 102.62 | AP28: A02.01 → S2.20 → 2/A11.03 → 3/A11.03 → 4/A11.03 → 1/A12.01 → 1/S5.20 → 4/S5.20 → 7/S5.20 → A09.01 → A00.30 → A09.27 → A09.33
A29: B #22 - Electrical 120 / NER 121 (south wall of Electrical). Stud 3-5/8" 362S137-33 MST @ 16" O.C.; bracing 1-1/2" C.R. channel @ 48" O.C. Electrical 120: 1 layer(s) 5/8 GYP @ 12.698 FT | NER 121: 1 layer(s) 5/8 GYP @ 12.698 FT (1 instance) | B29: 22 | C29: 9.58 | D29: 12.698 | E29: 2 | F29: 3-5/8" | G29: 8 | H29: =IF($F29="6""",$AL29,0) -> 0 | I29: =IF($F29="3-5/8""",$AL29,0) -> 101.58 | J29: =IF($F29="1-5/8""",$AL29,0) -> 0 | K29: =SUMIFS('Board by Face'!$I$5:$I$115,'Board by Face'!$A$5:$A$115,$B29) -> 243.29368 | Q29: 9.58 | R29: 9.58 | S29: 28.74 | AA29: 76.16 | AF29: 38.32 | AI29: none | AJ29: CLOSED | AK29: seal 1f8b6511c9a47902 | AL29: 101.58 | AP29: A02.01 → S2.20 → 2/A11.03 → 3/A11.03 → 4/A11.03 → 1/A12.01 → 1/S5.20 → 4/S5.20 → 7/S5.20 → A09.01 → A00.30 → A09.27 → A09.33
A30: B #19 - Janitor Closet 112 / Storage 117 (also carries tag #20, same wall). Stud 3-5/8" 362S137-33 MST @ 16" O.C.; bracing 1-1/2" C.R. channel @ 48" O.C. Janitor Closet 112: 1 layer(s) 5/8 GYP @ 12.743 FT | Storage 117: 1 layer(s) 5/8 GYP @ 12.743 FT (1 instance) | B30: 19 | C30: 3.5 | D30: 12.743 | E30: 2 | F30: 3-5/8" | G30: 3 | H30: =IF($F30="6""",$AL30,0) -> 0 | I30: =IF($F30="3-5/8""",$AL30,0) -> 38.23 | J30: =IF($F30="1-5/8""",$AL30,0) -> 0 | K30: =SUMIFS('Board by Face'!$I$5:$I$115,'Board by Face'!$A$5:$A$115,$B30) -> 89.201 | Q30: 3.5 | R30: 3.5 | S30: 10.5 | U30: 29.22 | AE30: 1 | AF30: 14 | AI30: none | AJ30: CLOSED | AK30: seal 3fed9fd55804aca5 | AL30: 38.23 | AP30: A02.01 → S2.20 → 1/A12.01 → 1/S5.20 → 4/S5.20 → 6/S5.20 → 7/S5.20 → A09.01 → A00.30 → A09.27 → A09.33 → M01.01
A31: TYPE B2
A32: B2 #27 - Corridor 111 / Men's Restroom 113 + Storage 117 + Wellness 115 (lleva tambien el tag #29, mismo wall). Stud 6" 600S137-33 MST @ 16" O.C.; bracing 1-1/2" C.R. channel @ 48" O.C. Men's Restroom 113: 1 layer(s) 5/8 GYP @ 13.052 FT | Storage 117: 1 layer(s) 5/8 GYP @ 13.052 FT | Wellness 115: 1 layer(s) 5/8 GYP @ 13.052 FT | Corridor 111: 1 layer(s) 5/8 GYP @ 13.052 FT (1 instance) | B32: 27 | C32: 15.787 | D32: 13.052 | E32: 2 | F32: 6" | G32: 24 | H32: =IF($F32="6""",$AL32,0) -> 313.25 | I32: =IF($F32="3-5/8""",$AL32,0) -> 0 | J32: =IF($F32="1-5/8""",$AL32,0) -> 0 | K32: =SUMIFS('Board by Face'!$I$5:$I$115,'Board by Face'!$A$5:$A$115,$B32) -> 272.1108 | L32: 10.9 | N32: 1.09 | Q32: 15.79 | R32: 15.79 | S32: 47.36 | U32: 6 | AE32: 3 | AF32: 63.15 | AG32: 10 | AI32: door 113 3.33 x 7.00 + door 117 3.33 x 7.00 + door 115 3.33 x 7.00 | AJ32: CLOSED | AK32: seal 7730432fa7356abd | AL32: 313.25 | AP32: A02.01 → B/A08.01 → S2.20 → 1/A12.01 → 3/A12.01 → A09.01 → 9/A00.41 → 10/A12.02 → 11/A12.02 → 1/S5.20 → 4/S5.20 → 6/S5.20 → 7/S5.20 → 9/S5.20 → A00.30 → A09.27 → A09.33 → E02.01 → M01.01 → P01.01 → P01.02
A33: B2 #28 - Break Room 118 / Cash Window 116 + Work Room 119 (lleva tambien el tag #30, mismo wall). Stud 6" 600S137-33 MST @ 16" O.C.; bracing 1-1/2" C.R. channel @ 48" O.C. Break Room 118: 1 layer(s) 5/8 GYP @ 13.052 FT | Cash Window 116: 1 layer(s) 5/8 GYP @ 13.052 FT | Work Room 119: 1 layer(s) 5/8 GYP @ 13.052 FT (1 instance) | B33: 28 | C33: 11.74 | D33: 13.052 | E33: 1.97 | F33: 6" | G33: 13 | H33: =IF($F33="6""",$AL33,0) -> 169.68 | I33: =IF($F33="3-5/8""",$AL33,0) -> 0 | J33: =IF($F33="1-5/8""",$AL33,0) -> 0 | K33: =SUMIFS('Board by Face'!$I$5:$I$115,'Board by Face'!$A$5:$A$115,$B33) -> 301.1488 | Q33: 11.74 | R33: 11.74 | S33: 35.22 | U33: 24.9 | AF33: 46.96 | AG33: 3.33 | AI33: none | AJ33: CLOSED | AK33: seal 038efd60d5bbdd8f | AL33: 169.68 | AP33: A02.01 → S2.20 → 1/A12.01 → 3/A12.01 → A09.01 → 7/A12.04 → 10/A12.04 → 11/A12.04 → 9/A12.05 → 1/S5.20 → 7/S5.20 → 9/S5.20 → A00.30 → A09.27 → A09.33 → A12.06 → E02.01 → M01.01 → P01.01 → P01.02
A34: B2 #25 - ATM Room 102 / Central Zone 103 (wall de la door 102). Stud 6" 600S137-33 MST @ 16" O.C.; bracing 1-1/2" C.R. channel @ 48" O.C. ATM Room 102: 1 layer(s) 5/8 GYP @ 15.375 FT | Central Zone 103: 1 layer(s) 5/8 GYP @ 15.375 FT (1 instance) | B34: 25 | C34: 5.667 | D34: 15.375 | E34: 2 | F34: 6" | G34: 9 | H34: =IF($F34="6""",$AL34,0) -> 138.38 | I34: =IF($F34="3-5/8""",$AL34,0) -> 0 | J34: =IF($F34="1-5/8""",$AL34,0) -> 0 | K34: =SUMIFS('Board by Face'!$I$5:$I$115,'Board by Face'!$A$5:$A$115,$B34) -> 112.94025 | Q34: 5.67 | R34: 5.67 | S34: 17 | AF34: 22.67 | AG34: 3.83 | AI34: door 102 3.83 x 8.00 | AJ34: CLOSED | AK34: seal dc201c1d1b0c9138 | AL34: 138.38 | AP34: A02.01 → S2.20 → 1/A12.01 → 3/A12.01 → A09.01 → 10/A12.02 → 11/A12.02 → 1/S5.20 → 7/S5.20 → 9/S5.20 → A00.30 → A09.27 → A09.33 → E02.01 → M01.01 → P01.01 → P01.02
A35: B2 #26 - Women's Restroom 114 / Corridor 111 (jamb sur de la door 114). Stud 6" 600S137-33 MST @ 16" O.C.; bracing 1-1/2" C.R. channel @ 48" O.C. Women's Restroom 114: 1 layer(s) 5/8 GYP @ 13.052 FT | Corridor 111: 1 layer(s) 5/8 GYP @ 13.052 FT (1 instance) | B35: 26 | C35: 1.82 | D35: 13.052 | E35: 2 | F35: 6" | G35: 6 | H35: =IF($F35="6""",$AL35,0) -> 78.31 | I35: =IF($F35="3-5/8""",$AL35,0) -> 0 | J35: =IF($F35="1-5/8""",$AL35,0) -> 0 | K35: =SUMIFS('Board by Face'!$I$5:$I$115,'Board by Face'!$A$5:$A$115,$B35) -> 47.50928 | L35: 9.1 | N35: 0.91 | Q35: 1.82 | R35: 1.82 | S35: 5.46 | U35: 2 | AF35: 7.28 | AG35: 3.33 | AI35: none | AJ35: CLOSED | AK35: seal 87cfa9ebe94dc6bf | AL35: 78.31 | AP35: A02.01 → 2/A08.01 → B/A08.01 → S2.20 → 1/A12.01 → 3/A12.01 → 1/S5.20 → 4/S5.20 → 7/S5.20 → 9/S5.20 → A09.01 → A00.30 → A09.27 → A09.33
A36: TYPE B2K
A37: B2K #31 - Office 4 CB 108 (customer side) / Cash Window 116 (teller side). Stud 6" 600S137-68 MST @ 24" O.C.; bracing 1-1/2" C.R. channel @ 48" O.C. Office 4 CB 108: 1 layer(s) 5/8 GYP @ 15.375 FT | Cash Window 116: 1 layer(s) 5/8 GYP @ 15.375 FT (1 instance) | B37: 31 | C37: 1.26 | D37: 15.375 | E37: 2 | F37: 6" | G37: 2 | H37: =IF($F37="6""",$AL37,0) -> 30.75 | I37: =IF($F37="3-5/8""",$AL37,0) -> 0 | J37: =IF($F37="1-5/8""",$AL37,0) -> 0 | K37: =SUMIFS('Board by Face'!$I$5:$I$115,'Board by Face'!$A$5:$A$115,$B37) -> 38.745 | Q37: 1.26 | R37: 1.26 | S37: 3.78 | Y37: 10.08 | Z37: 9.29 | AC37: 1.26 | AF37: 5.04 | AI37: none | AJ37: CLOSED | AK37: seal f0416b251e71edd3 | AL37: 30.75 | AP37: A02.01 → S2.20 → 4/A12.01 → 1/S5.20 → 4/S5.20 → 5/S5.20 → 7/S5.20 → A09.01 → A00.30 → A09.27 → A09.33 → E02.01 → M01.01 → P01.01 → P01.02
A38: TYPE BULKHEAD-G
A39: BULKHEAD-G #54 - Over the 4 office fronts at Offices 105, 106, 107 and 108 (alineacion x 1622.04/1631.28). Stud 1-5/8" 162S-family MST @ 16" O.C. DOUBLE ROW (2 rows of stud); bracing 1-1/2" C.R. channel @ 48" O.C. Lado oficina (105-108): 2 layer(s) 5/8 GYP x2 layers @ 7.333 FT | Central Zone 103: 2 layer(s) 5/8 GYP x2 layers @ 7.333 FT (1 instance) | B39: 54 | C39: 30 | D39: 7.333 | E39: 4 | F39: 1-5/8" | G39: 64 | H39: =IF($F39="6""",$AL39,0) -> 0 | I39: =IF($F39="3-5/8""",$AL39,0) -> 0 | J39: =IF($F39="1-5/8""",$AL39,0) -> 469.31 | K39: =SUMIFS('Board by Face'!$I$5:$I$115,'Board by Face'!$A$5:$A$115,$B39) -> 879.96 | Q39: 60 | R39: 60 | S39: 60 | U39: 30 | AC39: 120 | AF39: 120 | AG39: 30 | AI39: none | AJ39: CLOSED | AK39: seal 778c08f5074a3f2b | AL39: 469.31 | AP39: A02.01 → S2.20 → 7/A11.01 → 9/A12.01 → 1/S5.20 → 7/S5.20 → A09.01 → A00.01 → A09.27 → A09.33
A40: BULKHEAD-G #55 - Over the 2 office fronts at Offices 109 and 110 (alineacion x 1121.16/1133.88). Stud 1-5/8" 162S-family MST @ 16" O.C. DOUBLE ROW (2 rows of stud); bracing 1-1/2" C.R. channel @ 48" O.C. Lado oficina (109-110): 2 layer(s) 5/8 GYP x2 layers @ 7.333 FT | Area abierta al este (Waiting 104): 2 layer(s) 5/8 GYP x2 layers @ 7.333 FT (1 instance) | B40: 55 | C40: 15 | D40: 7.333 | E40: 4 | F40: 1-5/8" | G40: 32 | H40: =IF($F40="6""",$AL40,0) -> 0 | I40: =IF($F40="3-5/8""",$AL40,0) -> 0 | J40: =IF($F40="1-5/8""",$AL40,0) -> 234.66 | K40: =SUMIFS('Board by Face'!$I$5:$I$115,'Board by Face'!$A$5:$A$115,$B40) -> 439.98 | Q40: 30 | R40: 30 | S40: 30 | U40: 15 | AC40: 60 | AF40: 60 | AG40: 15 | AI40: none | AJ40: CLOSED | AK40: seal c904037bf9ccbc5c | AL40: 234.66 | AP40: A02.01 → S2.20 → 7/A11.01 → 9/A12.01 → 1/S5.20 → 7/S5.20 → A09.01 → A00.01 → A09.27 → A09.33
A41: TYPE C1
A42: C1 #36 - North wall of Calling Cubes 122, face towards Central Zone 103. Stud 3-5/8" 362S137-33 MST @ 16" O.C.; bracing 1-1/2" C.R. channel @ 48" O.C. Central Zone 103: 1 layer(s) 5/8 GYP @ 11.500 FT (1 instance) | B42: 36 | C42: 11.333 | D42: 11.5 | E42: 1 | F42: 3-5/8" | G42: 10 | H42: =IF($F42="6""",$AL42,0) -> 0 | I42: =IF($F42="3-5/8""",$AL42,0) -> 115 | J42: =IF($F42="1-5/8""",$AL42,0) -> 0 | K42: =SUMIFS('Board by Face'!$I$5:$I$115,'Board by Face'!$A$5:$A$115,$B42) -> 130.295 | Q42: 11.333 | R42: 11.333 | S42: 22.67 | U42: 10 | AI42: none | AJ42: CLOSED | AK42: seal ee061539aa99e04a | AL42: 115 | AP42: A02.01 → A04.01 → 2/A12.01 → 3/A12.01 → 6/A12.01 → 12/A12.01 → A09.01 → 9/A12.02 → 13/A12.02 → 1/S5.20 → 4/S5.20 → 7/S5.20 → A00.30 → A09.27 → A09.33
A43: C1 #37 - North face of the plumbing chase between restrooms 113 and 114. Stud 3-5/8" 362S137-33 MST @ 16" O.C.; bracing 1-1/2" C.R. channel @ 48" O.C. Women's Restroom 114: 1 layer(s) 5/8 GYP @ 9.000 FT (1 instance) | B43: 37 | C43: 5.6 | D43: 9 | E43: 1 | F43: 3-5/8" | G43: 8 | H43: =IF($F43="6""",$AL43,0) -> 0 | I43: =IF($F43="3-5/8""",$AL43,0) -> 72 | J43: =IF($F43="1-5/8""",$AL43,0) -> 0 | K43: =SUMIFS('Board by Face'!$I$5:$I$115,'Board by Face'!$A$5:$A$115,$B43) -> 50.4 | Q43: 5.6 | R43: 5.6 | S43: 11.2 | U43: 5.6 | AI43: none | AJ43: CLOSED | AK43: seal 8f93a0dfc5e6f9be | AL43: 72 | AP43: A02.01 → A04.01 → A08.01 → 2/A12.01 → 3/A12.01 → 6/A12.01 → 12/A12.01 → 1/S5.20 → 4/S5.20 → 7/S5.20 → 8/S5.20 → A09.01 → A00.30 → A09.27 → A09.33
A44: C1 #39 - South face of the plumbing chase between restrooms 113 and 114. Stud 3-5/8" 362S137-33 MST @ 16" O.C.; bracing 1-1/2" C.R. channel @ 48" O.C. Men's Restroom 113: 1 layer(s) 5/8 GYP @ 9.000 FT (1 instance) | B44: 39 | C44: 5.6 | D44: 9 | E44: 1 | F44: 3-5/8" | G44: 8 | H44: =IF($F44="6""",$AL44,0) -> 0 | I44: =IF($F44="3-5/8""",$AL44,0) -> 72 | J44: =IF($F44="1-5/8""",$AL44,0) -> 0 | K44: =SUMIFS('Board by Face'!$I$5:$I$115,'Board by Face'!$A$5:$A$115,$B44) -> 50.4 | Q44: 5.6 | R44: 5.6 | S44: 11.2 | U44: 5.6 | AI44: none | AJ44: CLOSED | AK44: seal 05f3cbbb46afc9d5 | AL44: 72 | AP44: A02.01 → A04.01 → A08.01 → 2/A12.01 → 3/A12.01 → 6/A12.01 → 12/A12.01 → 1/S5.20 → 4/S5.20 → 7/S5.20 → 8/S5.20 → A09.01 → A00.30 → A09.27 → A09.33
A45: C1 #32 - Entry pilaster of Vestibule 100, next to door 100A; it carries the push button (PB) and the card reader (CR). Stud 3-5/8" 362S137-33 MST @ 16" O.C.; bracing 1-1/2" C.R. channel @ 48" O.C. Vestibule 100: 1 layer(s) 5/8 GYP @ 10.000 FT (1 instance) | B45: 32 | C45: 4.56 | D45: 10 | E45: 1 | F45: 3-5/8" | G45: 5 | H45: =IF($F45="6""",$AL45,0) -> 0 | I45: =IF($F45="3-5/8""",$AL45,0) -> 50 | J45: =IF($F45="1-5/8""",$AL45,0) -> 0 | K45: =SUMIFS('Board by Face'!$I$5:$I$115,'Board by Face'!$A$5:$A$115,$B45) -> 45.6 | Q45: 4.56 | R45: 4.56 | S45: 9.12 | U45: 4 | AC45: 30 | AI45: none | AJ45: CLOSED | AK45: seal 18f719ea04d85cfd | AL45: 50 | AP45: A02.01 → A04.01 → 2/A12.01 → 3/A12.01 → 6/A12.01 → 12/A12.01 → 1/S5.20 → 4/S5.20 → 7/S5.20 → A09.01 → A00.30 → A09.27 → A09.33
A46: C1 #33 - Pilaster at the northwest corner of Vestibule 100. Stud 3-5/8" 362S137-33 MST @ 16" O.C.; bracing 1-1/2" C.R. channel @ 48" O.C. Vestibule 100: 1 layer(s) 5/8 GYP @ 10.000 FT (1 instance) | B46: 33 | C46: 3.58 | D46: 10 | E46: 1 | F46: 3-5/8" | G46: 5 | H46: =IF($F46="6""",$AL46,0) -> 0 | I46: =IF($F46="3-5/8""",$AL46,0) -> 50 | J46: =IF($F46="1-5/8""",$AL46,0) -> 0 | K46: =SUMIFS('Board by Face'!$I$5:$I$115,'Board by Face'!$A$5:$A$115,$B46) -> 35.8 | Q46: 3.58 | R46: 3.58 | S46: 7.16 | AC46: 30 | AI46: none | AJ46: CLOSED | AK46: seal 99e04a76facc8aa6 | AL46: 50 | AP46: A02.01 → A04.01 → 2/A12.01 → 3/A12.01 → 6/A12.01 → 12/A12.01 → 1/S5.20 → 4/S5.20 → 7/S5.20 → A09.01 → A00.30 → A09.27 → A09.33
A47: C1 #38 - Future FCAM, south face of the A1K wall that closes Cash Window 116. Stud 3-5/8" 362S137-33 MST @ 16" O.C.; bracing 1-1/2" C.R. channel @ 48" O.C. Cash Window 116: 1 layer(s) 5/8 GYP @ 9.000 FT (1 instance) | B47: 38 | C47: 3.39 | D47: 9 | E47: 1 | F47: 3-5/8" | G47: 4 | H47: =IF($F47="6""",$AL47,0) -> 0 | I47: =IF($F47="3-5/8""",$AL47,0) -> 36 | J47: =IF($F47="1-5/8""",$AL47,0) -> 0 | K47: =SUMIFS('Board by Face'!$I$5:$I$115,'Board by Face'!$A$5:$A$115,$B47) -> 30.51 | Q47: 3.39 | R47: 3.39 | S47: 6.78 | AI47: none | AJ47: CLOSED | AK47: seal ca69ddeec498e65b | AL47: 36 | AP47: A02.01 → A04.01 → 2/A12.01 → 3/A12.01 → 6/A12.01 → 12/A12.01 → 1/S5.20 → 4/S5.20 → 7/S5.20 → A09.01 → A00.30 → A09.27 → A09.33
A48: C1 #34 - Steel column enclosure between 24 HR Vestibule 101 and Central Zone 103; the column is drawn inside the box. Stud 3-5/8" 362S137-33 MST @ 16" O.C.; bracing 1-1/2" C.R. channel @ 48" O.C. Central Zone 103: 1 layer(s) 5/8 GYP @ 11.500 FT (1 instance) | B48: 34 | C48: 3.33 | D48: 11.5 | E48: 1 | F48: 3-5/8" | G48: 4 | H48: =IF($F48="6""",$AL48,0) -> 0 | I48: =IF($F48="3-5/8""",$AL48,0) -> 46 | J48: =IF($F48="1-5/8""",$AL48,0) -> 0 | K48: =SUMIFS('Board by Face'!$I$5:$I$115,'Board by Face'!$A$5:$A$115,$B48) -> 38.295 | Q48: 3.33 | R48: 3.33 | S48: 6.66 | AC48: 46 | AI48: none | AJ48: CLOSED | AK48: seal 8fb0489490dc755f | AL48: 46 | AP48: A02.01 → A04.01 → 2/A12.01 → 3/A12.01 → 6/A12.01 → 12/A12.01 → 1/S5.20 → 4/S5.20 → 7/S5.20 → A09.01 → A00.30 → A09.27 → A09.33
A49: C1 #35 - Steel column enclosure at the south end of the sloped ATM wall, between ATM Room 102 and Central Zone 103. Stud 3-5/8" 362S137-33 MST @ 16" O.C.; bracing 1-1/2" C.R. channel @ 48" O.C. Central Zone 103: 1 layer(s) 5/8 GYP @ 11.500 FT (1 instance) | B49: 35 | C49: 2.52 | D49: 11.5 | E49: 1 | F49: 3-5/8" | G49: 4 | H49: =IF($F49="6""",$AL49,0) -> 0 | I49: =IF($F49="3-5/8""",$AL49,0) -> 46 | J49: =IF($F49="1-5/8""",$AL49,0) -> 0 | K49: =SUMIFS('Board by Face'!$I$5:$I$115,'Board by Face'!$A$5:$A$115,$B49) -> 28.98 | Q49: 2.52 | R49: 2.52 | S49: 5.04 | AC49: 46 | AI49: none | AJ49: CLOSED | AK49: seal 3b9e6e7a71481bbb | AL49: 46 | AP49: A02.01 → A04.01 → 2/A12.01 → 3/A12.01 → 6/A12.01 → 12/A12.01 → 1/S5.20 → 4/S5.20 → 7/S5.20 → A09.01 → A00.30 → A09.27 → A09.33
A50: TYPE CANOPY-COL
A51: CANOPY-COL #66 - CANOPY COLUMN 1 (drive-through island, northmost -- A02.01 y=283.8). Stud 3-5/8" 362S137-33 MST @ 16" O.C.; bracing 1-1/2" C.R. channel @ 48" O.C. Exterior (4 faces of the wrap): 1 layer(s) 5/8 EXTERIOR GRADE FRT PLYWOOD @ 10.500 FT (1 instance) | B51: 66 | C51: 5.668 | D51: 10.5 | E51: 1.07 | F51: 3-5/8" | G51: 8 | H51: =IF($F51="6""",$AL51,0) -> 0 | I51: =IF($F51="3-5/8""",$AL51,0) -> 84 | J51: =IF($F51="1-5/8""",$AL51,0) -> 0 | K51: =SUMIFS('Board by Face'!$I$5:$I$115,'Board by Face'!$A$5:$A$115,$B51) -> 63.882 | Q51: 5.668 | R51: 5.668 | S51: 11.34 | AF51: 12.17 | AI51: none | AJ51: CLOSED | AK51: seal 159cfafc30d95d57 | AL51: 84 | AP51: A02.01 → D/A08.01 → 6/A08.11 → S2.10 → A/A09.21 → D/A09.22 → F/A09.22 → H/A09.23 → 2/A09.25 → 5/A09.25 → 9/S3.20 → 6/S5.10 → 10/S5.10 → A09.01 → A12.01 → 5/A09.26 → 9/A09.27 → 6/A09.31 → 7/S5.20 → A00.30 → A09.33
A52: CANOPY-COL #67 - CANOPY COLUMN 2 (drive-through island -- A02.01 y=564.2). Stud 3-5/8" 362S137-33 MST @ 16" O.C.; bracing 1-1/2" C.R. channel @ 48" O.C. Exterior (4 faces of the wrap): 1 layer(s) 5/8 EXTERIOR GRADE FRT PLYWOOD @ 10.500 FT (1 instance) | B52: 67 | C52: 5.668 | D52: 10.5 | E52: 1.07 | F52: 3-5/8" | G52: 8 | H52: =IF($F52="6""",$AL52,0) -> 0 | I52: =IF($F52="3-5/8""",$AL52,0) -> 84 | J52: =IF($F52="1-5/8""",$AL52,0) -> 0 | K52: =SUMIFS('Board by Face'!$I$5:$I$115,'Board by Face'!$A$5:$A$115,$B52) -> 63.882 | Q52: 5.668 | R52: 5.668 | S52: 11.34 | AF52: 12.17 | AI52: none | AJ52: CLOSED | AK52: seal 83d00f2c2952a67c | AL52: 84 | AP52: A02.01 → D/A08.01 → 6/A08.11 → S2.10 → A/A09.21 → D/A09.22 → F/A09.22 → H/A09.23 → 2/A09.25 → 5/A09.25 → 9/S3.20 → 6/S5.10 → 10/S5.10 → A09.01 → A12.01 → 5/A09.26 → 9/A09.27 → 6/A09.31 → 7/S5.20 → A00.30 → A09.33
A53: CANOPY-COL #68 - CANOPY COLUMN 3 (drive-through island -- A02.01 y=849.2). Stud 3-5/8" 362S137-33 MST @ 16" O.C.; bracing 1-1/2" C.R. channel @ 48" O.C. Exterior (4 faces of the wrap): 1 layer(s) 5/8 EXTERIOR GRADE FRT PLYWOOD @ 10.500 FT (1 instance) | B53: 68 | C53: 5.668 | D53: 10.5 | E53: 1.07 | F53: 3-5/8" | G53: 8 | H53: =IF($F53="6""",$AL53,0) -> 0 | I53: =IF($F53="3-5/8""",$AL53,0) -> 84 | J53: =IF($F53="1-5/8""",$AL53,0) -> 0 | K53: =SUMIFS('Board by Face'!$I$5:$I$115,'Board by Face'!$A$5:$A$115,$B53) -> 63.882 | Q53: 5.668 | R53: 5.668 | S53: 11.34 | AF53: 12.17 | AI53: none | AJ53: CLOSED | AK53: seal 871fd9270d16311a | AL53: 84 | AP53: A02.01 → D/A08.01 → 6/A08.11 → S2.10 → A/A09.21 → D/A09.22 → F/A09.22 → H/A09.23 → 2/A09.25 → 5/A09.25 → 9/S3.20 → 6/S5.10 → 10/S5.10 → A09.01 → A12.01 → 5/A09.26 → 9/A09.27 → 6/A09.31 → 7/S5.20 → A00.30 → A09.33
A54: CANOPY-COL #69 - CANOPY COLUMN 4 (drive-through island, southmost -- A02.01 y=1125.0). Stud 3-5/8" 362S137-33 MST @ 16" O.C.; bracing 1-1/2" C.R. channel @ 48" O.C. Exterior (4 faces of the wrap): 1 layer(s) 5/8 EXTERIOR GRADE FRT PLYWOOD @ 10.500 FT (1 instance) | B54: 69 | C54: 5.668 | D54: 10.5 | E54: 1.07 | F54: 3-5/8" | G54: 8 | H54: =IF($F54="6""",$AL54,0) -> 0 | I54: =IF($F54="3-5/8""",$AL54,0) -> 84 | J54: =IF($F54="1-5/8""",$AL54,0) -> 0 | K54: =SUMIFS('Board by Face'!$I$5:$I$115,'Board by Face'!$A$5:$A$115,$B54) -> 63.882 | Q54: 5.668 | R54: 5.668 | S54: 11.34 | AF54: 12.17 | AI54: none | AJ54: CLOSED | AK54: seal a46b2f79804210e6 | AL54: 84 | AP54: A02.01 → D/A08.01 → 6/A08.11 → S2.10 → A/A09.21 → D/A09.22 → F/A09.22 → H/A09.23 → 2/A09.25 → 5/A09.25 → 9/S3.20 → 6/S5.10 → 10/S5.10 → A09.01 → A12.01 → 5/A09.26 → 9/A09.27 → 6/A09.31 → 7/S5.20 → A00.30 → A09.33
A55: TYPE EXT-6CFMF
A56: EXT-6CFMF #61 - EAST facade (grid 8, x=1851.78) -- the 4 offices 105-108. Stud 6" 600S137-33 MST @ 16" O.C.; bracing 1-1/2" C.R. channel @ 48" O.C. Interior: 1 layer(s) 5/8 GYP @ 14.520 FT (1 instance) | B56: 61 | C56: 76.3 | D56: 14.52 | E56: 1 | F56: 6" | G56: 132 | H56: =IF($F56="6""",$AL56,0) -> 1916.64 | I56: =IF($F56="3-5/8""",$AL56,0) -> 0 | J56: =IF($F56="1-5/8""",$AL56,0) -> 0 | K56: =SUMIFS('Board by Face'!$I$5:$I$115,'Board by Face'!$A$5:$A$115,$B56) -> 1043.876 | Q56: 76.3 | R56: 76.3 | S56: 228.9 | X56: 1043.88 | AA56: 40 | AF56: 305.2 | AG56: 37.33 | AH56: 37.33 | AI56: window window GL-2 #1 (R.O. 8'-0" x 2'-0") 8.00 x 2.00 + window window GL-2 #2 (R.O. 8'-0" x 2'-0") 8.00 x 2.00 + window window GL-2 #3 (R.O. 8'-0" x 2'-0") 8.00 x 2.00 + window window GL-2 #4 (R.O. 8'-0" x 2'-0") 8.00 x 2.00 | AJ56: CLOSED | AK56: seal a3203de09a3a9d2f | AL56: 1916.64 | AN56: 1043.88 | AO56: 40 | AP56: A02.01 → 5/A08.11 → 6/A08.11 → A08.01 → 2/A09.01 → 1/A09.02 → A/A09.21 → B/A09.21 → C/A09.21 → D/A09.22 → E/A09.22 → F/A09.22 → H/A09.23 → J/A09.23 → 1/A09.25 → 2/A09.25 → 3/A09.25 → 4/A11.01 → 10/A11.03 → 3/A11.04 → 7/A11.04 → 9/A11.04 → 16/A11.04 → 2/S3.20 → 8/S3.20 → 6/S5.10 → 10/S5.10 → 11/S5.10 → 7/S5.11 → A12.01 → 1/A09.26 → 2/A09.26 → 4/A09.26 → 5/A09.26 → 6/A09.26 → 7/A09.26 → 9/A09.27 → 10/A09.27 → 11/A09.27 → 6/A09.31 → 7/S5.20 → A09.33
A57: EXT-6CFMF #62 - SOUTH facade (grid A, y=1702.14) -- service side, egress door 123. Stud 6" 600S137-33 MST @ 16" O.C.; bracing 1-1/2" C.R. channel @ 48" O.C. Interior: 1 layer(s) 5/8 GYP @ 12.531 FT (1 instance) | B57: 62 | C57: 52.7 | D57: 12.531 | E57: 1 | F57: 6" | G57: 46 | H57: =IF($F57="6""",$AL57,0) -> 576.43 | I57: =IF($F57="3-5/8""",$AL57,0) -> 0 | J57: =IF($F57="1-5/8""",$AL57,0) -> 0 | K57: =SUMIFS('Board by Face'!$I$5:$I$115,'Board by Face'!$A$5:$A$115,$B57) -> 637.0737 | Q57: 52.7 | R57: 52.7 | S57: 158.1 | X57: 637.07 | AF57: 210.8 | AG57: 4.66 | AI57: door door 123 de egreso 3.33 x 7.00 | AJ57: CLOSED | AK57: seal 3eacd1caf553f123 | AL57: 576.43 | AN57: 637.07 | AP57: A02.01 → 5/A08.11 → 6/A08.11 → A08.01 → S2.20 → A/A09.21 → B/A09.21 → C/A09.21 → D/A09.22 → E/A09.22 → F/A09.22 → H/A09.23 → J/A09.23 → 4/A11.01 → 10/A11.03 → 3/A11.04 → 7/A11.04 → 9/A11.04 → 16/A11.04 → 2/S3.20 → 8/S3.20 → 6/S5.10 → 10/S5.10 → 11/S5.10 → 7/S5.11 → A09.01 → A09.02 → A12.01 → 2/A09.26 → 4/A09.26 → 5/A09.26 → 7/A09.26 → 9/A09.27 → 11/A09.27 → 6/A09.31 → 7/S5.20 → A00.30 → A09.33
A58: EXT-6CFMF #63 - WEST LOW facade (grid 3, x=903.18) -- offices 109-110 and restrooms. Stud 6" 600S137-33 MST @ 16" O.C.; bracing 1-1/2" C.R. channel @ 48" O.C. Interior: 1 layer(s) 5/8 GYP @ 13.990 FT (1 instance) | B58: 63 | C58: 47.92 | D58: 13.99 | E58: 1 | F58: 6" | G58: 74 | H58: =IF($F58="6""",$AL58,0) -> 1035.26 | I58: =IF($F58="3-5/8""",$AL58,0) -> 0 | J58: =IF($F58="1-5/8""",$AL58,0) -> 0 | K58: =SUMIFS('Board by Face'!$I$5:$I$115,'Board by Face'!$A$5:$A$115,$B58) -> 638.4008 | L58: 59.79 | N58: 6.64 | Q58: 47.92 | R58: 47.92 | S58: 143.76 | U58: 25.33 | X58: 638.4 | AA58: 20 | AF58: 191.68 | AG58: 18.67 | AH58: 18.67 | AI58: window window GL-2 #1 (R.O. 8'-0" x 2'-0") 8.00 x 2.00 + window window GL-2 #2 (R.O. 8'-0" x 2'-0") 8.00 x 2.00 | AJ58: CLOSED | AK58: seal 689bc85d12113496 | AL58: 1035.26 | AN58: 638.4 | AO58: 20 | AP58: A02.01 → C/A08.01 → D/A08.01 → 5/A08.11 → 6/A08.11 → 2/A09.01 → 1/A09.02 → A/A09.21 → B/A09.21 → C/A09.21 → D/A09.22 → E/A09.22 → F/A09.22 → H/A09.23 → J/A09.23 → 1/A09.25 → 2/A09.25 → 3/A09.25 → 2/S3.20 → 8/S3.20 → 6/S5.10 → 10/S5.10 → 11/S5.10 → 7/S5.11 → A12.01 → 1/A09.26 → 2/A09.26 → 4/A09.26 → 5/A09.26 → 6/A09.26 → 7/A09.26 → 9/A09.27 → 10/A09.27 → 11/A09.27 → 6/A09.31 → 7/S5.20 → A00.21 → A09.33
A59: EXT-6CFMF #65 - WEST HIGH facade (grid 2, x=833.16) -- 24 hr vestibule and drive-up ATM. Stud 6" 600S137-33 MST @ 16" O.C.; bracing 1-1/2" C.R. channel @ 48" O.C. Interior: 1 layer(s) 5/8 GYP @ 15.375 FT (1 instance) | B59: 65 | C59: 21.88 | D59: 15.375 | E59: 1 | F59: 6" | G59: 27 | H59: =IF($F59="6""",$AL59,0) -> 415.12 | I59: =IF($F59="3-5/8""",$AL59,0) -> 0 | J59: =IF($F59="1-5/8""",$AL59,0) -> 0 | K59: =SUMIFS('Board by Face'!$I$5:$I$115,'Board by Face'!$A$5:$A$115,$B59) -> 330.735 | Q59: 21.88 | R59: 21.88 | S59: 65.64 | X59: 305.37 | AA59: 37.12 | AD59: 49.87 | AF59: 87.52 | AG59: 20.85 | AH59: 3.51 | AI59: framed opening R.O. del ATM drive-up NHA 9D 2.18 x 2.60 | AJ59: CLOSED | AK59: seal aded4bb735f151bd | AL59: 415.12 | AN59: 330.74 | AO59: 11.75 | AP59: A02.01 → D/A08.01 → 2/A08.11 → 3/A08.11 → 4/A08.11 → 5/A08.11 → 6/A08.11 → 7/A08.11 → 8/A08.11 → 9/A08.11 → A/A09.21 → B/A09.21 → C/A09.21 → D/A09.22 → E/A09.22 → F/A09.22 → H/A09.23 → J/A09.23 → 1/A09.25 → 2/A09.25 → 3/A09.25 → 2/S3.20 → 8/S3.20 → 6/S5.10 → 10/S5.10 → 11/S5.10 → 7/S5.11 → A09.01 → A09.02 → A12.01 → 1/A09.26 → 2/A09.26 → 4/A09.26 → 5/A09.26 → 6/A09.26 → 7/A09.26 → 9/A09.27 → 10/A09.27 → 11/A09.27 → 6/A09.31 → 7/S5.20 → A09.33
A60: EXT-6CFMF #60 - NORTH facade (grid F, y=328.74) -- entrance side. Stud 6" 600S137-33 MST @ 16" O.C.; bracing 1-1/2" C.R. channel @ 48" O.C. Interior: 1 layer(s) 5/8 GYP @ 15.375 FT (1 instance) | B60: 60 | C60: 14.95 | D60: 15.375 | E60: 1 | F60: 6" | G60: 14 | H60: =IF($F60="6""",$AL60,0) -> 215.25 | I60: =IF($F60="3-5/8""",$AL60,0) -> 0 | J60: =IF($F60="1-5/8""",$AL60,0) -> 0 | K60: =SUMIFS('Board by Face'!$I$5:$I$115,'Board by Face'!$A$5:$A$115,$B60) -> 229.85625 | Q60: 14.95 | R60: 14.95 | S60: 44.85 | X60: 229.86 | AA60: 29.32 | AF60: 59.8 | AG60: 42.97 | AI60: none | AJ60: CLOSED | AK60: seal 99b40ea2d02d7ef9 | AL60: 215.25 | AN60: 229.86 | AO60: 29.32 | AP60: A02.01 → 6/A08.11 → A08.01 → S2.20 → A/A09.21 → B/A09.21 → C/A09.21 → D/A09.22 → E/A09.22 → F/A09.22 → H/A09.23 → J/A09.23 → 1/A09.25 → 2/A09.25 → 3/A09.25 → 4/A11.01 → 10/A11.03 → 3/A11.04 → 7/A11.04 → 9/A11.04 → 16/A11.04 → 2/S3.20 → 8/S3.20 → 6/S5.10 → 10/S5.10 → 11/S5.10 → 7/S5.11 → A09.01 → A09.02 → A12.01 → 1/A09.26 → 2/A09.26 → 4/A09.26 → 5/A09.26 → 6/A09.26 → 7/A09.26 → 9/A09.27 → 10/A09.27 → 11/A09.27 → 6/A09.31 → 7/S5.20 → A00.30 → A09.33
A61: EXT-6CFMF #64 - West perimeter jog (y=839.58, grid 2 to grid 3). Stud 6" 600S137-33 MST @ 16" O.C.; bracing 1-1/2" C.R. channel @ 48" O.C. Interior: 1 layer(s) 5/8 GYP @ 15.375 FT (1 instance) | B61: 64 | C61: 3.89 | D61: 15.375 | E61: 1 | F61: 6" | G61: 5 | H61: =IF($F61="6""",$AL61,0) -> 76.88 | I61: =IF($F61="3-5/8""",$AL61,0) -> 0 | J61: =IF($F61="1-5/8""",$AL61,0) -> 0 | K61: =SUMIFS('Board by Face'!$I$5:$I$115,'Board by Face'!$A$5:$A$115,$B61) -> 59.80875 | Q61: 3.89 | R61: 3.89 | S61: 11.67 | X61: 59.81 | AF61: 15.56 | AI61: none | AJ61: CLOSED | AK61: seal 1a04cf242764cf6c | AL61: 76.88 | AN61: 59.81 | AP61: A02.01 → 6/A08.11 → A08.01 → A/A09.21 → B/A09.21 → C/A09.21 → D/A09.22 → E/A09.22 → F/A09.22 → H/A09.23 → J/A09.23 → 4/A11.01 → 10/A11.03 → 3/A11.04 → 7/A11.04 → 9/A11.04 → 16/A11.04 → 2/S3.20 → 8/S3.20 → 6/S5.10 → 10/S5.10 → 11/S5.10 → 7/S5.11 → A09.01 → A09.02 → A12.01 → 2/A09.26 → 4/A09.26 → 5/A09.26 → 7/A09.26 → 9/A09.27 → 11/A09.27 → 6/A09.31 → 7/S5.20 → A00.30 → A09.33
A62: TYPE EXT-PARAPET
A63: EXT-PARAPET #161 - EAST facade (grid 8, x=1851.78) -- the 4 offices 105-108 -- PARAPET INFILL, from B.O.D. up to T/ STUD. Stud 6" 54mil 600S162-54 MST @ 16" O.C.; bracing 1-1/2" C.R. channel @ 48" O.C. (1 instance) | B63: 161 | C63: 76.3 | D63: 2.897 | E63: 0 | F63: 6" 54mil | G63: 92 | H63: =IF($F63="6""",$AL63,0) -> 0 | I63: =IF($F63="3-5/8""",$AL63,0) -> 0 | J63: =IF($F63="1-5/8""",$AL63,0) -> 0 | K63: =SUMIFS('Board by Face'!$I$5:$I$115,'Board by Face'!$A$5:$A$115,$B63) -> 0 | Q63: 76.3 | R63: 76.3 | S63: 0 | U63: 76.3 | W63: 221.04 | X63: 221.04 | AE63: 77 | AF63: 152.6 | AI63: none | AJ63: CLOSED | AK63: seal ef38ead4712e6278 | AL63: 266.52 | AP63: A02.01 → A/A09.21 → C/A09.21 → D/A09.22 → H/A09.23 → J/A09.23 → 6/S5.10 → 10/S5.10 → 11/S5.10 → 7/S5.11 → A09.01 → A09.02 → A12.01 → 4/A09.26 → 7/S5.20 → A00.30 → A09.27 → A09.33
A64: EXT-PARAPET #162 - SOUTH facade (grid A, y=1702.14) -- service side, egress door 123 -- PARAPET INFILL, from B.O.D. up to T/ STUD. Stud 6" 54mil 600S162-54 MST @ 16" O.C.; bracing 1-1/2" C.R. channel @ 48" O.C. (1 instance) | B64: 162 | C64: 52.7 | D64: 4.886 | E64: 0 | F64: 6" 54mil | G64: 64 | H64: =IF($F64="6""",$AL64,0) -> 0 | I64: =IF($F64="3-5/8""",$AL64,0) -> 0 | J64: =IF($F64="1-5/8""",$AL64,0) -> 0 | K64: =SUMIFS('Board by Face'!$I$5:$I$115,'Board by Face'!$A$5:$A$115,$B64) -> 0 | Q64: 52.7 | R64: 52.7 | S64: 52.7 | U64: 52.7 | W64: 257.49 | X64: 257.49 | AE64: 53 | AF64: 105.4 | AI64: none | AJ64: CLOSED | AK64: seal 13d7c711fa03fb8f | AL64: 312.7 | AP64: A02.01 → S2.20 → A/A09.21 → C/A09.21 → D/A09.22 → H/A09.23 → J/A09.23 → 6/S5.10 → 10/S5.10 → 11/S5.10 → 7/S5.11 → A09.01 → A09.02 → A12.01 → 4/A09.26 → 7/S5.20 → A00.30 → A09.27 → A09.33
A65: EXT-PARAPET #163 - WEST LOW facade (grid 3, x=903.18) -- offices 109-110 and restrooms -- PARAPET INFILL, from B.O.D. up to T/ STUD. Stud 6" 54mil 600S162-54 MST @ 16" O.C.; bracing 1-1/2" C.R. channel @ 48" O.C. (1 instance) | B65: 163 | C65: 47.92 | D65: 3.427 | E65: 0 | F65: 6" 54mil | G65: 58 | H65: =IF($F65="6""",$AL65,0) -> 0 | I65: =IF($F65="3-5/8""",$AL65,0) -> 0 | J65: =IF($F65="1-5/8""",$AL65,0) -> 0 | K65: =SUMIFS('Board by Face'!$I$5:$I$115,'Board by Face'!$A$5:$A$115,$B65) -> 0 | Q65: 47.92 | R65: 47.92 | S65: 0 | U65: 47.92 | W65: 164.22 | X65: 164.22 | AE65: 48 | AF65: 95.84 | AI65: none | AJ65: CLOSED | AK65: seal d0130a7cdbf4c776 | AL65: 198.77 | AP65: A02.01 → A/A09.21 → C/A09.21 → D/A09.22 → H/A09.23 → J/A09.23 → 6/S5.10 → 10/S5.10 → 11/S5.10 → 7/S5.11 → A09.01 → A09.02 → A12.01 → 4/A09.26 → 7/S5.20 → A00.30 → A09.27 → A09.33
A66: EXT-PARAPET #165 - WEST HIGH facade (grid 2, x=833.16) -- 24 hr vestibule and drive-up ATM -- PARAPET INFILL, from B.O.D. up to T/ STUD. Stud 6" 54mil 600S162-54 MST @ 16" O.C.; bracing 1-1/2" C.R. channel @ 48" O.C. (1 instance) | B66: 165 | C66: 21.88 | D66: 4.292 | E66: 0 | F66: 6" 54mil | G66: 29 | H66: =IF($F66="6""",$AL66,0) -> 0 | I66: =IF($F66="3-5/8""",$AL66,0) -> 0 | J66: =IF($F66="1-5/8""",$AL66,0) -> 0 | K66: =SUMIFS('Board by Face'!$I$5:$I$115,'Board by Face'!$A$5:$A$115,$B66) -> 0 | Q66: 21.88 | R66: 21.88 | S66: 21.88 | U66: 21.88 | W66: 93.91 | X66: 93.91 | AE66: 22 | AF66: 43.76 | AI66: none | AJ66: CLOSED | AK66: seal bb5588df624beb73 | AL66: 124.47 | AP66: A02.01 → A/A09.21 → C/A09.21 → D/A09.22 → H/A09.23 → J/A09.23 → 6/S5.10 → 10/S5.10 → 11/S5.10 → 7/S5.11 → A09.01 → A09.02 → A12.01 → 4/A09.26 → 7/S5.20 → A00.30 → A09.27 → A09.33
A67: EXT-PARAPET #160 - NORTH facade (grid F, y=328.74) -- entrance side -- PARAPET INFILL, from B.O.D. up to T/ STUD. Stud 6" 54mil 600S162-54 MST @ 16" O.C.; bracing 1-1/2" C.R. channel @ 48" O.C. (1 instance) | B67: 160 | C67: 14.95 | D67: 2.042 | E67: 0 | F67: 6" 54mil | G67: 20 | H67: =IF($F67="6""",$AL67,0) -> 0 | I67: =IF($F67="3-5/8""",$AL67,0) -> 0 | J67: =IF($F67="1-5/8""",$AL67,0) -> 0 | K67: =SUMIFS('Board by Face'!$I$5:$I$115,'Board by Face'!$A$5:$A$115,$B67) -> 0 | Q67: 14.95 | R67: 14.95 | S67: 0 | U67: 14.95 | W67: 30.53 | X67: 30.53 | AE67: 15 | AF67: 29.9 | AI67: none | AJ67: CLOSED | AK67: seal a01717e19c2cd100 | AL67: 40.84 | AP67: A02.01 → S2.20 → A/A09.21 → C/A09.21 → D/A09.22 → H/A09.23 → J/A09.23 → 6/S5.10 → 10/S5.10 → 11/S5.10 → 7/S5.11 → A09.01 → A09.02 → A12.01 → 4/A09.26 → 7/S5.20 → A00.30 → A09.27 → A09.33
A68: EXT-PARAPET #164 - West perimeter jog (y=839.58, grid 2 to grid 3) -- PARAPET INFILL, from B.O.D. up to T/ STUD. Stud 6" 54mil 600S162-54 MST @ 16" O.C.; bracing 1-1/2" C.R. channel @ 48" O.C. (1 instance) | B68: 164 | C68: 3.89 | D68: 4.292 | E68: 0 | F68: 6" 54mil | G68: 7 | H68: =IF($F68="6""",$AL68,0) -> 0 | I68: =IF($F68="3-5/8""",$AL68,0) -> 0 | J68: =IF($F68="1-5/8""",$AL68,0) -> 0 | K68: =SUMIFS('Board by Face'!$I$5:$I$115,'Board by Face'!$A$5:$A$115,$B68) -> 0 | Q68: 3.89 | R68: 3.89 | S68: 3.89 | U68: 3.89 | W68: 16.7 | X68: 16.7 | AE68: 4 | AF68: 7.78 | AI68: none | AJ68: CLOSED | AK68: seal 9c62204d0618ecf0 | AL68: 30.04 | AP68: A02.01 → A/A09.21 → C/A09.21 → D/A09.22 → H/A09.23 → J/A09.23 → 6/S5.10 → 10/S5.10 → 11/S5.10 → 7/S5.11 → A09.01 → A09.02 → A12.01 → 4/A09.26 → 7/S5.20 → A00.30 → A09.27 → A09.33
A69: TYPE F
A70: F #40 - Wall inclinado 60 grados entre 24 HR VESTIBULE 101 (ATM LOBBY) y ATM ROOM 102. Stud 3-5/8" 362S137-33 MST @ 16" O.C.; bracing 1-1/2" C.R. channel @ 48" O.C. 24 HR VESTIBULE 101 (ATM LOBBY, lado publico): 1 layer(s) 5/8 GYP + 3/4 FRT PLYWOOD @ 15.375 FT | ATM ROOM 102: 1 layer(s) 5/8 GYP @ 9.000 FT (1 instance) | B70: 40 | C70: 17.762 | D70: 15.375 | E70: 2 | F70: 3-5/8" | G70: 24 | H70: =IF($F70="6""",$AL70,0) -> 0 | I70: =IF($F70="3-5/8""",$AL70,0) -> 369 | J70: =IF($F70="1-5/8""",$AL70,0) -> 0 | K70: =SUMIFS('Board by Face'!$I$5:$I$115,'Board by Face'!$A$5:$A$115,$B70) -> 418.91975 | Q70: 17.76 | R70: 17.76 | S70: 53.29 | U70: 21.41 | AA70: 262.37 | AF70: 71.05 | AG70: 3.58 | AH70: 3.58 | AI70: framed opening R.O. del ATM NHA 7800TC TTW WU (walk-up) 2.25 x 2.69 | AJ70: CLOSED | AK70: seal c822135c48c91fbe | AL70: 369 | AP70: A02.01 → 1/A08.11 → 5/A08.11 → 9/A08.11 → A04.01 → S2.20 → 12/A12.01 → A09.01 → 8/A12.06 → 9/A12.06 → 1/S5.20 → 4/S5.20 → 7/S5.20 → 9/S5.20 → A00.01 → A09.27 → A09.33
A71: TYPE G
A72: G #45 - Office 2 CL 106 / Office 3 SB 107. Stud 1-5/8" 162S-family MST @ 16" O.C. DOUBLE ROW (2 rows of stud); bracing 1-1/2" C.R. channel @ 48" O.C. Office 2 CL 106: 2 layer(s) 5/8 GYP x2 layers @ 15.375 FT | Office 3 SB 107: 2 layer(s) 5/8 GYP x2 layers @ 15.375 FT (1 instance) | B72: 45 | C72: 11.77 | D72: 15.375 | E72: 4 | F72: 1-5/8" | G72: 22 | H72: =IF($F72="6""",$AL72,0) -> 0 | I72: =IF($F72="3-5/8""",$AL72,0) -> 0 | J72: =IF($F72="1-5/8""",$AL72,0) -> 338.25 | K72: =SUMIFS('Board by Face'!$I$5:$I$115,'Board by Face'!$A$5:$A$115,$B72) -> 723.855 | Q72: 23.54 | R72: 23.54 | S72: 70.62 | U72: 4 | AB72: 101.52 | AF72: 47.08 | AI72: none | AJ72: CLOSED | AK72: seal c6e057cc76414ea0 | AL72: 338.25 | AP72: A02.01 → A04.01 → S2.20 → 6/A11.01 → 7/A11.04 → 5/A12.01 → 1/S5.20 → 7/S5.20 → 9/S5.20 → A09.01 → A00.01 → A09.27 → A09.33
A73: G #46 - Office 3 SB 107 / Office 4 CB 108. Stud 1-5/8" 162S-family MST @ 16" O.C. DOUBLE ROW (2 rows of stud); bracing 1-1/2" C.R. channel @ 48" O.C. Office 3 SB 107: 2 layer(s) 5/8 GYP x2 layers @ 15.375 FT | Office 4 CB 108: 2 layer(s) 5/8 GYP x2 layers @ 15.375 FT (1 instance) | B73: 46 | C73: 11.77 | D73: 15.375 | E73: 4 | F73: 1-5/8" | G73: 30 | H73: =IF($F73="6""",$AL73,0) -> 0 | I73: =IF($F73="3-5/8""",$AL73,0) -> 0 | J73: =IF($F73="1-5/8""",$AL73,0) -> 461.25 | K73: =SUMIFS('Board by Face'!$I$5:$I$115,'Board by Face'!$A$5:$A$115,$B73) -> 723.855 | Q73: 23.54 | R73: 23.54 | S73: 70.62 | U73: 4 | AB73: 101.52 | AD73: 12 | AF73: 47.08 | AI73: none | AJ73: CLOSED | AK73: seal a9d240d10ad50f93 | AL73: 461.25 | AP73: A02.01 → A04.01 → S2.20 → 5/A11.04 → 9/A11.04 → 5/A12.01 → 1/S5.20 → 6/S5.20 → 7/S5.20 → 9/S5.20 → A09.01 → A00.01 → A09.27 → A09.33 → M01.01
A74: G #48 - ATM Room 102 / Office 5 CB 109. Stud 1-5/8" 162S-family MST @ 16" O.C. DOUBLE ROW (2 rows of stud); bracing 1-1/2" C.R. channel @ 48" O.C. ATM Room 102: 2 layer(s) 5/8 GYP x2 layers @ 15.375 FT | Office 5 CB 109: 2 layer(s) 5/8 GYP x2 layers @ 15.375 FT (1 instance) | B74: 48 | C74: 11.625 | D74: 15.375 | E74: 4 | F74: 1-5/8" | G74: 26 | H74: =IF($F74="6""",$AL74,0) -> 0 | I74: =IF($F74="3-5/8""",$AL74,0) -> 0 | J74: =IF($F74="1-5/8""",$AL74,0) -> 399.75 | K74: =SUMIFS('Board by Face'!$I$5:$I$115,'Board by Face'!$A$5:$A$115,$B74) -> 714.9375 | Q74: 23.25 | R74: 23.25 | S74: 69.75 | U74: 4 | AD74: 6 | AF74: 46.5 | AI74: none | AJ74: CLOSED | AK74: seal a11bf7bf2f4fd70a | AL74: 399.75 | AP74: A02.01 → S2.20 → 16/A11.04 → 5/A12.01 → 1/S5.20 → 6/S5.20 → 7/S5.20 → 9/S5.20 → A09.01 → A00.01 → A09.27 → A09.33 → M01.01
A75: G #49 - Office 5 CB 109 / Office 6 CB 110. Stud 1-5/8" 162S-family MST @ 16" O.C. DOUBLE ROW (2 rows of stud); bracing 1-1/2" C.R. channel @ 48" O.C. Office 5 CB 109: 2 layer(s) 5/8 GYP x2 layers @ 15.375 FT | Office 6 CB 110: 2 layer(s) 5/8 GYP x2 layers @ 15.375 FT (1 instance) | B75: 49 | C75: 11.625 | D75: 15.375 | E75: 4 | F75: 1-5/8" | G75: 26 | H75: =IF($F75="6""",$AL75,0) -> 0 | I75: =IF($F75="3-5/8""",$AL75,0) -> 0 | J75: =IF($F75="1-5/8""",$AL75,0) -> 399.75 | K75: =SUMIFS('Board by Face'!$I$5:$I$115,'Board by Face'!$A$5:$A$115,$B75) -> 714.9375 | Q75: 23.25 | R75: 23.25 | S75: 69.75 | AB75: 200.54 | AD75: 6 | AF75: 46.5 | AI75: none | AJ75: CLOSED | AK75: seal f0693cf5177c3cea | AL75: 399.75 | AP75: A02.01 → A04.01 → S2.20 → 10/A11.03 → 14/A11.04 → 5/A12.01 → 1/S5.20 → 6/S5.20 → 7/S5.20 → 9/S5.20 → A09.01 → A00.01 → A09.27 → A09.33 → M01.01
A76: G #52 - Office 6 CB 110 / Women's Restroom 114 (SIN TAG, numero nuevo). Stud 1-5/8" 162S-family MST @ 16" O.C. DOUBLE ROW (2 rows of stud); bracing 1-1/2" C.R. channel @ 48" O.C. Office 6 CB 110: 2 layer(s) 5/8 GYP x2 layers @ 15.375 FT | Womens Restroom 114: 2 layer(s) 5/8 GYP x2 layers @ 15.375 FT (1 instance) | B76: 52 | C76: 11.625 | D76: 15.375 | E76: 4 | F76: 1-5/8" | G76: 30 | H76: =IF($F76="6""",$AL76,0) -> 0 | I76: =IF($F76="3-5/8""",$AL76,0) -> 0 | J76: =IF($F76="1-5/8""",$AL76,0) -> 461.25 | K76: =SUMIFS('Board by Face'!$I$5:$I$115,'Board by Face'!$A$5:$A$115,$B76) -> 714.9375 | L76: 52.31 | N76: 5.81 | Q76: 23.25 | R76: 23.25 | S76: 69.75 | U76: 9.67 | AD76: 12 | AF76: 46.5 | AI76: none | AJ76: CLOSED | AK76: seal 43721dd850e9c63f | AL76: 461.25 | AP76: A02.01 → 1/A08.01 → 8/A08.01 → C/A08.01 → A04.01 → S2.20 → 8/A11.03 → 5/A12.01 → 1/S5.20 → 6/S5.20 → 7/S5.20 → 9/S5.20 → A09.01 → A00.01 → A09.27 → A09.33 → M01.01
A77: G #47 - Office 4 CB 108 / teller line. Stud 1-5/8" 162S-family MST @ 16" O.C. DOUBLE ROW (2 rows of stud); bracing 1-1/2" C.R. channel @ 48" O.C. Office 4 CB 108: 2 layer(s) 5/8 GYP x2 layers @ 15.375 FT | Linea de teller: 2 layer(s) 5/8 GYP x2 layers @ 15.375 FT (1 instance) | B77: 47 | C77: 10.07 | D77: 15.375 | E77: 4 | F77: 1-5/8" | G77: 24 | H77: =IF($F77="6""",$AL77,0) -> 0 | I77: =IF($F77="3-5/8""",$AL77,0) -> 0 | J77: =IF($F77="1-5/8""",$AL77,0) -> 369 | K77: =SUMIFS('Board by Face'!$I$5:$I$115,'Board by Face'!$A$5:$A$115,$B77) -> 619.305 | Q77: 20.14 | R77: 20.14 | S77: 60.42 | AB77: 86.85 | AD77: 6 | AF77: 40.28 | AI77: none | AJ77: CLOSED | AK77: seal ae0af120fa3e5465 | AL77: 369 | AP77: A02.01 → A04.01 → S2.20 → 11/A11.04 → 5/A12.01 → 1/S5.20 → 6/S5.20 → 7/S5.20 → 9/S5.20 → A09.01 → A00.01 → A09.27 → A09.33 → M01.01
A78: G #42 - Return between the office fronts at 105 y 106. Stud 1-5/8" 162S-family MST @ 16" O.C. DOUBLE ROW (2 rows of stud); bracing 1-1/2" C.R. channel @ 48" O.C. Central Zone 103: 2 layer(s) 5/8 GYP x2 layers @ 15.375 FT | Offices 105-106: 2 layer(s) 5/8 GYP x2 layers @ 15.375 FT (1 instance) | B78: 42 | C78: 3.47 | D78: 15.375 | E78: 4 | F78: 1-5/8" | G78: 10 | H78: =IF($F78="6""",$AL78,0) -> 0 | I78: =IF($F78="3-5/8""",$AL78,0) -> 0 | J78: =IF($F78="1-5/8""",$AL78,0) -> 153.75 | K78: =SUMIFS('Board by Face'!$I$5:$I$115,'Board by Face'!$A$5:$A$115,$B78) -> 213.405 | Q78: 6.94 | R78: 6.94 | S78: 20.82 | AF78: 13.88 | AI78: none | AJ78: CLOSED | AK78: seal 64b6347a21c26f79 | AL78: 153.75 | AP78: A02.01 → S2.20 → 5/A12.01 → 1/S5.20 → 7/S5.20 → 9/S5.20 → A09.01 → A00.01 → A09.27 → A09.33
A79: G #43 - Return between the office fronts at 106 y 107. Stud 1-5/8" 162S-family MST @ 16" O.C. DOUBLE ROW (2 rows of stud); bracing 1-1/2" C.R. channel @ 48" O.C. Central Zone 103: 2 layer(s) 5/8 GYP x2 layers @ 15.375 FT | Offices 106-107: 2 layer(s) 5/8 GYP x2 layers @ 15.375 FT (1 instance) | B79: 43 | C79: 3.25 | D79: 15.375 | E79: 4 | F79: 1-5/8" | G79: 14 | H79: =IF($F79="6""",$AL79,0) -> 0 | I79: =IF($F79="3-5/8""",$AL79,0) -> 0 | J79: =IF($F79="1-5/8""",$AL79,0) -> 215.25 | K79: =SUMIFS('Board by Face'!$I$5:$I$115,'Board by Face'!$A$5:$A$115,$B79) -> 199.875 | Q79: 6.5 | R79: 6.5 | S79: 19.5 | AD79: 6 | AF79: 13 | AI79: none | AJ79: CLOSED | AK79: seal 2ff2b63919825b92 | AL79: 215.25 | AP79: A02.01 → S2.20 → 5/A12.01 → 1/S5.20 → 6/S5.20 → 7/S5.20 → 9/S5.20 → A09.01 → A00.01 → A09.27 → A09.33 → M01.01
A80: G #44 - Return between the office fronts at 107 y 108. Stud 1-5/8" 162S-family MST @ 16" O.C. DOUBLE ROW (2 rows of stud); bracing 1-1/2" C.R. channel @ 48" O.C. Central Zone 103: 2 layer(s) 5/8 GYP x2 layers @ 15.375 FT | Offices 107-108: 2 layer(s) 5/8 GYP x2 layers @ 15.375 FT (1 instance) | B80: 44 | C80: 3.25 | D80: 15.375 | E80: 4 | F80: 1-5/8" | G80: 10 | H80: =IF($F80="6""",$AL80,0) -> 0 | I80: =IF($F80="3-5/8""",$AL80,0) -> 0 | J80: =IF($F80="1-5/8""",$AL80,0) -> 153.75 | K80: =SUMIFS('Board by Face'!$I$5:$I$115,'Board by Face'!$A$5:$A$115,$B80) -> 199.875 | Q80: 6.5 | R80: 6.5 | S80: 19.5 | AF80: 13 | AI80: none | AJ80: CLOSED | AK80: seal 2a5975f6c813bee9 | AL80: 153.75 | AP80: A02.01 → S2.20 → 5/A12.01 → 1/S5.20 → 7/S5.20 → 9/S5.20 → A09.01 → A00.01 → A09.27 → A09.33
A81: G #41 - North return at the Office 1 ME 105 office front (UNTAGGED). Stud 1-5/8" 162S-family MST @ 16" O.C. DOUBLE ROW (2 rows of stud); bracing 1-1/2" C.R. channel @ 48" O.C. Central Zone 103: 2 layer(s) 5/8 GYP x2 layers @ 15.375 FT | Office 1 ME 105: 2 layer(s) 5/8 GYP x2 layers @ 15.375 FT (1 instance) | B81: 41 | C81: 2.42 | D81: 15.375 | E81: 4 | F81: 1-5/8" | G81: 8 | H81: =IF($F81="6""",$AL81,0) -> 0 | I81: =IF($F81="3-5/8""",$AL81,0) -> 0 | J81: =IF($F81="1-5/8""",$AL81,0) -> 123 | K81: =SUMIFS('Board by Face'!$I$5:$I$115,'Board by Face'!$A$5:$A$115,$B81) -> 148.83 | Q81: 4.84 | R81: 4.84 | S81: 14.52 | AF81: 9.68 | AI81: none | AJ81: CLOSED | AK81: seal 240a328ab2dda3de | AL81: 123 | AP81: A02.01 → S2.20 → 5/A12.01 → 1/S5.20 → 7/S5.20 → 9/S5.20 → A09.01 → A00.01 → A09.27 → A09.33
A82: TYPE G1
A83: G1 #50 - Office 1 ME 105 / Office 2 CL 106 (right block). Stud 1-5/8" 162S-family MST @ 16" O.C. DOUBLE ROW (2 rows of stud); bracing 1-1/2" C.R. channel @ 48" O.C. Office 1 ME 105: 2 layer(s) 5/8 GYP x2 layers @ 15.375 FT | Office 2 CL 106: 2 layer(s) 5/8 GYP x2 layers @ 15.375 FT (1 instance) | B83: 50 | C83: 11.77 | D83: 15.375 | E83: 4 | F83: 1-5/8" | G83: 30 | H83: =IF($F83="6""",$AL83,0) -> 0 | I83: =IF($F83="3-5/8""",$AL83,0) -> 0 | J83: =IF($F83="1-5/8""",$AL83,0) -> 461.25 | K83: =SUMIFS('Board by Face'!$I$5:$I$115,'Board by Face'!$A$5:$A$115,$B83) -> 723.855 | Q83: 23.54 | R83: 23.54 | S83: 70.62 | U83: 4 | AD83: 12 | AF83: 47.08 | AI83: none | AJ83: CLOSED | AK83: seal bc794c614f269517 | AL83: 461.25 | AP83: A02.01 → S2.20 → 4/A11.01 → 6/A11.03 → 15/A11.04 → 5/A12.01 → 6/S5.20 → 7/S5.20 → 9/S5.20 → A09.01 → A00.01 → A09.27 → A09.33 → M01.01 → P01.01
A84: G1 #51 - South return at the Office 5 CB 109 office front (left block). Stud 1-5/8" 162S-family MST @ 16" O.C. DOUBLE ROW (2 rows of stud); bracing 1-1/2" C.R. channel @ 48" O.C. Office 5 CB 109: 2 layer(s) 5/8 GYP x2 layers @ 15.375 FT | Area abierta al este del office front (Waiting 104): 2 layer(s) 5/8 GYP x2 layers @ 15.375 FT (1 instance) | B84: 51 | C84: 2.67 | D84: 15.375 | E84: 4 | F84: 1-5/8" | G84: 10 | H84: =IF($F84="6""",$AL84,0) -> 0 | I84: =IF($F84="3-5/8""",$AL84,0) -> 0 | J84: =IF($F84="1-5/8""",$AL84,0) -> 153.75 | K84: =SUMIFS('Board by Face'!$I$5:$I$115,'Board by Face'!$A$5:$A$115,$B84) -> 164.205 | Q84: 5.34 | R84: 5.34 | S84: 16.02 | AF84: 10.68 | AI84: none | AJ84: CLOSED | AK84: seal 5f1c942218aa57cf | AL84: 153.75 | AP84: A02.01 → S2.20 → 6/A11.03 → 15/A11.04 → 5/A12.01 → 7/S5.20 → 9/S5.20 → A09.01 → A00.01 → A09.27 → A09.33
A85: G1 #53 - South return at the Office 6 CB 110 office front, UNTAGGED (left block). Stud 1-5/8" 162S-family MST @ 16" O.C. DOUBLE ROW (2 rows of stud); bracing 1-1/2" C.R. channel @ 48" O.C. Office 6 CB 110: 2 layer(s) 5/8 GYP x2 layers @ 15.375 FT | Area abierta al este del office front (Waiting 104): 2 layer(s) 5/8 GYP x2 layers @ 15.375 FT (1 instance) | B85: 53 | C85: 2.67 | D85: 15.375 | E85: 4 | F85: 1-5/8" | G85: 10 | H85: =IF($F85="6""",$AL85,0) -> 0 | I85: =IF($F85="3-5/8""",$AL85,0) -> 0 | J85: =IF($F85="1-5/8""",$AL85,0) -> 153.75 | K85: =SUMIFS('Board by Face'!$I$5:$I$115,'Board by Face'!$A$5:$A$115,$B85) -> 164.205 | Q85: 5.34 | R85: 5.34 | S85: 16.02 | AF85: 10.68 | AI85: none | AJ85: CLOSED | AK85: seal 4fd0e58727f7b139 | AL85: 153.75 | AP85: A02.01 → S2.20 → 6/A11.03 → 15/A11.04 → 5/A12.01 → 7/S5.20 → 9/S5.20 → A09.01 → A00.01 → A09.27 → A09.33
A86: TOTAL - PARTITIONS | C86: =SUM(C5:C85) -> 881.143 | D86: =SUM(D5:D85) -> 832.821 | E86: =SUM(E5:E85) -> 134.2 | G86: =SUM(G5:G85) -> 1287 | H86: =SUM(H5:H85) -> 5486.56 | I86: =SUM(I5:I85) -> 3588.2 | J86: =SUM(J5:J85) -> 4547.72 | K86: =SUM(K5:K85) -> 15809.1 | L86: =SUM(L5:L85) -> 132.1 | M86: =SUM(M5:M85) -> 0 | N86: =SUM(N5:N85) -> 14.45 | ... AH86: =SUM(AH5:AH85) -> 65.09 | AL86: =SUM(AL5:AL85) -> 14595.82 | AM86: =SUM(AM5:AM85) -> 0 | AN86: =SUM(AN5:AN85) -> 2939.76 | AO86: =SUM(AO5:AO85) -> 101.07

Sheet Board by Face
A1: BOARD BY FACE - one row per face, because the two faces of a wall rarely share a height
A2: Board (SF) = Length x Height x Layers - Openings deducted. Every row reproduces the sealed closure for that face; the closure's own wording is in SOURCE.
A4: Wall # | B4: Type | C4: Face (room) | D4: Board type | E4: Length (LF) | F4: Height (FT) | G4: Layers | H4: Openings deducted (SF) | I4: Board (SF) | J4: SOURCE - closure wording
A5: 8 | B5: A1 | C5: Corridor 111 | D5: 5/8 GYP | E5: 17.06 | F5: 9 | G5: 1 | H5: 0 | I5: =E5*F5*G5-H5 -> 153.54 | J5: face oeste completa, Corridor 111: 17.06 x 9.00 = 153.54 SF. La door 118B NO se deduce porque su opening cae FUERA de este tramo (entre y=1326.36 y y=1386.36, en el quiebre contra el wall A5 #16); solo se carga aqui su header y sus jamb studs. Height: A04.01 da el tag ACT-4 con dimension impresa 8'-6" en CORRIDOR 111 y 3/A12.01 pone el edge of board 6" por encima del scheduled ceiling = 9.00 ft. Una layer de 5/8" gypsum board por face, fila A1 del schedule de 3/A12.01.
A6: 8 | B6: A1 | C6: Break Room 118 | D6: 5/8 GYP | E6: 2.91 | F6: 9 | G6: 1 | H6: 0 | I6: =E6*F6*G6-H6 -> 26.19 | J6: face este, zona Break Room 118: 2.91 x 9.00 = 26.22 SF. CORREGIDO 5-oct-2026: la face este se mide FACE TO FACE, no de eje a eje. El board de esta face arranca en el extremo norte del wall (y=1386.36) y MUERE en la face norte del primer wall tipo B (y=1438.80): 52.44 pt / 18 = 2.913 ft. Medir hasta el EJE del wall B (y=1442.46) metia 0.204 ft de board que no existe, porque ahi esta el nucleo del wall B; y ademas el cierre de B #18 YA arranca en x=1241.76, la face este de este wall, asi que contar hasta el eje duplicaba. Cielo ACT-5 con dimension impresa 8'-6" en A04.01 + los 6" de 3/A12.01 = 9.00 ft
A7: 8 | B7: A1 | C7: Electrical 120 | D7: 5/8 GYP | E7: 5.83 | F7: 12.82 | G7: 1 | H7: 0 | I7: =E7*F7*G7-H7 -> 74.7406 | J7: face este, zona Electrical 120: 5.83 x 12.82 = 74.78 SF. CORREGIDO 5-oct-2026: face to face entre los dos walls tipo B, y=1446.12 a y=1551.12 = 105.00 pt / 18 = 5.833 ft, que es EXACTAMENTE la dimension impresa 5'-10" de A02.01 (cadena en x=1277.76, ticks localizados descontando el sobretiro de punta de flecha de 6.72 pt, simetrico en los dos extremos). A04.01 le pone a ELECTRICAL 120 los key notes 1 y 10; el 1 es textual 'OPEN TO STRUCTURE ABOVE' y no hay tag ACT ni dimension de cielo: el board sube al DECK. B.O.D. interpolado en el extremo ALTO de la zona (y=1446.12 de A02.01 = y=1429.40 de S2.20) = 13.052 - (200.10/454.6) x 0.521 = 12.82 ft. Una layer de 5/8" gypsum board, fila A1 del schedule de 3/A12.01, que ademas manda el stud a UNDERSIDE OF STRUCTURE con continuous slip track.
A8: 8 | B8: A1 | C8: NER 121 | D8: 5/8 GYP | E8: 7.5 | F8: 12.69 | G8: 1 | H8: 0 | I8: =E8*F8*G8-H8 -> 95.175 | J8: face este, zona NER 121: 7.50 x 12.69 = 95.17 SF. CORREGIDO 5-oct-2026: face to face de la face sur del segundo wall B (y=1558.44) al extremo sur (y=1693.44) = 135.00 pt / 18 = 7.500 ft, que es EXACTAMENTE la dimension impresa 7'-6" de A02.01, misma cadena x=1277.76. A04.01 le pone a NER 121 los mismos key notes 1 y 10: OPEN TO STRUCTURE ABOVE, board al DECK. B.O.D. interpolado en el extremo ALTO de la zona (y=1558.44 de A02.01 = y=1541.72 de S2.20) = 13.052 - (312.42/454.6) x 0.521 = 12.69 ft. Una layer de 5/8" gypsum board, fila A1 del schedule de 3/A12.01.
A9: 1 | B9: A1 | C9: Central Zone 103 | D9: 5/8 GYP | E9: 16.42 | F9: 12 | G9: 1 | H9: 0 | I9: =E9*F9*G9-H9 -> 197.04 | J9: 16.42 LF x 12.00 ft x 1 layer = 197.04 SF = 197.04 SF. 5/8" gypsum board, una layer por face segun la fila A1 de 3/A12.01.
A10: 1 | B10: A1 | C10: Calling Cubes 122 | D10: 5/8 GYP | E10: 16.42 | F10: 9 | G10: 1 | H10: 0 | I10: =E10*F10*G10-H10 -> 147.78 | J10: 16.42 LF x 9.00 ft x 1 layer = 147.78 SF = 147.78 SF. 5/8" gypsum board, una layer por face segun la fila A1 de 3/A12.01.
A11: 5 | B11: A1 | C11: Calling Cubes 122 | D11: 5/8 GYP | E11: 15.23 | F11: 9 | G11: 1 | H11: 0 | I11: =E11*F11*G11-H11 -> 137.07 | J11: 15.23 LF x 9.00 ft x 1 layer = 137.07 SF = 137.07 SF. 5/8" gypsum board, una layer por face segun la fila A1 de 3/A12.01.
A12: 5 | B12: A1 | C12: Break Room 118 | D12: 5/8 GYP | E12: 15.23 | F12: 9 | G12: 1 | H12: 0 | I12: =E12*F12*G12-H12 -> 137.07 | J12: 15.23 LF x 9.00 ft x 1 layer = 137.07 SF = 137.07 SF. 5/8" gypsum board, una layer por face segun la fila A1 de 3/A12.01.
A13: 9 | B13: A1 | C13: Cash Window 116 | D13: 5/8 GYP | E13: 11.67 | F13: 9.5 | G13: 1 | H13: 23.33 | I13: =E13*F13*G13-H13 -> 87.535 | J13: 11.67 LF x 9.50 ft x 1 layer = 110.84 SF; menos la abertura 119 de 3.333 x 7.00 = 23.33 SF = 87.51 SF. 5/8" gypsum board, una layer por face segun la fila A1 de 3/A12.01.
A14: 9 | B14: A1 | C14: Work Room 119 | D14: 5/8 GYP | E14: 11.67 | F14: 9 | G14: 1 | H14: 23.33 | I14: =E14*F14*G14-H14 -> 81.7 | J14: 11.67 LF x 9.00 ft x 1 layer = 105.00 SF; menos la abertura 119 de 3.333 x 7.00 = 23.33 SF = 81.67 SF. 5/8" gypsum board, una layer por face segun la fila A1 de 3/A12.01.
A15: 6 | B15: A1 | C15: Cash Window 116 | D15: 5/8 GYP | E15: 5.5 | F15: 9.5 | G15: 1 | H15: 26.66 | I15: =E15*F15*G15-H15 -> 25.59 | J15: 5.50 LF x 9.50 ft x 1 layer = 52.25 SF; menos la abertura 118A de 3.333 x 8.00 = 26.66 SF = 25.59 SF. 5/8" gypsum board, una layer por face segun la fila A1 de 3/A12.01.
A16: 6 | B16: A1 | C16: Break Room 118 | D16: 5/8 GYP | E16: 5.5 | F16: 9 | G16: 1 | H16: 26.66 | I16: =E16*F16*G16-H16 -> 22.84 | J16: 5.50 LF x 9.00 ft x 1 layer = 49.50 SF; menos la abertura 118A de 3.333 x 8.00 = 26.66 SF = 22.84 SF. 5/8" gypsum board, una layer por face segun la fila A1 de 3/A12.01.
... A115: 53 | B115: G1 | C115: Area abierta al este del office front (Waiting 104) | D115: 5/8 GYP x2 layers | E115: 2.67 | F115: 15.375 | G115: 2 | H115: 0 | I115: =E115*F115*G115-H115 -> 82.1025 | J115: 2.670 LF x 15.375 ft de alto (a underside of structure, 5/A12.01) x 2 layers de 5/8" por face
C116: TOTAL BOARD (SF) | I116: =SUM(I5:I115) -> 15809.1

Sheet Ceilings & Soffits
A1: GYPSUM CEILINGS, SOFFITS AND DRIVE-UP CANOPY - separate tables, never mixed with partitions
A2: A soffit is BUILT: its labor and its material do not look like a flat ceiling's. ACT and open-to-deck areas are excluded and named on Clarifications.
A4: Group | B4: ID | C4: Element | D4: Height A.F.F. (FT) | E4: Area (SF) | F4: Board (SF) | G4: Furring Channel (LF) | H4: Carrying Channel (LF) | I4: Hanger Wire (LF) | J4: 3-5/8" Stud (LF) | K4: 3-5/8" Stud (pcs) | L4: Track (LF) | M4: Bracing (LF) | N4: Sheathing FRT Ply (SF) | O4: Corner Bead / Ceiling Trim (LF) | P4: Blocking (LF) | Q4: Access Panel (pcs) | R4: Status | S4: Seal | T4: Detail sequence (RCP → section → detail → schedule)
A5: CEILING GWB | B5: CIELO-70 | C5: VESTIBULE 100 | E5: 131.3 | F5: 131.3 | G5: 98.48 | H5: 32.83 | I5: 48.38 | Q5: 1 | R5: CLOSED | S5: 5bd1ec5d0fcc167b | T5: A04.01 → A02.01 → S2.20 → A12.01 → 3/A09.33 → 7/A09.33 → 10/A09.33
A6: CEILING GWB | B6: CIELO-71 | C6: 24 HR VESTIBULE 101 | E6: 163.92 | F6: 163.92 | G6: 122.94 | H6: 40.98 | I6: 59.12 | R6: CLOSED | S6: 0d32abc5f7c5bddf | T6: A04.01 → S2.20 → A12.01 → 3/A09.33 → 7/A09.33 → 10/A09.33
A7: CEILING GWB | B7: CIELO-72 | C7: WAITING 104 | E7: 510.8 | F7: 510.8 | G7: 383.1 | H7: 127.7 | I7: 140 | R7: CLOSED | S7: 11d7860858a6b528 | T7: A04.01 → S2.20 → A12.01 → 3/A09.33 → 7/A09.33 → 10/A09.33
A8: CEILING GWB | B8: CIELO-73 | C8: WOMEN'S RESTROOM 114 | E8: 76.75 | F8: 76.75 | G8: 57.56 | H8: 19.19 | I8: 34.38 | R8: CLOSED | S8: ef1501f9315bda5a | T8: A04.01 → A02.01 → S2.20 → A12.01 → 3/A09.33 → 7/A09.33 → 10/A09.33
A9: CEILING GWB | B9: CIELO-74 | C9: MEN'S RESTROOM 113 | E9: 76.17 | F9: 76.17 | G9: 57.13 | H9: 19.04 | I9: 34.38 | R9: CLOSED | S9: c795cff7ebb6a001 | T9: A04.01 → S2.20 → A12.01 → 3/A09.33 → 7/A09.33 → 10/A09.33
A10: SOFFIT | B10: SOFFIT-80 | C10: SOFFIT-80 | E10: 41 | F10: 41 | K10: 26 | L10: 61.7 | O10: 42.86 | P10: 12.01 | R10: CLOSED | S10: 190433897dc8f674 | T10: A04.01 → 9/A12.01 → 10/A09.33
A11: CANOPY | B11: CANOPY-81 | C11: CANOPY-81 | E11: 561.75 | J11: 427.25 | L11: 99.92 | M11: 131.48 | N11: 561.75 | R11: CLOSED | S11: fef35eab36b7ebbd | T11: A04.01 → A02.01 → D/A09.22 → F/A09.22 → A09.01 → A09.02 → A09.21 → 3/A09.26 → 7/A09.26 → 15/A09.27 → 16/A09.27 → 10/A09.33 → 7/S5.20
A12: CANOPY | B12: CANOPY-82 | C12: CANOPY-82 | E12: 474.22 | J12: 356.66 | L12: 87.17 | M12: 113.02 | N12: 474.22 | R12: CLOSED | S12: 37191aedb28a90bb | T12: A04.01 → A02.01 → D/A09.22 → F/A09.22 → A09.01 → A09.02 → A09.21 → 3/A09.26 → 7/A09.26 → 15/A09.27 → 16/A09.27 → 10/A09.33 → 7/S5.20
A13: CANOPY | B13: CANOPY-83 | C13: CANOPY-83 | E13: 230.61 | J13: 176.29 | L13: 123.12 | M13: 57.56 | N13: 230.61 | R13: CLOSED | S13: ecd9ed69f3bcb5e6 | T13: A04.01 → A02.01 → D/A09.22 → F/A09.22 → A09.01 → A09.02 → A09.21 → 3/A09.26 → 7/A09.26 → 15/A09.27 → 16/A09.27 → 10/A09.33 → 7/S5.20
A14: CANOPY | B14: CANOPY-84 | C14: CANOPY-84 | E14: 118.52 | J14: 91.27 | L14: 101.02 | N14: 118.52 | R14: CLOSED | S14: 82e1ba339408e9f8 | T14: A04.01 → A02.01 → D/A09.22 → F/A09.22 → A09.01 → A09.02 → A09.21 → 3/A09.26 → 7/A09.26 → 15/A09.27 → 16/A09.27 → 10/A09.33 → 7/S5.20
A15: CANOPY | B15: CANOPY-85 | C15: CANOPY-85 | E15: 383.28 | J15: 288.92 | L15: 411.24 | N15: 383.28 | R15: CLOSED | S15: 6337f0fad40bbc4c | T15: A04.01 → A02.01 → 1/A09.01 → 2/A09.02 → D/A09.22 → F/A09.22 → A09.21 → 3/A09.26 → 7/A09.26 → 15/A09.27 → 16/A09.27 → 7/S5.20
C16: TOTAL | D16: =SUM(D5:D15) -> 0 | E16: =SUM(E5:E15) -> 2768.32 | F16: =SUM(F5:F15) -> 999.94 | G16: =SUM(G5:G15) -> 719.21 | H16: =SUM(H5:H15) -> 239.74 | I16: =SUM(I5:I15) -> 316.26 | J16: =SUM(J5:J15) -> 1340.39 | K16: =SUM(K5:K15) -> 26 | ... Q16: =SUM(Q5:Q15) -> 1

Sheet Other Scope
A1: SCOPE THAT IS NOT A PARTITION - MEP penetrations, recessed fixture openings, misc
A2: Ground-up job: there is no Demolition Plan, so an MEP penetration is a FRAMED OPENING, not a patch. Every penetration was measured on its own - the 1/4-sheet threshold is never cumulative.
A4: Group | B4: ID | C4: Description | D4: Line item | E4: Qty | F4: Unit | G4: Seal
A5: MEP PENETRATIONS | B5: MEP | C5: MEP | D5: DEDUCCION_BOARD_MEP | E5: 38.36 | F5: SF | G5: 2ee850c5da7659b2
A6: MEP PENETRATIONS | B6: MEP | C6: MEP | D6: FRAMED_OPENING_MEP | E6: 43 | F6: LF | G6: 2ee850c5da7659b2
A7: MEP PENETRATIONS | B7: MEP | C7: MEP | D7: REFUERZO_STUD_MEP | E7: 18 | F7: pcs | G7: 2ee850c5da7659b2
A8: RECESSED FIXTURE OPENINGS | B8: HUECOS | C8: HUECOS | D8: FRAMED_OPENING_DIFUSOR | E8: 10.67 | F8: LF | G8: 7d8caa7409375969
A9: RECESSED FIXTURE OPENINGS | B9: HUECOS | C9: HUECOS | D9: FRAMED_OPENING_RANURA | E9: 112 | F9: LF | G9: 7d8caa7409375969
A10: RECESSED FIXTURE OPENINGS | B10: HUECOS | C10: HUECOS | D10: GYPSUM_EDGE_TRIM | E10: 122.67 | F10: LF | G10: 7d8caa7409375969
A11: RECESSED FIXTURE OPENINGS | B11: HUECOS | C11: HUECOS | D11: RETORNO_BOARD_RANURA | E11: PENDING | F11: LF | G11: no cuantificado - ver Pending Items
A12: MISC SCOPE | B12: LADDER-90 | C12: JANITOR CLOSET 112 (el marcador del key note 9 de A04.01 cae dentro del cuarto, en pt 960, 1541) | D12: BLOCKING_2X_FRT | E12: 6 | F12: LF | G12: 288a5526f7319968
A13: MISC SCOPE | B13: WR-92 | C13: WR-92 | D13: BOARD_REGULAR_A_RESTAR | E13: 100.8 | F13: SF | G13: 289e8bf1446af7d4
A14: MISC SCOPE | B14: WR-92 | C14: WR-92 | D14: BOARD_WR | E14: 100.8 | F14: SF | G14: 289e8bf1446af7d4
A15: MISC SCOPE | B15: PURLIN-97 | C15: Every wall running EAST-WEST that goes up to the deck: 21 walls, 189.08 LF de top track. | D15: PURLIN_1X1X1_16GA | E15: 141.81 | F15: LF | G15: 3c1e4b6e392a0e8b
A16: WET AREAS | B16: HUMEDA-93 | C16: JANITOR CLOSET 112, corner. El marcador del key note 6 del FINISH PLAN cae dentro del cuarto (pt 965.4, 1534.0) y su linea guia apunta al oeste, a pt x=913.7, que es la face interior del wall exterior oeste (x=911.88): el mop sink va en la esquina contra esa face. | D16: PVC INSIDE CORNER TRIM MOLDING | E16: 4 | F16: LF | G16: dbf3f948b58f6fc7
A17: WET AREAS | B17: HUMEDA-93 | C17: JANITOR CLOSET 112, corner. El marcador del key note 6 del FINISH PLAN cae dentro del cuarto (pt 965.4, 1534.0) y su linea guia apunta al oeste, a pt x=913.7, que es la face interior del wall exterior oeste (x=911.88): el mop sink va en la esquina contra esa face. | D17: CLEAR SEALANT | E17: PENDING | F17: LF | G17: no cuantificado - ver Pending Items
A18: WET AREAS | B18: HUMEDA-93 | C18: JANITOR CLOSET 112, corner. El marcador del key note 6 del FINISH PLAN cae dentro del cuarto (pt 965.4, 1534.0) y su linea guia apunta al oeste, a pt x=913.7, que es la face interior del wall exterior oeste (x=911.88): el mop sink va en la esquina contra esa face. | D18: FRP WC-3 | E18: PENDING | F18: SF | G18: no cuantificado - ver Pending Items
A19: WET AREAS | B19: HUMEDA-93 | C19: JANITOR CLOSET 112, corner. El marcador del key note 6 del FINISH PLAN cae dentro del cuarto (pt 965.4, 1534.0) y su linea guia apunta al oeste, a pt x=913.7, que es la face interior del wall exterior oeste (x=911.88): el mop sink va en la esquina contra esa face. | D19: PVC EDGE TRIM MOLDING | E19: PENDING | F19: LF | G19: no cuantificado - ver Pending Items
A20: WET AREAS | B20: HUMEDA-94 | C20: INSIDE face of the west exterior wall (#63) at the restroom runs 113 y 114 -- la wall de los inodoros | D20: BOARD_REGULAR_A_RESTAR | E20: 112.94 | F20: SF | G20: f075a0d59055f329
A21: WET AREAS | B21: HUMEDA-94 | C21: INSIDE face of the west exterior wall (#63) at the restroom runs 113 y 114 -- la wall de los inodoros | D21: BOARD_WR | E21: 112.94 | F21: SF | G21: f075a0d59055f329
A22: MILLWORK BLOCKING | B22: MWBLK-MW11 | C22: CASH WINDOW 116 | D22: BLOCKING | E22: 13.5 | F22: LF | G22: c919275b7d9ef7ac
A23: MILLWORK BLOCKING | B23: MWBLK-MW06A-2 | C23: JANITOR CLOSET 112 (east side) | D23: BLOCKING | E23: 8.22 | F23: LF | G23: 7558a389c353d1a6

Sheet Material Summary
A1: MATERIAL SUMMARY - NET / WASTE / PURCHASE, and purchase converted to real selling units
A2: Waste lives HERE, in its own column, never inside a takeoff quantity. Percentages and sheet/stick sizes come from Inputs - change them there.
A4: Material | B4: Unit | C4: Net | D4: Waste % | E4: Waste | F4: Purchase | G4: Selling unit | H4: Pieces to buy | I4: Where it comes from
A5: METAL FRAMING
A6: 6" metal stud 600S137-33 / -68 (LF of material) | B6: LF | C6: ='Partition Takeoff'!H86 -> 5486.56 | D6: =Inputs!$B$5 -> 0.15 | E6: =C6*D6 -> 822.984 | F6: =C6+E6 -> 6309.544 | G6: ="stick "&TEXT(Inputs!$B$10,"0")&" ft" -> stick 20 ft | H6: =CEILING(F6/Inputs!$B$10,1) -> 316 | I6: Partition Takeoff "6" Metal Stud (LF)". A12.01 PARTITION SCHEDULE gives A5 and B2 a 6" stud with 7-1/4" wall thickness; the exterior walls and B2K are 6" too
A7: 6" parapet infill stud 600S162-54 @ 16" O.C. (LF of material) | B7: LF | C7: =SUMIFS('Partition Takeoff'!$AL$5:$AL$85,'Partition Takeoff'!$F$5:$F$85,"6"" 54mil") -> 973.34 | D7: =Inputs!$B$5 -> 0.15 | E7: =C7*D7 -> 146.001 | F7: =C7+E7 -> 1119.341 | G7: ="stick "&TEXT(Inputs!$B$10,"0")&" ft" -> stick 20 ft | H7: =CEILING(F7/Inputs!$B$10,1) -> 56 | I7: Separate line from the 33 mil stud: 11/S5.10 PARAPET INFILL FRAMING calls the parapet "600S162-54 @ 16" W/ 600T125-54 TOP & BOT." - 54 mil and a 1-5/8" flange, a different product and a different price from the 600S137-33 of the wall below. The wall below stops at the deflection track on the perimeter beam (6/S5.10 and 10/S5.10)
A8: 3-5/8" metal stud 362S137-33 / -68 (LF of material) | B8: LF | C8: ='Partition Takeoff'!I86+'Ceilings & Soffits'!J16 -> 4928.59 | D8: =Inputs!$B$5 -> 0.15 | E8: =C8*D8 -> 739.2885 | F8: =C8+E8 -> 5667.8785 | G8: ="stick "&TEXT(Inputs!$B$10,"0")&" ft" -> stick 20 ft | H8: =CEILING(F8/Inputs!$B$10,1) -> 284 | I8: Partition Takeoff 3-5/8" column + Ceilings & Soffits 3-5/8" column (drive-up canopy)
A9: 1-5/8" metal stud (LF of material) | B9: LF | C9: ='Partition Takeoff'!J86 -> 4547.72 | D9: =Inputs!$B$5 -> 0.15 | E9: =C9*D9 -> 682.158 | F9: =C9+E9 -> 5229.878 | G9: ="stick "&TEXT(Inputs!$B$10,"0")&" ft" -> stick 20 ft | H9: =CEILING(F9/Inputs!$B$10,1) -> 262 | I9: Partition Takeoff "1-5/8" Metal Stud (LF)" - types G, G1 and the office-front bulkhead, double row
A10: Bottom track 6" | B10: LF | C10: =SUMIFS('Partition Takeoff'!$Q$5:$Q$85,'Partition Takeoff'!$F$5:$F$85,"6""") -> 293.04 | D10: =Inputs!$B$5 -> 0.15 | E10: =C10*D10 -> 43.956 | F10: =C10+E10 -> 336.996 | G10: ="run "&TEXT(Inputs!$B$11,"0")&" ft" -> run 10 ft | H10: =CEILING(F10/Inputs!$B$11,1) -> 34 | I10: Track follows the stud of its wall. SUMIFS over the Stud Size column of Partition Takeoff
A11: Bottom track 3-5/8" | B11: LF | C11: =SUMIFS('Partition Takeoff'!$Q$5:$Q$85,'Partition Takeoff'!$F$5:$F$85,"3-5/8""") -> 227.482 | D11: =Inputs!$B$5 -> 0.15 | E11: =C11*D11 -> 34.1223 | F11: =C11+E11 -> 261.6043 | G11: ="run "&TEXT(Inputs!$B$11,"0")&" ft" -> run 10 ft | H11: =CEILING(F11/Inputs!$B$11,1) -> 27 | I11: Partition Takeoff
A12: Parapet bottom track 600T125-54 (PAF to steel beam) | B12: LF | C12: =SUMIFS('Partition Takeoff'!$Q$5:$Q$85,'Partition Takeoff'!$F$5:$F$85,"6"" 54mil") -> 217.64 | D12: =Inputs!$B$5 -> 0.15 | E12: =C12*D12 -> 32.646 | F12: =C12+E12 -> 250.286 | G12: ="run "&TEXT(Inputs!$B$11,"0")&" ft" -> run 10 ft | H12: =CEILING(F12/Inputs!$B$11,1) -> 26 | I12: 11/S5.10: "600T125-54 TOP & BOT." with "PAFs SPACED AT 12" O.C. MAX." into the steel beam - not the Hilti anchor into concrete that the wall below uses
A13: Parapet top track 600T125-54 | B13: LF | C13: =SUMIFS('Partition Takeoff'!$R$5:$R$85,'Partition Takeoff'!$F$5:$F$85,"6"" 54mil") -> 217.64 | D13: =Inputs!$B$5 -> 0.15 | E13: =C13*D13 -> 32.646 | F13: =C13+E13 -> 250.286 | G13: ="run "&TEXT(Inputs!$B$11,"0")&" ft" -> run 10 ft | H13: =CEILING(F13/Inputs!$B$11,1) -> 26 | I13: 11/S5.10: "600T125-54 TOP & BOT.". No deflection track here - the deflection track is the one below, against the beam that moves
A14: Bottom track 1-5/8" | B14: LF | C14: =SUMIFS('Partition Takeoff'!$Q$5:$Q$85,'Partition Takeoff'!$F$5:$F$85,"1-5/8""") -> 285.97 | D14: =Inputs!$B$5 -> 0.15 | E14: =C14*D14 -> 42.8955 | F14: =C14+E14 -> 328.8655 | G14: ="run "&TEXT(Inputs!$B$11,"0")&" ft" -> run 10 ft | H14: =CEILING(F14/Inputs!$B$11,1) -> 33 | I14: Partition Takeoff
A15: Top / deflection track 6" | B15: LF | C15: =SUMIFS('Partition Takeoff'!$R$5:$R$85,'Partition Takeoff'!$F$5:$F$85,"6""") -> 293.04 | D15: =Inputs!$B$5 -> 0.15 | E15: =C15*D15 -> 43.956 | F15: =C15+E15 -> 336.996 | G15: ="run "&TEXT(Inputs!$B$11,"0")&" ft" -> run 10 ft | H15: =CEILING(F15/Inputs!$B$11,1) -> 34 | I15: Separate row from bottom track - never combined. Control: bottom + top = 2 runs per row of stud
A16: Top / deflection track 3-5/8" | B16: LF | C16: =SUMIFS('Partition Takeoff'!$R$5:$R$85,'Partition Takeoff'!$F$5:$F$85,"3-5/8""") -> 227.482 | D16: =Inputs!$B$5 -> 0.15 | E16: =C16*D16 -> 34.1223 | F16: =C16+E16 -> 261.6043 | G16: ="run "&TEXT(Inputs!$B$11,"0")&" ft" -> run 10 ft | H16: =CEILING(F16/Inputs!$B$11,1) -> 27 | I16: Partition Takeoff
A17: Top / deflection track 1-5/8" | B17: LF | C17: =SUMIFS('Partition Takeoff'!$R$5:$R$85,'Partition Takeoff'!$F$5:$F$85,"1-5/8""") -> 285.97 | D17: =Inputs!$B$5 -> 0.15 | E17: =C17*D17 -> 42.8955 | F17: =C17+E17 -> 328.8655 | G17: ="run "&TEXT(Inputs!$B$11,"0")&" ft" -> run 10 ft | H17: =CEILING(F17/Inputs!$B$11,1) -> 33 | I17: Partition Takeoff
A18: Track, ceilings / soffits / canopy | B18: LF | C18: ='Ceilings & Soffits'!L16 -> 884.17 | D18: =Inputs!$B$5 -> 0.15 | E18: =C18*D18 -> 132.6255 | F18: =C18+E18 -> 1016.7955 | G18: ="run "&TEXT(Inputs!$B$11,"0")&" ft" -> run 10 ft | H18: =CEILING(F18/Inputs!$B$11,1) -> 102 | I18: Ceilings & Soffits. On a soffit the track sits at the two ENDS of each stud and on the two side edges
A19: Bracing 1-1/2" C.R. channel @ 48" O.C. | B19: LF | C19: ='Partition Takeoff'!S86+'Ceilings & Soffits'!M16 -> 2557.43 | D19: =Inputs!$B$5 -> 0.15 | E19: =C19*D19 -> 383.6145 | F19: =C19+E19 -> 2941.0445 | G19: ="C.R. channel "&TEXT(Inputs!$B$16,"0")&" ft" -> C.R. channel 16 ft | H19: =CEILING(F19/Inputs!$B$16,1) -> 184 | I19: 7/S5.20 note F: "BRIDGING AND BRACING: 1 1/2" C.R. CHANNEL @ 48" O.C." with CONTINUOUS BRIDGING
A20: Additional head track at openings over 4'-0" wide | B20: LF | C20: ='Partition Takeoff'!AM86 -> 0 | D20: =Inputs!$B$5 -> 0.15 | E20: =C20*D20 -> 0 | F20: =C20+E20 -> 0 | G20: ="run "&TEXT(Inputs!$B$11,"0")&" ft" -> run 10 ft | H20: =CEILING(F20/Inputs!$B$11,1) -> 0 | I20: 2/S5.20 HEAD TRACK @ NON LOAD BRG: "ADD FULL LENGTH ADDL HEAD TRACK @ OPNG >4'-0"". A SECOND head track on every opening wider than 4 ft - the six 8'-0" GL-2 windows on walls 61 and 63. No door reaches 4 ft, so none of them carries it
A21: Header / metal stud box beam | B21: LF | C21: ='Partition Takeoff'!AG86 -> 221.86 | D21: =Inputs!$B$5 -> 0.15 | E21: =C21*D21 -> 33.279 | F21: =C21+E21 -> 255.139 | G21: ="stick "&TEXT(Inputs!$B$10,"0")&" ft" -> stick 20 ft | H21: =CEILING(F21/Inputs!$B$10,1) -> 13 | I21: Each opening with ITS OWN R.O. width + 1.333 ft bearing (8" each side). Includes the ATM metal stud box beam
A22: Sill track | B22: LF | C22: ='Partition Takeoff'!AH86 -> 65.09 | D22: =Inputs!$B$5 -> 0.15 | E22: =C22*D22 -> 9.7635 | F22: =C22+E22 -> 74.8535 | G22: ="run "&TEXT(Inputs!$B$11,"0")&" ft" -> run 10 ft | H22: =CEILING(F22/Inputs!$B$11,1) -> 8 | I22: Only openings WITH a sill: windows (B/GLAZING 6'-6"), the drive-up ATM, and the framed duct opening on wall 9. Doors carry header only
A23: Framed openings - MEP, light slots and diffusers | B23: LF | C23: =SUMIFS('Other Scope'!$E:$E,'Other Scope'!$D:$D,"FRAMED_OPENING_MEP")+SUMIFS('Other Scope'!$E:$E,'Other Scope'!$D:$D,"FRAMED_OPENING_RANURA")+SUMIFS('Other Scope'!$E:$E,'Other Scope'!$D:$D,"FRAMED_OPENING_DIFUSOR") -> 165.67 | D23: =Inputs!$B$5 -> 0.15 | E23: =C23*D23 -> 24.8505 | F23: =C23+E23 -> 190.5205 | G23: ="stick "&TEXT(Inputs!$B$10,"0")&" ft" -> stick 20 ft | H23: =CEILING(F23/Inputs!$B$10,1) -> 10 | I23: Other Scope. Ground-up job, so an MEP penetration is a framed opening, not a patch. Excludes the penetrations already inside walls 43, 46, 47, 48, 49, 50 and 52
A24: Stud reinforcement at MEP penetrations | B24: pcs | C24: =SUMIFS('Other Scope'!$E:$E,'Other Scope'!$D:$D,"REFUERZO_STUD_MEP") -> 18 | F24: =C24 -> 18 | G24: each | H24: =CEILING(F24,1) -> 18 | I24: Other Scope. One per stud the duct crosses. 6/S5.20 WEB PENETRATION limits the web hole and forbids cutting the flanges
A25: 3-5/8" stud, CSR soffit (pieces - length pending) | B25: pcs | C25: ='Ceilings & Soffits'!K16 -> 26 | F25: =C25 -> 26 | G25: each | H25: =CEILING(F25,1) -> 26 | I25: 10/A09.33 CSR soffit: 26 pieces at 16" O.C. BOTH ways. A09.33 labels the soffit framing "3 5/8" METAL STUD FRAMING AND TRACK @ 16" O.C." - size CONFIRMED, individual length PENDING. See Pending Items
A26: Purlin 1x1x1 16 ga, top track to deck | B26: LF | C26: =SUMIFS('Other Scope'!$E:$E,'Other Scope'!$D:$D,"PURLIN_1X1X1_16GA") -> 141.81 | D26: =Inputs!$B$5 -> 0.15 | E26: =C26*D26 -> 21.2715 | F26: =C26+E26 -> 163.0815 | G26: ="run "&TEXT(Inputs!$B$11,"0")&" ft" -> run 10 ft | H26: =CEILING(F26/Inputs!$B$11,1) -> 17 | I26: A09.33, top-track-to-deck detail: "1X1X1 16GA PURLIN, ACROSS MIN. (2) FLUTES" - needed wherever the deck flute runs PARALLEL to the track, because there is no valley to fasten into. 185.61 LF of top track on walls that run east-west and go to deck, at 0.75 LF of purlin per LF of track. The detail itself says VIF FLUTE DIRECTION, so the flute direction is DERIVED from the joist direction on S2.20 and declared on Clarifications. Exterior walls and the inclined wall 40 are not included - see Pending
A27: Furring channel (ceilings) | B27: LF | C27: ='Ceilings & Soffits'!G16 -> 719.21 | D27: =Inputs!$B$5 -> 0.15 | E27: =C27*D27 -> 107.8815 | F27: =C27+E27 -> 827.0915 | G27: ="hat channel "&TEXT(Inputs!$B$17,"0")&" ft" -> hat channel 12 ft | H27: =CEILING(F27/Inputs!$B$17,1) -> 69 | I27: Ceilings & Soffits
A28: Carrying channel (ceilings) | B28: LF | C28: ='Ceilings & Soffits'!H16 -> 239.74 | D28: =Inputs!$B$5 -> 0.15 | E28: =C28*D28 -> 35.961 | F28: =C28+E28 -> 275.701 | G28: ="C.R. channel "&TEXT(Inputs!$B$16,"0")&" ft" -> C.R. channel 16 ft | H28: =CEILING(F28/Inputs!$B$16,1) -> 18 | I28: Ceilings & Soffits
A29: Hanger wire | B29: LF | C29: ='Ceilings & Soffits'!I16 -> 316.26 | D29: =Inputs!$B$5 -> 0.15 | E29: =C29*D29 -> 47.439 | F29: =C29+E29 -> 363.699 | G29: continuous coil | H29: =CEILING(F29,1) -> 364 | I29: Length = B.O. Deck minus that zone's ceiling height. Bought as a continuous coil by gauge, never pre-cut
A30: Extra framing - sistered stud and furring at the ATM recess | B30: LF | C30: ='Partition Takeoff'!AD86 -> 109.87 | D30: =Inputs!$B$5 -> 0.15 | E30: =C30*D30 -> 16.4805 | F30: =C30+E30 -> 126.3505 | G30: ="stick "&TEXT(Inputs!$B$10,"0")&" ft" -> stick 20 ft | H30: =CEILING(F30/Inputs!$B$10,1) -> 7 | I30: 6/A08.11: 2-1/2" stud sistered to the 6" stud, and the furring under the fiber cement panel
A31: BOARD AND SUBSTRATE
A32: 5/8" gypsum board, regular | B32: SF | C32: ='Partition Takeoff'!K86+'Ceilings & Soffits'!F16-SUMIFS('Other Scope'!$E:$E,'Other Scope'!$D:$D,"BOARD_REGULAR_A_RESTAR") -> 16595.3 | D32: =Inputs!$B$6 -> 0.06 | E32: =C32*D32 -> 995.71799 | F32: =C32+E32 -> 17591.018 | G32: =TEXT(Inputs!$B$7,"0")&"x"&TEXT(Inputs!$B$8,"0")&" ft sheet" -> 4x12 ft sheet | H32: =CEILING(F32/Inputs!$B$9,1) -> 367 | I32: Partition Takeoff (fed face by face from Board by Face) + gypsum ceilings and the CSR soffit, MINUS the area that A08.01 sheet note F turns moisture-resistant
A33: 5/8" gypsum board, MOISTURE RESISTANT | B33: SF | C33: =SUMIFS('Other Scope'!$E:$E,'Other Scope'!$D:$D,"BOARD_WR") -> 213.74 | D33: =Inputs!$B$6 -> 0.06 | E33: =C33*D33 -> 12.8244 | F33: =C33+E33 -> 226.5644 | G33: =TEXT(Inputs!$B$7,"0")&"x"&TEXT(Inputs!$B$8,"0")&" ft sheet" -> 4x12 ft sheet | H33: =CEILING(F33/Inputs!$B$9,1) -> 5 | I33: A08.01 sheet note F: "USE MOISTURE RESISTANT GYPSUM BOARD BEHIND TOILET AND LAVATORY". TWO fixtures on TWO different walls: the LAVATORY side is the chase (walls 37 and 39, 100.80 SF) and the TOILET side is the inside face of the west exterior wall in both restrooms (112.94 SF). Reclassification, not new board - the same area comes out of the regular gypsum line
A34: 5/8" EXTERIOR gypsum sheathing (deck to top of parapet) | B34: SF | C34: ='Partition Takeoff'!W86 -> 783.89 | D34: =Inputs!$B$6 -> 0.06 | E34: =C34*D34 -> 47.0334 | F34: =C34+E34 -> 830.9234 | G34: =TEXT(Inputs!$B$7,"0")&"x"&TEXT(Inputs!$B$8,"0")&" ft sheet" -> 4x12 ft sheet | H34: =CEILING(F34/Inputs!$B$9,1) -> 18 | I34: H/A09.23, textual: "5/8" EXTERIOR GYPSUM SHEATHING". It is the INSIDE face of the parapet and it does not exist below the deck - a different material from the interior board, priced on its own line
A35: FRP WC-3 | B35: SF | C35: ='Partition Takeoff'!L86+SUMIFS('Other Scope'!$E:$E,'Other Scope'!$D:$D,"FRP WC-3") -> 132.1 | D35: =Inputs!$B$6 -> 0.06 | E35: =C35*D35 -> 7.926 | F35: =C35+E35 -> 140.026 | G35: =TEXT(Inputs!$B$7,"0")&"x"&TEXT(Inputs!$B$8,"0")&" ft sheet" -> 4x12 ft sheet | H35: =CEILING(F35/Inputs!$B$9,1) -> 3 | I35: Restrooms 113 / 114 up to 4'-6" (5'-0" to top of FRP minus the 6" cove base), plus the mop sink FRP of Janitor Closet 112 - that one is PENDING on width
A36: Cement board (substrate under the FRP cove base band) | B36: SF | C36: ='Partition Takeoff'!N86 -> 14.45 | D36: =Inputs!$B$6 -> 0.06 | E36: =C36*D36 -> 0.867 | F36: =C36+E36 -> 15.317 | G36: =TEXT(Inputs!$B$7,"0")&"x"&TEXT(Inputs!$B$8,"0")&" ft sheet" -> 4x12 ft sheet | H36: =CEILING(F36/Inputs!$B$9,1) -> 1 | I36: Carried under the 6" cove base band only - see Clarifications for exactly where
A37: Exterior sheathing 5/8" FRT plywood bonded to 2-1/2" polyiso | B37: SF | C37: ='Partition Takeoff'!X86 -> 3698.28 | D37: =Inputs!$B$6 -> 0.06 | E37: =C37*D37 -> 221.8968 | F37: =C37+E37 -> 3920.1768 | G37: =TEXT(Inputs!$B$7,"0")&"x"&TEXT(Inputs!$B$8,"0")&" ft sheet" -> 4x12 ft sheet | H37: =CEILING(F37/Inputs!$B$9,1) -> 82 | I37: H/A09.23, textual: "SHEATHING/INSULATION SYSTEM: 5/8" FRT PLYWOOD BONDED TO 2 1/2" POLYISO INSULATION"
A38: 5/8" glass mat sheathing (exterior face of the stud) | B38: SF | C38: ='Partition Takeoff'!AN86 -> 2939.76 | D38: =Inputs!$B$6 -> 0.06 | E38: =C38*D38 -> 176.3856 | F38: =C38+E38 -> 3116.1456 | G38: =TEXT(Inputs!$B$7,"0")&"x"&TEXT(Inputs!$B$8,"0")&" ft sheet" -> 4x12 ft sheet | H38: =CEILING(F38/Inputs!$B$9,1) -> 65 | I38: Found 3-Oct-2026 by following the detail chain. The 1"=1'-0" wall sections do not label this layer, but every detail they point to does: 5/A09.26 SECTION DETAIL @ ACM BASE and 9/A09.27 SECTION DETAIL @ METAL PANEL BASE label "5/8" GLASS MAT SHEATHING" with the arrow on the OUTSIDE face of the 6" metal stud, and 7/A09.26 repeats it at mid height ("SPRAY FOAM INSULATION ON 5/8" GLASS-MAT SHEATHING"). All 95 sheets were swept for "GLASS MAT" / "GLASS-MAT": it appears only on A09.26 and A09.27 and never above the deck, so it is carried slab to B.O.D. and does not continue up the parapet
A39: Gypsum board jamb return at openings | B39: SF | C39: ='Partition Takeoff'!AO86 -> 101.07 | D39: =Inputs!$B$6 -> 0.06 | E39: =C39*D39 -> 6.0642 | F39: =C39+E39 -> 107.1342 | G39: =TEXT(Inputs!$B$7,"0")&"x"&TEXT(Inputs!$B$8,"0")&" ft sheet" -> 4x12 ft sheet | H39: =CEILING(F39/Inputs!$B$9,1) -> 3 | I39: 11/A09.27 and 2/A09.26 SECTION DETAIL @ STOREFRONT HEAD, textual: "GYPSUM BOARD JAMB RETURN BEYOND"; 1/A09.25 and 2/A09.25 close it in plan with "5/8" GYPSUM BOARD" turning into the aluminum frame. The return WIDTH is not dimensioned on any of the four details - the 6" stud depth is used. See Clarifications
A40: Ballistic panel 3/8" UL752 | B40: SF | C40: ='Partition Takeoff'!Y86 -> 74 | D40: =Inputs!$B$6 -> 0.06 | E40: =C40*D40 -> 4.44 | F40: =C40+E40 -> 78.44 | G40: =TEXT(Inputs!$B$7,"0")&"x"&TEXT(Inputs!$B$8,"0")&" ft sheet" -> 4x12 ft sheet | H40: =CEILING(F40/Inputs!$B$9,1) -> 2 | I40: Types A1K and B2K - 4/A12.01, bullet-resistant assembly
A41: 3/8" gypsum board | B41: SF | C41: ='Partition Takeoff'!Z86 -> 57.04 | D41: =Inputs!$B$6 -> 0.06 | E41: =C41*D41 -> 3.4224 | F41: =C41+E41 -> 60.4624 | G41: =TEXT(Inputs!$B$7,"0")&"x"&TEXT(Inputs!$B$8,"0")&" ft sheet" -> 4x12 ft sheet | H41: =CEILING(F41/Inputs!$B$9,1) -> 2 | I41: A1K / B2K: 3/8" gyp above the ballistic panel, 4/A12.01
A42: FRT plywood substrate | B42: SF | C42: ='Partition Takeoff'!AA86 -> 647.95 | D42: =Inputs!$B$6 -> 0.06 | E42: =C42*D42 -> 38.877 | F42: =C42+E42 -> 686.827 | G42: =TEXT(Inputs!$B$7,"0")&"x"&TEXT(Inputs!$B$8,"0")&" ft sheet" -> 4x12 ft sheet | H42: =CEILING(F42/Inputs!$B$9,1) -> 15 | I42: Type F 3/4" FRT plywood (12/A12.01), backboards, and the 5/8" FRT plywood in the ATM recess
A43: Level 5 finish | B43: SF | C43: ='Partition Takeoff'!AB86 -> 490.43 | D43: =Inputs!$B$6 -> 0.06 | E43: =C43*D43 -> 29.4258 | F43: =C43+E43 -> 519.8558 | G43: =TEXT(Inputs!$B$7,"0")&"x"&TEXT(Inputs!$B$8,"0")&" ft sheet" -> 4x12 ft sheet | H43: =CEILING(F43/Inputs!$B$9,1) -> 11 | I43: Where the Finish Schedule calls for it. Board only - the coating is Div 09 90 00
A44: 5/8" FRT plywood sheathing (canopy and soffits) | B44: SF | C44: ='Ceilings & Soffits'!N16 -> 1768.38 | D44: =Inputs!$B$6 -> 0.06 | E44: =C44*D44 -> 106.1028 | F44: =C44+E44 -> 1874.4828 | G44: =TEXT(Inputs!$B$7,"0")&"x"&TEXT(Inputs!$B$8,"0")&" ft sheet" -> 4x12 ft sheet | H44: =CEILING(F44/Inputs!$B$9,1) -> 40 | I44: 15 and 16/A09.27: "5/8" EXT. GRADE FRT PLYWOOD SHEATHING ON 3 5/8" METAL STUD FRAMING"
A45: TRIM AND ACCESSORIES
A46: METAL trim - corner bead, casing bead, shadow molding, gypsum edge trim | B46: LF | C46: ='Partition Takeoff'!AC86+'Ceilings & Soffits'!O16+SUMIFS('Other Scope'!$E:$E,'Other Scope'!$D:$D,"GYPSUM_EDGE_TRIM") -> 514.77 | D46: =Inputs!$B$5 -> 0.15 | E46: =C46*D46 -> 77.2155 | F46: =C46+E46 -> 591.9855 | G46: ="trim stick "&TEXT(Inputs!$B$18,"0")&" ft" -> trim stick 10 ft | H46: =CEILING(F46/Inputs!$B$18,1) -> 60 | I46: Partition Takeoff trim column + Ceilings & Soffits corner bead + the gypsum edge trim of the recessed light slots. CARRIES 15% WASTE because it is METAL trim cut to length, the same as track - not a box item.
A47: PVC trim - edge trim molding and inside corner molding at the FRP | B47: LF | C47: =SUMIFS('Other Scope'!$E:$E,'Other Scope'!$D:$D,"PVC EDGE TRIM MOLDING")+SUMIFS('Other Scope'!$E:$E,'Other Scope'!$D:$D,"PVC INSIDE CORNER TRIM MOLDING") -> 4 | D47: =Inputs!$B$6 -> 0.06 | E47: =C47*D47 -> 0.24 | F47: =C47+E47 -> 4.24 | G47: ="trim stick "&TEXT(Inputs!$B$18,"0")&" ft" -> trim stick 10 ft | H47: =CEILING(F47/Inputs!$B$18,1) -> 1 | I47: SPLIT OUT 11-Oct-2026. These two were riding inside the metal trim line and taking 15%. They are PVC, not metal - 3/A08.01 RESTROOM FRP/TILE DETAIL and 5 and 7/A08.01 label them "PVC EDGE TRIM MOLDING" and "PVC INSIDE CORNER TRIM MOLDING" - so under the standing rule they take the same percentage as the board, 6%. Today the difference is pennies (4.00 LF carried, the mop sink run still PENDING), but mixing two waste classes in one row is how the error grows silently the day the PENDING figure comes in.
A48: Power-driven fasteners and duct sleeves | B48: pcs | C48: ='Partition Takeoff'!AE86 -> 239 | F48: =C48 -> 239 | G48: each | H48: =CEILING(F48,1) -> 239 | I48: 4/A12.01: "POWER DRIVEN FASTENERS @ 2'-0" O.C. ALTERNATING SIDES AND WITHIN 3" OF EACH END OF TRACK"
A49: Blocking FRT / 2X FRT wood | B49: LF | C49: ='Partition Takeoff'!U86+'Ceilings & Soffits'!P16+SUMIFS('Other Scope'!$E:$E,'Other Scope'!$D:$D,"BLOCKING_2X_FRT")+SUMIFS('Other Scope'!$E:$E,'Other Scope'!$D:$D,"BLOCKING") -> 748 | D49: =Inputs!$B$6 -> 0.06 | E49: =C49*D49 -> 44.88 | F49: =C49+E49 -> 792.88 | G49: LF | H49: =CEILING(F49,1) -> 793 | I49: Accessory by accessory, each one its own length + 8" bearing each side (A08.01 sheet note E), plus the roof-hatch ladder blocking of 3/A09.30, plus the MILLWORK BLOCKING block of Other Scope: MW11 (13.50 LF) and the second MW06A (8.22 LF), the two that the wall-by-wall sweep could not pick up
A50: Acoustical sealant | B50: LF | C50: ='Partition Takeoff'!AF86 -> 2652.66 | D50: =Inputs!$B$6 -> 0.06 | E50: =C50*D50 -> 159.1596 | F50: =C50+E50 -> 2811.8196 | G50: tube | H50: =CEILING(F50/Inputs!$B$15,1) -> 113 | I50: Partition Takeoff. Converted to tubes at the coverage set on Inputs. WASTE 11-Oct-2026: carried at 6%. It is a LENGTH measured off the plan, run by run, not a yield figure, and the standing rule says everything that is not metal takes the same percentage as the board. Before today it carried none, which is why it was the only plan-measured material in the book buying exactly its net.
A51: Access panel 2'x2' | B51: pcs | C51: ='Ceilings & Soffits'!Q16 -> 1 | F51: =C51 -> 1 | G51: each | H51: =CEILING(F51,1) -> 1 | I51: A04.01 key note 4: "2' X 2' LOCKING ACCESS PANEL. KEYED TO MATCH MAIN ENTRY" - marker only in Vestibule 100
A52: TAPING, FASTENERS AND INSTALLATION ACCESSORIES
A53: Drywall screws 1-1/4" bugle head | B53: pcs | C53: =(C32+C33+C41)*Inputs!$B$20 -> 20239.296 | F53: =C53 -> 20239.296 | G53: each | H53: =CEILING(F53,1) -> 20240 | I53: RENDIMIENTO, no viene del plano: screws por SF de board, celda B20 de Inputs. Por defecto 1.2/SF, que es lo que da GA-216 con campo a 12" O.C. y perimetro a 8" sobre framing a 16" O.C. Aplica al board interior (regular + W.R. + 3/8")
A54: Framing screws, pan head self-drilling | B54: pcs | C54: =CEILING((C6+C8+C9)/Inputs!$B$10,1)*Inputs!$B$21 -> 2996 | F54: =C54 -> 2996 | G54: each | H54: =CEILING(F54,1) -> 2996 | I54: RENDIMIENTO: screws por pieza de stud, celda B21 de Inputs. Por defecto 4 = 2 por union stud-track en cada extremo
A55: Power-driven fasteners, slab pins for the bottom track | B55: pcs | C55: =(C10+C11+C14)/Inputs!$B$22*1 -> 403.246 | F55: =C55 -> 403.246 | G55: each | H55: =CEILING(F55,1) -> 404 | I55: RENDIMIENTO: espaciamiento de los pines, celda B22 de Inputs. Por defecto 2 ft, que es lo que pide 4/A12.01: "POWER DRIVEN FASTENERS @ 2'-0" O.C. ALTERNATING SIDES". Solo el bottom track; el top va atornillado a la estructura
A56: Joint compound, all purpose | B56: lb | C56: =(C32+C33+C41)*Inputs!$B$23 -> 1214.3577 | F56: =C56 -> 1214.3577 | G56: lb | H56: =CEILING(F56,1) -> 1215 | I56: RENDIMIENTO: libras por SF de board, celda B23 de Inputs. Por defecto 0.072 = 72 lb por cada 1,000 SF, el consumo tipico de un acabado nivel 4
A57: Joint tape, paper | B57: LF | C57: =(C32+C33+C41)*Inputs!$B$24 -> 6240.4495 | F57: =C57 -> 6240.4495 | G57: LF | H57: =CEILING(F57,1) -> 6241 | I57: RENDIMIENTO: LF de tape por SF de board, celda B24 de Inputs. Por defecto 0.37 = 370 LF por cada 1,000 SF
A59: Every figure above is a formula. Nothing on this sheet is typed in.
A60: The five accessory lines are YIELDS, not drawing quantities: they are marked DERIVED, each one names the yield it used, and the yield lives in a yellow Inputs cell so you can set your own.

Sheet Clarifications
A1: CLARIFICATIONS & EXCLUSIONS - part of the bid, never omitted
A3: # | B3: Subject | C3: Statement
A4: A. SCOPE OF THIS PROPOSAL
A5: 2 | B5: Divisions included | C5: CSI Division 05 40 00 Cold-Formed Metal Framing and Division 09 20 00 / 09 29 00 Gypsum Board Assemblies only. Metal framing, gypsum board and the substrates the drywall trade installs.
A6: 3 | B6: New construction | C6: Ground-up building: the set has NO Demolition Plan. Every partition, ceiling and soffit priced here is new work. No patch-and-repair allowance is carried, and none is needed.
A7: 4 | B7: Quantities are net | C7: All takeoff quantities are NET. Waste is shown separately on Material Summary at 15% on metal and 6% on board, applied by type, and is NOT buried inside any takeoff figure.
A8: 5 | B8: Board sheet size | C8: Purchase quantities convert at the sheet size set on the Inputs tab (currently 4 ft x 12 ft). Change it there and every piece count re-rounds up automatically.
A9: B. WHAT IS EXCLUDED, AND WHY
A10: 7 | B10: Insulation - EXCLUDED by instruction | C10: Excluded at the estimator's instruction, not because the drawings omit it. The set DOES call for it: H/A09.23 labels "SPRAY FOAM INSULATION" in the 6" CFMF cavity and "MIN. 6" RIGID INSULATION ABOVE ROOF DECK", and A04.01 key note 11 reads "INSTALL SOUND BATT INSULATION ABOVE CEILING". Add on request. NOTE: the 2-1/2" polyiso IS carried, because H/A09.23 specifies it as "5/8" FRT PLYWOOD BONDED TO 2 1/2" POLYISO INSULATION" - it arrives bonded to the sheathing we install and cannot be separated from it.
A11: 8 | B11: Aluminum storefront - Div 08, 48.14 LF | C11: ALUMINUM STOREFRONT SYSTEM AF-2 with GL-2 glazing and the entrance doors are Division 08 43 13. A02.01 note E and the A09.01 legend confirm it. Its length is measured and declared here (41.64 LF north + 6.50 LF west) so the reviewer can see it was not overlooked - but no material is carried for it.
A12: 9 | B12: Office front DFC-1A - Div 08 | C12: A02.01 note E, textual: "ALLSTEEL OFFICE FRONT SYSTEM: DFC-1A ASPECT. ORDERED BY GC. FURNISHED AND INSTALLED BY BANK VENDOR." Excluded. The gypsum bulkhead ABOVE it (walls 54 and 55) IS carried, because that is framing and board.
A13: 10 | B13: Metal wall panel and coping - Div 07 | C13: FORMED METAL WALL PANEL EPS-1 / EPS-3 / EPS-5, the 7/8" hat channel that comes with that system, the continuous vapor-permeable AWB and the ACM coping are Division 07 42 13 / 07 27 00. Our work stops at the sheathing.
A14: 11 | B14: Portland cement plaster on the canopy - Div 09 24 00 | C14: "5/8" PORTLAND CEMENT PLASTER SYSTEM (PT-4) ON (2) LAYERS GRADE 'D' BUILDING PAPER" (15 and 16/A09.27) is the plasterer's, with its own lath and its SA-2 / SA-4 screeds. We carry the 3-5/8" metal stud framing and the 5/8" FRT plywood sheathing underneath it.
A15: 12 | B15: Acoustical ceiling tile and grid - Div 09 51 00 | C15: ACT-4 / ACT-5 suspended tile and grid are excluded. Only GYPSUM ceilings are carried: 5 of them, 958.94 SF. Areas marked "OPEN TO STRUCTURE ABOVE" (A04.01 key note 1) carry no ceiling at all.
A16: 13 | B16: ATM surrounds, plinths and bollards | C16: The ATM SURROUND comes with the equipment - the ATM EQUIPMENT PURCHASE ORDER FORM on A08.11 assigns surround "FRAME-R-SUR-54-SINGLE-STD-NG_3.0" to the drive-up unit. The plinths are FRT wood carpentry (Div 06): "(2) LAYERS 3/4" FRT PLYWOOD PLINTH", "2X4 FRT PERIMETER FRAMING", "4X4 FRT FRAMING". The bollards are miscellaneous metals. All excluded. What IS carried is the metal stud box beam over the opening, the 2-1/2" studs sistered to the 6" studs, and the FRT plywood and furring in the recess.
A17: 14 | B17: Fiber cement panel at the drive-up ATM - Div 07 | C17: 6/A08.11 reads "FIBER CEMENT PANEL ON FURRING ON 5/8" FRT PLYWOOD". The panel is a facade product and is not in the A09.01 / A09.02 exterior material legend alongside the finishes others are already pricing - it is carried with the rainscreen. The substrate under it (furring and 5/8" FRT plywood) IS ours and IS quantified.
A18: 15 | B18: Bridging clips | C18: No clips are carried. 7/S5.20 TYPICAL STUD FASTENER SCHEDULE resolves bracing with screws ("DIAGONAL BRACING TO STUD: 1/2" #8 TEKS LOW, 1 @ EACH STUD") and lists no bridging clip; sub-detail 1/S5.20 sub-detalle F of S5.20 calls WELD at each stud crossing. Welding is priced in the labor. If the field requires clips instead, they are a priced alternate.
A19: 16 | B19: Openings - how they are treated in this takeoff | C19: BOARD is NET: every door, window and equipment rough opening is deducted, face by face, at its R.O. width x height x the faces and layers of that wall. 673.54 SF are deducted across the 23 openings of 14 walls, and each deduction is written in the wall it belongs to, never as a lump sum. METAL is NOT deducted: the stud run is continuous over and under an opening, and on top of the field studs each opening ADDS 2 studs per jamb plus cripples above and below a window (a door gets no cripples - it has no sill). Two openings deduct ZERO board on purpose and the reason is in their closure: door 118B falls in the jog BETWEEN walls 8 and 16, where neither wall has board to deduct, and the 8" duct sleeve on wall 9 is 1.00 SF - a cut, not a removed sheet. Storefront and office-front openings are not deducted either, because those runs carry no board at all (Div 08).
A20: 17 | B20: Taping, fasteners and installation accessories - INCLUDED, by YIELD | C20: Drywall screws, framing screws, power-driven pins, joint compound and joint tape ARE carried. None of them is a drawing quantity - the drawings do not count screws - so each one is DERIVED from a stated yield, and every yield sits in its own yellow Inputs cell so you can set your own: 1.2 drywall screws per SF of board (GA-216 field 12" O.C., perimeter 8" O.C. over framing at 16" O.C.), 4 framing screws per stud piece (2 per stud-to-track connection at each end), power-driven pins at 2'-0" O.C. on the bottom track only - the figure 4/A12.01 calls out - 0.072 lb of joint compound per SF and 0.37 LF of tape per SF (72 lb and 370 LF per 1,000 SF, typical level 4). Corner bead, casing bead, shadow molding and gypsum edge trim are quantified from the details and carried on the Trim line, not by yield. Change any yield on Inputs and the purchase figure re-rounds.
A21: 18 | B21: Purlin at the top track - INCLUDED, flute direction V.I.F. | C21: A09.33 details the top track fastening to the steel deck and rules, textual: "STL TRACK, CL TO BE BETWEEN ATTACHED FLUTES, NO EXCEPTION" and "1X1X1 16GA PURLIN, ACROSS MIN. (2) FLUTES". Where the deck flute runs PARALLEL to the track there is no valley to fasten into, so a 16 ga purlin spanning at least two flutes is required and the fastener goes through it. 139.21 LF are carried, from the 185.61 LF of top track on walls that run east-west and go to deck. Flute direction is DERIVED: Type B deck spans between joists, and the joists on S2.20 run north-south, so the flutes run east-west. The detail itself says "ALTERNATE CEILING DETAIL, VIF FLUTE DIRECTION", so this is verified in the field before ordering; if the flutes run the other way the purlin moves to the north-south walls (131.43 LF of track) and the figure changes. Exterior walls and the inclined wall 40 are NOT included and are named on Pending Items.
... A24: 21 | B24: Wet areas - every room with a plumbing fixture, and what board it gets | C24: Four rooms in this building have a plumbing fixture and each one was checked against THREE sources: the toilet-room sheet notes (what board type is required), the Finish Plan and its key notes (what wall finish each room gets), and the plumbing drawings (where the water actually is). RESTROOMS 113 and 114: FRP WC-3 to 4'-6", ceramic cove base, and moisture-resistant gypsum board behind BOTH fixtures - the lavatory side is the chase and the toilet side is the inside face of the west exterior wall, 213.74 SF of W.R. in total. JANITOR CLOSET 112: FRP from floor to 4'-0" on both walls at the mop sink corner, per Finish Plan key note 6 and 5/A08.01 - height confirmed, width pending the fixture size. BREAK ROOM 118: has a break sink but the drawings call for no wet-wall finish - see Pending Items. The W.R. board is a RECLASSIFICATION, not new board: the same area comes out of the regular gypsum line, and it changes the price because each board type carries its own waste.
A25: C. CONDITIONS AND ASSUMPTIONS THAT AFFECT THE PRICE
A26: 23 | B26: Stud height to underside of structure | C26: Interior partitions run to the deck at 15'-4 1/2" north of grid B (S2.20, T/STEEL, NO SLOPE). South of grid B the deck slopes 1/4" per foot from 13'-0 5/8" down to 12'-6 3/8"; walls in that zone are priced at the interpolated height stated on each row. Exterior studs run from slab to T.O. PARAPET 1 at 17'-9".
A27: 24 | B27: Gypsum board height differs from stud height on the exterior wall | C27: H/A09.23 reads "5/8" GYP. BOARD @ PERIMETER EXTERIOR WALL TO DECK" - the interior face stops at the deck, not the parapet. The strip from deck to top of parapet is "5/8" EXTERIOR GYPSUM SHEATHING" and is carried on its own line. Pricing both to the parapet would have overstated the interior board.
A28: 25 | B28: Cementitious backer - where it IS and where it is NOT carried | C28: Cement board is carried ONLY under the 6" cove-base band at the bottom of the FRP walls (14.46 SF, which is 0.50 ft of the 5.00 ft FRP height). It is NOT carried behind the full height of the FRP: the wall types draw the FRP directly on gypsum board and no detail calls for a backer behind it. Trade practice would put a cementitious backer behind the whole wet area; if the owner wants that, it is roughly 130 SF more and is offered as a priced alternate rather than assumed. Stated plainly here so the scope is not read either way by accident.
A29: 26 | B29: Ceiling perimeter sealant - RFI | C29: A04.01 does not label perimeter sealant at gypsum ceilings and no ceiling detail draws it. None is carried. Confirm before award.
A30: 27 | B30: Exterior elevation titles are swapped - RFI | C30: The titles of 1/A09.01 and 2/A09.02 are crossed. The grid bubble order proves it: the sheet titled "SOUTH ELEVATION" runs grids 8 to 1 left to right, which is the NORTH facade, and it carries the entrance storefront that sits at the top of the plan; the one titled "NORTH ELEVATION" runs 1 to 8 and carries egress door EXPT-1, which is at the bottom of the plan. Quantities here follow the GRIDS, not the titles. Confirm before award.
A31: 28 | B31: Drive-up canopy fascia does not run over the building | C31: 2/A09.02 (the real SOUTH facade) shows the canopy only between grids 1 and 3; from grid 3 east the wall runs straight up to the parapet. The 56.13 LF of fascia that a plan-only reading would have carried over the building footprint DOES NOT EXIST and is not billed. Geometry confirms it independently: the edge-weight line at that location stops at grid 3 and the line that continues is a lighter paving edge.
A32: 29 | B32: Wall type F, ATM lobby side | C32: The ATM ROOM 102 face of the inclined wall stops at 9'-0" (ACT-5 at 8'-6" plus 6"), not at the deck. Carrying it to 15.375 ft would have inflated that face's board by 71%.
A33: 30 | B33: Face-by-face board | C33: Board is quantified FACE BY FACE, not "both sides". Where one side of a wall faces several rooms at different ceiling heights, each room is its own row on the Board by Face tab with its own length and height. The room name on each row is what defines the side.
A34: 31 | B34: Field verification | C34: All dimensions were taken from the vector geometry of the PDF at the sheet's own printed scale and cross-checked against the printed dimension strings. Where a printed dimension exists it governs. Final dimensions to be verified in the field before fabrication.
A35: 32 | B35: Ceiling transition at gypsum-to-ACT edges - NOT CARRIED, see Pending | C35: 7/A09.33 TYPICAL CEILING TRANSITION DETAIL (3"=1'-0") draws a 6" gypsum transition wherever a gypsum ceiling meets a scheduled ceiling at a different height: "3 5/8" METAL STUD KICKER AT 48" O.C. ATTACH TO STRUCTURE ABOVE", "5/8" GYPSUM BOARD", "CORNER BEAD - TYPICAL" both sides and "SHADOW MOLDING AS SPECIFIED". The five gypsum ceilings have 167.68 LF of perimeter in total. How much of that perimeter dies against a wall or storefront (no transition) versus against an ACT ceiling at another height (transition) is NOT carried in this price and has to be confirmed edge by edge on A04.01. Per LF it would add 1.00 SF of board (6" on two faces), one kicker every 4 ft, two runs of corner bead and one run of shadow molding.
A36: D. WHAT IS INCLUDED THAT IS EASY TO MISS
A37: 34 | B37: Restroom scope on the exterior wall | C37: The inside face of the west exterior wall is the toilet wall of restrooms 113 and 114. It carries 25.33 LF of FRT blocking (A08.01 sheet note E, accessory by accessory), 66.44 SF of FRP WC-3 and its cement board. Restroom 113 does NOT get the TA-9 sanitary napkin disposal: the A08.01 TOILET ACCESSORY LEGEND gives it LOCATION "WOMEN" only.
A38: 35 | B38: Blocking for everything that hangs | C38: Blocking is carried accessory by accessory - each one its own length plus 8" of bearing each side - for grab bars, dispensers, artwork, millwork, the roof-hatch ladder and the media monitor. Surface-mounted blocking and blocking inside the partition are distinguished.
A39: 36 | B39: MEP penetrations framed, not patched | C39: 26 penetrations were located by registering the M, E and P backgrounds onto the architectural plan and verifying the registration against the 30-degree ATM wall. All are under a quarter sheet, but the building is new, so each is carried as a FRAMED OPENING with its head, sill and stud reinforcement - never as a patch.
A40: 37 | B40: Openings for recessed fixtures | C40: The continuous light slots and the diffusers get framed openings and gypsum edge trim, quantified from the RCP fixture layout itself rather than from a generic allowance.
A41: 38 | B41: Canopy soffit and fascia framing | C41: The drive-up canopy carries 1,768.38 SF of 5/8" FRT plywood sheathing on 3-5/8" metal stud framing at 16" O.C., plus its track and bridging. On a soffit the track sits at the two ENDS of each stud and along the two side edges - it is reported that way, and the check is that the two add up to the full perimeter.

Sheet Pending Items
A1: PENDING ITEMS - what is missing, why, and who to ask
A2: Nothing on this list was invented to close a gap. Where the drawings do not resolve a quantity, the quantity is not carried and it is named here.
A4: # | B4: Item | C4: Area | D4: What exactly is missing, and why | E4: Ask | F4: Impact
A5: 1 | B5: Size of the second duct crossing wall A1 #9 | C5: Partitions | D5: M01.01 crosses wall A1 #9 TWICE, not once. The first duct is labelled 8" dia. and lands in the solid part of the wall. The second lands at A02.01 x 1801.57-1813.57, inside the 3'-4" R.O. of door 119, so in the building it passes above the header through the cripple studs. It is drawn 8" wide in plan, but its printed size is not legible on the sheet: the 10"x12" label belongs to the horizontal main above it, not to this branch. Both are carried as framed openings at 1.00 LF of header and 1.00 LF of sill track each, per 6/S5.20 (an 8" duct will not pass through the web of a 3 5/8" stud and the flanges may not be cut). If the second one is bigger than 8", its framed opening grows. | E5: Mechanical engineer - confirm the size of the branch duct over door 119 | F5: The framed opening of one duct
A6: 2 | B6: "@ LOW ROOF" on S2.20, north of grid B | C6: Partitions | D6: S2.20 carries FOUR B.O.D. callouts and only one of them is north of grid B: "B.O.D. EL. 15'-4 1/2"" with "NO SLOPE" in its own box right under it. Every wall north of grid B is carried at 15.375 ft on that callout, cross-checked against H/A09.23 "T/ STEEL 15'-4 1/2"". What is NOT settled: the words "@ LOW ROOF" sit south of the W16x31/W16x26 beam line, in the same band as walls A1 #1 to #4, and they carry no elevation of their own. They read as the tail of the "STL SUPPORT, REF. 3/S5.11" callout rather than as a roof zone, but the sheet does not prove it either way, and there is no second B.O.D. in that band to compare against. If there really is a lower roof there, every stud and every bracing row in that band changes. | E6: Structural engineer - confirm the deck elevation in the band between the W16x31 beam and grid B | F6: Stud length and bracing rows on every wall north of grid B
A7: 3 | B7: W14x22 roof beam sits directly over wall A1 #8 on grid 5 | C7: Partitions | D7: S2.20 ROOF FRAMING PLAN draws a W14x22 beam on grid 5 whose centerline (x=1472.64) is 0.13" from the centerline of wall A1 #8 (x=1472.44) once the two sheets are registered on their own grid bubbles (dx +234.34 pt over 8 columns, dy -16.72 pt over 9 rows, both sheets at 18.00 pt/ft). 3/A12.01 sends the stud to UNDERSIDE OF STRUCTURE with a continuous slip track, and along this wall line the underside of structure is the bottom flange of that beam, 13 3/4" below the bottom of deck. The take-off carries the stud to B.O.D. (12.89 ft at the high end), which is the LONGER and therefore safe number, and matches the architect wording in 12/A12.01 ("SPAN BETWEEN STUD TRACKS AT FLOOR AND DECK ABOVE"). If the slip track lands on the beam soffit instead, the stud drops to about 11.75 ft and the bracing goes from 3 rows to 2. Nothing is changed without the decision - the delta is named here. | E7: Architect / GC - confirm whether the head of wall lands on the beam or on the deck | F7: Stud 1.15 ft per piece on 21 pieces, plus 1 bracing row (17.06 LF)
A8: 4 | B8: Track-to-slab fastener spacing: two different numbers in the set | C8: Partitions | D8: The SILL TRACK ANCHORAGE table of 7/S5.20 gives INTERIOR WALLS "HILTI DNI 32 P8 @ 12" O.C."; the FASTENER SCHEDULE next to 3/S5.20 WALL CONNECTION AT SLAB gives LEVEL 1-3 "16" O.C." with "ATTACH TRACK TO SLAB W/ (1) 0.157" dia. P.A.F. W/ 1 1/4" MIN. EMBED. LOCATED AT CENTER OF TRACK. REF. SCHEDULE FOR SPACING". Both read on track to slab. The take-off prices the TIGHTER of the two (12" O.C.) so the bid is not short; the difference is roughly a third of the pin count on every interior wall. | E8: Structural engineer - confirm which schedule governs interior partitions | F8: About 1/3 of the powder actuated pins on every interior wall
A9: 5 | B9: Blocking at the edge of gypboard - CLOSED 10-Oct-2026 | C9: Partitions | D9: CLOSED, no longer pending. 4/S5.20 TYPICAL BLOCKING DETAIL carries a boxed note, textual: "PROVIDE BLOCKING AT THE EDGE OF GYPBOARD.", with STUD BLOCKING 362CR22 (TYP.) and CLIP ANGLE 362CR22 (TYP.) & BLOCKING W/ SCREWS (TYP.). When this item was written the note had been applied to wall A1 #8 only. The full sweep was run on 10-Oct-2026 against every closed face: it found 96 LF missing - 78.24 LF on the four A5 walls (which had been EXCLUDED in error when their closer was written, with the board at 9.00/9.50 ft against studs of 12.9-15.4 ft) and 17.76 LF on wall F #40. Both were added and the sweep now comes out at zero across all 67 walls. | E9: Closed - no action needed | F9: Was 96 LF of 362CR22; already carried
A10: 6 | B10: The five GWB ceilings cite no detail - CLOSED 10-Oct-2026 | C10: Ceilings | D10: CLOSED, no longer pending. CIELO-70 through CIELO-74 used to stop at A04.01 and cite not one detail. The A09.33 TYPICAL CEILING DETAILS sheet was opened on 10-Oct-2026, eight of its nine details for the first time, and the chain now closes: 7/A09.33 TYPICAL CEILING TRANSITION DETAIL governs a change of ceiling height and proves the NEGATIVE here - A04.01 gives each of the five rooms a single height tag, so none steps, so none carries the kicker, the vertical face or the corner bead it draws; and 3/A09.33 LIGHT FIXTURE INSTALLATION carries the seismic bracing note, excluded with its alternate calculated at 267.99 LF of 12 gauge wire because the anchorage it mandates ("SECURED TO THE MAIN RUNNER INTERSECTION") does not exist in a gypsum ceiling. Four line items that were neither quantified NOR excluded - CORNER_BEAD, PERIMETER_ANGLE, SHADOW_MOLDING and the seismic bracing - now carry a verified motive. | E10: Closed - no action needed | F10: Edge condition of the 5 rooms, resolved
A11: 7 | B11: Storefront pier framing at the 24 HR vestibule | C11: Partitions | D11: A12.10 24 HR VESTIBULE PLAN puts one bubble on each end pier of the vestibule storefront wall: 1/A09.25 DETAIL @ STOREFRONT PIER on the west one and 2/A09.25 DETAIL @ WINDOW JAMB on the east one. Both details are plan cuts and both label framing that IS ours: "6" CFMF", "3 5/8" METAL STUD", "5/8" GYPSUM BOARD" and "3/4" FRT PLYWOOD" at the jambs. What is NOT resolvable is the SIZE of the box. The printed strings on 1/A09.25 (3", 1'-9", 1'-0", 4") run from the grid lines F and G and from the face of the storefront, not from the four faces of the pier, and they do not close on the drawn outline: the outline measures about 2'-6 1/2" by 2'-0" on the sheet geometry while the strings would give 2'-0" and 1'-3". Rather than pick one reading, nothing is carried for the pier BOX. What IS carried, and is not affected, is the 3/4" FRT plywood and the gypsum board jamb return around every opening, which come from the head and sill details. Two piers at about 10 LF of perimeter each by 8'-6" would be roughly 170 SF of board and about 20 studs - that is the size of the question, not an estimate. | E11: Architect - dimension the pier box on 1/A09.25 and 2/A09.25 | F11: Two piers: about 170 SF of board and 20 studs
A12: 8 | B12: Width of the plywood backing and the jamb return | C12: Partitions | D12: Five details cut the frame of the openings and all five label the material - 11/A09.27 and 2/A09.26 at the head ("3/4" FRT PLYWOOD", "GYPSUM BOARD JAMB RETURN BEYOND"), 10/A09.27 at the sill, 1/A09.25 and 2 and 3/A09.25 at the jambs - but NONE of them dimensions how wide the strip is. The 6" stud depth it backs is used, which is what the details draw. If the real return is deeper the quantity scales directly with it. | E12: Architect, or field decision at shop drawings | F12: Scales directly with the width
A13: 9 | B13: Purlin at exterior walls and the inclined wall | C13: Partitions | D13: The 139.21 LF of purlin carried cover the interior walls that run east-west and go to deck. The six exterior walls and the inclined wall 40 have no straight orientation in the band table, so whether their top track runs parallel to the flute is a field condition - the detail itself says VIF FLUTE DIRECTION. Not estimated. If all of them turned out to need it, at the same 0.75 LF per LF it would be about 180 LF more. | E13: Field verification before ordering | F13: Up to about 180 LF of purlin
A14: 10 | B14: Ceiling transition perimeter | C14: Ceilings | D14: How much of the 167.68 LF of gypsum-ceiling perimeter meets an ACT ceiling at a different height, and therefore takes the 6" transition of 7/A09.33 (kicker @ 48" O.C., board both faces, 2 corner beads, shadow molding). A mechanical wall test was run and it does NOT resolve the restroom edges, so no number is carried rather than a guessed one. | E14: Architect / A04.01 edge by edge | F14: Affects price
A15: 11 | B15: CSR soffit stud length | C15: Soffits | D15: The CSR soffit carries 26 pieces of 3-5/8" stud (size confirmed on A09.33: "3 5/8" METAL STUD FRAMING AND TRACK @ 16" O.C."), but 10/A09.33 does not dimension the soffit drop, so the LF of each piece is not derivable. Pieces are carried; length is not. | E15: Architect - soffit drop dimension | F15: Minor
A16: 12 | B16: Walls 51 and 53 may be short | C16: Partitions | D16: On the left office-front band (x 1121.16 / 1133.88) the face at x=1133.88 runs continuous 981.00 to 1044.12 (3.507 ft) and 1179.12 to 1236.36 (3.180 ft), while both closures took 2.667 ft. Those may be the junctions with walls 4 and 26, or 0.84 + 0.51 ft of uncounted wall. Needs a zoom of A02.01 at x 1115-1140 / y 975-1240 to see where each type dies. | E16: Re-measure on A02.01 | F16: Up to 1.35 LF of wall
... A28: 24 | B28: CSR soffit vertical face | C28: Soffits | D28: Excluded: 10/A09.33 draws the soffit dying into a SCHEDULED PARTITION with continuous corner bead, with no free vertical face, and walls A1K 11 and 12 sit at exactly the same x range. If a free face appears in the field it is 30.85 SF, declared as an alternate. | E28: Field verification | F28: Alternate 30.85 SF

Sheet Sheet Index
A1: SHEET INDEX - where every number came from
A3: Sheet | B3: Title | C3: PDF page | D3: What was taken from it
A4: A00.30 | B4: Door Schedule | C4: 31 | D4: Door leaf widths and heights used for header and board deduction
A5: A02.01 | B5: Construction Plan | C5: 23 | D5: Every wall length and every opening clear, by vector geometry at 1/4"=1'-0"
A6: A04.01 | B6: Reflected Ceiling Plan | C6: 28 | D6: Gypsum vs ACT ceilings, heights, key notes, fixture layout for hanger wire
A7: A08.01 | B7: Enlarged Restroom Plans & Elevations | C7: 31 | D7: Toilet accessories, sheet note E on blocking, FRP extent
A8: A08.11 | B8: ATM Details | C8: 32 | D8: Drive-up and walk-up ATM R.O., box beam, sistered studs, plinth and surround
A9: A09.01 | B9: Exterior Elevations (west + north) | C9: 34 | D9: Canopy extent and datums; grid order proves the title swap
A10: A09.02 | B10: Exterior Elevations (south + east) | C10: 35 | D10: Canopy extent, EXPT-1 door, exterior material legend
A11: A09.23 | B11: Wall Sections | C11: 38 | D11: H/A09.23: full exterior wall build-up and each layer's height
A12: A09.25 | B12: Plan Details | C12: 39 | D12: Exterior wall plan details, corner and jamb conditions
A13: A09.27 | B13: Gypsum Section Details | C13: 41 | D13: 15 and 16/A09.27: drive-up canopy soffit and fascia build-up and datums
A14: A09.30 | B14: Roof Details | C14: 42 | D14: Roof hatch and ladder
A15: A09.33 | B15: Ceiling Details | C15: 44 | D15: 10/A09.33: CSR soffit, corner bead, FRTW blocking, ceiling trim
... A22: P01.01 / P01.02 | B22: Plumbing Plans | C22: 90 | D22: Plumbing penetrations crossed against every wall

Sheet Detail log
A1: DETAIL LOG - why the chain goes to each sheet, and what came out of it
A2: One row per link of the Detail sequence shown on the Partition Takeoff and Ceilings & Soffits tabs, in the order the sheets were read. "What was taken from it" is quoted from the sealed closure, not retyped.
A4: Element | B4: Step | C4: Sheet / detail | D4: Used for | E4: What this detail is, and why the chain goes there | F4: Cited in | G4: What was taken from it
A5: A1 #8 | B5: 1 | C5: A02.01 | D5: Dimension | E5: Construction Plan. Entry sheet for partitions and openings: vector geometry of every wall face at 1/4"=1'-0", the leader of every partition tag, the Construction Plan Legend (new vs. existing) and the Construction Plan Notes. | F5: BOARD, HEADER, SUSTRATO_PLYWOOD, face[2].board_height, face[3].board_height, length, scope[0].chain[0], scope[1].chain[0], scope[1].chain[1] | G5: CORREGIDO 5-oct-2026: face to face entre los dos walls tipo B, y=1446.12 a y=1551.12 = 105.00 pt / 18 = 5.833 ft, que es EXACTAMENTE la dimension impresa 5'-10" de A02.01 (cadena en x=1277.76, ticks localizados descontando el sobretiro de punta de flecha de 6.72 pt, simetrico en los dos extremos).
B6: 2 | C6: A04.01 | D6: Dimension | E6: Reflected Ceiling Plan. Entry sheet for ceilings, soffits and canopy; on walls it gives the BOARD HEIGHT: each room ceiling tag with its printed A.F.F. dimension, plus the ceiling key notes. | F6: BOARD, face[0].board_height, face[1].board_height, face[2].board_height, face[3].board_height | G6: A04.01: tag ACT-4 con dimension impresa 8'-6" junto al room tag CORRIDOR 111, mas los 6" de 3/A12.01 = 9.00 ft
B7: 3 | C7: S2.20 | D7: Dimension | E7: "ROOF FRAMING PLAN". Source of the STUD HEIGHT: every B.O.D. callout on the sheet and the slope of the bay between grids B and A (1/4" per foot). | F7: BOARD, face[2].board_height, face[3].board_height, stud_height | G7: interpolado en el extremo ALTO de la zona (y=1446.12 de A02.01 = y=1429.40 de S2.20) = 13.052 - (200.10/454.6) x 0.521 = 12.82 ft.
B8: 4 | C8: 2/A11.03 | D8: Quantity | E8: "ELECTRICAL ELEVATION", measured width 9.540 ft (343.44 pt / 36). It DOES label 3/4" FRT PLYWOOD with a leader to the hatched field and prints its 8'-0" height: it is the SOURCE of the plywood of wall B #18. CORRECTED 10-oct-2026 -- it had been recorded as "draws NO plywood (verified)", and the sheet says otherwise. | F8: SUSTRATO_PLYWOOD | G8: CORREGIDO 6-oct-2026: antes se citaban tambien 2/A11.03, 4/A11.03 y 7/A11.03.
B9: 5 | C9: 3/A11.03 | D9: Quantity | E9: "ELECTRICAL ELEVATION 2", measured width 5.833 ft. Panel backing board. | F9: SUSTRATO_PLYWOOD | G9: La height sale de las dos elevaciones interiores DE ESTE WALL, identificadas por WIDTH contra la planta (regla 61, A11.03 esta a 1/2"=1'-0" = 36 pt/pie): 3/A11.03 ELECTRICAL ELEVATION dibuja 210.00 pt = 5.833 ft, EXACTAMENTE la dimension impresa 5'-10", y 5/A11.03 NER ELEVATION dibuja 270.00 pt = 7.500 ft, EXACTAMENTE…
B10: 6 | C10: 4/A11.03 | D10: Quantity | E10: "ELECTRICAL ELEVATION", measured width 9.517 ft (342.60 pt / 36). It DOES label 3/4" FRT PLYWOOD and prints its 8'-0" height: it is the SOURCE of the plywood of wall B #22. CORRECTED 10-oct-2026 -- it had been recorded as opened and ruled out, and the sheet says otherwise. The bubbles of the top row of A11.03 run 4, 3, 2 from the left, not 2, 3, 4. | F10: SUSTRATO_PLYWOOD | G10: CORREGIDO 6-oct-2026: antes se citaban tambien 2/A11.03, 4/A11.03 y 7/A11.03.
B11: 7 | C11: 5/A11.03 | D11: Quantity | E11: "NER ELEVATION", measured width 7.500 ft. THIS is the plywood one: dimension chain 8'-0" + 6" puts the panel from 6" A.F.F. to 8'-6" A.F.F. | F11: SUSTRATO_PLYWOOD | G11: La height sale de las dos elevaciones interiores DE ESTE WALL, identificadas por WIDTH contra la planta (regla 61, A11.03 esta a 1/2"=1'-0" = 36 pt/pie): 3/A11.03 ELECTRICAL ELEVATION dibuja 210.00 pt = 5.833 ft, EXACTAMENTE la dimension impresa 5'-10", y 5/A11.03 NER ELEVATION dibuja 270.00 pt = 7.500 ft, EXACTAMENTE…
B12: 8 | C12: 7/A11.03 | D12: Ruled out | E12: "NER ELEVATION" (TECH 1 / TECH 2 rack). Draws NO plywood: verified, and that is why it is NOT the source of the substrate. | F12: SUSTRATO_PLYWOOD | G12: CORREGIDO 6-oct-2026: antes se citaban tambien 2/A11.03, 4/A11.03 y 7/A11.03.
B13: 9 | C13: 1/A12.01 | D13: Quantity | E13: "PARTITION TYPE B, B2". Stud, layers per face, wall thickness and sealant of types B and B2. On a B wall it is the source; on an A1 wall it enters as a CONTRAST (B does label sealant top AND bottom, A1 only at the bottom). | F13: SEALANT | G13: Contraste que prueba que no es omision mia: 1/A12.01 (B y B2) SI rotula sealant arriba Y abajo.
B14: 10 | C14: 3/A12.01 | D14: Dimension | E14: "PARTITION TYPE A1 & A5". 3 5/8" stud, layers per face, WALL THICKNESS 4 7/8", slip track at the top, acoustic sealant at the slab and the 6" of board above the scheduled ceiling. | F14: BOARD, SEALANT, STUD, TRACK_BOTTOM, TRACK_TOP, excluded.INSULATION, face[0].board_height, face[1].board_height, face[2].board_height, face[3].board_height, scope[0].chain[1], stud_height | G14: A04.01: tag ACT-4 con dimension impresa 8'-6" junto al room tag CORRIDOR 111, mas los 6" de 3/A12.01 = 9.00 ft
B15: 11 | C15: 4/A12.01 | D15: Quantity | E15: "PARTITION TYPE A1K & A5K". The K types. On an A1 wall it enters as a CONTRAST: detail 4 calls for 14 GA @ 24" O.C. MAX in its own note and detail 3 does not, so on the A1 the 7/S5.20 schedule governs. | F15: STUD | G15: El detalle 3/A12.01 no trae nota de construccion propia que lo contradiga (a diferencia de 4/A12.01, que para los walls K pide 14 GA @ 24" O.C.
B16: 12 | C16: A09.01 | D16: Exclusion | E16: Exterior Elevations: "SOUTH ELEVATION" and "WEST ELEVATION" at 1/4"=1'-0". Extent of each exterior material and the material legend, verbatim "CJ CONTROL JOINT; PAINT TO MATCH STUCCO FINISH COLOR" - that joint is the STUCCO joint, not gypsum. | F16: excluded.CONTROL_JOINT | G16: Solo aparece en tres sitios y NINGUNO es de gypsum board: (1) la lista de abreviaturas de la portada, que define 'CJ CONTROL JOINT'; (2) la hoja civil de pavimentos, con su propio schedule de juntas segun la American Concrete Pavement Association; y (3) la leyenda de materiales exteriores de A09.01/A09.02, textual: '…
B17: 13 | C17: 10/A12.02 | D17: Quantity | E17: "HEAD @ HOLLOW METAL FRAME" at 3"=1'-0". Head of the hollow metal frame: labels SCHEDULED PARTITION, METAL STUD, METAL CLIP, HOLLOW METAL FRAME and 1/2" of board lap per face inside the frame throat. | F17: HEADER, excluded.CLIPS, openings[0].head | G17: Door 118B del Door Schedule de A00.30, hoja 3'-0", hollow metal frame, HEAD 10/A12.02 y JAMB 11/A12.02, columna SILL vacia.
... B31: 27 | C31: P01.02 | D31: Exclusion | E31: "PLUMBING PLAN SUPPLY" at 1/4"=1'-0". The same cross-check for the supply piping. | F31: excluded.PATCH | G31: Ademas el cruce MEP corrido contra M01.01, P01.01, P01.02 y E02.01 no encuentra ninguna penetracion por debajo de la height de board: en obra nueva el MEP se instala ANTES del board.
A32: A1 #1 | B32: 1 | C32: A02.01 | D32: Dimension | E32: Construction Plan. Entry sheet for partitions and openings: vector geometry of every wall face at 1/4"=1'-0", the leader of every partition tag, the Construction Plan Legend (new vs. existing) and the Construction Plan Notes. | F32: BLOCKING, excluded.HEADER, length, scope[0].chain[0], scope[1].chain[0], scope[1].chain[1] | G32: A02.01 geometria vectorial: faces lw1.20 en y=967.44 y y=974.76, separacion 7.32 pt = 4.88" contra los 4 7/8" del schedule de 3/A12.01.
B33: 2 | C33: A04.01 | D33: Dimension | E33: Reflected Ceiling Plan. Entry sheet for ceilings, soffits and canopy; on walls it gives the BOARD HEIGHT: each room ceiling tag with its printed A.F.F. dimension, plus the ceiling key notes. | F33: face[0].board_height, face[1].board_height | G33: A04.01: tag ACT-4 con dimension impresa 11'-6" junto al room tag CENTRAL ZONE 103, mas los 6" sobre el scheduled ceiling de 3/A12.01 = 12.00 ft
B34: 3 | C34: S2.20 | D34: Dimension | E34: "ROOF FRAMING PLAN". Source of the STUD HEIGHT: every B.O.D. callout on the sheet and the slope of the bay between grids B and A (1/4" per foot). | F34: stud_height | G34: S2.20: al norte del eje B el B.O.D.
B35: 4 | C35: 1/A12.01 | D35: Quantity | E35: "PARTITION TYPE B, B2". Stud, layers per face, wall thickness and sealant of types B and B2. On a B wall it is the source; on an A1 wall it enters as a CONTRAST (B does label sealant top AND bottom, A1 only at the bottom). | F35: SEALANT | G35: Contraste que prueba que no es omision mia: 1/A12.01 (B y B2) SI rotula sealant arriba Y abajo.
B36: 5 | C36: 3/A12.01 | D36: Dimension | E36: "PARTITION TYPE A1 & A5". 3 5/8" stud, layers per face, WALL THICKNESS 4 7/8", slip track at the top, acoustic sealant at the slab and the 6" of board above the scheduled ceiling. | F36: BOARD, SEALANT, STUD, TRACK_BOTTOM, TRACK_TOP, excluded.INSULATION, face[0].board_height, face[1].board_height, length, scope[0].chain[1], stud_height | G36: A04.01: tag ACT-4 con dimension impresa 11'-6" junto al room tag CENTRAL ZONE 103, mas los 6" sobre el scheduled ceiling de 3/A12.01 = 12.00 ft
B37: 6 | C37: 4/A12.01 | D37: Quantity | E37: "PARTITION TYPE A1K & A5K". The K types. On an A1 wall it enters as a CONTRAST: detail 4 calls for 14 GA @ 24" O.C. MAX in its own note and detail 3 does not, so on the A1 the 7/S5.20 schedule governs. | F37: STUD | G37: El detalle 3/A12.01 no trae nota de construccion propia que lo contradiga (a diferencia de 4/A12.01, que para los walls K pide 14 GA @ 24" O.C.
B38: 7 | C38: A09.01 | D38: Exclusion | E38: Exterior Elevations: "SOUTH ELEVATION" and "WEST ELEVATION" at 1/4"=1'-0". Extent of each exterior material and the material legend, verbatim "CJ CONTROL JOINT; PAINT TO MATCH STUCCO FINISH COLOR" - that joint is the STUCCO joint, not gypsum. | F38: excluded.CONTROL_JOINT | G38: Solo aparece en tres sitios y NINGUNO es de gypsum board: (1) la lista de abreviaturas de la portada, que define 'CJ CONTROL JOINT'; (2) la hoja civil de pavimentos, con su propio schedule de juntas segun la American Concrete Pavement Association; y (3) la leyenda de materiales exteriores de A09.01/A09.02, textual: '…
B39: 8 | C39: 10/A12.02 | D39: Exclusion | E39: "HEAD @ HOLLOW METAL FRAME" at 3"=1'-0". Head of the hollow metal frame: labels SCHEDULED PARTITION, METAL STUD, METAL CLIP, HOLLOW METAL FRAME and 1/2" of board lap per face inside the frame throat. | F39: excluded.CLIPS | G39: El otro es el METAL CLIP que 10/A12.02 HEAD @ HOLLOW METAL FRAME rotula en la union del door frame con el stud del header, y ese se excluye por DIVISION, no por soldadura: 11/A12.02 JAMB @ HOLLOW METAL FRAME llama METAL ANCHOR a la misma pieza en la jamb, o sea es el anchorage del hollow metal frame, que viene con la…
B40: 9 | C40: 11/A12.02 | D40: Exclusion | E40: "JAMB @ HOLLOW METAL FRAME" at 3"=1'-0". Jamb of the same frame: it calls METAL ANCHOR the piece detail 10 calls METAL CLIP, so the piece is frame anchorage (Div 08), not a clip of ours. | F40: excluded.CLIPS | G40: El otro es el METAL CLIP que 10/A12.02 HEAD @ HOLLOW METAL FRAME rotula en la union del door frame con el stud del header, y ese se excluye por DIVISION, no por soldadura: 11/A12.02 JAMB @ HOLLOW METAL FRAME llama METAL ANCHOR a la misma pieza en la jamb, o sea es el anchorage del hollow metal frame, que viene con la…
B41: 10 | C41: 1/S5.20 | D41: Quantity | E41: "TYPICAL WALL FRAMING DETAILS". Holds sub-details A through F; sub-detail F "BRIDGING AND BRACING - CONTINUOUS BRIDGING" is the bracing one: 1 1/2" C.R. CHANNEL welded to every stud. (Bracing is NOT in 5/S5.20, which is TYPICAL WALL FRAMING CONNX.) | F41: BRACING, excluded.CLIPS | G41: por el punchout del alma, soldado a cada stud (1/S5.20 sub-detalle F de S5.20).
B42: 11 | C42: 4/S5.20 | D42: Quantity | E42: "TYPICAL BLOCKING DETAIL". STUD BLOCKING 362CR22 and CLIP ANGLE 362CR22, with the boxed verbatim note "PROVIDE BLOCKING AT THE EDGE OF GYPBOARD." - source of the blocking at EVERY free edge of board. | F42: BLOCKING | G42: BOARD FREE EDGE: 4/S5.20 TYPICAL BLOCKING DETAIL carries a boxed note, TEXTUAL: 'PROVIDE BLOCKING AT THE EDGE OF GYPBOARD.', with STUD BLOCKING 362CR22 (TYP.) and CLIP ANGLE 362CR22 (TYP.) & BLOCKING W/ SCREWS (TYP.).
B43: 12 | C43: 7/S5.20 | D43: Quantity | E43: "METAL STUDS SCHEDULES". The profile: web, flange, lip, mils, gauge and the APPLICATION column with the spacing ("INTERIOR WALLS @ 16" O.C."), plus the SILL TRACK ANCHORAGE and the FASTENER SCHEDULE. | F43: STUD, TRACK_BOTTOM | G43: 7/S5.20 METAL STUDS SCHEDULES, renglon 362S137-33: alma 3 5/8", ala 1 3/8", lip 3/8", 33 mil = 20 ga, APPLICATION 'INTERIOR WALLS @ 16" O.C.'.
B44: 13 | C44: A00.01 | D44: Scope | E44: Cover sheet and Drawing Index. Proof by ABSENCE: the index lists no interior Demolition Plan, which is why there is no patch-and-repair line item. | F44: excluded.PATCH, scope[1].chain[0] | G44: A02.01 Construction Plan Legend: la grafia de dos lineas limpias es NEW PARTITION (SEE SCHEDULE); no hay Demolition Plan interior en el Drawing Index de A00.01
... B51: 20 | C51: P01.02 | D51: Exclusion | E51: "PLUMBING PLAN SUPPLY" at 1/4"=1'-0". The same cross-check for the supply piping. | F51: excluded.PATCH | G51: Ademas el cruce MEP corrido contra M01.01, P01.01, P01.02 y E02.01 no encuentra ninguna penetracion por debajo de la height de board: en obra nueva el MEP se instala ANTES del board.
A52: A1 #5 | B52: 1 | C52: A02.01 | D52: Dimension | E52: Construction Plan. Entry sheet for partitions and openings: vector geometry of every wall face at 1/4"=1'-0", the leader of every partition tag, the Construction Plan Legend (new vs. existing) and the Construction Plan Notes. | F52: BLOCKING, excluded.HEADER, length, scope[0].chain[0], scope[1].chain[0], scope[1].chain[1], stud_height | G52: A02.01 geometria vectorial: faces lw1.20 en y=1316.76 y y=1324.08, separacion 7.32 pt = 4.88".
B53: 2 | C53: A04.01 | D53: Dimension | E53: Reflected Ceiling Plan. Entry sheet for ceilings, soffits and canopy; on walls it gives the BOARD HEIGHT: each room ceiling tag with its printed A.F.F. dimension, plus the ceiling key notes. | F53: face[0].board_height, face[1].board_height | G53: A04.01: tag ACT-5 con dimension impresa 8'-6", mas los 6" de 3/A12.01 = 9.00 ft
B54: 3 | C54: S2.20 | D54: Dimension | E54: "ROOF FRAMING PLAN". Source of the STUD HEIGHT: every B.O.D. callout on the sheet and the slope of the bay between grids B and A (1/4" per foot). | F54: stud_height | G54: S2.20: el wall esta en la bahia EN PENDIENTE.
B55: 4 | C55: 1/A12.01 | D55: Quantity | E55: "PARTITION TYPE B, B2". Stud, layers per face, wall thickness and sealant of types B and B2. On a B wall it is the source; on an A1 wall it enters as a CONTRAST (B does label sealant top AND bottom, A1 only at the bottom). | F55: SEALANT | G55: Contraste que prueba que no es omision mia: 1/A12.01 (B y B2) SI rotula sealant arriba Y abajo.
B56: 5 | C56: 3/A12.01 | D56: Dimension | E56: "PARTITION TYPE A1 & A5". 3 5/8" stud, layers per face, WALL THICKNESS 4 7/8", slip track at the top, acoustic sealant at the slab and the 6" of board above the scheduled ceiling. | F56: BOARD, SEALANT, STUD, TRACK_BOTTOM, TRACK_TOP, excluded.INSULATION, face[0].board_height, face[1].board_height, scope[0].chain[1], stud_height | G56: A04.01: tag ACT-5 con dimension impresa 8'-6", mas los 6" de 3/A12.01 = 9.00 ft
B57: 6 | C57: 4/A12.01 | D57: Quantity | E57: "PARTITION TYPE A1K & A5K". The K types. On an A1 wall it enters as a CONTRAST: detail 4 calls for 14 GA @ 24" O.C. MAX in its own note and detail 3 does not, so on the A1 the 7/S5.20 schedule governs. | F57: STUD | G57: El detalle 3/A12.01 no trae nota de construccion propia que lo contradiga (a diferencia de 4/A12.01, que para los walls K pide 14 GA @ 24" O.C.
B58: 7 | C58: A09.01 | D58: Exclusion | E58: Exterior Elevations: "SOUTH ELEVATION" and "WEST ELEVATION" at 1/4"=1'-0". Extent of each exterior material and the material legend, verbatim "CJ CONTROL JOINT; PAINT TO MATCH STUCCO FINISH COLOR" - that joint is the STUCCO joint, not gypsum. | F58: excluded.CONTROL_JOINT | G58: Solo aparece en tres sitios y NINGUNO es de gypsum board: (1) la lista de abreviaturas de la portada, que define 'CJ CONTROL JOINT'; (2) la hoja civil de pavimentos, con su propio schedule de juntas segun la American Concrete Pavement Association; y (3) la leyenda de materiales exteriores de A09.01/A09.02, textual: '…
B59: 8 | C59: 10/A12.02 | D59: Exclusion | E59: "HEAD @ HOLLOW METAL FRAME" at 3"=1'-0". Head of the hollow metal frame: labels SCHEDULED PARTITION, METAL STUD, METAL CLIP, HOLLOW METAL FRAME and 1/2" of board lap per face inside the frame throat. | F59: excluded.CLIPS | G59: El otro es el METAL CLIP que 10/A12.02 HEAD @ HOLLOW METAL FRAME rotula en la union del door frame con el stud del header, y ese se excluye por DIVISION, no por soldadura: 11/A12.02 JAMB @ HOLLOW METAL FRAME llama METAL ANCHOR a la misma pieza en la jamb, o sea es el anchorage del hollow metal frame, que viene con la…
B60: 9 | C60: 11/A12.02 | D60: Exclusion | E60: "JAMB @ HOLLOW METAL FRAME" at 3"=1'-0". Jamb of the same frame: it calls METAL ANCHOR the piece detail 10 calls METAL CLIP, so the piece is frame anchorage (Div 08), not a clip of ours. | F60: excluded.CLIPS | G60: El otro es el METAL CLIP que 10/A12.02 HEAD @ HOLLOW METAL FRAME rotula en la union del door frame con el stud del header, y ese se excluye por DIVISION, no por soldadura: 11/A12.02 JAMB @ HOLLOW METAL FRAME llama METAL ANCHOR a la misma pieza en la jamb, o sea es el anchorage del hollow metal frame, que viene con la…
B61: 10 | C61: 1/S5.20 | D61: Quantity | E61: "TYPICAL WALL FRAMING DETAILS". Holds sub-details A through F; sub-detail F "BRIDGING AND BRACING - CONTINUOUS BRIDGING" is the bracing one: 1 1/2" C.R. CHANNEL welded to every stud. (Bracing is NOT in 5/S5.20, which is TYPICAL WALL FRAMING CONNX.) | F61: BRACING, excluded.CLIPS | G61: por el punchout del alma, soldado a cada stud (1/S5.20 sub-detalle F de S5.20).
B62: 11 | C62: 4/S5.20 | D62: Quantity | E62: "TYPICAL BLOCKING DETAIL". STUD BLOCKING 362CR22 and CLIP ANGLE 362CR22, with the boxed verbatim note "PROVIDE BLOCKING AT THE EDGE OF GYPBOARD." - source of the blocking at EVERY free edge of board. | F62: BLOCKING | G62: BOARD FREE EDGE: 4/S5.20 TYPICAL BLOCKING DETAIL carries a boxed note, TEXTUAL: 'PROVIDE BLOCKING AT THE EDGE OF GYPBOARD.', with STUD BLOCKING 362CR22 (TYP.) and CLIP ANGLE 362CR22 (TYP.) & BLOCKING W/ SCREWS (TYP.).
B63: 12 | C63: 7/S5.20 | D63: Quantity | E63: "METAL STUDS SCHEDULES". The profile: web, flange, lip, mils, gauge and the APPLICATION column with the spacing ("INTERIOR WALLS @ 16" O.C."), plus the SILL TRACK ANCHORAGE and the FASTENER SCHEDULE. | F63: STUD, TRACK_BOTTOM | G63: 7/S5.20 METAL STUDS SCHEDULES, renglon 362S137-33: alma 3 5/8", ala 1 3/8", lip 3/8", 33 mil = 20 ga, APPLICATION 'INTERIOR WALLS @ 16" O.C.'.
B64: 13 | C64: A00.01 | D64: Scope | E64: Cover sheet and Drawing Index. Proof by ABSENCE: the index lists no interior Demolition Plan, which is why there is no patch-and-repair line item. | F64: excluded.PATCH, scope[1].chain[0] | G64: A02.01 Construction Plan Legend: la grafia de dos lineas limpias es NEW PARTITION (SEE SCHEDULE); no hay Demolition Plan interior en el Drawing Index de A00.01
... B73: 22 | C73: P01.02 | D73: Exclusion | E73: "PLUMBING PLAN SUPPLY" at 1/4"=1'-0". The same cross-check for the supply piping. | F73: excluded.PATCH | G73: Ademas el cruce MEP corrido contra M01.01, P01.01, P01.02 y E02.01 no encuentra ninguna penetracion por debajo de la height de board: en obra nueva el MEP se instala ANTES del board.
A74: A1 #9 | B74: 1 | C74: A02.01 | D74: Dimension | E74: Construction Plan. Entry sheet for partitions and openings: vector geometry of every wall face at 1/4"=1'-0", the leader of every partition tag, the Construction Plan Legend (new vs. existing) and the Construction Plan Notes. | F74: BLOCKING, HEADER, length, scope[0].chain[0], scope[1].chain[0], scope[1].chain[1], stud_height | G74: A02.01 geometria vectorial: faces lw1.20 en y=1488.12 y y=1495.44, separacion 7.32 pt = 4.88".
B75: 2 | C75: A04.01 | D75: Dimension | E75: Reflected Ceiling Plan. Entry sheet for ceilings, soffits and canopy; on walls it gives the BOARD HEIGHT: each room ceiling tag with its printed A.F.F. dimension, plus the ceiling key notes. | F75: face[0].board_height, face[1].board_height | G75: A04.01: tag ACT-4 con dimension impresa 9'-0" junto al room tag CASH WINDOW 116 -el area FUTURE FCAM esta dentro de ese mismo cuarto-, mas los 6" de 3/A12.01 = 9.50 ft
B76: 3 | C76: S2.20 | D76: Dimension | E76: "ROOF FRAMING PLAN". Source of the STUD HEIGHT: every B.O.D. callout on the sheet and the slope of the bay between grids B and A (1/4" per foot). | F76: stud_height | G76: S2.20: el wall esta en la bahia EN PENDIENTE.
B77: 4 | C77: 1/A12.01 | D77: Quantity | E77: "PARTITION TYPE B, B2". Stud, layers per face, wall thickness and sealant of types B and B2. On a B wall it is the source; on an A1 wall it enters as a CONTRAST (B does label sealant top AND bottom, A1 only at the bottom). | F77: SEALANT | G77: Contraste que prueba que no es omision mia: 1/A12.01 (B y B2) SI rotula sealant arriba Y abajo.
B78: 5 | C78: 3/A12.01 | D78: Dimension | E78: "PARTITION TYPE A1 & A5". 3 5/8" stud, layers per face, WALL THICKNESS 4 7/8", slip track at the top, acoustic sealant at the slab and the 6" of board above the scheduled ceiling. | F78: BOARD, SEALANT, STUD, TRACK_BOTTOM, TRACK_TOP, excluded.INSULATION, face[0].board_height, face[1].board_height, scope[0].chain[1], stud_height | G78: A04.01: tag ACT-4 con dimension impresa 9'-0" junto al room tag CASH WINDOW 116 -el area FUTURE FCAM esta dentro de ese mismo cuarto-, mas los 6" de 3/A12.01 = 9.50 ft
B79: 6 | C79: 4/A12.01 | D79: Quantity | E79: "PARTITION TYPE A1K & A5K". The K types. On an A1 wall it enters as a CONTRAST: detail 4 calls for 14 GA @ 24" O.C. MAX in its own note and detail 3 does not, so on the A1 the 7/S5.20 schedule governs. | F79: STUD | G79: El detalle 3/A12.01 no trae nota de construccion propia que lo contradiga (a diferencia de 4/A12.01, que para los walls K pide 14 GA @ 24" O.C.
B80: 7 | C80: A09.01 | D80: Exclusion | E80: Exterior Elevations: "SOUTH ELEVATION" and "WEST ELEVATION" at 1/4"=1'-0". Extent of each exterior material and the material legend, verbatim "CJ CONTROL JOINT; PAINT TO MATCH STUCCO FINISH COLOR" - that joint is the STUCCO joint, not gypsum. | F80: excluded.CONTROL_JOINT | G80: Solo aparece en tres sitios y NINGUNO es de gypsum board: (1) la lista de abreviaturas de la portada, que define 'CJ CONTROL JOINT'; (2) la hoja civil de pavimentos, con su propio schedule de juntas segun la American Concrete Pavement Association; y (3) la leyenda de materiales exteriores de A09.01/A09.02, textual: '…
B81: 8 | C81: 10/A12.02 | D81: Quantity | E81: "HEAD @ HOLLOW METAL FRAME" at 3"=1'-0". Head of the hollow metal frame: labels SCHEDULED PARTITION, METAL STUD, METAL CLIP, HOLLOW METAL FRAME and 1/2" of board lap per face inside the frame throat. | F81: HEADER, excluded.CLIPS, openings[0].head | G81: (a) DOOR 119, 3.33 LF: Door Schedule de A00.30, FROM CASH WINDOW, tipo A, hoja 3'-0" x 7'-0" x 1 3/4" WOOD, hollow metal frame, HEAD 10/A12.02 y JAMB 11/A12.02, columna SILL vacia, HARDWARE GROUP 12.
B82: 9 | C82: 11/A12.02 | D82: Quantity | E82: "JAMB @ HOLLOW METAL FRAME" at 3"=1'-0". Jamb of the same frame: it calls METAL ANCHOR the piece detail 10 calls METAL CLIP, so the piece is frame anchorage (Div 08), not a clip of ours. | F82: HEADER, excluded.CLIPS | G82: (a) DOOR 119, 3.33 LF: Door Schedule de A00.30, FROM CASH WINDOW, tipo A, hoja 3'-0" x 7'-0" x 1 3/4" WOOD, hollow metal frame, HEAD 10/A12.02 y JAMB 11/A12.02, columna SILL vacia, HARDWARE GROUP 12.
B83: 10 | C83: 1/S5.20 | D83: Quantity | E83: "TYPICAL WALL FRAMING DETAILS". Holds sub-details A through F; sub-detail F "BRIDGING AND BRACING - CONTINUOUS BRIDGING" is the bracing one: 1 1/2" C.R. CHANNEL welded to every stud. (Bracing is NOT in 5/S5.20, which is TYPICAL WALL FRAMING CONNX.) | F83: BRACING, excluded.CLIPS | G83: por el punchout del alma, soldado a cada stud (1/S5.20 sub-detalle F de S5.20).
B84: 11 | C84: 2/S5.20 | D84: Quantity | E84: "HEAD TRACK @ NON LOAD BRG". The head track and the verbatim condition "ADD FULL LENGTH ADDL HEAD TRACK @ OPNG >4'-0"": an opening of 4'-0" or less takes a SINGLE track. | F84: HEADER | G84: Head track SENCILLO: 9/S5.20 OPNG IN NON-LOAD-BRG WALLS pone el doble solo @ OPNG > 4'-0" y 2/S5.20 repite la condicional.
B85: 12 | C85: 4/S5.20 | D85: Quantity | E85: "TYPICAL BLOCKING DETAIL". STUD BLOCKING 362CR22 and CLIP ANGLE 362CR22, with the boxed verbatim note "PROVIDE BLOCKING AT THE EDGE OF GYPBOARD." - source of the blocking at EVERY free edge of board. | F85: BLOCKING | G85: BOARD FREE EDGE: 4/S5.20 TYPICAL BLOCKING DETAIL carries a boxed note, TEXTUAL: 'PROVIDE BLOCKING AT THE EDGE OF GYPBOARD.', with STUD BLOCKING 362CR22 (TYP.) and CLIP ANGLE 362CR22 (TYP.) & BLOCKING W/ SCREWS (TYP.).
B86: 13 | C86: 6/S5.20 | D86: Quantity | E86: "PENETRATION THRU STUDS". How the stud is reinforced where a duct passes through. | F86: HEADER, SILL_TRACK, openings[1].head, openings[1].sill, openings[2].head, openings[2].sill | G86: 6/S5.20 limita el agujero del alma a 3 1/2" de diametro en stud de 6" y PROHIBE cortar las alas, asi que un ducto de 8" no pasa por el alma de un stud de 3 5/8": exige hueco framing.
... B97: 24 | C97: P01.02 | D97: Exclusion | E97: "PLUMBING PLAN SUPPLY" at 1/4"=1'-0". The same cross-check for the supply piping. | F97: excluded.PATCH | G97: Ademas el cruce MEP corrido contra M01.01, P01.01, P01.02 y E02.01 no encuentra ninguna penetracion por debajo de la height de board: en obra nueva el MEP se instala ANTES del board.
A98: A1 #6 | B98: 1 | C98: A02.01 | D98: Dimension | E98: Construction Plan. Entry sheet for partitions and openings: vector geometry of every wall face at 1/4"=1'-0", the leader of every partition tag, the Construction Plan Legend (new vs. existing) and the Construction Plan Notes. | F98: HEADER, length.source, scope[0].chain[0], scope[1].chain[0], scope[1].chain[1], stud_height | G98: A02.01: dimension impresa 5'-6" = 5.500 ft, con sus DOS ticks de 45 grados localizados en x=1522.9 y x=1622.2 -- que son exactamente los dos extremos de este wall, asi que la dimension es de ESTE tramo y no de uno vecino.
B99: 2 | C99: A04.01 | D99: Dimension | E99: Reflected Ceiling Plan. Entry sheet for ceilings, soffits and canopy; on walls it gives the BOARD HEIGHT: each room ceiling tag with its printed A.F.F. dimension, plus the ceiling key notes. | F99: face[0].board_height, face[1].board_height | G99: A04.01: tag ACT-4 con dimension impresa 9'-0" junto al room tag CASH WINDOW 116 -el area FUTURE FCAM esta dentro de ese mismo cuarto-, mas los 6" de 3/A12.01 = 9.50 ft
B100: 3 | C100: S2.20 | D100: Dimension | E100: "ROOF FRAMING PLAN". Source of the STUD HEIGHT: every B.O.D. callout on the sheet and the slope of the bay between grids B and A (1/4" per foot). | F100: stud_height | G100: S2.20: el wall esta en la bahia EN PENDIENTE.
B101: 4 | C101: 1/A12.01 | D101: Quantity | E101: "PARTITION TYPE B, B2". Stud, layers per face, wall thickness and sealant of types B and B2. On a B wall it is the source; on an A1 wall it enters as a CONTRAST (B does label sealant top AND bottom, A1 only at the bottom). | F101: SEALANT | G101: Contraste que prueba que no es omision mia: 1/A12.01 (B y B2) SI rotula sealant arriba Y abajo.
B102: 5 | C102: 3/A12.01 | D102: Dimension | E102: "PARTITION TYPE A1 & A5". 3 5/8" stud, layers per face, WALL THICKNESS 4 7/8", slip track at the top, acoustic sealant at the slab and the 6" of board above the scheduled ceiling. | F102: BOARD, SEALANT, STUD, TRACK_BOTTOM, TRACK_TOP, excluded.INSULATION, face[0].board_height, face[1].board_height, scope[0].chain[1], stud_height | G102: A04.01: tag ACT-4 con dimension impresa 9'-0" junto al room tag CASH WINDOW 116 -el area FUTURE FCAM esta dentro de ese mismo cuarto-, mas los 6" de 3/A12.01 = 9.50 ft
B103: 6 | C103: 4/A12.01 | D103: Quantity | E103: "PARTITION TYPE A1K & A5K". The K types. On an A1 wall it enters as a CONTRAST: detail 4 calls for 14 GA @ 24" O.C. MAX in its own note and detail 3 does not, so on the A1 the 7/S5.20 schedule governs. | F103: STUD | G103: El detalle 3/A12.01 no trae nota de construccion propia que lo contradiga (a diferencia de 4/A12.01, que para los walls K pide 14 GA @ 24" O.C.
B104: 7 | C104: A09.01 | D104: Exclusion | E104: Exterior Elevations: "SOUTH ELEVATION" and "WEST ELEVATION" at 1/4"=1'-0". Extent of each exterior material and the material legend, verbatim "CJ CONTROL JOINT; PAINT TO MATCH STUCCO FINISH COLOR" - that joint is the STUCCO joint, not gypsum. | F104: excluded.CONTROL_JOINT | G104: Solo aparece en tres sitios y NINGUNO es de gypsum board: (1) la lista de abreviaturas de la portada, que define 'CJ CONTROL JOINT'; (2) la hoja civil de pavimentos, con su propio schedule de juntas segun la American Concrete Pavement Association; y (3) la leyenda de materiales exteriores de A09.01/A09.02, textual: '…
B105: 8 | C105: 10/A12.02 | D105: Quantity | E105: "HEAD @ HOLLOW METAL FRAME" at 3"=1'-0". Head of the hollow metal frame: labels SCHEDULED PARTITION, METAL STUD, METAL CLIP, HOLLOW METAL FRAME and 1/2" of board lap per face inside the frame throat. | F105: HEADER, excluded.CLIPS, openings[0].head | G105: Door 118A del Door Schedule de A00.30, hoja 3'-0", hollow metal frame, HEAD 10/A12.02 y JAMB 11/A12.02, columna SILL vacia.
B106: 9 | C106: 11/A12.02 | D106: Quantity | E106: "JAMB @ HOLLOW METAL FRAME" at 3"=1'-0". Jamb of the same frame: it calls METAL ANCHOR the piece detail 10 calls METAL CLIP, so the piece is frame anchorage (Div 08), not a clip of ours. | F106: HEADER, excluded.CLIPS | G106: Door 118A del Door Schedule de A00.30, hoja 3'-0", hollow metal frame, HEAD 10/A12.02 y JAMB 11/A12.02, columna SILL vacia.
B107: 10 | C107: 1/S5.20 | D107: Quantity | E107: "TYPICAL WALL FRAMING DETAILS". Holds sub-details A through F; sub-detail F "BRIDGING AND BRACING - CONTINUOUS BRIDGING" is the bracing one: 1 1/2" C.R. CHANNEL welded to every stud. (Bracing is NOT in 5/S5.20, which is TYPICAL WALL FRAMING CONNX.) | F107: BRACING, excluded.CLIPS | G107: por el punchout del alma, soldado a cada stud (1/S5.20 sub-detalle F de S5.20).
B108: 11 | C108: 2/S5.20 | D108: Quantity | E108: "HEAD TRACK @ NON LOAD BRG". The head track and the verbatim condition "ADD FULL LENGTH ADDL HEAD TRACK @ OPNG >4'-0"": an opening of 4'-0" or less takes a SINGLE track. | F108: HEADER | G108: 9/S5.20 OPNG IN NON-LOAD-BRG WALLS rotula 'HEAD TRACK (DOUBLE TRACK @ OPNG > 4'-0")' y 2/S5.20 HEAD TRACK @ NON LOAD BRG repite la condicional 'ADD FULL LENGTH ADDL HEAD TRACK @ OPNG >4'-0"'.
B109: 12 | C109: 4/S5.20 | D109: Quantity | E109: "TYPICAL BLOCKING DETAIL". STUD BLOCKING 362CR22 and CLIP ANGLE 362CR22, with the boxed verbatim note "PROVIDE BLOCKING AT THE EDGE OF GYPBOARD." - source of the blocking at EVERY free edge of board. | F109: BLOCKING | G109: BOARD FREE EDGE: 4/S5.20 TYPICAL BLOCKING DETAIL carries a boxed note, TEXTUAL: 'PROVIDE BLOCKING AT THE EDGE OF GYPBOARD.', with STUD BLOCKING 362CR22 (TYP.) and CLIP ANGLE 362CR22 (TYP.) & BLOCKING W/ SCREWS (TYP.).
B110: 13 | C110: 7/S5.20 | D110: Quantity | E110: "METAL STUDS SCHEDULES". The profile: web, flange, lip, mils, gauge and the APPLICATION column with the spacing ("INTERIOR WALLS @ 16" O.C."), plus the SILL TRACK ANCHORAGE and the FASTENER SCHEDULE. | F110: STUD, TRACK_BOTTOM | G110: 7/S5.20 METAL STUDS SCHEDULES, renglon 362S137-33: alma 3 5/8", ala 1 3/8", lip 3/8", 33 mil = 20 ga, APPLICATION 'INTERIOR WALLS @ 16" O.C.'.
... B119: 22 | C119: P01.02 | D119: Exclusion | E119: "PLUMBING PLAN SUPPLY" at 1/4"=1'-0". The same cross-check for the supply piping. | F119: excluded.PATCH | G119: Ademas el cruce MEP corrido contra M01.01, P01.01, P01.02 y E02.01 no encuentra ninguna penetracion por debajo de la height de board: en obra nueva el MEP se instala ANTES del board.
A120: A1 #4 | B120: 1 | C120: A02.01 | D120: Dimension | E120: Construction Plan. Entry sheet for partitions and openings: vector geometry of every wall face at 1/4"=1'-0", the leader of every partition tag, the Construction Plan Legend (new vs. existing) and the Construction Plan Notes. | F120: HEADER, length.source, scope[0].chain[0], scope[1].chain[0], scope[1].chain[1] | G120: A02.01 printed dimension 5'-0" = 5.000 ft, with its TWO 45-degree ticks located at x=1133.9 and x=1223.9: those are exactly the two ends of this wall, so the dimension belongs to THIS run and not to a neighbouring one (two other dimension lines run alongside, the 7'-6" CLEAR FINISHED OPENING of the office front and th…
B121: 2 | C121: A04.01 | D121: Dimension | E121: Reflected Ceiling Plan. Entry sheet for ceilings, soffits and canopy; on walls it gives the BOARD HEIGHT: each room ceiling tag with its printed A.F.F. dimension, plus the ceiling key notes. | F121: face[0].board_height, face[1].board_height | G121: A04.01: tag ACT-4 con dimension impresa 8'-6" junto al room tag CORRIDOR 111, mas los 6" de 3/A12.01 = 9.00 ft
B122: 3 | C122: S2.20 | D122: Dimension | E122: "ROOF FRAMING PLAN". Source of the STUD HEIGHT: every B.O.D. callout on the sheet and the slope of the bay between grids B and A (1/4" per foot). | F122: stud_height | G122: S2.20: al norte del eje B el B.O.D.
B123: 4 | C123: 1/A12.01 | D123: Quantity | E123: "PARTITION TYPE B, B2". Stud, layers per face, wall thickness and sealant of types B and B2. On a B wall it is the source; on an A1 wall it enters as a CONTRAST (B does label sealant top AND bottom, A1 only at the bottom). | F123: SEALANT | G123: Contraste que prueba que no es omision mia: 1/A12.01 (B y B2) SI rotula sealant arriba Y abajo.
B124: 5 | C124: 3/A12.01 | D124: Dimension | E124: "PARTITION TYPE A1 & A5". 3 5/8" stud, layers per face, WALL THICKNESS 4 7/8", slip track at the top, acoustic sealant at the slab and the 6" of board above the scheduled ceiling. | F124: BOARD, SEALANT, STUD, TRACK_BOTTOM, TRACK_TOP, excluded.INSULATION, face[0].board_height, face[1].board_height, length.source, scope[0].chain[1], stud_height | G124: A04.01: tag ACT-4 con dimension impresa 8'-6" junto al room tag CORRIDOR 111, mas los 6" de 3/A12.01 = 9.00 ft
B125: 6 | C125: 4/A12.01 | D125: Quantity | E125: "PARTITION TYPE A1K & A5K". The K types. On an A1 wall it enters as a CONTRAST: detail 4 calls for 14 GA @ 24" O.C. MAX in its own note and detail 3 does not, so on the A1 the 7/S5.20 schedule governs. | F125: STUD | G125: El detalle 3/A12.01 no trae nota de construccion propia que lo contradiga (a diferencia de 4/A12.01, que para los walls K pide 14 GA @ 24" O.C.
B126: 7 | C126: A09.01 | D126: Exclusion | E126: Exterior Elevations: "SOUTH ELEVATION" and "WEST ELEVATION" at 1/4"=1'-0". Extent of each exterior material and the material legend, verbatim "CJ CONTROL JOINT; PAINT TO MATCH STUCCO FINISH COLOR" - that joint is the STUCCO joint, not gypsum. | F126: excluded.CONTROL_JOINT | G126: Solo aparece en tres sitios y NINGUNO es de gypsum board: (1) la lista de abreviaturas de la portada, que define 'CJ CONTROL JOINT'; (2) la hoja civil de pavimentos, con su propio schedule de juntas segun la American Concrete Pavement Association; y (3) la leyenda de materiales exteriores de A09.01/A09.02, textual: '…
B127: 8 | C127: 10/A12.02 | D127: Quantity | E127: "HEAD @ HOLLOW METAL FRAME" at 3"=1'-0". Head of the hollow metal frame: labels SCHEDULED PARTITION, METAL STUD, METAL CLIP, HOLLOW METAL FRAME and 1/2" of board lap per face inside the frame throat. | F127: HEADER, excluded.CLIPS, openings[0].head | G127: Door 111 del Door Schedule de A00.30, hoja 3'-0", hollow metal frame, HEAD 10/A12.02 y JAMB 11/A12.02, columna SILL vacia.
B128: 9 | C128: 11/A12.02 | D128: Quantity | E128: "JAMB @ HOLLOW METAL FRAME" at 3"=1'-0". Jamb of the same frame: it calls METAL ANCHOR the piece detail 10 calls METAL CLIP, so the piece is frame anchorage (Div 08), not a clip of ours. | F128: HEADER, excluded.CLIPS | G128: Door 111 del Door Schedule de A00.30, hoja 3'-0", hollow metal frame, HEAD 10/A12.02 y JAMB 11/A12.02, columna SILL vacia.
B129: 10 | C129: 1/S5.20 | D129: Quantity | E129: "TYPICAL WALL FRAMING DETAILS". Holds sub-details A through F; sub-detail F "BRIDGING AND BRACING - CONTINUOUS BRIDGING" is the bracing one: 1 1/2" C.R. CHANNEL welded to every stud. (Bracing is NOT in 5/S5.20, which is TYPICAL WALL FRAMING CONNX.) | F129: BRACING, excluded.CLIPS | G129: por el punchout del alma, soldado a cada stud (1/S5.20 sub-detalle F de S5.20).
B130: 11 | C130: 2/S5.20 | D130: Quantity | E130: "HEAD TRACK @ NON LOAD BRG". The head track and the verbatim condition "ADD FULL LENGTH ADDL HEAD TRACK @ OPNG >4'-0"": an opening of 4'-0" or less takes a SINGLE track. | F130: HEADER | G130: 9/S5.20 OPNG IN NON-LOAD-BRG WALLS rotula 'HEAD TRACK (DOUBLE TRACK @ OPNG > 4'-0")' y 2/S5.20 HEAD TRACK @ NON LOAD BRG repite la condicional 'ADD FULL LENGTH ADDL HEAD TRACK @ OPNG >4'-0"'.
B131: 12 | C131: 4/S5.20 | D131: Quantity | E131: "TYPICAL BLOCKING DETAIL". STUD BLOCKING 362CR22 and CLIP ANGLE 362CR22, with the boxed verbatim note "PROVIDE BLOCKING AT THE EDGE OF GYPBOARD." - source of the blocking at EVERY free edge of board. | F131: BLOCKING | G131: BOARD FREE EDGE: 4/S5.20 TYPICAL BLOCKING DETAIL carries a boxed note, TEXTUAL: 'PROVIDE BLOCKING AT THE EDGE OF GYPBOARD.', with STUD BLOCKING 362CR22 (TYP.) and CLIP ANGLE 362CR22 (TYP.) & BLOCKING W/ SCREWS (TYP.).
B132: 13 | C132: 7/S5.20 | D132: Quantity | E132: "METAL STUDS SCHEDULES". The profile: web, flange, lip, mils, gauge and the APPLICATION column with the spacing ("INTERIOR WALLS @ 16" O.C."), plus the SILL TRACK ANCHORAGE and the FASTENER SCHEDULE. | F132: STUD, TRACK_BOTTOM | G132: 7/S5.20 METAL STUDS SCHEDULES, renglon 362S137-33: alma 3 5/8", ala 1 3/8", lip 3/8", 33 mil = 20 ga, APPLICATION 'INTERIOR WALLS @ 16" O.C.'.
... B141: 22 | C141: P01.02 | D141: Exclusion | E141: "PLUMBING PLAN SUPPLY" at 1/4"=1'-0". The same cross-check for the supply piping. | F141: excluded.PATCH | G141: Ademas el cruce MEP corrido contra M01.01, P01.01, P01.02 y E02.01 no encuentra ninguna penetracion por debajo de la height de board: en obra nueva el MEP se instala ANTES del board.
A142: A1 #2 | B142: 1 | C142: A02.01 | D142: Dimension | E142: Construction Plan. Entry sheet for partitions and openings: vector geometry of every wall face at 1/4"=1'-0", the leader of every partition tag, the Construction Plan Legend (new vs. existing) and the Construction Plan Notes. | F142: BLOCKING, excluded.HEADER, length.source, scope[0].chain[0], scope[1].chain[0], scope[1].chain[1] | G142: A02.01: dimension impresa 3'-1 1/2" con ticks en los dos extremos de la banda (y=974.76 y y=1031.04), medida FACE OF FINISH TO FACE OF FINISH segun la nota D de la hoja.
B143: 2 | C143: A04.01 | D143: Dimension | E143: Reflected Ceiling Plan. Entry sheet for ceilings, soffits and canopy; on walls it gives the BOARD HEIGHT: each room ceiling tag with its printed A.F.F. dimension, plus the ceiling key notes. | F143: face[0].board_height, face[1].board_height | G143: A04.01: tag ACT-5 con dimension impresa 8'-6", mas los 6" de 3/A12.01 = 9.00 ft
B144: 3 | C144: S2.20 | D144: Dimension | E144: "ROOF FRAMING PLAN". Source of the STUD HEIGHT: every B.O.D. callout on the sheet and the slope of the bay between grids B and A (1/4" per foot). | F144: stud_height | G144: S2.20: al norte del eje B el B.O.D.
B145: 4 | C145: 1/A12.01 | D145: Quantity | E145: "PARTITION TYPE B, B2". Stud, layers per face, wall thickness and sealant of types B and B2. On a B wall it is the source; on an A1 wall it enters as a CONTRAST (B does label sealant top AND bottom, A1 only at the bottom). | F145: SEALANT | G145: Contraste que prueba que no es omision mia: 1/A12.01 (B y B2) SI rotula sealant arriba Y abajo.
B146: 5 | C146: 3/A12.01 | D146: Dimension | E146: "PARTITION TYPE A1 & A5". 3 5/8" stud, layers per face, WALL THICKNESS 4 7/8", slip track at the top, acoustic sealant at the slab and the 6" of board above the scheduled ceiling. | F146: BOARD, SEALANT, STUD, TRACK_BOTTOM, TRACK_TOP, excluded.INSULATION, face[0].board_height, face[1].board_height, scope[0].chain[1], stud_height | G146: A04.01: tag ACT-5 con dimension impresa 8'-6", mas los 6" de 3/A12.01 = 9.00 ft
B147: 6 | C147: 4/A12.01 | D147: Quantity | E147: "PARTITION TYPE A1K & A5K". The K types. On an A1 wall it enters as a CONTRAST: detail 4 calls for 14 GA @ 24" O.C. MAX in its own note and detail 3 does not, so on the A1 the 7/S5.20 schedule governs. | F147: STUD | G147: El detalle 3/A12.01 no trae nota de construccion propia que lo contradiga (a diferencia de 4/A12.01, que para los walls K pide 14 GA @ 24" O.C.
B148: 7 | C148: A09.01 | D148: Exclusion | E148: Exterior Elevations: "SOUTH ELEVATION" and "WEST ELEVATION" at 1/4"=1'-0". Extent of each exterior material and the material legend, verbatim "CJ CONTROL JOINT; PAINT TO MATCH STUCCO FINISH COLOR" - that joint is the STUCCO joint, not gypsum. | F148: excluded.CONTROL_JOINT | G148: Solo aparece en tres sitios y NINGUNO es de gypsum board: (1) la lista de abreviaturas de la portada, que define 'CJ CONTROL JOINT'; (2) la hoja civil de pavimentos, con su propio schedule de juntas segun la American Concrete Pavement Association; y (3) la leyenda de materiales exteriores de A09.01/A09.02, textual: '…
B149: 8 | C149: 10/A12.02 | D149: Exclusion | E149: "HEAD @ HOLLOW METAL FRAME" at 3"=1'-0". Head of the hollow metal frame: labels SCHEDULED PARTITION, METAL STUD, METAL CLIP, HOLLOW METAL FRAME and 1/2" of board lap per face inside the frame throat. | F149: excluded.CLIPS | G149: El otro es el METAL CLIP que 10/A12.02 HEAD @ HOLLOW METAL FRAME rotula en la union del door frame con el stud del header, y ese se excluye por DIVISION, no por soldadura: 11/A12.02 JAMB @ HOLLOW METAL FRAME llama METAL ANCHOR a la misma pieza en la jamb, o sea es el anchorage del hollow metal frame, que viene con la…
B150: 9 | C150: 11/A12.02 | D150: Exclusion | E150: "JAMB @ HOLLOW METAL FRAME" at 3"=1'-0". Jamb of the same frame: it calls METAL ANCHOR the piece detail 10 calls METAL CLIP, so the piece is frame anchorage (Div 08), not a clip of ours. | F150: excluded.CLIPS | G150: El otro es el METAL CLIP que 10/A12.02 HEAD @ HOLLOW METAL FRAME rotula en la union del door frame con el stud del header, y ese se excluye por DIVISION, no por soldadura: 11/A12.02 JAMB @ HOLLOW METAL FRAME llama METAL ANCHOR a la misma pieza en la jamb, o sea es el anchorage del hollow metal frame, que viene con la…
B151: 10 | C151: 1/S5.20 | D151: Quantity | E151: "TYPICAL WALL FRAMING DETAILS". Holds sub-details A through F; sub-detail F "BRIDGING AND BRACING - CONTINUOUS BRIDGING" is the bracing one: 1 1/2" C.R. CHANNEL welded to every stud. (Bracing is NOT in 5/S5.20, which is TYPICAL WALL FRAMING CONNX.) | F151: BRACING, excluded.CLIPS | G151: por el punchout del alma, soldado a cada stud (1/S5.20 sub-detalle F de S5.20).
B152: 11 | C152: 4/S5.20 | D152: Quantity | E152: "TYPICAL BLOCKING DETAIL". STUD BLOCKING 362CR22 and CLIP ANGLE 362CR22, with the boxed verbatim note "PROVIDE BLOCKING AT THE EDGE OF GYPBOARD." - source of the blocking at EVERY free edge of board. | F152: BLOCKING | G152: BOARD FREE EDGE: 4/S5.20 TYPICAL BLOCKING DETAIL carries a boxed note, TEXTUAL: 'PROVIDE BLOCKING AT THE EDGE OF GYPBOARD.', with STUD BLOCKING 362CR22 (TYP.) and CLIP ANGLE 362CR22 (TYP.) & BLOCKING W/ SCREWS (TYP.).
B153: 12 | C153: 7/S5.20 | D153: Quantity | E153: "METAL STUDS SCHEDULES". The profile: web, flange, lip, mils, gauge and the APPLICATION column with the spacing ("INTERIOR WALLS @ 16" O.C."), plus the SILL TRACK ANCHORAGE and the FASTENER SCHEDULE. | F153: STUD, TRACK_BOTTOM | G153: 7/S5.20 METAL STUDS SCHEDULES, renglon 362S137-33: alma 3 5/8", ala 1 3/8", lip 3/8", 33 mil = 20 ga, APPLICATION 'INTERIOR WALLS @ 16" O.C.'.
B154: 13 | C154: A00.01 | D154: Scope | E154: Cover sheet and Drawing Index. Proof by ABSENCE: the index lists no interior Demolition Plan, which is why there is no patch-and-repair line item. | F154: excluded.PATCH, scope[1].chain[0] | G154: A02.01 Construction Plan Legend: la grafia de dos lineas limpias es NEW PARTITION (SEE SCHEDULE); no hay Demolition Plan interior en el Drawing Index de A00.01
...

Sheet Handoff - Bid Set
A1: EVERY SHEET OF THE BID SET - read from the DRAWING INDEX of A00.00 and from the title block of each page
A2: 94 PDF pages = 92 sheets in the index + 2 extra copies of A02.02. State CONFIRMADO means a title block was read on that page; DERIVADO means it was assigned by position (civil and landscape sheets, whose consultant title block has another format).
A4: Sheet | B4: Title | C4: PDF page | D4: State
A5: A00.00 | B5: DRAWING INDEX, LOCATION MAP & PROJECT INFORMATION | C5: 2 | D5: [CONFIRMADO]
A6: C1.0 | B6: COVER SHEET | C6: 1 | D6: [DERIVADO]
A7: C1.1 | B7: GENERAL NOTES | C7: 3 | D7: [DERIVADO]
A8: C1.2 | B8: ALTA LAND TITLE | C8: 4 | D8: [DERIVADO]
A9: C1.3 | B9: ALTA LAND TITLE | C9: 5 | D9: [DERIVADO]
A10: C1.4 | B10: ALTA LAND TITLE | C10: 6 | D10: [DERIVADO]
A11: C2.0 | B11: DEMOLITION AND EROSION CONTROL PLAN | C11: 7 | D11: [DERIVADO]
A12: C3.0 | B12: SITE PLAN | C12: 8 | D12: [DERIVADO]
A13: C4.0 | B13: GRADING PLAN | C13: 9 | D13: [DERIVADO]
A14: C5.0 | B14: DRAINAGE PLAN | C14: 10 | D14: [DERIVADO]
A15: C5.1 | B15: DRAINAGE PROFILE | C15: 11 | D15: [DERIVADO]
... A96: P03.01 | B96: PLUMBING RISER DIAGRAMS | C96: 94 | D96: [CONFIRMADO]
A98: Revision log of A00.00
A99: IF Schematic Design Final | C99: 09/29/2023
A100: IF COE Package | C100: 11/09/2023
A101: IF Design Development 90% | C101: 07/19/2024
A102: IF Design Development Final | C102: 08/19/2024
A103: IF Construction Document | C103: 09/20/2024
A104: IF Construction Document Final | C104: 12/05/2024
A105: IF CD 90 | C105: 08/15/2025
A106: IF Permit | C106: 08/26/2025

Sheet Handoff - Types
A1: PARTITION TYPES - composition, source and sealed state
A3: Tag | B3: Walls | C3: Stud size | D3: Designation | E3: O.C. | F3: Rows | G3: Brace O.C. | H3: Board by face | I3: Stud height ft | J3: State of the height | K3: Source of the stud profile | L3: Insulation
A4: A1 | B4: #1, #2, #3, #4, #5, #6, #7, #8, #9 | C4: 3-5/8" | D4: 362S137-33 | E4: 16 | F4: 1 | G4: 48 | H4: 5/8 GYP x1 (walls #1, #2, #3, #4, #5, #6, #7, #8, #9) | I4: 15.375 ft on #1, #2, #3, #4 | 12.971 ft on #5 | 12.927 ft on #6 | 12.963 ft on #7 | 12.890 ft on #8 | 12.775 ft on #9 | J4: [DERIVADO] | [DERIVADO] | [DERIVADO] | [DERIVADO] | [DERIVADO] | [DERIVADO] | K4: 7/S5.20 METAL STUD PROPERTIES, fila 3 5/8", APPLICATION "INTERIOR WALLS @ 16" O.C." | L4: Fuera de alcance por instruccion de Rodolfo del 19-sep-2026: 'por ahora no hacemos insulation'. El plano SI la pide -el schedule de 3/A12.01 dice INSULATION YES
A5: A1K | B5: #11, #12, #13 | C5: 3-5/8" | D5: 362S137-68 | E5: 24 | F5: 1 | G5: 48 | H5: 5/8 GYP 1 layer x1 (walls #11, #12, #13) | I5: 15.375 ft on #11 | 12.933 ft on #12 | 12.921 ft on #13 | J5: [DERIVADO] | [DERIVADO] | [DERIVADO] | K5: 4/A12.01 fila A1K: "14 GA. METAL STUDS @ 24" O.C. MAX" (balistico; mas grueso que el 33 mil del schedule) | L5: Excluida por instruccion de alcance del usuario. El plano SI la pide: la fila A1K del schedule de 4/A12.01 pone INSULATION YES y el detalle dibuja la cavidad. D
A6: A5 | B6: #14, #15, #16, #17 | C6: 6" | D6: 600S137-33 | E6: 16 | F6: 1 | G6: 48 | H6: 5/8 GYP x1 (walls #14, #15, #16, #17) | I6: 15.375 ft on #14, #15 | 13.052 ft on #16 | 12.927 ft on #17 | J6: [DERIVADO] | [DERIVADO] | [DERIVADO] | K6: A12.01 PARTITION SCHEDULE, fila "A5 | 6" | -- | -- | 5/8" | 7 1/4" | YES": stud de 6" y WALL THICKNESS 7 1/4" = 6 + 5/8 + 5/8. El thickness medido en planta (10.92 pt = 7.28") lo confirma | L6: Out of scope by Rodolfo's instruction of 19-sep-2026. The drawings DO call for it: the A5 row of the A12.01 schedule reads INSULATION YES and 3/A12.01 PARTITION
A7: B | B7: #18, #19, #20, #21, #22, #23 | C7: 3-5/8" | D7: 362S137-33 | E7: 16 | F7: 1 | G7: 48 | H7: 5/8 GYP x1 (walls #18, #19, #20, #21, #22, #23) | I7: 12.827 ft on #18 | 12.743 ft on #19 | 12.748 ft on #20 | 12.666 ft on #21 | 12.698 ft on #22 | 12.831 ft on #23 | J7: [DERIVADO] | [DERIVADO] | [DERIVADO] | [DERIVADO] | [DERIVADO] | [DERIVADO] | K7: A12.01 PARTITION SCHEDULE, fila "B | 3 5/8" | -- | -- | 5/8" | 4 7/8" | YES" = 3 5/8 + 5/8 + 5/8 | L7: Out of scope by Rodolfo's instruction of 19-sep-2026. The drawings DO ask for it: the B row of the A12.01 schedule reads INSULATION YES and 1/A12.01 PARTITION T
A8: B2 | B8: #25, #26, #27, #28 | C8: 6" | D8: 600S137-33 | E8: 16 | F8: 1 | G8: 48 | H8: 5/8 GYP x1 (walls #25, #26, #27, #28) | I8: 15.375 ft on #25 | 13.052 ft on #26, #27, #28 | J8: [DERIVADO] | [DERIVADO] | K8: A12.01 PARTITION SCHEDULE, fila "B2 | 6" | -- | -- | 5/8" | 7 1/4" | YES". El propio cierre nombra 600S137-33 y 600T125-33, y el thickness medido (10.80 pt = 7.20") cuadra con 7 1/4" | L8: Fuera de alcance por instruccion de Rodolfo del 19-sep-2026: 'por ahora no hacemos insulation'. 1/A12.01 marca INSULATION: YES para B2 y dibuja BATT INSULATION,
A9: B2K | B9: #31 | C9: 6" | D9: 600S137-68 | E9: 24 | F9: 1 | G9: 48 | H9: 5/8 GYP x1 (walls #31) | I9: 15.375 ft on #31 | J9: [DERIVADO] | K9: 4/A12.01: "14 GA. METAL STUDS @ 24" O.C. MAX"; alma y ala de la fila de 6" de S5.20, calibre 68 mil | L9: Out of scope by Rodolfo's instruction of 19-sep-2026. The drawings DO call for it: the A5K row of 4/A12.01 PARTITION TYPE A1K & A5K, from which B2K is derived,
A10: BULKHEAD-G | B10: #54, #55 | C10: 1-5/8" | D10: 162S-family | E10: 16 | F10: 2 | G10: 48 | H10: 5/8 GYP x2 layers x2 (walls #54, #55) | I10: 7.333 ft on #54, #55 | J10: [DERIVADO] | K10: 8 y 9/A12.01 BULKHEAD del office front: stud 1 5/8" (familia G), doble row | L10: Excluida por instruccion de alcance del usuario. El detalle 9/A12.01 SI dibuja la cavidad con el SOUNDGUARD ISOLATOR BY MARINOWARE entre las dos rows y la fila
A11: C1 | B11: #32, #33, #34, #35, #36, #37, #38, #39 | C11: 3-5/8" | D11: 362S137-33 | E11: 16 | F11: 1 | G11: 48 | H11: 5/8 GYP x1 (walls #32, #33, #34, #35, #36, #37, #38, #39) | I11: 10.000 ft on #32, #33 | 11.500 ft on #34, #35, #36 | 9.000 ft on #37, #38, #39 | J11: [DERIVADO] | [DERIVADO] | [DERIVADO] | K11: 7/S5.20 METAL STUD PROPERTIES, fila 3 5/8" | L11: Out of scope by Rodolfo's instruction of 19-sep-2026, and 6/A12.01 PARTITION TYPE C1 does not draw it either: C1 is furring against the structure, with no cavit
A12: CANOPY-COL | B12: #66, #67, #68, #69 | C12: 3-5/8" | D12: 362S137-33 | E12: 16 | F12: 1 | G12: 48 | H12: 5/8 EXTERIOR GRADE FRT PLYWOOD x1 (walls #66, #67, #68, #69) | I12: 10.500 ft on #66, #67, #68, #69 | J12: [DERIVADO] | K12: 5/A09.25 DETAIL @ CANOPY COLUMN: "STUCCO SYSTEM (PT-03) ON 5/8" EXTERIOR GRADE FRT PLYWOOD ON 3-5/8" METAL FRAMING" | L12: EXCLUDED por instruccion de alcance del usuario (no insulation en este bid). 5/A09.25 no rotula insulation dentro del furring de la columna; el "SPRAY FOAM INSU
A13: EXT-6CFMF | B13: #60, #61, #62, #63, #64, #65 | C13: 6" | D13: 600S137-33 | E13: 16 | F13: 1 | G13: 48 | H13: 5/8 GYP x1 (walls #60, #61, #62, #63, #64, #65) | I13: 15.375 ft on #60, #64, #65 | 14.520 ft on #61 | 12.531 ft on #62 | 13.990 ft on #63 | J13: [DERIVADO] | [DERIVADO] | [DERIVADO] | [DERIVADO] | K13: 7/S5.20 fila 6", APPLICATION "EXTERIOR WALLS @ 16" O.C."; H/A09.23 rotula "6" CFMF" | L13: Excluida por instruccion de alcance del usuario. El plano SI la pide: H/A09.23 rotula SPRAY FOAM INSULATION en la cavidad del 6" CFMF y MIN. 6" RIGID INSULATION
A14: EXT-PARAPET | B14: #160, #161, #162, #163, #164, #165 | C14: 6" 54mil | D14: 600S162-54 | E14: 16 | F14: 1 | G14: 48 | H14: 5/8 EXTERIOR GYPSUM SHEATHING x1 (walls #160, #161, #162, #163, #164, #165) | I14: 2.042 ft on #160 | 2.897 ft on #161 | 4.886 ft on #162 | 3.427 ft on #163 | 4.292 ft on #164, #165 | J14: [DERIVADO] | [DERIVADO] | [DERIVADO] | [DERIVADO] | [DERIVADO] | K14: 11/S5.10 PARAPET INFILL FRAMING: "PARAPET WALL INFILL FRAMING TO BE 600S162-54 @ 16" W/ 600T125-54 TOP & BOT." -- 54 mil, NO los 33 mil del wall de abajo | L14: Excluida por instruccion de alcance del usuario. El plano SI la pide: H/A09.23 rotula SPRAY FOAM INSULATION en la cavidad del 6" CFMF y MIN. 6" RIGID INSULATION
A15: F | B15: #40 | C15: 3-5/8" | D15: 362S137-33 | E15: 16 | F15: 1 | G15: 48 | H15: 5/8 GYP + 3/4 FRT PLYWOOD x1 (walls #40) | 5/8 GYP x1 (walls #40) | I15: 15.375 ft on #40 | J15: [DERIVADO] | K15: 12/A12.01 PARTITION TYPE F, rotulado TEXTUALMENTE 3 5/8" @ 16" O.C. | L15: Excluida por instruccion de alcance del usuario. El detalle 12/A12.01 SI la dibuja y la rotula BATT INSULATION dentro de la cavidad. Delta declarado en Clarific
... A17: G1 | B17: #50, #51, #53 | C17: 1-5/8" | D17: 162S-family | E17: 16 | F17: 2 | G17: 48 | H17: 5/8 GYP x2 layers x2 (walls #50, #51, #53) | I17: 15.375 ft on #50, #51, #53 | J17: [DERIVADO] | K17: 5/A12.01 fila G1: stud 1 5/8", doble row | L17: Excluida por instruccion de alcance del usuario (NO INSULATION). El plano SI la pide: la fila G1 del schedule de A12.01 pone INSULATION YES y el detalle 5/A12.0

Sheet Handoff - Locations
A1: NUMBERED LOCATION LIST PER TAG - the official wall numbering fixed 13-sep-2026
A2: What Rodolfo explicitly confirmed is a SEPARATE fact from what was quantified, and it was never written to a file. The confirmation column says what is recorded; where nothing is recorded it says PENDIENTE rather than claiming a confirmation.
A4: Tag | B4: # | C4: Wall | D4: Location as sealed | E4: LF | F4: State of the LF | G4: Confirmed by Rodolfo
A5: A1 | B5: 1 | C5: #1 | D5: Central Zone 103 / Calling Cubes 122 - north wall of Calling Cubes | E5: 16.42 | F5: [DERIVADO] | G5: [PENDIENTE] see Handoff - Open Items
A6: A1 | B6: 2 | C6: #2 | D6: MW01 niche / Calling Cubes 122 - back of the printer cabinet | E6: 3.13 | F6: [CONFIRMADO] | G6: [PENDIENTE] see Handoff - Open Items
A7: A1 | B7: 3 | C7: #3 | D7: MW01 niche / Calling Cubes 122 - south close of the niche | E7: 2.63 | F7: [CONFIRMADO] | G7: [PENDIENTE] see Handoff - Open Items
A8: A1 | B8: 4 | C8: #4 | D8: Corridor 111 - jambs of door 111, entry from Central Zone | E8: 5 | F8: [CONFIRMADO] | G8: [PENDIENTE] see Handoff - Open Items
A9: A1 | B9: 5 | C9: #5 | D9: Calling Cubes 122 / Break Room 118 - carries MW21 on the south face | E9: 15.23 | F9: [DERIVADO] | G9: [PENDIENTE] see Handoff - Open Items
A10: A1 | B10: 6 | C10: #6 | D10: Break Room 118 / Future FCAM - carries door 118A | E10: 5.5 | F10: [CONFIRMADO] | G10: [PENDIENTE] see Handoff - Open Items
A11: A1 | B11: 7 | C11: #7 | D11: Break Room 118 / Cash Window 116 - vertical return between walls A1-5 and A1-6 | E11: 1.73 | F11: [DERIVADO] | G11: [PENDIENTE] see Handoff - Open Items
A12: A1 | B12: 8 | C12: #8 | D12: Corridor 111 / Break Room 118 + Electrical 120 + NER 121 - the long wall (tags #8 and #10) | E12: 17.06 | F12: [DERIVADO] | G12: [PENDIENTE] see Handoff - Open Items
A13: A1 | B13: 9 | C13: #9 | D13: Cash Window 116 / Work Room 119 - north wall of the Work Room, carries MW12 and door 119 | E13: 11.667 | F13: [DERIVADO] | G13: [PENDIENTE] see Handoff - Open Items
A14: A1K | B14: 1 | C14: #11 | D14: NORTH head of Cash Window 116 / CSR line (banda y 1120.68/1128.48) | E14: 3.417 | F14: [CONFIRMADO] | G14: [PENDIENTE] see Handoff - Open Items
A15: A1K | B15: 2 | C15: #12 | D15: SOUTH head of Cash Window 116 (banda y 1344.72/1352.64) | E15: 3.413 | F15: [DERIVADO] | G15: [PENDIENTE] see Handoff - Open Items
A16: A1K | B16: 3 | C16: #13 | D16: Southwest return at Cash Window 116 (banda y 1355.28/1363.08) | E16: 1.16 | F16: [DERIVADO] | G16: [PENDIENTE] see Handoff - Open Items
... A71: G1 | B71: 3 | C71: #53 | D71: South return at the Office 6 CB 110 office front, UNTAGGED (left block) | E71: 2.67 | F71: [DERIVADO] | G71: [PENDIENTE] see Handoff - Open Items

Sheet Handoff - Open Items
A1: WHAT IS STILL MISSING - sealed pendings, traceability backlog and orphan closures
A3: A. Sealed closures with NO generator (orphans)
A4: Block | B4: Walls | C4: What is missing
A6: B. [CONFIRMADO] fields that cite no printed dimension (ratchet 0, only goes down)
A7: Element | B7: Field | C7: Sealed value | D7: Text that cites no dimension
A9: C. The same datum carrying two state tags
A10: Field | B10: Value | C10: Sheet cited | D10: States and how many walls carry each
A12: D. What Rodolfo confirmed, and what is only verified by code
A13: Subject | B13: State | C13: What is recorded, and where
A14: numeracion | B14: [CONFIRMADO] | C14: Rodolfo fijo la numeracion oficial de walls el 13-sep-2026: A1 #1-10 / A1K #11-13 / A5 #14-17 / B #18-24 / B2 #25-30 / B2K #31 / C1 #32-39 / F #40 / G #41-49 / G1 #50-51, agrupada por tag, y ANULO la numeracion por longitud descendente y el plano BOA_48_muros_numerados.png. Consta en el registro del proyecto.
A15: soffits_19_69 | B15: [CONFIRMADO] | C15: El 15-sep-2026 ordeno AGREGAR los 19.69 LF de ceiling transition que faltaban contra su take-off manual (247.85 contra 228.16 LF).
A16: este_suma_tramos | B16: [CONFIRMADO] | C16: El usuario DETECTO el error del eje ESTE: el 72'-8 1/4" se habia armado sumando tramos de una dimension string con ticks DOBLES, que mide cuartos face to face y no incluye el thickness de los 6 walls perpendiculares.
A17: barrido_por_tag | B17: [PENDIENTE] | C17: La regla del 12-sep-2026 exige parar al cerrar el barrido de cada tag y esperar confirmacion explicita de que la lista de ubicaciones esta completa. El registro del proyecto deja el barrido de A02.01 como "EN CURSO, pendiente de confirmacion del usuario" y su proximo paso escrito es exactamente "mostrar al usuario la lista numerada de ubicaciones por tag y esperar su confirmacion explicita". NO consta en ningun archivo que esa confirmacion se haya dado tag por tag. Lo que SI consta es el barrido verificado por codigo (los 51 tags de A02.01 extraidos del texto del PDF, con su imagen circulada) y la compuerta de planos marcados, que comprueba que el LF rotulado en el plano de cada tipo coincide con el cierre sellado. Son dos cosas distintas y el handoff no las puede presentar como una.

Sheet Handoff - Approved
A1: ASSUMPTIONS AND DECISIONS RODOLFO APPROVED - each with what approved it
A3: Decision | B3: What it means in the numbers | C3: What approved it
A4: No insulation | B4: Located and cited everywhere it occurs and EXCLUDED with the motive written in every closure. The drawings DO call for it (the A1K row of 4/A12.01 reads INSULATION YES and the detail draws the cavity); the delta is declared in Clarifications and in Pending Items #22. | C4: Standing scope order from Rodolfo: no insulation, no cabinets, no light fixtures.
A5: No cabinets, no light fixtures | B5: Same treatment: located, cited, EXCLUDED with motive. | C5: Same standing scope order.
A6: Waste 15% metal / 6% board | B6: Applied on NET, by type, each type separately, and shown in its own NET / WASTE / PURCHASE columns, never buried in a takeoff figure. | C6: Standing order from Rodolfo.
A7: Storefront and officefront are Division 08 | B7: The DFC-1A officefront of offices 105-110 is bought and installed through the bank vendor (note N of the Door Schedule, A00.30) and the aluminium storefront AF-2 with GL-2 glazing is Division 08. Only the bulkhead above the officefront and its framing are ours. | C7: Confirmed as scope by Rodolfo; the drawing note is quoted in Clarifications.
A8: South zone deck height taken at the HIGH end | B8: In the sloped bay the B.O.D. runs from 13'-0 5/8" to 12'-6 3/8". The quote uses the high end of each wall, interpolated at the y of that wall by bod_s(y), because studs are cut to the highest condition of the zone. Total variation of the zone is 6 1/4". | C8: Criterion adopted and recorded 2026-09-15; it moves under 1% of the board SF.
A9: Track-to-slab fastener spacing at 12" O.C. | B9: Three values live in the set: 12" O.C. (SILL TRACK ANCHORAGE of 7/S5.20, interior walls), 16" O.C. (FASTENER SCHEDULE next to 3/S5.20) and 2'-0" O.C. (the box of 4/A12.01, which governs its own type). The tightest, 12" O.C., is quoted and the difference goes to Clarifications and to Pending Items #4. | C9: Criterion adopted; it is an open RFI, priced on the safe side meanwhile.
A10: Cementitious backer board under any tile | B10: Trade judgement that prevails over what the drawing shows, with the difference noted. | C10: Standing order from Rodolfo.
A11: Accesorios always include trims, taping, drywall screws, framing screws and track pins | B11: No line item is left out of the accessory group. | C11: Standing order from Rodolfo.
A12: Everything in English | B12: Material, tool, component, process and abbreviation names of the drywall and metal frame trades are written in English in every deliverable and in every response, enforced by verif_idioma.py and verif_respuesta.py. | C12: Permanent inviolable instruction from Rodolfo, 7-oct-2026, quoted in full in adenda v39.
