Workbook

Sheet Inputs
A1: Bank of America - Broomfield, CO (CO1-111) | METAL FRAMING & DRYWALL TAKEOFF
A2: Bid set: 2025.08.26_CO1-111_Broomfield_PERMIT SET_BID SET.pdf · 2026-10-16 · Edit ONLY the yellow cells.
A3: PARAMETER | B3: VALUE | C3: NOTE / SOURCE
A4: Waste - ALL METAL, any type | B4: 0.15 | C4: Estimator standing rule.
A5: Waste - EVERYTHING THAT IS NOT METAL | B5: 0.06 | C5: Same figure as board.
A6: Board sheet width (ft) | B6: 4
A7: Board sheet length (ft) | B7: 12
A8: SF per board sheet | B8: =B6*B7 -> 48 | C8: Width x length.
A9: Stud stock length (ft) | B9: 20
A10: Track stock length (ft) | B10: 10

Sheet Partition Takeoff
A1: ORGANIZED PARTITION TAKEOFF - Bank of America - Broomfield, CO (CO1-111)
A2: Grouped by partition type. Every row cites its DETAIL/SHEET and its status.
A4: Partition / Scope | B4: Wall # | C4: Length (LF) | D4: Height (FT) | E4: Layers | F4: Stud Size | G4: Stud O.C. (in) | H4: Board (SF) | I4: Location | J4: Source (DETAIL/SHEET) | K4: Status
A5: TYPE A1
A6: A1 #1 - Calling Cubes 122 north / Waiting 104 || Waiting 104 (GB 11'-0"): 1L 5/8" gypsum board to 11.5 ft x 16.42 LF | Calling Cubes 122 (ACT-5 8'-6"): 1L 5/8" gypsum board to 9.0 ft x 14.4 LF | MW01 niche (A04.01 key note 1 OPEN TO STRUCTURE): 1L 5/8" gypsum board to 15.375 ft x 2.02 LF | B6: 1 | C6: 16.42 | D6: 15.375 | E6: 2 | F6: 3-5/8" 362S137-33 | G6: 16 | H6: 349.49 | I6: Calling Cubes 122 north / Waiting 104 || Waiting 104 (GB 11'-0"): 1L 5/8" gypsum board to 11.5 ft x 16.42 LF | Calling Cubes 122 (ACT-5 8'-6"): 1L 5/8" gypsum board to 9.0 ft x 14.4 LF | MW01 niche (A04.01 key note 1 OPEN TO STRUCTURE): 1L 5/8" gypsum board to 15.375 ft x 2.02 LF | J6: 3/A12.01; 7/S5.20 | K6: [DERIVADO]
A7: A1 #2 - MW01 niche east / Calling Cubes 122 || MW01 niche (A04.01 key note 1 OPEN TO STRUCTURE): 1L 5/8" gypsum board to 15.375 ft x 3.533 LF | Calling Cubes 122 (ACT-5 8'-6"): 1L 5/8" gypsum board to 9.0 ft x 3.533 LF | B7: 2 | C7: 3.533 | D7: 15.375 | E7: 2 | F7: 3-5/8" 362S137-33 | G7: 16 | H7: 86.12 | I7: MW01 niche east / Calling Cubes 122 || MW01 niche (A04.01 key note 1 OPEN TO STRUCTURE): 1L 5/8" gypsum board to 15.375 ft x 3.533 LF | Calling Cubes 122 (ACT-5 8'-6"): 1L 5/8" gypsum board to 9.0 ft x 3.533 LF | J7: 3/A12.01; 7/S5.20 | K7: [DERIVADO]
A8: A1 #3 - MW01 niche south / Calling Cubes 122 || MW01 niche (A04.01 key note 1 OPEN TO STRUCTURE): 1L 5/8" gypsum board to 15.375 ft x 2.02 LF | Calling Cubes 122 (ACT-5 8'-6"): 1L 5/8" gypsum board to 9.0 ft x 2.02 LF | B8: 3 | C8: 2.02 | D8: 15.375 | E8: 2 | F8: 3-5/8" 362S137-33 | G8: 16 | H8: 49.24 | I8: MW01 niche south / Calling Cubes 122 || MW01 niche (A04.01 key note 1 OPEN TO STRUCTURE): 1L 5/8" gypsum board to 15.375 ft x 2.02 LF | Calling Cubes 122 (ACT-5 8'-6"): 1L 5/8" gypsum board to 9.0 ft x 2.02 LF | J8: 3/A12.01; 7/S5.20 | K8: [DERIVADO]
A9: A1 #4 - Corridor 111 north (door 111) || Central Zone 103 aisle (ACT-4 11'-6"): 1L 5/8" gypsum board to 12.0 ft x 5.587 LF | Corridor 111 (ACT-4 8'-6"): 1L 5/8" gypsum board to 9.0 ft x 5.587 LF | B9: 4 | C9: 5.587 | D9: 15.375 | E9: 2 | F9: 3-5/8" 362S137-33 | G9: 16 | H9: 62.88 | I9: Corridor 111 north (door 111) || Central Zone 103 aisle (ACT-4 11'-6"): 1L 5/8" gypsum board to 12.0 ft x 5.587 LF | Corridor 111 (ACT-4 8'-6"): 1L 5/8" gypsum board to 9.0 ft x 5.587 LF | J9: 3/A12.01; 7/S5.20 | K9: [DERIVADO]
A10: A1 #5 - Calling Cubes 122 south / Break 118 || Calling Cubes 122 (ACT-5 8'-6"): 1L 5/8" gypsum board to 9.0 ft x 15.233 LF | Break Room 118 (ACT-5 8'-6"): 1L 5/8" gypsum board to 9.0 ft x 15.233 LF | B10: 5 | C10: 15.233 | D10: 12.971 | E10: 2 | F10: 3-5/8" 362S137-33 | G10: 16 | H10: 274.2 | I10: Calling Cubes 122 south / Break 118 || Calling Cubes 122 (ACT-5 8'-6"): 1L 5/8" gypsum board to 9.0 ft x 15.233 LF | Break Room 118 (ACT-5 8'-6"): 1L 5/8" gypsum board to 9.0 ft x 15.233 LF | J10: 3/A12.01; 7/S5.20 | K10: [DERIVADO]
A11: A1 #6 - Break 118 NE stub || Break Room 118 (ACT-5 8'-6"): 1L 5/8" gypsum board to 9.0 ft x 1.733 LF | Waiting 104 east aisle (ACT-4 9'-0"): 1L 5/8" gypsum board to 9.5 ft x 1.733 LF | B11: 6 | C11: 1.733 | D11: 12.963 | E11: 2 | F11: 3-5/8" 362S137-33 | G11: 16 | H11: 32.06 | I11: Break 118 NE stub || Break Room 118 (ACT-5 8'-6"): 1L 5/8" gypsum board to 9.0 ft x 1.733 LF | Waiting 104 east aisle (ACT-4 9'-0"): 1L 5/8" gypsum board to 9.5 ft x 1.733 LF | J11: 3/A12.01; 7/S5.20 | K11: [DERIVADO]
A12: A1 #7 - Break 118 north (door 118A) || Waiting 104 east aisle (ACT-4 9'-0"): 1L 5/8" gypsum board to 9.5 ft x 5.107 LF | Break Room 118 (ACT-5 8'-6"): 1L 5/8" gypsum board to 9.0 ft x 5.107 LF | B12: 7 | C12: 5.107 | D12: 12.927 | E12: 2 | F12: 3-5/8" 362S137-33 | G12: 16 | H12: 40.04 | I12: Break 118 north (door 118A) || Waiting 104 east aisle (ACT-4 9'-0"): 1L 5/8" gypsum board to 9.5 ft x 5.107 LF | Break Room 118 (ACT-5 8'-6"): 1L 5/8" gypsum board to 9.0 ft x 5.107 LF | J12: 3/A12.01; 7/S5.20 | K12: [DERIVADO]
A13: A1 #8 - Corridor 111 east / Break, Electrical 120, NER 121 || Corridor 111 (ACT-4 8'-6"): 1L 5/8" gypsum board to 9.0 ft x 17.06 LF | Break Room 118 (ACT-5 8'-6"): 1L 5/8" gypsum board to 9.0 ft x 2.913 LF | Electrical 120 / NER 121 (A04.01 key note 1 OPEN TO STRUCTURE): 1L 5/8" gypsum board to 12.891 ft x 14.147 LF | B13: 8 | C13: 17.06 | D13: 12.891 | E13: 2 | F13: 3-5/8" 362S137-33 | G13: 16 | H13: 362.13 | I13: Corridor 111 east / Break, Electrical 120, NER 121 || Corridor 111 (ACT-4 8'-6"): 1L 5/8" gypsum board to 9.0 ft x 17.06 LF | Break Room 118 (ACT-5 8'-6"): 1L 5/8" gypsum board to 9.0 ft x 2.913 LF | Electrical 120 / NER 121 (A04.01 key note 1 OPEN TO STRUCTURE): 1L 5/8" gypsum board to 12.891 ft x 14.147 LF | J13: 3/A12.01; 7/S5.20 | K13: [DERIVADO]
A14: A1 #9 - Work Room 119 north / Cash Window 116 (door 119) || Cash Window 116 (ACT-4 9'-0"): 1L 5/8" gypsum board to 9.5 ft x 11.667 LF | Work Room 119 (ACT-5 8'-6"): 1L 5/8" gypsum board to 9.0 ft x 11.667 LF | B14: 9 | C14: 11.667 | D14: 12.775 | E14: 2 | F14: 3-5/8" 362S137-33 | G14: 16 | H14: 168.07 | I14: Work Room 119 north / Cash Window 116 (door 119) || Cash Window 116 (ACT-4 9'-0"): 1L 5/8" gypsum board to 9.5 ft x 11.667 LF | Work Room 119 (ACT-5 8'-6"): 1L 5/8" gypsum board to 9.0 ft x 11.667 LF | J14: 3/A12.01; 7/S5.20 | K14: [CONFIRMADO]
A15: A1 #10 - Drinking fountain alcove (back + 2 returns 1.90 ft) - SIN TAG, nota A/A02.01 || Corridor 111 drinking fountain alcove (ACT-4 8'-6"): 1L 5/8" gypsum board to 9.0 ft x 8.01 LF | Women's 114 / Men's 113 returns + back wall above/below chase (GB 8'-6"): 1L 5/8" gypsum board to 9.0 ft x 6.93 LF | B15: 10 | C15: 8.01 | D15: 12.952 | E15: 1.87 | F15: 3-5/8" 362S137-33 | G15: 16 | H15: 134.46 | I15: Drinking fountain alcove (back + 2 returns 1.90 ft) - SIN TAG, nota A/A02.01 || Corridor 111 drinking fountain alcove (ACT-4 8'-6"): 1L 5/8" gypsum board to 9.0 ft x 8.01 LF | Women's 114 / Men's 113 returns + back wall above/below chase (GB 8'-6"): 1L 5/8" gypsum board to 9.0 ft x 6.93 LF | J15: 3/A12.01; 7/S5.20 | K15: [DERIVADO]
A16: TYPE A1K
A17: A1K #11 - Cash Window 116 teller line north || Teller side: 1L 5/8" gypsum board to 15.375 ft x 3.417 LF | Customer side (5/8" over 3/8" UL752 fiberglass to 8'-0"): 1L 5/8" gypsum board to 15.375 ft x 3.417 LF | B17: 11 | C17: 3.417 | D17: 15.375 | E17: 2 | F17: 3-5/8" 362S137-68 | G17: 24 | H17: 105.08 | I17: Cash Window 116 teller line north || Teller side: 1L 5/8" gypsum board to 15.375 ft x 3.417 LF | Customer side (5/8" over 3/8" UL752 fiberglass to 8'-0"): 1L 5/8" gypsum board to 15.375 ft x 3.417 LF | J17: 4/A12.01; 7/S5.20 | K17: [CONFIRMADO]
A18: A1K #12 - Cash Window 116 teller line south || Teller side: 1L 5/8" gypsum board to 12.939 ft x 4.573 LF | Customer side (5/8" over 3/8" UL752 fiberglass to 8'-0"): 1L 5/8" gypsum board to 12.939 ft x 4.573 LF | B18: 12 | C18: 4.573 | D18: 12.939 | E18: 2 | F18: 3-5/8" 362S137-68 | G18: 24 | H18: 118.34 | I18: Cash Window 116 teller line south || Teller side: 1L 5/8" gypsum board to 12.939 ft x 4.573 LF | Customer side (5/8" over 3/8" UL752 fiberglass to 8'-0"): 1L 5/8" gypsum board to 12.939 ft x 4.573 LF | J18: 4/A12.01; 7/S5.20 | K18: [DERIVADO]
A19: TYPE A5
A20: A5 #13 - Calling Cubes 122 east || Calling Cubes 122 (ACT-5 8'-6"): 1L 5/8" gypsum board to 9.0 ft x 19.0 LF | Waiting 104 east aisle (ACT-4 11'-6" north of y=1110.72): 1L 5/8" gypsum board to 12.0 ft x 7.553 LF | Waiting 104 east aisle (ACT-4 9'-0" south of y=1110.72): 1L 5/8" gypsum board to 9.5 ft x 11.447 LF | B20: 13 | C20: 19 | D20: 15.375 | E20: 2 | F20: 6" 600S137-33 | G20: 16 | H20: 370.39 | I20: Calling Cubes 122 east || Calling Cubes 122 (ACT-5 8'-6"): 1L 5/8" gypsum board to 9.0 ft x 19.0 LF | Waiting 104 east aisle (ACT-4 11'-6" north of y=1110.72): 1L 5/8" gypsum board to 12.0 ft x 7.553 LF | Waiting 104 east aisle (ACT-4 9'-0" south of y=1110.72): 1L 5/8" gypsum board to 9.5 ft x 11.447 LF | J20: 3/A12.01; 7/S5.20 | K20: [CONFIRMADO]
A21: A5 #14 - Calling Cubes 122 west / Corridor (FEC-1) || Central Zone 103 west aisle (ACT-4 11'-6"): 1L 5/8" gypsum board to 12.0 ft x 10.593 LF | Calling Cubes 122 (ACT-5 8'-6"): 1L 5/8" gypsum board to 9.0 ft x 10.593 LF | B21: 14 | C21: 10.593 | D21: 15.375 | E21: 2 | F21: 6" 600S137-33 | G21: 16 | H21: 222.46 | I21: Calling Cubes 122 west / Corridor (FEC-1) || Central Zone 103 west aisle (ACT-4 11'-6"): 1L 5/8" gypsum board to 12.0 ft x 10.593 LF | Calling Cubes 122 (ACT-5 8'-6"): 1L 5/8" gypsum board to 9.0 ft x 10.593 LF | J21: 3/A12.01; 7/S5.20 | K21: [DERIVADO]
A22: A5 #15 - Calling Cubes 122 west at door 122 || Corridor 111 (ACT-4 8'-6"): 1L 5/8" gypsum board to 9.0 ft x 5.0 LF | Calling Cubes 122 (ACT-5 8'-6"): 1L 5/8" gypsum board to 9.0 ft x 5.0 LF | B22: 15 | C22: 5 | D22: 15.375 | E22: 2 | F22: 6" 600S137-33 | G22: 16 | H22: 42.22 | I22: Calling Cubes 122 west at door 122 || Corridor 111 (ACT-4 8'-6"): 1L 5/8" gypsum board to 9.0 ft x 5.0 LF | Calling Cubes 122 (ACT-5 8'-6"): 1L 5/8" gypsum board to 9.0 ft x 5.0 LF | J22: 3/A12.01; 7/S5.20 | K22: [DERIVADO]
A23: A5 #16 - Break 118 / Cash Window 116 || Break Room 118 (ACT-5 8'-6"): 1L 5/8" gypsum board to 9.0 ft x 3.713 LF | Cash Window 116 (ACT-4 9'-0"): 1L 5/8" gypsum board to 9.5 ft x 3.713 LF | B23: 16 | C23: 3.713 | D23: 12.927 | E23: 2 | F23: 6" 600S137-33 | G23: 16 | H23: 68.69 | I23: Break 118 / Cash Window 116 || Break Room 118 (ACT-5 8'-6"): 1L 5/8" gypsum board to 9.0 ft x 3.713 LF | Cash Window 116 (ACT-4 9'-0"): 1L 5/8" gypsum board to 9.5 ft x 3.713 LF | J23: 3/A12.01; 7/S5.20 | K23: [DERIVADO]
A24: TYPE B
A25: B #17 - Men's 113 south / Janitor 112 (door 112) || Men's 113 (GB 8'-6", board to deck 1/A12.01): 1L 5/8" gypsum board to 12.751 ft x 11.733 LF | Janitor 112 (OPEN TO STRUCTURE): 1L 5/8" gypsum board to 12.751 ft x 11.733 LF | B25: 17 | C25: 11.733 | D25: 12.751 | E25: 2 | F25: 3-5/8" 362S137-33 | G25: 16 | H25: 251.44 | I25: Men's 113 south / Janitor 112 (door 112) || Men's 113 (GB 8'-6", board to deck 1/A12.01): 1L 5/8" gypsum board to 12.751 ft x 11.733 LF | Janitor 112 (OPEN TO STRUCTURE): 1L 5/8" gypsum board to 12.751 ft x 11.733 LF | J25: 1/A12.01; 7/S5.20 | K25: [DERIVADO]
A26: B #18 - Janitor 112 / Storage 117 || Janitor 112: 1L 5/8" gypsum board to 12.743 ft x 3.5 LF | Storage 117: 1L 5/8" gypsum board to 12.743 ft x 3.5 LF | B26: 18 | C26: 3.5 | D26: 12.743 | E26: 2 | F26: 3-5/8" 362S137-33 | G26: 16 | H26: 89.2 | I26: Janitor 112 / Storage 117 || Janitor 112: 1L 5/8" gypsum board to 12.743 ft x 3.5 LF | Storage 117: 1L 5/8" gypsum board to 12.743 ft x 3.5 LF | J26: 1/A12.01; 7/S5.20 | K26: [DERIVADO]
A27: B #19 - Janitor 112 + Storage 117 / Wellness 115 || Janitor 112 / Storage 117: 1L 5/8" gypsum board to 12.67 ft x 11.733 LF | Wellness 115: 1L 5/8" gypsum board to 12.67 ft x 11.733 LF | B27: 19 | C27: 11.733 | D27: 12.67 | E27: 2 | F27: 3-5/8" 362S137-33 | G27: 16 | H27: 297.32 | I27: Janitor 112 + Storage 117 / Wellness 115 || Janitor 112 / Storage 117: 1L 5/8" gypsum board to 12.67 ft x 11.733 LF | Wellness 115: 1L 5/8" gypsum board to 12.67 ft x 11.733 LF | J27: 1/A12.01; 7/S5.20 | K27: [DERIVADO]
A28: B #20 - Electrical 120 north || Electrical 120: 1L 5/8" gypsum board to 12.831 ft x 9.583 LF | Corridor 111 / Break 118: 1L 5/8" gypsum board to 12.831 ft x 9.583 LF | B28: 20 | C28: 9.583 | D28: 12.831 | E28: 2 | F28: 3-5/8" 362S137-33 | G28: 16 | H28: 245.92 | I28: Electrical 120 north || Electrical 120: 1L 5/8" gypsum board to 12.831 ft x 9.583 LF | Corridor 111 / Break 118: 1L 5/8" gypsum board to 12.831 ft x 9.583 LF | J28: 1/A12.01; 7/S5.20 | K28: [CONFIRMADO]
A29: B #21 - Electrical 120 / NER 121 || Electrical 120: 1L 5/8" gypsum board to 12.702 ft x 9.583 LF | NER 121: 1L 5/8" gypsum board to 12.702 ft x 9.583 LF | B29: 21 | C29: 9.583 | D29: 12.702 | E29: 2 | F29: 3-5/8" 362S137-33 | G29: 16 | H29: 243.44 | I29: Electrical 120 / NER 121 || Electrical 120: 1L 5/8" gypsum board to 12.702 ft x 9.583 LF | NER 121: 1L 5/8" gypsum board to 12.702 ft x 9.583 LF | J29: 1/A12.01; 7/S5.20 | K29: [CONFIRMADO]
A30: B #22 - Electrical 120 + NER 121 east (doors 120,121) || Electrical 120 / NER 121: 1L 5/8" gypsum board to 12.831 ft x 14.147 LF | Break Room 118: 1L 5/8" gypsum board to 12.831 ft x 14.147 LF | B30: 22 | C30: 14.147 | D30: 12.831 | E30: 2 | F30: 3-5/8" 362S137-33 | G30: 16 | H30: 267.48 | I30: Electrical 120 + NER 121 east (doors 120,121) || Electrical 120 / NER 121: 1L 5/8" gypsum board to 12.831 ft x 14.147 LF | Break Room 118: 1L 5/8" gypsum board to 12.831 ft x 14.147 LF | J30: 1/A12.01; 7/S5.20 | K30: [DERIVADO]
A31: TYPE B2
A32: B2 #23 - ATM Room 102 east (door 102) || ATM Room 102: 1L 5/8" gypsum board to 15.375 ft x 5.333 LF | Central Zone 103: 1L 5/8" gypsum board to 15.375 ft x 5.333 LF | B32: 23 | C32: 5.333 | D32: 15.375 | E32: 2 | F32: 6" 600S137-33 | G32: 16 | H32: 101.38 | I32: ATM Room 102 east (door 102) || ATM Room 102: 1L 5/8" gypsum board to 15.375 ft x 5.333 LF | Central Zone 103: 1L 5/8" gypsum board to 15.375 ft x 5.333 LF | J32: 1/A12.01; 7/S5.20 | K32: [DERIVADO]
A33: B2 #24 - Corridor 111 west: Women's 114, Men's 113, Storage 117, Wellness 115 || Corridor 111: 1L 5/8" gypsum board to 13.101 ft x 25.393 LF | Women's 114 / Men's 113 / Storage 117 / Wellness 115: 1L 5/8" gypsum board to 13.101 ft x 25.393 LF | B33: 24 | C33: 25.393 | D33: 15.375 | E33: 2 | F33: 6" 600S137-33 | G33: 16 | H33: 417.22 | I33: Corridor 111 west: Women's 114, Men's 113, Storage 117, Wellness 115 || Corridor 111: 1L 5/8" gypsum board to 13.101 ft x 25.393 LF | Women's 114 / Men's 113 / Storage 117 / Wellness 115: 1L 5/8" gypsum board to 13.101 ft x 25.393 LF | J33: 1/A12.01; 7/S5.20 | K33: [DERIVADO]
A34: B2 #25 - Break 118 / Work Room 119 || Break Room 118: 1L 5/8" gypsum board to 12.781 ft x 11.74 LF | Work Room 119: 1L 5/8" gypsum board to 12.781 ft x 11.74 LF | B34: 25 | C34: 11.74 | D34: 12.781 | E34: 2 | F34: 6" 600S137-33 | G34: 16 | H34: 300.1 | I34: Break 118 / Work Room 119 || Break Room 118: 1L 5/8" gypsum board to 12.781 ft x 11.74 LF | Work Room 119: 1L 5/8" gypsum board to 12.781 ft x 11.74 LF | J34: 1/A12.01; 7/S5.20 | K34: [DERIVADO]
A35: TYPE B2K
A36: B2K #26 - Office 108 south / Cash Window 116 at teller line || Office 108 (board to deck): 1L 5/8" gypsum board to 15.375 ft x 1.773 LF | Waiting 104 customer side (5/8" over 3/8" UL752 fiberglass to 8'-0"): 1L 5/8" gypsum board to 15.375 ft x 1.773 LF | B36: 26 | C36: 1.773 | D36: 15.375 | E36: 2 | F36: 6" 600S137-68 | G36: 24 | H36: 54.52 | I36: Office 108 south / Cash Window 116 at teller line || Office 108 (board to deck): 1L 5/8" gypsum board to 15.375 ft x 1.773 LF | Waiting 104 customer side (5/8" over 3/8" UL752 fiberglass to 8'-0"): 1L 5/8" gypsum board to 15.375 ft x 1.773 LF | J36: 4/A12.01; 7/S5.20 | K36: [DERIVADO]
A37: TYPE C1
A38: C1 #27 - Plumbing chase - Women's 114 face || Women's 114 (GB 8'-6"): 1L 5/8" gypsum board to 9.0 ft x 10.027 LF | B38: 27 | C38: 10.027 | D38: 12.918 | E38: 1 | F38: 3-5/8" 362S137-33 | G38: 16 | H38: 90.24 | I38: Plumbing chase - Women's 114 face || Women's 114 (GB 8'-6"): 1L 5/8" gypsum board to 9.0 ft x 10.027 LF | J38: 6/A12.01; 7/S5.20 | K38: [DERIVADO]
A39: C1 #28 - Plumbing chase - Men's 113 face || Men's 113 (GB 8'-6"): 1L 5/8" gypsum board to 9.0 ft x 10.027 LF | B39: 28 | C39: 10.027 | D39: 12.896 | E39: 1 | F39: 3-5/8" 362S137-33 | G39: 16 | H39: 90.24 | I39: Plumbing chase - Men's 113 face || Men's 113 (GB 8'-6"): 1L 5/8" gypsum board to 9.0 ft x 10.027 LF | J39: 6/A12.01; 7/S5.20 | K39: [DERIVADO]
A40: C1 #29 - Monitor furring (key note 7) Waiting 104 || Waiting 104 (GB 11'-0") face + 2 returns 8": 1L 5/8" gypsum board to 11.5 ft x 11.333 LF | B40: 29 | C40: 11.333 | D40: 15.375 | E40: 1 | F40: 3-5/8" 362S137-33 | G40: 16 | H40: 130.33 | I40: Monitor furring (key note 7) Waiting 104 || Waiting 104 (GB 11'-0") face + 2 returns 8": 1L 5/8" gypsum board to 11.5 ft x 11.333 LF | J40: 6/A12.01; 7/S5.20 | K40: [DERIVADO]
A41: C1 #30 - Future FCAM furring || Future FCAM / Cash Window 116 (ACT-4 9'-0"): 1L 5/8" gypsum board to 9.5 ft x 2.153 LF | B41: 30 | C41: 2.153 | D41: 12.925 | E41: 1 | F41: 3-5/8" 362S137-33 | G41: 16 | H41: 20.45 | I41: Future FCAM furring || Future FCAM / Cash Window 116 (ACT-4 9'-0"): 1L 5/8" gypsum board to 9.5 ft x 2.153 LF | J41: 6/A12.01; 7/S5.20 | K41: [DERIVADO]
A42: C1 #31 - Column furring Vestibule 100 NW || Vestibule perimeter of column (GB 10'-0" + 6"): 1L 5/8" gypsum board to 10.5 ft x 3.893 LF | B42: 31 | C42: 3.893 | D42: 15.375 | E42: 1 | F42: 6" 600S162-54 | G42: 16 | H42: 40.88 | I42: Column furring Vestibule 100 NW || Vestibule perimeter of column (GB 10'-0" + 6"): 1L 5/8" gypsum board to 10.5 ft x 3.893 LF | J42: 1/A09.25; 7/S5.20 | K42: [DERIVADO]
A43: C1 #32 - Column furring Vestibule 100 NE || Vestibule perimeter of column (GB 10'-0" + 6"): 1L 5/8" gypsum board to 10.5 ft x 4.0 LF | B43: 32 | C43: 4 | D43: 15.375 | E43: 1 | F43: 6" 600S162-54 | G43: 16 | H43: 42 | I43: Column furring Vestibule 100 NE || Vestibule perimeter of column (GB 10'-0" + 6"): 1L 5/8" gypsum board to 10.5 ft x 4.0 LF | J43: 2/A09.25; 7/S5.20 | K43: [DERIVADO]
A44: C1 #33 - Column furring Vestibule 100/101 E || Vestibule perimeter of column (GB 10'-0" + 6"): 1L 5/8" gypsum board to 10.5 ft x 4.0 LF | B44: 33 | C44: 4 | D44: 15.375 | E44: 1 | F44: 3-5/8" 362S137-33 | G44: 16 | H44: 42 | I44: Column furring Vestibule 100/101 E || Vestibule perimeter of column (GB 10'-0" + 6"): 1L 5/8" gypsum board to 10.5 ft x 4.0 LF | J44: 6/A12.01; 7/S5.20 | K44: [DERIVADO]
A45: C1 #34 - Column furring 24HR Vestibule 101 SE || Vestibule perimeter of column (GB 10'-0" + 6"): 1L 5/8" gypsum board to 10.5 ft x 4.293 LF | B45: 34 | C45: 4.293 | D45: 15.375 | E45: 1 | F45: 6" 600S162-54 | G45: 16 | H45: 45.08 | I45: Column furring 24HR Vestibule 101 SE || Vestibule perimeter of column (GB 10'-0" + 6"): 1L 5/8" gypsum board to 10.5 ft x 4.293 LF | J45: 3/A08.21; 7/S5.20 | K45: [DERIVADO]
A46: TYPE F
A47: F #35 - 24HR Vestibule 101 / ATM Room 102 (60 deg) || 24HR Vestibule 101 (5/8" GWB to GB ceiling 10'-0"): 1L 5/8" gypsum board to 10.0 ft x 18.066 LF | ATM Room 102 (ACT-5 8'-6" + 6"): 1L 5/8" gypsum board to 9.0 ft x 18.066 LF | B47: 35 | C47: 18.066 | D47: 15.375 | E47: 2 | F47: 3-5/8" 362S137-33 | G47: 16 | H47: 331.16 | I47: 24HR Vestibule 101 / ATM Room 102 (60 deg) || 24HR Vestibule 101 (5/8" GWB to GB ceiling 10'-0"): 1L 5/8" gypsum board to 10.0 ft x 18.066 LF | ATM Room 102 (ACT-5 8'-6" + 6"): 1L 5/8" gypsum board to 9.0 ft x 18.066 LF | J47: 12/A12.01; 7/S5.20 | K47: [DERIVADO]
A48: TYPE G
A49: G #36 - ATM Room 102 / Office 109 || ATM Room 102: 2L 5/8" gypsum board to 15.375 ft x 11.625 LF | Office 109: 2L 5/8" gypsum board to 15.375 ft x 11.625 LF | B49: 36 | C49: 11.625 | D49: 15.375 | E49: 4 | F49: 1-5/8" 162S125-33 | G49: 16 | H49: 714.94 | I49: ATM Room 102 / Office 109 || ATM Room 102: 2L 5/8" gypsum board to 15.375 ft x 11.625 LF | Office 109: 2L 5/8" gypsum board to 15.375 ft x 11.625 LF | J49: 5/A12.01; 7/S5.20 | K49: [CONFIRMADO]
A50: G #37 - Office 109 / Office 110 || Office 109: 2L 5/8" gypsum board to 15.375 ft x 11.625 LF | Office 110: 2L 5/8" gypsum board to 15.375 ft x 11.625 LF | B50: 37 | C50: 11.625 | D50: 15.375 | E50: 4 | F50: 1-5/8" 162S125-33 | G50: 16 | H50: 714.94 | I50: Office 109 / Office 110 || Office 109: 2L 5/8" gypsum board to 15.375 ft x 11.625 LF | Office 110: 2L 5/8" gypsum board to 15.375 ft x 11.625 LF | J50: 5/A12.01; 7/S5.20 | K50: [CONFIRMADO]
A51: G #38 - Office 110 / Women's 114 || Office 110: 2L 5/8" gypsum board to 15.375 ft x 11.625 LF | Women's 114: 2L 5/8" gypsum board to 15.375 ft x 11.625 LF | B51: 38 | C51: 11.625 | D51: 15.375 | E51: 4 | F51: 1-5/8" 162S125-33 | G51: 16 | H51: 714.94 | I51: Office 110 / Women's 114 || Office 110: 2L 5/8" gypsum board to 15.375 ft x 11.625 LF | Women's 114: 2L 5/8" gypsum board to 15.375 ft x 11.625 LF | J51: 5/A12.01; 7/S5.20 | K51: [CONFIRMADO]
A52: G #39 - Office 106 / Office 107 || Office 106: 2L 5/8" gypsum board to 15.375 ft x 11.771 LF | Office 107: 2L 5/8" gypsum board to 15.375 ft x 11.771 LF | B52: 39 | C52: 11.771 | D52: 15.375 | E52: 4 | F52: 1-5/8" 162S125-33 | G52: 16 | H52: 723.92 | I52: Office 106 / Office 107 || Office 106: 2L 5/8" gypsum board to 15.375 ft x 11.771 LF | Office 107: 2L 5/8" gypsum board to 15.375 ft x 11.771 LF | J52: 5/A12.01; 7/S5.20 | K52: [CONFIRMADO]
A53: G #40 - Office 107 / Office 108 || Office 107: 2L 5/8" gypsum board to 15.375 ft x 11.771 LF | Office 108: 2L 5/8" gypsum board to 15.375 ft x 11.771 LF | B53: 40 | C53: 11.771 | D53: 15.375 | E53: 4 | F53: 1-5/8" 162S125-33 | G53: 16 | H53: 723.92 | I53: Office 107 / Office 108 || Office 107: 2L 5/8" gypsum board to 15.375 ft x 11.771 LF | Office 108: 2L 5/8" gypsum board to 15.375 ft x 11.771 LF | J53: 5/A12.01; 7/S5.20 | K53: [CONFIRMADO]
A54: G #41 - Office 108 / Cash Window 116 || Office 108: 2L 5/8" gypsum board to 15.375 ft x 11.771 LF | Cash Window 116: 2L 5/8" gypsum board to 15.375 ft x 11.771 LF | B54: 41 | C54: 11.771 | D54: 15.375 | E54: 4 | F54: 1-5/8" 162S125-33 | G54: 16 | H54: 723.92 | I54: Office 108 / Cash Window 116 || Office 108: 2L 5/8" gypsum board to 15.375 ft x 11.771 LF | Cash Window 116: 2L 5/8" gypsum board to 15.375 ft x 11.771 LF | J54: 5/A12.01; 7/S5.20 | K54: [CONFIRMADO]
A55: G #42 - Office 105 front stub N - SIN TAG (= tipo de los stubs vecinos) || Office 105: 2L 5/8" gypsum board to 15.375 ft x 2.42 LF | Central Zone 103: 2L 5/8" gypsum board to 15.375 ft x 2.42 LF | B55: 42 | C55: 2.42 | D55: 15.375 | E55: 4 | F55: 1-5/8" 162S125-33 | G55: 16 | H55: 148.82 | I55: Office 105 front stub N - SIN TAG (= tipo de los stubs vecinos) || Office 105: 2L 5/8" gypsum board to 15.375 ft x 2.42 LF | Central Zone 103: 2L 5/8" gypsum board to 15.375 ft x 2.42 LF | J55: 5/A12.01; 7/S5.20 | K55: [DERIVADO]
A56: G #43 - Office 105/106 front stub || Office 105/106: 2L 5/8" gypsum board to 15.375 ft x 3.467 LF | Central Zone 103: 2L 5/8" gypsum board to 15.375 ft x 3.467 LF | B56: 43 | C56: 3.467 | D56: 15.375 | E56: 4 | F56: 1-5/8" 162S125-33 | G56: 16 | H56: 213.22 | I56: Office 105/106 front stub || Office 105/106: 2L 5/8" gypsum board to 15.375 ft x 3.467 LF | Central Zone 103: 2L 5/8" gypsum board to 15.375 ft x 3.467 LF | J56: 5/A12.01; 7/S5.20 | K56: [DERIVADO]
A57: G #44 - Office 106/107 front stub || Office 106/107: 2L 5/8" gypsum board to 15.375 ft x 3.253 LF | Central Zone 103: 2L 5/8" gypsum board to 15.375 ft x 3.253 LF | B57: 44 | C57: 3.253 | D57: 15.375 | E57: 4 | F57: 1-5/8" 162S125-33 | G57: 16 | H57: 200.06 | I57: Office 106/107 front stub || Office 106/107: 2L 5/8" gypsum board to 15.375 ft x 3.253 LF | Central Zone 103: 2L 5/8" gypsum board to 15.375 ft x 3.253 LF | J57: 5/A12.01; 7/S5.20 | K57: [DERIVADO]
A58: G #45 - Office 107/108 front stub || Office 107/108: 2L 5/8" gypsum board to 15.375 ft x 3.251 LF | Central Zone 103: 2L 5/8" gypsum board to 15.375 ft x 3.251 LF | B58: 45 | C58: 3.251 | D58: 15.375 | E58: 4 | F58: 1-5/8" 162S125-33 | G58: 16 | H58: 199.94 | I58: Office 107/108 front stub || Office 107/108: 2L 5/8" gypsum board to 15.375 ft x 3.251 LF | Central Zone 103: 2L 5/8" gypsum board to 15.375 ft x 3.251 LF | J58: 5/A12.01; 7/S5.20 | K58: [DERIVADO]
A59: TYPE G1
A60: G1 #46 - Office 105 / Office 106 || Office 105: 2L 5/8" gypsum board to 15.375 ft x 11.771 LF | Office 106: 2L 5/8" gypsum board to 15.375 ft x 11.771 LF | B60: 46 | C60: 11.771 | D60: 15.375 | E60: 4 | F60: 1-5/8" 162S125-33 | G60: 16 | H60: 723.92 | I60: Office 105 / Office 106 || Office 105: 2L 5/8" gypsum board to 15.375 ft x 11.771 LF | Office 106: 2L 5/8" gypsum board to 15.375 ft x 11.771 LF | J60: 5/A12.01; 7/S5.20 | K60: [CONFIRMADO]
A61: G1 #47 - Office 109/110 front stub || Office 109/110: 2L 5/8" gypsum board to 15.375 ft x 3.507 LF | Central Zone 103: 2L 5/8" gypsum board to 15.375 ft x 3.507 LF | B61: 47 | C61: 3.507 | D61: 15.375 | E61: 4 | F61: 1-5/8" 162S125-33 | G61: 16 | H61: 215.68 | I61: Office 109/110 front stub || Office 109/110: 2L 5/8" gypsum board to 15.375 ft x 3.507 LF | Central Zone 103: 2L 5/8" gypsum board to 15.375 ft x 3.507 LF | J61: 5/A12.01; 7/S5.20 | K61: [DERIVADO]
A62: G1 #48 - Office 109 front stub N - SIN TAG || Office 109: 2L 5/8" gypsum board to 15.375 ft x 1.173 LF | Central Zone 103: 2L 5/8" gypsum board to 15.375 ft x 1.173 LF | B62: 48 | C62: 1.173 | D62: 15.375 | E62: 4 | F62: 1-5/8" 162S125-33 | G62: 16 | H62: 72.14 | I62: Office 109 front stub N - SIN TAG || Office 109: 2L 5/8" gypsum board to 15.375 ft x 1.173 LF | Central Zone 103: 2L 5/8" gypsum board to 15.375 ft x 1.173 LF | J62: 5/A12.01; 7/S5.20 | K62: [DERIVADO]
A63: G1 #49 - Office 110 front stub S - SIN TAG || Office 110: 2L 5/8" gypsum board to 15.375 ft x 3.18 LF | Central Zone 103: 2L 5/8" gypsum board to 15.375 ft x 3.18 LF | B63: 49 | C63: 3.18 | D63: 15.375 | E63: 4 | F63: 1-5/8" 162S125-33 | G63: 16 | H63: 195.58 | I63: Office 110 front stub S - SIN TAG || Office 110: 2L 5/8" gypsum board to 15.375 ft x 3.18 LF | Central Zone 103: 2L 5/8" gypsum board to 15.375 ft x 3.18 LF | J63: 5/A12.01; 7/S5.20 | K63: [DERIVADO]
A64: TYPE BULKHEAD-OF
A65: BULKHEAD-OF #61 - Office 105 front bulkhead (8/A12.01 + 9/A12.01) || Office 105: 2L 5/8" gypsum board to 7.333 ft x 7.5 LF | Central Zone 103: 2L 5/8" gypsum board to 7.333 ft x 7.5 LF | B65: 61 | C65: 7.5 | D65: 7.333 | E65: 4 | F65: 1-5/8" 162S125-33 | G65: 16 | H65: 220 | I65: Office 105 front bulkhead (8/A12.01 + 9/A12.01) || Office 105: 2L 5/8" gypsum board to 7.333 ft x 7.5 LF | Central Zone 103: 2L 5/8" gypsum board to 7.333 ft x 7.5 LF | J65: 9/A12.01; 7/S5.20 | K65: [CONFIRMADO]
A66: BULKHEAD-OF #62 - Office 106 front bulkhead (8/A12.01 + 9/A12.01) || Office 106: 2L 5/8" gypsum board to 7.333 ft x 7.5 LF | Central Zone 103: 2L 5/8" gypsum board to 7.333 ft x 7.5 LF | B66: 62 | C66: 7.5 | D66: 7.333 | E66: 4 | F66: 1-5/8" 162S125-33 | G66: 16 | H66: 220 | I66: Office 106 front bulkhead (8/A12.01 + 9/A12.01) || Office 106: 2L 5/8" gypsum board to 7.333 ft x 7.5 LF | Central Zone 103: 2L 5/8" gypsum board to 7.333 ft x 7.5 LF | J66: 9/A12.01; 7/S5.20 | K66: [CONFIRMADO]
A67: BULKHEAD-OF #63 - Office 107 front bulkhead (8/A12.01 + 9/A12.01) || Office 107: 2L 5/8" gypsum board to 7.333 ft x 7.5 LF | Central Zone 103: 2L 5/8" gypsum board to 7.333 ft x 7.5 LF | B67: 63 | C67: 7.5 | D67: 7.333 | E67: 4 | F67: 1-5/8" 162S125-33 | G67: 16 | H67: 220 | I67: Office 107 front bulkhead (8/A12.01 + 9/A12.01) || Office 107: 2L 5/8" gypsum board to 7.333 ft x 7.5 LF | Central Zone 103: 2L 5/8" gypsum board to 7.333 ft x 7.5 LF | J67: 9/A12.01; 7/S5.20 | K67: [CONFIRMADO]
A68: BULKHEAD-OF #64 - Office 108 front bulkhead (8/A12.01 + 9/A12.01) || Office 108: 2L 5/8" gypsum board to 7.333 ft x 7.5 LF | Central Zone 103: 2L 5/8" gypsum board to 7.333 ft x 7.5 LF | B68: 64 | C68: 7.5 | D68: 7.333 | E68: 4 | F68: 1-5/8" 162S125-33 | G68: 16 | H68: 220 | I68: Office 108 front bulkhead (8/A12.01 + 9/A12.01) || Office 108: 2L 5/8" gypsum board to 7.333 ft x 7.5 LF | Central Zone 103: 2L 5/8" gypsum board to 7.333 ft x 7.5 LF | J68: 9/A12.01; 7/S5.20 | K68: [CONFIRMADO]
A69: BULKHEAD-OF #65 - Office 109 front bulkhead (8/A12.01 + 9/A12.01) || Office 109: 2L 5/8" gypsum board to 7.333 ft x 7.5 LF | Central Zone 103: 2L 5/8" gypsum board to 7.333 ft x 7.5 LF | B69: 65 | C69: 7.5 | D69: 7.333 | E69: 4 | F69: 1-5/8" 162S125-33 | G69: 16 | H69: 220 | I69: Office 109 front bulkhead (8/A12.01 + 9/A12.01) || Office 109: 2L 5/8" gypsum board to 7.333 ft x 7.5 LF | Central Zone 103: 2L 5/8" gypsum board to 7.333 ft x 7.5 LF | J69: 9/A12.01; 7/S5.20 | K69: [CONFIRMADO]
A70: BULKHEAD-OF #66 - Office 110 front bulkhead (8/A12.01 + 9/A12.01) || Office 110: 2L 5/8" gypsum board to 7.333 ft x 7.5 LF | Central Zone 103: 2L 5/8" gypsum board to 7.333 ft x 7.5 LF | B70: 66 | C70: 7.5 | D70: 7.333 | E70: 4 | F70: 1-5/8" 162S125-33 | G70: 16 | H70: 220 | I70: Office 110 front bulkhead (8/A12.01 + 9/A12.01) || Office 110: 2L 5/8" gypsum board to 7.333 ft x 7.5 LF | Central Zone 103: 2L 5/8" gypsum board to 7.333 ft x 7.5 LF | J70: 9/A12.01; 7/S5.20 | K70: [CONFIRMADO]
A71: TYPE EXT
A72: EXT #50 - EXT north wall Office 105 (grid F, 7-8) || Interior face tramo 1 (5/8" GYP BOARD @ PERIMETER EXTERIOR WALL TO DECK, C/A09.21): 1L 5/8" gypsum board to 15.375 ft x 12.64 LF | Exterior face nailbase (4/A09.26, C/A09.21): 1L 5/8" FRT plywood bonded to 2-1/2" polyiso (nailbase) to 16.917 ft x 12.64 LF | B72: 50 | C72: 12.64 | D72: 14.362 | E72: 1 | F72: 6" 600S162-54 | G72: 16 | H72: 408.17 | I72: EXT north wall Office 105 (grid F, 7-8) || Interior face tramo 1 (5/8" GYP BOARD @ PERIMETER EXTERIOR WALL TO DECK, C/A09.21): 1L 5/8" gypsum board to 15.375 ft x 12.64 LF | Exterior face nailbase (4/A09.26, C/A09.21): 1L 5/8" FRT plywood bonded to 2-1/2" polyiso (nailbase) to 16.917 ft x 12.64 LF | J72: C/A09.21; 7/S5.20 | K72: [DERIVADO]
A73: EXT #51 - EXT north storefront head Central Zone 103 (grid F, 4-7) || Interior face above storefront head (2/A09.26 to deck): 1L 5/8" gypsum board to 6.875 ft x 26.25 LF | Exterior face nailbase (4/A09.26, C/A09.21): 1L 5/8" FRT plywood bonded to 2-1/2" polyiso (nailbase) to 8.917 ft x 26.25 LF | B73: 51 | C73: 26.25 | D73: 5.4 | E73: 1 | F73: 6" 600S162-54 | G73: 16 | H73: 414.54 | I73: EXT north storefront head Central Zone 103 (grid F, 4-7) || Interior face above storefront head (2/A09.26 to deck): 1L 5/8" gypsum board to 6.875 ft x 26.25 LF | Exterior face nailbase (4/A09.26, C/A09.21): 1L 5/8" FRT plywood bonded to 2-1/2" polyiso (nailbase) to 8.917 ft x 26.25 LF | J73: C/A09.21; 7/S5.20 | K73: [DERIVADO]
A74: EXT #52 - EXT north storefront head Vestibule 100 (grid G, 2-4) - tower PARAPET 2 || Interior face above storefront head (2/A09.26 to deck): 1L 5/8" gypsum board to 6.875 ft x 12.563 LF | Exterior face nailbase (4/A09.26, C/A09.21): 1L 5/8" FRT plywood bonded to 2-1/2" polyiso (nailbase) to 11.167 ft x 12.563 LF | B74: 52 | C74: 12.563 | D74: 5.862 | E74: 1 | F74: 6" 600S162-54 | G74: 16 | H74: 226.66 | I74: EXT north storefront head Vestibule 100 (grid G, 2-4) - tower PARAPET 2 || Interior face above storefront head (2/A09.26 to deck): 1L 5/8" gypsum board to 6.875 ft x 12.563 LF | Exterior face nailbase (4/A09.26, C/A09.21): 1L 5/8" FRT plywood bonded to 2-1/2" polyiso (nailbase) to 11.167 ft x 12.563 LF | J74: C/A09.21; 7/S5.20 | K74: [DERIVADO]
A75: EXT #53 - EXT west storefront head Vestibule 100 (grid 2, G-E.4) - tower || Interior face above storefront head (2/A09.26 to deck): 1L 5/8" gypsum board to 6.875 ft x 6.5 LF | Exterior face nailbase (4/A09.26, C/A09.21): 1L 5/8" FRT plywood bonded to 2-1/2" polyiso (nailbase) to 11.167 ft x 6.5 LF | B75: 53 | C75: 6.5 | D75: 5.862 | E75: 1 | F75: 6" 600S162-54 | G75: 16 | H75: 117.28 | I75: EXT west storefront head Vestibule 100 (grid 2, G-E.4) - tower || Interior face above storefront head (2/A09.26 to deck): 1L 5/8" gypsum board to 6.875 ft x 6.5 LF | Exterior face nailbase (4/A09.26, C/A09.21): 1L 5/8" FRT plywood bonded to 2-1/2" polyiso (nailbase) to 11.167 ft x 6.5 LF | J75: C/A09.21; 7/S5.20 | K75: [DERIVADO]
A76: EXT #54 - EXT west wall 24HR Vestibule 101 (grid 2) || Interior face tramo 1 (5/8" GYP BOARD @ PERIMETER EXTERIOR WALL TO DECK, C/A09.21): 1L 5/8" gypsum board to 15.375 ft x 15.773 LF | Exterior face nailbase (4/A09.26, C/A09.21): 1L 5/8" FRT plywood bonded to 2-1/2" polyiso (nailbase) to 19.167 ft x 15.773 LF | B76: 54 | C76: 15.773 | D76: 14.362 | E76: 1 | F76: 6" 600S162-54 | G76: 16 | H76: 544.83 | I76: EXT west wall 24HR Vestibule 101 (grid 2) || Interior face tramo 1 (5/8" GYP BOARD @ PERIMETER EXTERIOR WALL TO DECK, C/A09.21): 1L 5/8" gypsum board to 15.375 ft x 15.773 LF | Exterior face nailbase (4/A09.26, C/A09.21): 1L 5/8" FRT plywood bonded to 2-1/2" polyiso (nailbase) to 19.167 ft x 15.773 LF | J76: C/A09.21; 7/S5.20 | K76: [DERIVADO]
A77: EXT #55 - EXT west ATM niche Day 1 drive-up ATM (6/A08.11) || Interior face tramo 1 (5/8" GYP BOARD @ PERIMETER EXTERIOR WALL TO DECK, C/A09.21): 1L 5/8" gypsum board to 15.375 ft x 5.687 LF | Exterior face nailbase (4/A09.26, C/A09.21): 1L 5/8" FRT plywood (6/A08.11, under furring + fiber cement) to 19.167 ft x 5.687 LF | B77: 55 | C77: 5.687 | D77: 14.362 | E77: 1 | F77: 6" 600S162-54 | G77: 16 | H77: 185.1 | I77: EXT west ATM niche Day 1 drive-up ATM (6/A08.11) || Interior face tramo 1 (5/8" GYP BOARD @ PERIMETER EXTERIOR WALL TO DECK, C/A09.21): 1L 5/8" gypsum board to 15.375 ft x 5.687 LF | Exterior face nailbase (4/A09.26, C/A09.21): 1L 5/8" FRT plywood (6/A08.11, under furring + fiber cement) to 19.167 ft x 5.687 LF | J77: C/A09.21; 7/S5.20 | K77: [DERIVADO]
A78: EXT #56 - EXT jog ATM Room 102 / Office 109 (y 840) || Interior face tramo 1 (5/8" GYP BOARD @ PERIMETER EXTERIOR WALL TO DECK, C/A09.21): 1L 5/8" gypsum board to 15.375 ft x 4.413 LF | Exterior face nailbase (4/A09.26, C/A09.21): 1L 5/8" FRT plywood bonded to 2-1/2" polyiso (nailbase) to 16.917 ft x 4.413 LF | B78: 56 | C78: 4.413 | D78: 14.362 | E78: 1 | F78: 6" 600S162-54 | G78: 16 | H78: 142.5 | I78: EXT jog ATM Room 102 / Office 109 (y 840) || Interior face tramo 1 (5/8" GYP BOARD @ PERIMETER EXTERIOR WALL TO DECK, C/A09.21): 1L 5/8" gypsum board to 15.375 ft x 4.413 LF | Exterior face nailbase (4/A09.26, C/A09.21): 1L 5/8" FRT plywood bonded to 2-1/2" polyiso (nailbase) to 16.917 ft x 4.413 LF | J78: C/A09.21; 7/S5.20 | K78: [DERIVADO]
A79: EXT #57 - EXT west wall Offices 109-110 + Restrooms (grid 3) || Interior face tramo 1 (5/8" GYP BOARD @ PERIMETER EXTERIOR WALL TO DECK, C/A09.21): 1L 5/8" gypsum board to 15.375 ft x 22.562 LF | Interior face tramo 2 (5/8" GYP BOARD @ PERIMETER EXTERIOR WALL TO DECK, C/A09.21): 1L 5/8" gypsum board to 13.052 ft x 24.851 LF | Exterior face nailbase (4/A09.26, C/A09.21): 1L 5/8" FRT plywood bonded to 2-1/2" polyiso (nailbase) to 16.917 ft x 47.413 LF | B79: 57 | C79: 47.413 | D79: 14.362 | E79: 1 | F79: 6" 600S162-54 | G79: 16 | H79: 1377.34 | I79: EXT west wall Offices 109-110 + Restrooms (grid 3) || Interior face tramo 1 (5/8" GYP BOARD @ PERIMETER EXTERIOR WALL TO DECK, C/A09.21): 1L 5/8" gypsum board to 15.375 ft x 22.562 LF | Interior face tramo 2 (5/8" GYP BOARD @ PERIMETER EXTERIOR WALL TO DECK, C/A09.21): 1L 5/8" gypsum board to 13.052 ft x 24.851 LF | Exterior face nailbase (4/A09.26, C/A09.21): 1L 5/8" FRT plywood bonded to 2-1/2" polyiso (nailbase) to 16.917 ft x 47.413 LF | J79: C/A09.21; 7/S5.20 | K79: [DERIVADO]
A80: EXT #58 - EXT south wall (grid A) || Interior face tramo 1 (5/8" GYP BOARD @ PERIMETER EXTERIOR WALL TO DECK, C/A09.21): 1L 5/8" gypsum board to 12.539 ft x 51.733 LF | Exterior face nailbase (4/A09.26, C/A09.21): 1L 5/8" FRT plywood bonded to 2-1/2" polyiso (nailbase) to 16.917 ft x 51.733 LF | B80: 58 | C80: 51.733 | D80: 11.526 | E80: 1 | F80: 6" 600S162-54 | G80: 16 | H80: 1469.41 | I80: EXT south wall (grid A) || Interior face tramo 1 (5/8" GYP BOARD @ PERIMETER EXTERIOR WALL TO DECK, C/A09.21): 1L 5/8" gypsum board to 12.539 ft x 51.733 LF | Exterior face nailbase (4/A09.26, C/A09.21): 1L 5/8" FRT plywood bonded to 2-1/2" polyiso (nailbase) to 16.917 ft x 51.733 LF | J80: C/A09.21; 7/S5.20 | K80: [DERIVADO]
A81: EXT #59 - EXT east wall (grid 8) || Interior face tramo 1 (5/8" GYP BOARD @ PERIMETER EXTERIOR WALL TO DECK, C/A09.21): 1L 5/8" gypsum board to 15.375 ft x 50.478 LF | Interior face tramo 2 (5/8" GYP BOARD @ PERIMETER EXTERIOR WALL TO DECK, C/A09.21): 1L 5/8" gypsum board to 13.052 ft x 24.855 LF | Exterior face nailbase (4/A09.26, C/A09.21): 1L 5/8" FRT plywood bonded to 2-1/2" polyiso (nailbase) to 16.917 ft x 75.333 LF | B81: 59 | C81: 75.333 | D81: 14.362 | E81: 1 | F81: 6" 600S162-54 | G81: 16 | H81: 2182.92 | I81: EXT east wall (grid 8) || Interior face tramo 1 (5/8" GYP BOARD @ PERIMETER EXTERIOR WALL TO DECK, C/A09.21): 1L 5/8" gypsum board to 15.375 ft x 50.478 LF | Interior face tramo 2 (5/8" GYP BOARD @ PERIMETER EXTERIOR WALL TO DECK, C/A09.21): 1L 5/8" gypsum board to 13.052 ft x 24.855 LF | Exterior face nailbase (4/A09.26, C/A09.21): 1L 5/8" FRT plywood bonded to 2-1/2" polyiso (nailbase) to 16.917 ft x 75.333 LF | J81: C/A09.21; 7/S5.20 | K81: [DERIVADO]
A82: TYPE PARAPET
A83: PARAPET #- - P1 north (grid F, x1143->1860) :: 6" parapet stud 600S162-54 = 81.68 LF | B83: - | C83: 81.68 | D83: 0 | E83: 1 | F83: 6" | G83: 16 | H83: 0 | I83: P1 north (grid F, x1143->1860) :: 6" parapet stud 600S162-54 = 81.68 LF | J83: 59.4: bays=ROUNDUP(39.86/5'-0" HSS max)=8; studs/bay=2+max(0,ROUNDUP((4.983-0.6)/1.333)-1)=5; 40 studs x h 2.042 (T/STUD - B.O.D. promedio del tramo, 55.3) = 81.68 LF; 11/S5.10 | K83: [DERIVADO]
A84: PARAPET #- - P2 tower north leg (grid G, 2->4) :: 6" parapet stud 600S162-54 = 68.67 LF | B84: - | C84: 68.67 | D84: 0 | E84: 1 | F84: 6" | G84: 16 | H84: 0 | I84: P2 tower north leg (grid G, 2->4) :: 6" parapet stud 600S162-54 = 68.67 LF | J84: 59.4: bays=ROUNDUP(17.73/5'-0" HSS max)=4; studs/bay=2+max(0,ROUNDUP((4.433-0.6)/1.333)-1)=4; 16 studs x h 4.292 (T/STUD - B.O.D. promedio del tramo, 55.3) = 68.67 LF; 11/S5.10 | K84: [DERIVADO]
A85: PARAPET #- - P2 tower west leg (grid 2, G->D) :: 6" parapet stud 600S162-54 = 120.18 LF | B85: - | C85: 120.18 | D85: 0 | E85: 1 | F85: 6" | G85: 16 | H85: 0 | I85: P2 tower west leg (grid 2, G->D) :: 6" parapet stud 600S162-54 = 120.18 LF | J85: 59.4: bays=ROUNDUP(30.36/5'-0" HSS max)=7; studs/bay=2+max(0,ROUNDUP((4.337-0.6)/1.333)-1)=4; 28 studs x h 4.292 (T/STUD - B.O.D. promedio del tramo, 55.3) = 120.18 LF; 11/S5.10 | K85: [DERIVADO]
A86: PARAPET #- - P2 tower return at grid 4 (roof both sides) :: 6" parapet stud 600S162-54 = 21.46 LF | B86: - | C86: 21.46 | D86: 0 | E86: 1 | F86: 6" | G86: 16 | H86: 0 | I86: P2 tower return at grid 4 (roof both sides) :: 6" parapet stud 600S162-54 = 21.46 LF | J86: 59.4: bays=ROUNDUP(4.61/5'-0" HSS max)=1; studs/bay=2+max(0,ROUNDUP((4.61-0.6)/1.333)-1)=5; 5 studs x h 4.292 (T/STUD - B.O.D. promedio del tramo, 55.3) = 21.46 LF; 11/S5.10 | K86: [DERIVADO]
A87: PARAPET #- - P1 west jog (y 848) :: 6" parapet stud 600S162-54 = 8.17 LF | B87: - | C87: 8.17 | D87: 0 | E87: 1 | F87: 6" | G87: 16 | H87: 0 | I87: P1 west jog (y 848) :: 6" parapet stud 600S162-54 = 8.17 LF | J87: 59.4: bays=ROUNDUP(3.95/5'-0" HSS max)=1; studs/bay=2+max(0,ROUNDUP((3.95-0.6)/1.333)-1)=4; 4 studs x h 2.042 (T/STUD - B.O.D. promedio del tramo, 55.3) = 8.17 LF; 11/S5.10 | K87: [DERIVADO]
A88: PARAPET #- - P1 west grid 3 north of B :: 6" parapet stud 600S162-54 = 40.84 LF | B88: - | C88: 40.84 | D88: 0 | E88: 1 | F88: 6" | G88: 16 | H88: 0 | I88: P1 west grid 3 north of B :: 6" parapet stud 600S162-54 = 40.84 LF | J88: 59.4: bays=ROUNDUP(22.09/5'-0" HSS max)=5; studs/bay=2+max(0,ROUNDUP((4.418-0.6)/1.333)-1)=4; 20 studs x h 2.042 (T/STUD - B.O.D. promedio del tramo, 55.3) = 40.84 LF; 11/S5.10 | K88: [DERIVADO]
A89: PARAPET #- - P1 west grid 3 south of B :: 6" parapet stud 600S162-54 = 111.14 LF | B89: - | C89: 111.14 | D89: 0 | E89: 1 | F89: 6" | G89: 16 | H89: 0 | I89: P1 west grid 3 south of B :: 6" parapet stud 600S162-54 = 111.14 LF | J89: 59.4: bays=ROUNDUP(25.74/5'-0" HSS max)=6; studs/bay=2+max(0,ROUNDUP((4.29-0.6)/1.333)-1)=4; 24 studs x h 4.631 (T/STUD - B.O.D. promedio del tramo, 55.3) = 111.14 LF; 11/S5.10 | K89: [DERIVADO]
A90: PARAPET #- - P1 south (grid A) :: 6" parapet stud 600S162-54 = 268.78 LF | B90: - | C90: 268.78 | D90: 0 | E90: 1 | F90: 6" | G90: 16 | H90: 0 | I90: P1 south (grid A) :: 6" parapet stud 600S162-54 = 268.78 LF | J90: 59.4: bays=ROUNDUP(53.59/5'-0" HSS max)=11; studs/bay=2+max(0,ROUNDUP((4.872-0.6)/1.333)-1)=5; 55 studs x h 4.887 (T/STUD - B.O.D. promedio del tramo, 55.3) = 268.78 LF; 11/S5.10 | K90: [DERIVADO]
A91: PARAPET #- - P1 east north of B :: 6" parapet stud 600S162-54 = 112.31 LF | B91: - | C91: 112.31 | D91: 0 | E91: 1 | F91: 6" | G91: 16 | H91: 0 | I91: P1 east north of B :: 6" parapet stud 600S162-54 = 112.31 LF | J91: 59.4: bays=ROUNDUP(51.45/5'-0" HSS max)=11; studs/bay=2+max(0,ROUNDUP((4.677-0.6)/1.333)-1)=5; 55 studs x h 2.042 (T/STUD - B.O.D. promedio del tramo, 55.3) = 112.31 LF; 11/S5.10 | K91: [DERIVADO]
A92: PARAPET #- - P1 east south of B :: 6" parapet stud 600S162-54 = 111.14 LF | B92: - | C92: 111.14 | D92: 0 | E92: 1 | F92: 6" | G92: 16 | H92: 0 | I92: P1 east south of B :: 6" parapet stud 600S162-54 = 111.14 LF | J92: 59.4: bays=ROUNDUP(25.74/5'-0" HSS max)=6; studs/bay=2+max(0,ROUNDUP((4.29-0.6)/1.333)-1)=4; 24 studs x h 4.631 (T/STUD - B.O.D. promedio del tramo, 55.3) = 111.14 LF; 11/S5.10 | K92: [DERIVADO]
A93: PARAPET #- - all runs roof side :: 5/8" exterior gypsum sheathing (parapet roof side) = 985.9 SF | B93: - | C93: 0 | D93: 0 | E93: 1 | F93: - | G93: 16 | H93: 985.9 | I93: all runs roof side :: 5/8" exterior gypsum sheathing (parapet roof side) = 985.9 SF | J93: sum LF x (T/STUD - B.O.D.) por tramo (55.3); return P2 ambas caras; C/A09.21, E/A09.22, J/A09.23 (4/A09.26 dice DENS DECK -> RFI-PAR) | K93: [DERIVADO]
A94: TYPE ROOF STEP
A95: ROOF STEP #- - grid B 3->8 :: 3-5/8" metal stud 362S137-33 = 99.89 LF | B95: - | C95: 99.89 | D95: 0 | E95: 1 | F95: 3-5/8" | G95: 16 | H95: 0 | I95: grid B 3->8 :: 3-5/8" metal stud 362S137-33 = 99.89 LF | J95: 6/A02.02 3 5/8" METAL STUD @ 16" O.C.: (40+1+2) x 2.323 (15'-4 1/2" - 13'-0 5/8", S2.20; 9/S5.10) | K95: [DERIVADO]
A96: ROOF STEP #- - grid B interior :: 5/8" gypsum board, regular = 121.57 SF | B96: - | C96: 0 | D96: 0 | E96: 1 | F96: - | G96: 16 | H96: 121.57 | I96: grid B interior :: 5/8" gypsum board, regular = 121.57 SF | J96: 6/A02.02 interior 5/8" gyp bd tight to deck | K96: [DERIVADO]
A97: TYPE CANOPY
A98: CANOPY #- - North canopy (grid 2->8) fascia :: 3-5/8" metal stud 362S137-33 = 93.01 LF | B98: - | C98: 93.01 | D98: 0 | E98: 1 | F98: 3-5/8" | G98: 16 | H98: 0 | I98: North canopy (grid 2->8) fascia :: 3-5/8" metal stud 362S137-33 = 93.01 LF | J98: fascia 60.51 LF (linea fascia ext., ag_canopy): (46+1) x 1.979 (T/STUD 12'-7" - B/STUD 10'-7 1/4") 7/A09.26; O.C. 16" de 4/A09.33 (RFI-CAN-OC) | K98: [DERIVADO]
A99: CANOPY #- - North canopy (grid 2->8) fascia :: 5/8" ext. grade FRT plywood sheathing (canopy) = 161.38 SF | B99: - | C99: 0 | D99: 0 | E99: 1 | F99: - | G99: 16 | H99: 161.38 | I99: North canopy (grid 2->8) fascia :: 5/8" ext. grade FRT plywood sheathing (canopy) = 161.38 SF | J99: 60.51 x (cara 2'-2" T/CANOPY 12'-8" - B/CANOPY 10'-6" + top 6") 3/A09.26, 7/A09.26 | K99: [DERIVADO]
A100: CANOPY #- - North canopy (grid 2->8) soffit :: 3-5/8" metal stud 362S137-33 = 173.31 LF | B100: - | C100: 173.31 | D100: 0 | E100: 1 | F100: 3-5/8" | G100: 16 | H100: 0 | I100: North canopy (grid 2->8) soffit :: 3-5/8" metal stud 362S137-33 = 173.31 LF | J100: joists @16" 4/A09.33: 47 pcs x ancho soffit [(16.2, 3.0), (41.34, 3.979)]; 7/A09.26 | K100: [DERIVADO]
A101: CANOPY #- - North canopy (grid 2->8) soffit :: 5/8" ext. grade FRT plywood sheathing (canopy) = 213.09 SF | B101: - | C101: 0 | D101: 0 | E101: 1 | F101: - | G101: 16 | H101: 213.09 | I101: North canopy (grid 2->8) soffit :: 5/8" ext. grade FRT plywood sheathing (canopy) = 213.09 SF | J101: soffit [(16.2, 3.0), (41.34, 3.979)] = 213.09 SF; 7/A09.26 (4/A09.33 dice exterior sheathing -> RFI-CAN-SH) | K101: [DERIVADO]
...

Sheet Material Summary
A1: MATERIAL SUMMARY - NET / WASTE / PURCHASE
A2: Waste lives HERE, in its own column, never inside the net quantity.
A3: Material | B3: Unit | C3: Net | D3: Waste % | E3: Waste | F3: Purchase | G3: Selling unit | H3: Pieces to buy | I3: Where it comes from
A4: 3-5/8" metal stud 362S137-33 | B4: LF | C4: 5698.21 | D4: =Inputs!$B$4 -> 0.15 | E4: =C4*D4 -> 854.7315 | F4: =C4+E4 -> 6552.9415 | G4: stick 20 ft | H4: =ROUNDUP(ROUNDUP(F4/15.375,0)/MAX(1,INT(20/15.375)),0) -> 427 | I4: CANOPY - Drive-up canopy west (grid 1-2/3) fascia: fascia 96.11 LF (linea fascia ext., ag_canopy): (73+1) x 1.979 (T/STUD 12'-7" - B/STUD 10'-7 1/4") 7/A09.26; O.C. 16" de 4/A09.33 (RFI-CAN-OC); CANOPY - Drive-up canopy west (grid 1-2/3) soffit: joists @16" 16/A09.27, 4/A09.33: area 989.59 SF / 1.333 ft (G->D 30.0 ft x 17'-1 1/2" + D->B 22.67 x 20'-11 7/8", ag_canopy); soporte a W10 beams RFI-DU; CANOPY - East canopy (grid 8) fascia: fascia 52.135 LF (linea fascia ext., ag_canopy): (40+1) x 1.979 (T/STUD 12'-7" - B/STUD 10'-7 1/4") 7/A09.26; O.C. 16" de 4/A09.33 (RFI-CAN-OC); CANOPY - East canopy (grid 8) soffit: joists @16" 4/A09.33: 37 pcs x ancho soffit [(47.365, 2.479)]; 7/A09.26; CANOPY - North canopy (grid 2->8) fascia: fascia 60.51 LF (linea fascia ext., ag_canopy): (46+1) x 1.979 (T/STUD 12'-7" - B/STUD 10'-7 1/4") 7/A09.26; O.C. 16" de 4/A09.33 (RFI-CAN-OC); CANOPY - North canop
A5: Bottom track 3-5/8" 362T125-33 | B5: LF | C5: 285.24 | D5: =Inputs!$B$4 -> 0.15 | E5: =C5*D5 -> 42.786 | F5: =C5+E5 -> 328.026 | G5: piece 10 ft | H5: =ROUNDUP(F5/10,0) -> 33 | I5: PIERS - 4 canopy columns: 5/A09.25 perimetro FOS 4 x 1.417 x 4 piers; ROOF STEP - grid B: 52'-4" S2.20 grid 3->8; 6/A02.02; W01 A1 3/A12.01 sello 21b3cc3c7933b572; W02 A1 3/A12.01 sello 5435aab96bad5038; W03 A1 3/A12.01 sello 52b9539bdb85f850; W04 A1 3/A12.01 sello f6908b5e96529b81; W05 A1 3/A12.01 sello 77c98fd16912ccb6; W06 A1 3/A12.01 sello 50854be1d82abd09; W07 A1 3/A12.01 sello 5449e1f18e17b029; W08 A1 3/A12.01 sello faf33c2cddff049d; W09 A1 3/A12.01 sello 4eb93537580359dc; W10 A1 3/A12.01 sello 7c299b0b68f0d0e2; W11 A1K 4/A12.01 sello ee3920121adce127; W12 A1K 4/A12.01 sello 61c7e94e82ba5e79; W17 B 1/A12.01 sello e01658d5f20c92da; W18 B 1/A12.01 sello f89b5e3ef2e13df6; W19 B 1/A12.01 sello 013f94d9afec83ac; W20 B 1/A12.01 sello 22ce136a5b1726f1; W21 B 1/A12.01 sello dedb77a109eddb52; W22 B 1/A12.01 sello 7d3688e2dc552404; W27 C1 6/A12.01 sello e025ee77e70b13c2; W28 C1 6/A12.01 sell
A6: Top track 3-5/8" - continuous slip track (RFI-SLIP designacion) | B6: LF | C6: 154.63 | D6: =Inputs!$B$4 -> 0.15 | E6: =C6*D6 -> 23.1945 | F6: =C6+E6 -> 177.8245 | G6: piece 10 ft | H6: =ROUNDUP(F6/10,0) -> 18 | I6: W01 A1 3/A12.01 sello 21b3cc3c7933b572; W02 A1 3/A12.01 sello 5435aab96bad5038; W03 A1 3/A12.01 sello 52b9539bdb85f850; W04 A1 3/A12.01 sello f6908b5e96529b81; W05 A1 3/A12.01 sello 77c98fd16912ccb6; W06 A1 3/A12.01 sello 50854be1d82abd09; W07 A1 3/A12.01 sello 5449e1f18e17b029; W08 A1 3/A12.01 sello faf33c2cddff049d; W09 A1 3/A12.01 sello 4eb93537580359dc; W10 A1 3/A12.01 sello 7c299b0b68f0d0e2; W11 A1K 4/A12.01 sello ee3920121adce127; W12 A1K 4/A12.01 sello 61c7e94e82ba5e79; W17 B 1/A12.01 sello e01658d5f20c92da; W18 B 1/A12.01 sello f89b5e3ef2e13df6; W19 B 1/A12.01 sello 013f94d9afec83ac; W20 B 1/A12.01 sello 22ce136a5b1726f1; W21 B 1/A12.01 sello dedb77a109eddb52; W22 B 1/A12.01 sello 7d3688e2dc552404
A7: bracing 1-1/2" C.R. channel (F/1/S5.20) | B7: LF | C7: 2250.78 | D7: =Inputs!$B$4 -> 0.15 | E7: =C7*D7 -> 337.617 | F7: =C7+E7 -> 2588.397 | G7: piece 16 ft | H7: =ROUNDUP(F7/16,0) -> 162 | I7: W01 A1 3/A12.01 sello 21b3cc3c7933b572; W02 A1 3/A12.01 sello 5435aab96bad5038; W03 A1 3/A12.01 sello 52b9539bdb85f850; W04 A1 3/A12.01 sello f6908b5e96529b81; W05 A1 3/A12.01 sello 77c98fd16912ccb6; W06 A1 3/A12.01 sello 50854be1d82abd09; W07 A1 3/A12.01 sello 5449e1f18e17b029; W08 A1 3/A12.01 sello faf33c2cddff049d; W09 A1 3/A12.01 sello 4eb93537580359dc; W10 A1 3/A12.01 sello 7c299b0b68f0d0e2; W11 A1K 4/A12.01 sello ee3920121adce127; W12 A1K 4/A12.01 sello 61c7e94e82ba5e79; W13 A5 3/A12.01 sello f95759932e232b8d; W14 A5 3/A12.01 sello 865ddc60d1cdf1fd; W15 A5 3/A12.01 sello c393d8380767a185; W16 A5 3/A12.01 sello a5ba89c61fd91cfd; W17 B 1/A12.01 sello e01658d5f20c92da; W18 B 1/A12.01 sello f89b5e3ef2e13df6; W19 B 1/A12.01 sello 013f94d9afec83ac; W20 B 1/A12.01 sello 22ce136a5b1726f1; W21 B 1/A12.01 sello dedb77a109eddb52; W22 B 1/A12.01 sello 7d3688e2dc552404; W23 B2 1/A12.01 sello 2e
A8: Bridging clip angles (F/1/S5.20 attach each side) | B8: EA | C8: 5470 | D8: =Inputs!$B$4 -> 0.15 | E8: =C8*D8 -> 820.5 | F8: =C8+E8 -> 6290.5 | G8: EA | H8: =ROUNDUP(F8,0) -> 6291 | I8: W01 A1 3/A12.01 sello 21b3cc3c7933b572; W02 A1 3/A12.01 sello 5435aab96bad5038; W03 A1 3/A12.01 sello 52b9539bdb85f850; W04 A1 3/A12.01 sello f6908b5e96529b81; W05 A1 3/A12.01 sello 77c98fd16912ccb6; W06 A1 3/A12.01 sello 50854be1d82abd09; W07 A1 3/A12.01 sello 5449e1f18e17b029; W08 A1 3/A12.01 sello faf33c2cddff049d; W09 A1 3/A12.01 sello 4eb93537580359dc; W10 A1 3/A12.01 sello 7c299b0b68f0d0e2; W11 A1K 4/A12.01 sello ee3920121adce127; W12 A1K 4/A12.01 sello 61c7e94e82ba5e79; W13 A5 3/A12.01 sello f95759932e232b8d; W14 A5 3/A12.01 sello 865ddc60d1cdf1fd; W15 A5 3/A12.01 sello c393d8380767a185; W16 A5 3/A12.01 sello a5ba89c61fd91cfd; W17 B 1/A12.01 sello e01658d5f20c92da; W18 B 1/A12.01 sello f89b5e3ef2e13df6; W19 B 1/A12.01 sello 013f94d9afec83ac; W20 B 1/A12.01 sello 22ce136a5b1726f1; W21 B 1/A12.01 sello dedb77a109eddb52; W22 B 1/A12.01 sello 7d3688e2dc552404; W23 B2 1/A12.01 sello 2e
A9: Batt insulation (partitions, A12.01 INSULATION YES) | B9: SF | C9: 5136.84 | D9: =Inputs!$B$5 -> 0.06 | E9: =C9*D9 -> 308.2104 | F9: =C9+E9 -> 5445.0504 | G9: SF | H9: =ROUNDUP(F9,0) -> 5446 | I9: W01 A1 3/A12.01 sello 21b3cc3c7933b572; W02 A1 3/A12.01 sello 5435aab96bad5038; W03 A1 3/A12.01 sello 52b9539bdb85f850; W04 A1 3/A12.01 sello f6908b5e96529b81; W05 A1 3/A12.01 sello 77c98fd16912ccb6; W06 A1 3/A12.01 sello 50854be1d82abd09; W07 A1 3/A12.01 sello 5449e1f18e17b029; W08 A1 3/A12.01 sello faf33c2cddff049d; W09 A1 3/A12.01 sello 4eb93537580359dc; W10 A1 3/A12.01 sello 7c299b0b68f0d0e2; W11 A1K 4/A12.01 sello ee3920121adce127; W12 A1K 4/A12.01 sello 61c7e94e82ba5e79; W13 A5 3/A12.01 sello f95759932e232b8d; W14 A5 3/A12.01 sello 865ddc60d1cdf1fd; W15 A5 3/A12.01 sello c393d8380767a185; W16 A5 3/A12.01 sello a5ba89c61fd91cfd; W17 B 1/A12.01 sello e01658d5f20c92da; W18 B 1/A12.01 sello f89b5e3ef2e13df6; W19 B 1/A12.01 sello 013f94d9afec83ac; W20 B 1/A12.01 sello 22ce136a5b1726f1; W21 B 1/A12.01 sello dedb77a109eddb52; W22 B 1/A12.01 sello 7d3688e2dc552404; W23 B2 1/A12.01 sello 2e
A10: Acoustical sealant (partition details) | B10: LF | C10: 994.68 | D10: =Inputs!$B$5 -> 0.06 | E10: =C10*D10 -> 59.6808 | F10: =C10+E10 -> 1054.3608 | G10: tube (approx 30 LF per 28 oz tube) | H10: =ROUNDUP(F10/30,0) -> 36 | I10: W01 A1 3/A12.01 sello 21b3cc3c7933b572; W02 A1 3/A12.01 sello 5435aab96bad5038; W03 A1 3/A12.01 sello 52b9539bdb85f850; W04 A1 3/A12.01 sello f6908b5e96529b81; W05 A1 3/A12.01 sello 77c98fd16912ccb6; W06 A1 3/A12.01 sello 50854be1d82abd09; W07 A1 3/A12.01 sello 5449e1f18e17b029; W08 A1 3/A12.01 sello faf33c2cddff049d; W09 A1 3/A12.01 sello 4eb93537580359dc; W10 A1 3/A12.01 sello 7c299b0b68f0d0e2; W11 A1K 4/A12.01 sello ee3920121adce127; W12 A1K 4/A12.01 sello 61c7e94e82ba5e79; W13 A5 3/A12.01 sello f95759932e232b8d; W14 A5 3/A12.01 sello 865ddc60d1cdf1fd; W15 A5 3/A12.01 sello c393d8380767a185; W16 A5 3/A12.01 sello a5ba89c61fd91cfd; W17 B 1/A12.01 sello e01658d5f20c92da; W18 B 1/A12.01 sello f89b5e3ef2e13df6; W19 B 1/A12.01 sello 013f94d9afec83ac; W20 B 1/A12.01 sello 22ce136a5b1726f1; W21 B 1/A12.01 sello dedb77a109eddb52; W22 B 1/A12.01 sello 7d3688e2dc552404; W23 B2 1/A12.01 sello 2e
A11: 5/8" gypsum board, regular (walls) | B11: SF | C11: 16308.65 | D11: =Inputs!$B$5 -> 0.06 | E11: =C11*D11 -> 978.519 | F11: =C11+E11 -> 17287.169 | G11: 4x12 sheet | H11: =ROUNDUP(F11/48,0) -> 361 | I11: ROOF STEP - grid B interior: 6/A02.02 interior 5/8" gyp bd tight to deck; SOFFITS - Coiling grille head bulkhead: 4/A08.21: 13'-4" x 2'-10" (cara 2'-0" + fondo 4" + retorno 6"); SOFFITS - Door 100A bulkhead: 5/A12.10 cara CZ: 6.417 x (11'-6" ACT - 10'-0" + 6") (RFI-100A 8" vs 1'-6"); W01 A1 3/A12.01 sello 21b3cc3c7933b572; W02 A1 3/A12.01 sello 5435aab96bad5038; W03 A1 3/A12.01 sello 52b9539bdb85f850; W04 A1 3/A12.01 sello f6908b5e96529b81; W05 A1 3/A12.01 sello 77c98fd16912ccb6; W06 A1 3/A12.01 sello 50854be1d82abd09; W07 A1 3/A12.01 sello 5449e1f18e17b029; W08 A1 3/A12.01 sello faf33c2cddff049d; W09 A1 3/A12.01 sello 4eb93537580359dc; W10 A1 3/A12.01 sello 7c299b0b68f0d0e2; W11 A1K 4/A12.01 sello ee3920121adce127; W12 A1K 4/A12.01 sello 61c7e94e82ba5e79; W13 A5 3/A12.01 sello f95759932e232b8d; W14 A5 3/A12.01 sello 865ddc60d1cdf1fd; W15 A5 3/A12.01 sello c393d8380767a185; W16 A5 3/A12.
A12: Header track at openings 3-5/8" 1-2 members (9/S5.20 header schedule) | B12: LF | C12: 36.26 | D12: =Inputs!$B$4 -> 0.15 | E12: =C12*D12 -> 5.439 | F12: =C12+E12 -> 41.699 | G12: piece 10 ft | H12: =ROUNDUP(F12/10,0) -> 5 | I12: W04 A1 3/A12.01 sello f6908b5e96529b81; W07 A1 3/A12.01 sello 5449e1f18e17b029; W08 A1 3/A12.01 sello faf33c2cddff049d; W09 A1 3/A12.01 sello 4eb93537580359dc; W17 B 1/A12.01 sello e01658d5f20c92da; W22 B 1/A12.01 sello 7d3688e2dc552404; W35 F 12/A12.01 sello 3c13c67afd687dd0
A13: 3-5/8" metal stud 362S137-68 (14 GA, A1K) | B13: LF | C13: 154.51 | D13: =Inputs!$B$4 -> 0.15 | E13: =C13*D13 -> 23.1765 | F13: =C13+E13 -> 177.6865 | G13: stick 20 ft | H13: =ROUNDUP(ROUNDUP(F13/15.375,0)/MAX(1,INT(20/15.375)),0) -> 12 | I13: W11 A1K 4/A12.01 sello ee3920121adce127; W12 A1K 4/A12.01 sello 61c7e94e82ba5e79
A14: Ballistic panel 3/8" UL752 Level-2 fiberglass (4/A12.01) | B14: SF | C14: 78.1 | D14: =Inputs!$B$5 -> 0.06 | E14: =C14*D14 -> 4.686 | F14: =C14+E14 -> 82.786 | G14: 4x8 sheet | H14: =ROUNDUP(F14/32,0) -> 3 | I14: W11 A1K 4/A12.01 sello ee3920121adce127; W12 A1K 4/A12.01 sello 61c7e94e82ba5e79; W26 B2K 4/A12.01 sello c076de1397ab3c20
A15: 3/8" gypsum board (A1K/B2K above 8'-0") | B15: SF | C15: 60.87 | D15: =Inputs!$B$5 -> 0.06 | E15: =C15*D15 -> 3.6522 | F15: =C15+E15 -> 64.5222 | G15: 4x12 sheet | H15: =ROUNDUP(F15/48,0) -> 2 | I15: W11 A1K 4/A12.01 sello ee3920121adce127; W12 A1K 4/A12.01 sello 61c7e94e82ba5e79; W26 B2K 4/A12.01 sello c076de1397ab3c20
A16: PAF power-driven fasteners @2'-0" (4/A12.01) | B16: EA | C16: 9 | D16: 0 | E16: =C16*D16 -> 0 | F16: =C16+E16 -> 9 | G16: EA | H16: =ROUNDUP(F16,0) -> 9 | I16: W11 A1K 4/A12.01 sello ee3920121adce127; W12 A1K 4/A12.01 sello 61c7e94e82ba5e79; W26 B2K 4/A12.01 sello c076de1397ab3c20
A17: 6" metal stud 600S137-33 (A5, B2) | B17: LF | C17: 1559.67 | D17: =Inputs!$B$4 -> 0.15 | E17: =C17*D17 -> 233.9505 | F17: =C17+E17 -> 1793.6205 | G17: stick 20 ft | H17: =ROUNDUP(ROUNDUP(F17/15.375,0)/MAX(1,INT(20/15.375)),0) -> 117 | I17: W13 A5 3/A12.01 sello f95759932e232b8d; W14 A5 3/A12.01 sello 865ddc60d1cdf1fd; W15 A5 3/A12.01 sello c393d8380767a185; W16 A5 3/A12.01 sello a5ba89c61fd91cfd; W23 B2 1/A12.01 sello 2eb81d359b80a45a; W24 B2 1/A12.01 sello 096978eb34e1638d; W25 B2 1/A12.01 sello 06d2acd3de0259f7
A18: Bottom track 6" 600T125-33 | B18: LF | C18: 94.71 | D18: =Inputs!$B$4 -> 0.15 | E18: =C18*D18 -> 14.2065 | F18: =C18+E18 -> 108.9165 | G18: piece 10 ft | H18: =ROUNDUP(F18/10,0) -> 11 | I18: W13 A5 3/A12.01 sello f95759932e232b8d; W14 A5 3/A12.01 sello 865ddc60d1cdf1fd; W15 A5 3/A12.01 sello c393d8380767a185; W16 A5 3/A12.01 sello a5ba89c61fd91cfd; W23 B2 1/A12.01 sello 2eb81d359b80a45a; W24 B2 1/A12.01 sello 096978eb34e1638d; W25 B2 1/A12.01 sello 06d2acd3de0259f7; W26 B2K 4/A12.01 sello c076de1397ab3c20; W31 C1 1/A09.25 sello 5dee9cceb331770e; W32 C1 2/A09.25 sello 2738baba44cdc605; W34 C1 3/A08.21 sello 58b4f82827ca137a
A19: Top track 6" - continuous slip track (RFI-SLIP designacion) | B19: LF | C19: 82.53 | D19: =Inputs!$B$4 -> 0.15 | E19: =C19*D19 -> 12.3795 | F19: =C19+E19 -> 94.9095 | G19: piece 10 ft | H19: =ROUNDUP(F19/10,0) -> 10 | I19: W13 A5 3/A12.01 sello f95759932e232b8d; W14 A5 3/A12.01 sello 865ddc60d1cdf1fd; W15 A5 3/A12.01 sello c393d8380767a185; W16 A5 3/A12.01 sello a5ba89c61fd91cfd; W23 B2 1/A12.01 sello 2eb81d359b80a45a; W24 B2 1/A12.01 sello 096978eb34e1638d; W25 B2 1/A12.01 sello 06d2acd3de0259f7; W26 B2K 4/A12.01 sello c076de1397ab3c20
A20: Header track at openings 6" 1-2 members (9/S5.20 header schedule) | B20: LF | C20: 49.15 | D20: =Inputs!$B$4 -> 0.15 | E20: =C20*D20 -> 7.3725 | F20: =C20+E20 -> 56.5225 | G20: piece 10 ft | H20: =ROUNDUP(F20/10,0) -> 6 | I20: W15 A5 3/A12.01 sello c393d8380767a185; W16 A5 3/A12.01 sello a5ba89c61fd91cfd; W23 B2 1/A12.01 sello 2eb81d359b80a45a; W24 B2 1/A12.01 sello 096978eb34e1638d
A21: 6" metal stud 600S137-68 (14 GA, B2K) | B21: LF | C21: 61.5 | D21: =Inputs!$B$4 -> 0.15 | E21: =C21*D21 -> 9.225 | F21: =C21+E21 -> 70.725 | G21: stick 20 ft | H21: =ROUNDUP(ROUNDUP(F21/15.375,0)/MAX(1,INT(20/15.375)),0) -> 5 | I21: W26 B2K 4/A12.01 sello c076de1397ab3c20
A22: Top track 3-5/8" - track to structure | B22: LF | C22: 78.28 | D22: =Inputs!$B$4 -> 0.15 | E22: =C22*D22 -> 11.742 | F22: =C22+E22 -> 90.022 | G22: piece 10 ft | H22: =ROUNDUP(F22/10,0) -> 10 | I22: PIERS - 4 canopy columns: 5/A09.25 perimetro FOS; W27 C1 6/A12.01 sello e025ee77e70b13c2; W28 C1 6/A12.01 sello 867df2b6a71c9c94; W29 C1 6/A12.01 sello cca875d4b2e04bd0; W30 C1 6/A12.01 sello 5909efb9dc26dc6c; W33 C1 6/A12.01 sello fcf7609a84560dba; W35 F 12/A12.01 sello 3c13c67afd687dd0
A23: 5/8" gypsum board, moisture resistant (59.9 chase face WC + lav) | B23: SF | C23: 180.48 | D23: =Inputs!$B$5 -> 0.06 | E23: =C23*D23 -> 10.8288 | F23: =C23+E23 -> 191.3088 | G23: 4x12 sheet | H23: =ROUNDUP(F23/48,0) -> 4 | I23: W27 C1 6/A12.01 sello e025ee77e70b13c2; W28 C1 6/A12.01 sello 867df2b6a71c9c94
A24: 6" metal stud 600S162-54 (exterior walls, storefront piers, grille HSS box) | B24: LF | C24: 3271.6 | D24: =Inputs!$B$4 -> 0.15 | E24: =C24*D24 -> 490.74 | F24: =C24+E24 -> 3762.34 | G24: stick 20 ft | H24: =ROUNDUP(ROUNDUP(F24/15.375,0)/MAX(1,INT(20/15.375)),0) -> 245 | I24: W31 C1 1/A09.25 sello 5dee9cceb331770e; W32 C1 2/A09.25 sello 2738baba44cdc605; W34 C1 3/A08.21 sello 58b4f82827ca137a; W50 EXT C/A09.21 sello ee1c924fe5e55fb3; W51 EXT C/A09.21 sello 201ecf20dc3fd426; W52 EXT C/A09.21 sello 307a0c2a7d3666c9; W53 EXT C/A09.21 sello c751f520bd6ec886; W54 EXT C/A09.21 sello 37735d04dc7852bf; W55 EXT C/A09.21 sello 5cb81bd71d6f856c; W56 EXT C/A09.21 sello a98ba16555237b45; W57 EXT C/A09.21 sello 8b3f46dfd7304cc0; W58 EXT C/A09.21 sello 554cb31baf022658; W59 EXT C/A09.21 sello 605495145e5721ea
A25: Top track 6" - track to structure | B25: LF | C25: 12.18 | D25: =Inputs!$B$4 -> 0.15 | E25: =C25*D25 -> 1.827 | F25: =C25+E25 -> 14.007 | G25: piece 10 ft | H25: =ROUNDUP(F25/10,0) -> 2 | I25: W31 C1 1/A09.25 sello 5dee9cceb331770e; W32 C1 2/A09.25 sello 2738baba44cdc605; W34 C1 3/A08.21 sello 58b4f82827ca137a
A26: Sill track 3-5/8" (53.7) | B26: LF | C26: 3.58 | D26: =Inputs!$B$4 -> 0.15 | E26: =C26*D26 -> 0.537 | F26: =C26+E26 -> 4.117 | G26: piece 10 ft | H26: =ROUNDUP(F26/10,0) -> 1 | I26: W35 F 12/A12.01 sello 3c13c67afd687dd0
A27: 3/4" FRT plywood (F wall public side, 12/A12.01) | B27: SF | C27: 271.72 | D27: =Inputs!$B$5 -> 0.06 | E27: =C27*D27 -> 16.3032 | F27: =C27+E27 -> 288.0232 | G27: 4x8 sheet | H27: =ROUNDUP(F27/32,0) -> 10 | I27: W35 F 12/A12.01 sello 3c13c67afd687dd0
A28: 1-5/8" metal stud 162S125-33 (G/G1 double row, bulkheads) | B28: LF | C28: 4044.62 | D28: =Inputs!$B$4 -> 0.15 | E28: =C28*D28 -> 606.693 | F28: =C28+E28 -> 4651.313 | G28: stick 20 ft | H28: =ROUNDUP(ROUNDUP(F28/15.375,0)/MAX(1,INT(20/15.375)),0) -> 303 | I28: W36 G 5/A12.01 sello f434642610a09e2b; W37 G 5/A12.01 sello 84239d0ace2ed989; W38 G 5/A12.01 sello a28516492c3483b9; W39 G 5/A12.01 sello 56f17ec8ea036919; W40 G 5/A12.01 sello 6b2dac7988434ba7; W41 G 5/A12.01 sello de769043d0526987; W42 G 5/A12.01 sello eff32985b3965963; W43 G 5/A12.01 sello fb5e001e3f29a9f9; W44 G 5/A12.01 sello adfbc7d60b094a42; W45 G 5/A12.01 sello 1c3b1935079253f4; W46 G1 5/A12.01 sello 65ca1372db0dda9e; W47 G1 5/A12.01 sello eebc87bae9146a7c; W48 G1 5/A12.01 sello f5d95dd8b751ab0e; W49 G1 5/A12.01 sello 0e94c82b77f78452; W61 BULKHEAD-OF 9/A12.01 sello f2c9c06f874adf15; W62 BULKHEAD-OF 9/A12.01 sello 6b989f008fb374d3; W63 BULKHEAD-OF 9/A12.01 sello 6d09d6d67a488b5f; W64 BULKHEAD-OF 9/A12.01 sello a422d5fb730daed5; W65 BULKHEAD-OF 9/A12.01 sello 103629ff26a3b1d9; W66 BULKHEAD-OF 9/A12.01 sello 847e6bb890ea7524
A29: Bottom track 1-5/8" 162T125-33 | B29: LF | C29: 294.41 | D29: =Inputs!$B$4 -> 0.15 | E29: =C29*D29 -> 44.1615 | F29: =C29+E29 -> 338.5715 | G29: piece 10 ft | H29: =ROUNDUP(F29/10,0) -> 34 | I29: W36 G 5/A12.01 sello f434642610a09e2b; W37 G 5/A12.01 sello 84239d0ace2ed989; W38 G 5/A12.01 sello a28516492c3483b9; W39 G 5/A12.01 sello 56f17ec8ea036919; W40 G 5/A12.01 sello 6b2dac7988434ba7; W41 G 5/A12.01 sello de769043d0526987; W42 G 5/A12.01 sello eff32985b3965963; W43 G 5/A12.01 sello fb5e001e3f29a9f9; W44 G 5/A12.01 sello adfbc7d60b094a42; W45 G 5/A12.01 sello 1c3b1935079253f4; W46 G1 5/A12.01 sello 65ca1372db0dda9e; W47 G1 5/A12.01 sello eebc87bae9146a7c; W48 G1 5/A12.01 sello f5d95dd8b751ab0e; W49 G1 5/A12.01 sello 0e94c82b77f78452; W61 BULKHEAD-OF 9/A12.01 sello f2c9c06f874adf15; W62 BULKHEAD-OF 9/A12.01 sello 6b989f008fb374d3; W63 BULKHEAD-OF 9/A12.01 sello 6d09d6d67a488b5f; W64 BULKHEAD-OF 9/A12.01 sello a422d5fb730daed5; W65 BULKHEAD-OF 9/A12.01 sello 103629ff26a3b1d9; W66 BULKHEAD-OF 9/A12.01 sello 847e6bb890ea7524
A30: Top track 1-5/8" - track to structure | B30: LF | C30: 204.41 | D30: =Inputs!$B$4 -> 0.15 | E30: =C30*D30 -> 30.6615 | F30: =C30+E30 -> 235.0715 | G30: piece 10 ft | H30: =ROUNDUP(F30/10,0) -> 24 | I30: W36 G 5/A12.01 sello f434642610a09e2b; W37 G 5/A12.01 sello 84239d0ace2ed989; W38 G 5/A12.01 sello a28516492c3483b9; W39 G 5/A12.01 sello 56f17ec8ea036919; W40 G 5/A12.01 sello 6b2dac7988434ba7; W41 G 5/A12.01 sello de769043d0526987; W42 G 5/A12.01 sello eff32985b3965963; W43 G 5/A12.01 sello fb5e001e3f29a9f9; W44 G 5/A12.01 sello adfbc7d60b094a42; W45 G 5/A12.01 sello 1c3b1935079253f4; W46 G1 5/A12.01 sello 65ca1372db0dda9e; W47 G1 5/A12.01 sello eebc87bae9146a7c; W48 G1 5/A12.01 sello f5d95dd8b751ab0e; W49 G1 5/A12.01 sello 0e94c82b77f78452
A31: Bottom track 6" 600T125-33 (exterior, 7/S5.20) | B31: LF | C31: 258.29 | D31: =Inputs!$B$4 -> 0.15 | E31: =C31*D31 -> 38.7435 | F31: =C31+E31 -> 297.0335 | G31: piece 10 ft | H31: =ROUNDUP(F31/10,0) -> 30 | I31: W50 EXT C/A09.21 sello ee1c924fe5e55fb3; W51 EXT C/A09.21 sello 201ecf20dc3fd426; W52 EXT C/A09.21 sello 307a0c2a7d3666c9; W53 EXT C/A09.21 sello c751f520bd6ec886; W54 EXT C/A09.21 sello 37735d04dc7852bf; W55 EXT C/A09.21 sello 5cb81bd71d6f856c; W56 EXT C/A09.21 sello a98ba16555237b45; W57 EXT C/A09.21 sello 8b3f46dfd7304cc0; W58 EXT C/A09.21 sello 554cb31baf022658; W59 EXT C/A09.21 sello 605495145e5721ea
A32: Top / deflection track 6" 600T200-97 (exterior, 7/S5.20, 10/S5.10) | B32: LF | C32: 258.29 | D32: =Inputs!$B$4 -> 0.15 | E32: =C32*D32 -> 38.7435 | F32: =C32+E32 -> 297.0335 | G32: piece 10 ft | H32: =ROUNDUP(F32/10,0) -> 30 | I32: W50 EXT C/A09.21 sello ee1c924fe5e55fb3; W51 EXT C/A09.21 sello 201ecf20dc3fd426; W52 EXT C/A09.21 sello 307a0c2a7d3666c9; W53 EXT C/A09.21 sello c751f520bd6ec886; W54 EXT C/A09.21 sello 37735d04dc7852bf; W55 EXT C/A09.21 sello 5cb81bd71d6f856c; W56 EXT C/A09.21 sello a98ba16555237b45; W57 EXT C/A09.21 sello 8b3f46dfd7304cc0; W58 EXT C/A09.21 sello 554cb31baf022658; W59 EXT C/A09.21 sello 605495145e5721ea
A33: 5/8" FRT plywood bonded to 2-1/2" polyiso (nailbase), exterior | B33: SF | C33: 3529.82 | D33: =Inputs!$B$5 -> 0.06 | E33: =C33*D33 -> 211.7892 | F33: =C33+E33 -> 3741.6092 | G33: 4x8 sheet | H33: =ROUNDUP(F33/32,0) -> 117 | I33: W50 EXT C/A09.21 sello ee1c924fe5e55fb3; W51 EXT C/A09.21 sello 201ecf20dc3fd426; W52 EXT C/A09.21 sello 307a0c2a7d3666c9; W53 EXT C/A09.21 sello c751f520bd6ec886; W54 EXT C/A09.21 sello 37735d04dc7852bf; W56 EXT C/A09.21 sello a98ba16555237b45; W57 EXT C/A09.21 sello 8b3f46dfd7304cc0; W58 EXT C/A09.21 sello 554cb31baf022658; W59 EXT C/A09.21 sello 605495145e5721ea
A34: 5/8" glass mat sheathing | B34: SF | C34: 441.22 | D34: =Inputs!$B$5 -> 0.06 | E34: =C34*D34 -> 26.4732 | F34: =C34+E34 -> 467.6932 | G34: 4x8 sheet | H34: =ROUNDUP(F34/32,0) -> 15 | I34: W50 EXT C/A09.21 sello ee1c924fe5e55fb3; W51 EXT C/A09.21 sello 201ecf20dc3fd426; W52 EXT C/A09.21 sello 307a0c2a7d3666c9; W53 EXT C/A09.21 sello c751f520bd6ec886; W54 EXT C/A09.21 sello 37735d04dc7852bf; W55 EXT C/A09.21 sello 5cb81bd71d6f856c; W56 EXT C/A09.21 sello a98ba16555237b45; W57 EXT C/A09.21 sello 8b3f46dfd7304cc0; W58 EXT C/A09.21 sello 554cb31baf022658; W59 EXT C/A09.21 sello 605495145e5721ea
A35: Sealant at base of gypsum (exterior, 5/A09.26) | B35: LF | C35: 209.65 | D35: =Inputs!$B$5 -> 0.06 | E35: =C35*D35 -> 12.579 | F35: =C35+E35 -> 222.229 | G35: tube (approx 30 LF per 28 oz tube) | H35: =ROUNDUP(F35/30,0) -> 8 | I35: W50 EXT C/A09.21 sello ee1c924fe5e55fb3; W54 EXT C/A09.21 sello 37735d04dc7852bf; W55 EXT C/A09.21 sello 5cb81bd71d6f856c; W56 EXT C/A09.21 sello a98ba16555237b45; W57 EXT C/A09.21 sello 8b3f46dfd7304cc0; W58 EXT C/A09.21 sello 554cb31baf022658; W59 EXT C/A09.21 sello 605495145e5721ea
A36: Header - storefront head steel header framing (2/A09.26) | B36: LF | C36: 98.63 | D36: =Inputs!$B$4 -> 0.15 | E36: =C36*D36 -> 14.7945 | F36: =C36+E36 -> 113.4245 | G36: piece 10 ft | H36: =ROUNDUP(F36/10,0) -> 12 | I36: W51 EXT C/A09.21 sello 201ecf20dc3fd426; W52 EXT C/A09.21 sello 307a0c2a7d3666c9; W53 EXT C/A09.21 sello c751f520bd6ec886
A37: FRT blocking (3/4" plywood strip) | B37: LF | C37: 94 | D37: =Inputs!$B$5 -> 0.06 | E37: =C37*D37 -> 5.64 | F37: =C37+E37 -> 99.64 | G37: piece 8 ft | H37: =ROUNDUP(F37/8,0) -> 13 | I37: BLOCKING - 85" display monitor (key note 7): 13/A12.02, 9/A12.02: 3'-8 1/4" LF (alto 18" A03.01 por 53.3, RFI-MON); W51 EXT C/A09.21 sello 201ecf20dc3fd426; W52 EXT C/A09.21 sello 307a0c2a7d3666c9; W53 EXT C/A09.21 sello c751f520bd6ec886; W61 BULKHEAD-OF 9/A12.01 sello f2c9c06f874adf15; W62 BULKHEAD-OF 9/A12.01 sello 6b989f008fb374d3; W63 BULKHEAD-OF 9/A12.01 sello 6d09d6d67a488b5f; W64 BULKHEAD-OF 9/A12.01 sello a422d5fb730daed5; W65 BULKHEAD-OF 9/A12.01 sello 103629ff26a3b1d9; W66 BULKHEAD-OF 9/A12.01 sello 847e6bb890ea7524
A38: metal trim - corner bead | B38: LF | C38: 741.25 | D38: =Inputs!$B$4 -> 0.15 | E38: =C38*D38 -> 111.1875 | F38: =C38+E38 -> 852.4375 | G38: piece 10 ft | H38: =ROUNDUP(F38/10,0) -> 86 | I38: 53.1/56.9 metal trim (criterio 53.1): column furring 4 cajas x 4 aristas x 10.5 + monitor furring 2 x 11.5 + office front jambs 12 x 2 x 8.042 (10/A12.01 CORNER BEAD TYPICAL); CEILINGS - East aisle transition: 7/A09.33 corner bead; CEILINGS - Waiting 104 transition: 7/A09.33 CORNER BEAD TYPICAL x 2 runs x 77.03; SOFFITS - CSR soffit: CORNER BEAD 2 x 12.0 9/A12.08; SOFFITS - Coiling grille head bulkhead: 4/A08.21 corner bead 2 aristas x 13'-4"; SOFFITS - Door 100A bulkhead: 5/A12.10 corner bead; W51 EXT C/A09.21 sello 201ecf20dc3fd426; W52 EXT C/A09.21 sello 307a0c2a7d3666c9; W53 EXT C/A09.21 sello c751f520bd6ec886; W61 BULKHEAD-OF 9/A12.01 sello f2c9c06f874adf15; W62 BULKHEAD-OF 9/A12.01 sello 6b989f008fb374d3; W63 BULKHEAD-OF 9/A12.01 sello 6d09d6d67a488b5f; W64 BULKHEAD-OF 9/A12.01 sello a422d5fb730daed5; W65 BULKHEAD-OF 9/A12.01 sello 103629ff26a3b1d9; W66 BULKHEAD-OF 9/A12.01 sello 8
A39: metal trim - casing / J-bead | B39: LF | C39: 250.31 | D39: =Inputs!$B$4 -> 0.15 | E39: =C39*D39 -> 37.5465 | F39: =C39+E39 -> 287.8565 | G39: piece 10 ft | H39: =ROUNDUP(F39/10,0) -> 29 | I39: 53.1: board contra window frame GL-2 8'-0"x2'-0": 6 windows x 20 LF; A09.01/A09.02; EXTERIOR - Storefront piers jambs: 53.1: 4 retornos x 8.5 contra storefront 1,2/A09.25; W51 EXT C/A09.21 sello 201ecf20dc3fd426; W52 EXT C/A09.21 sello 307a0c2a7d3666c9; W53 EXT C/A09.21 sello c751f520bd6ec886
A40: Header - exterior windows/doors box 2-600T (RFI-HDR-EXT, 9/S5.20) | B40: LF | C40: 120.17 | D40: =Inputs!$B$4 -> 0.15 | E40: =C40*D40 -> 18.0255 | F40: =C40+E40 -> 138.1955 | G40: piece 10 ft | H40: =ROUNDUP(F40/10,0) -> 14 | I40: W55 EXT C/A09.21 sello 5cb81bd71d6f856c; W57 EXT C/A09.21 sello 8b3f46dfd7304cc0; W58 EXT C/A09.21 sello 554cb31baf022658; W59 EXT C/A09.21 sello 605495145e5721ea
A41: Sill track 6" (53.7) | B41: LF | C41: 59.51 | D41: =Inputs!$B$4 -> 0.15 | E41: =C41*D41 -> 8.9265 | F41: =C41+E41 -> 68.4365 | G41: piece 10 ft | H41: =ROUNDUP(F41/10,0) -> 7 | I41: W55 EXT C/A09.21 sello 5cb81bd71d6f856c; W57 EXT C/A09.21 sello 8b3f46dfd7304cc0; W59 EXT C/A09.21 sello 605495145e5721ea
A42: 5/8" ext. grade FRT plywood sheathing (canopy) | B42: SF | C42: 2351.51 | D42: =Inputs!$B$5 -> 0.06 | E42: =C42*D42 -> 141.0906 | F42: =C42+E42 -> 2492.6006 | G42: 4x8 sheet | H42: =ROUNDUP(F42/32,0) -> 78 | I42: CANOPY - Drive-up canopy west (grid 1-2/3) fascia: 96.11 x (cara 2'-2" T/CANOPY 12'-8" - B/CANOPY 10'-6" + top 6") 3/A09.26, 7/A09.26; CANOPY - Drive-up canopy west (grid 1-2/3) soffit: soffit drive-up 989.59 SF; 15/A09.27, 16/A09.27; CANOPY - East canopy (grid 8) fascia: 52.135 x (cara 2'-2" T/CANOPY 12'-8" - B/CANOPY 10'-6" + top 6") 3/A09.26, 7/A09.26; CANOPY - East canopy (grid 8) soffit: soffit [(47.365, 2.479)] = 117.42 SF; 7/A09.26 (4/A09.33 dice exterior sheathing -> RFI-CAN-SH); CANOPY - North canopy (grid 2->8) fascia: 60.51 x (cara 2'-2" T/CANOPY 12'-8" - B/CANOPY 10'-6" + top 6") 3/A09.26, 7/A09.26; CANOPY - North canopy (grid 2->8) soffit: soffit [(16.2, 3.0), (41.34, 3.979)] = 213.09 SF; 7/A09.26 (4/A09.33 dice exterior sheathing -> RFI-CAN-SH); CANOPY - South canopy (grid A) fascia: 23.05 x (cara 2'-2" T/CANOPY 12'-8" - B/CANOPY 10'-6" + top 6") 3/A09.26, 7/A09.26; CANOPY
A43: 2-1/2" metal stud sistered (6/A08.11) | B43: LF | C43: 30.75 | D43: =Inputs!$B$4 -> 0.15 | E43: =C43*D43 -> 4.6125 | F43: =C43+E43 -> 35.3625 | G43: stick 20 ft | H43: =ROUNDUP(ROUNDUP(F43/14.362,0)/MAX(1,INT(20/14.362)),0) -> 3 | I43: W55 EXT C/A09.21 sello 5cb81bd71d6f856c
A44: mineral wool insulation | B44: SF | C44: 162.57 | D44: =Inputs!$B$5 -> 0.06 | E44: =C44*D44 -> 9.7542 | F44: =C44+E44 -> 172.3242 | G44: SF | H44: =ROUNDUP(F44,0) -> 173 | I44: ROOF STEP - grid B: 6/A02.02 w/ mineral wool; W55 EXT C/A09.21 sello 5cb81bd71d6f856c
A45: Top track 1-5/8" - continuous slip track (RFI-SLIP designacion) | B45: LF | C45: 90 | D45: =Inputs!$B$4 -> 0.15 | E45: =C45*D45 -> 13.5 | F45: =C45+E45 -> 103.5 | G45: piece 10 ft | H45: =ROUNDUP(F45/10,0) -> 11 | I45: W61 BULKHEAD-OF 9/A12.01 sello f2c9c06f874adf15; W62 BULKHEAD-OF 9/A12.01 sello 6b989f008fb374d3; W63 BULKHEAD-OF 9/A12.01 sello 6d09d6d67a488b5f; W64 BULKHEAD-OF 9/A12.01 sello a422d5fb730daed5; W65 BULKHEAD-OF 9/A12.01 sello 103629ff26a3b1d9; W66 BULKHEAD-OF 9/A12.01 sello 847e6bb890ea7524
A46: Header / box beam - office bulkhead (9/A12.01) | B46: LF | C46: 53 | D46: =Inputs!$B$4 -> 0.15 | E46: =C46*D46 -> 7.95 | F46: =C46+E46 -> 60.95 | G46: piece 10 ft | H46: =ROUNDUP(F46/10,0) -> 7 | I46: W61 BULKHEAD-OF 9/A12.01 sello f2c9c06f874adf15; W62 BULKHEAD-OF 9/A12.01 sello 6b989f008fb374d3; W63 BULKHEAD-OF 9/A12.01 sello 6d09d6d67a488b5f; W64 BULKHEAD-OF 9/A12.01 sello a422d5fb730daed5; W65 BULKHEAD-OF 9/A12.01 sello 103629ff26a3b1d9; W66 BULKHEAD-OF 9/A12.01 sello 847e6bb890ea7524
A47: metal trim - shadow molding | B47: LF | C47: 172.12 | D47: =Inputs!$B$4 -> 0.15 | E47: =C47*D47 -> 25.818 | F47: =C47+E47 -> 197.938 | G47: piece 10 ft | H47: =ROUNDUP(F47/10,0) -> 20 | I47: CEILINGS - East aisle transition: 7/A09.33 shadow molding; CEILINGS - Waiting 104 transition: 7/A09.33 SHADOW MOLDING AS SPECIFIED; W61 BULKHEAD-OF 9/A12.01 sello f2c9c06f874adf15; W62 BULKHEAD-OF 9/A12.01 sello 6b989f008fb374d3; W63 BULKHEAD-OF 9/A12.01 sello 6d09d6d67a488b5f; W64 BULKHEAD-OF 9/A12.01 sello a422d5fb730daed5; W65 BULKHEAD-OF 9/A12.01 sello 103629ff26a3b1d9; W66 BULKHEAD-OF 9/A12.01 sello 847e6bb890ea7524
A48: 6" parapet stud 600S162-54 (11/S5.10) | B48: LF | C48: 944.37 | D48: =Inputs!$B$4 -> 0.15 | E48: =C48*D48 -> 141.6555 | F48: =C48+E48 -> 1086.0255 | G48: stick 20 ft | H48: =ROUNDUP(ROUNDUP(F48/2.042,0)/MAX(1,INT(20/2.042)),0) -> 60 | I48: PARAPET - P1 east north of B: 59.4: bays=ROUNDUP(51.45/5'-0" HSS max)=11; studs/bay=2+max(0,ROUNDUP((4.677-0.6)/1.333)-1)=5; 55 studs x h 2.042 (T/STUD - B.O.D. promedio del tramo, 55.3) = 112.31 LF; 11/S5.10; PARAPET - P1 east south of B: 59.4: bays=ROUNDUP(25.74/5'-0" HSS max)=6; studs/bay=2+max(0,ROUNDUP((4.29-0.6)/1.333)-1)=4; 24 studs x h 4.631 (T/STUD - B.O.D. promedio del tramo, 55.3) = 111.14 LF; 11/S5.10; PARAPET - P1 north (grid F, x1143->1860): 59.4: bays=ROUNDUP(39.86/5'-0" HSS max)=8; studs/bay=2+max(0,ROUNDUP((4.983-0.6)/1.333)-1)=5; 40 studs x h 2.042 (T/STUD - B.O.D. promedio del tramo, 55.3) = 81.68 LF; 11/S5.10; PARAPET - P1 south (grid A): 59.4: bays=ROUNDUP(53.59/5'-0" HSS max)=11; studs/bay=2+max(0,ROUNDUP((4.872-0.6)/1.333)-1)=5; 55 studs x h 4.887 (T/STUD - B.O.D. promedio del tramo, 55.3) = 268.78 LF; 11/S5.10; PARAPET - P1 west grid 3 north of B: 59.4: bays=ROUND
A49: Bottom track - parapet 600T125-54 (11/S5.10) | B49: LF | C49: 275.12 | D49: =Inputs!$B$4 -> 0.15 | E49: =C49*D49 -> 41.268 | F49: =C49+E49 -> 316.388 | G49: piece 10 ft | H49: =ROUNDUP(F49/10,0) -> 32 | I49: PARAPET - all runs: 2 x 275.12 LF (TOP & BOT. = 2 renglones, 54.2) 11/S5.10
A50: Top track - parapet 600T125-54 (11/S5.10) | B50: LF | C50: 275.12 | D50: =Inputs!$B$4 -> 0.15 | E50: =C50*D50 -> 41.268 | F50: =C50+E50 -> 316.388 | G50: piece 10 ft | H50: =ROUNDUP(F50/10,0) -> 32 | I50: PARAPET - all runs: 2 x 275.12 LF (TOP & BOT. = 2 renglones, 54.2) 11/S5.10
A51: 5/8" exterior gypsum sheathing (parapet roof side) | B51: SF | C51: 985.9 | D51: =Inputs!$B$5 -> 0.06 | E51: =C51*D51 -> 59.154 | F51: =C51+E51 -> 1045.054 | G51: 4x8 sheet | H51: =ROUNDUP(F51/32,0) -> 33 | I51: PARAPET - all runs roof side: sum LF x (T/STUD - B.O.D.) por tramo (55.3); return P2 ambas caras; C/A09.21, E/A09.22, J/A09.23 (4/A09.26 dice DENS DECK -> RFI-PAR)
A52: 3/4" FRT plywood blocking (parapet top) | B52: LF | C52: 550.24 | D52: =Inputs!$B$5 -> 0.06 | E52: =C52*D52 -> 33.0144 | F52: =C52+E52 -> 583.2544 | G52: piece 8 ft | H52: =ROUNDUP(F52/8,0) -> 73 | I52: PARAPET - all runs top: 3/4" F.R.T. PLYWOOD BLOCKING AS REQUIRED under ACM coping 4/A09.26: 275.12 LF x 2 plies dibujados (58.6)
A53: PAF power-actuated fasteners | B53: EA | C53: 289 | D53: =Inputs!$B$4 -> 0.15 | E53: =C53*D53 -> 43.35 | F53: =C53+E53 -> 332.35 | G53: EA | H53: =ROUNDUP(F53,0) -> 333 | I53: PARAPET - all runs: PAFs SPACED AT 12" O.C. MAX 11/S5.10: sum(ceil(L)+1)
A54: bracing 1-1/2" C.R. channel | B54: LF | C54: 157.77 | D54: =Inputs!$B$4 -> 0.15 | E54: =C54*D54 -> 23.6655 | F54: =C54+E54 -> 181.4355 | G54: piece 16 ft | H54: =ROUNDUP(F54/16,0) -> 12 | I54: PARAPET - runs >= 4 ft: 1 fila @48" en tramos de parapet >= 4'-0" (37: bridging no cruza el deflection track); F/1/S5.20
A55: Top / deflection track 3-5/8" (metal slip clip, roof step) | B55: LF | C55: 52.33 | D55: =Inputs!$B$4 -> 0.15 | E55: =C55*D55 -> 7.8495 | F55: =C55+E55 -> 60.1795 | G55: piece 10 ft | H55: =ROUNDUP(F55/10,0) -> 7 | I55: ROOF STEP - grid B: 6/A02.02 metal slip clip
A56: purlin 1x1x1 16 GA | B56: LF | C56: 68.98 | D56: =Inputs!$B$4 -> 0.15 | E56: =C56*D56 -> 10.347 | F56: =C56+E56 -> 79.327 | G56: piece 10 ft | H56: =ROUNDUP(F56/10,0) -> 8 | I56: ROOF STEP - grid B purlin: 59.1: top track E-W a deck, flute E-W (S2.20): 52.333 x 0.75; 10/A09.33; SOFFITS - CSR soffit purlin: 10/A09.33 ALTERNATE CEILING DETAIL: tracks a deck N-S; flutes E-W (S2.20) -> perpendicular; VIF -> CRITERIO: 2 tracks x12 x0.75 (59.1); SOFFITS - Vestibule head door 101 purlin: 10/A09.33: track E-W a deck paralelo al flute E-W (S2.20) -> 15.646 x 0.75 (59.1)
A57: 5/8" FRT plywood bonded to 2-1/2" polyiso (nailbase) | B57: SF | C57: 170.77 | D57: =Inputs!$B$5 -> 0.06 | E57: =C57*D57 -> 10.2462 | F57: =C57+E57 -> 181.0162 | G57: 4x8 sheet | H57: =ROUNDUP(F57/32,0) -> 6 | I57: EXTERIOR - Storefront piers 1,2/A09.25 bajo el head: 1/A09.25 (2.0+1.25=3.25 ft) + 2/A09.25 (1.979+0.917=2.896) x (8.5-0.5); ROOF STEP - grid B exterior: 6/A02.02 roof membrane on 5/8" FRT plywood bonded to polyiso
A58: 2x FRT wood blocking | B58: LF | C58: 52.33 | D58: =Inputs!$B$5 -> 0.06 | E58: =C58*D58 -> 3.1398 | F58: =C58+E58 -> 55.4698 | G58: piece 8 ft | H58: =ROUNDUP(F58/8,0) -> 7 | I58: ROOF STEP - grid B: 6/A02.02 2x FRT blocking (1 run)
A59: Ceiling / soffit track (canopy) | B59: LF | C59: 878.45 | D59: =Inputs!$B$4 -> 0.15 | E59: =C59*D59 -> 131.7675 | F59: =C59+E59 -> 1010.2175 | G59: piece 10 ft | H59: =ROUNDUP(F59/10,0) -> 102 | I59: CANOPY - Drive-up canopy west (grid 1-2/3) fascia: top + bottom de la caja de fascia 2 x 96.11; 7/A09.26 (58.2); CANOPY - Drive-up canopy west (grid 1-2/3) soffit: 58.3 linea del muro 56.21 + fascia int 96.11; 16/A09.27; CANOPY - East canopy (grid 8) fascia: top + bottom de la caja de fascia 2 x 52.135; 7/A09.26 (58.2); CANOPY - East canopy (grid 8) soffit: 58.3: track en la linea del muro 47.365 + linea interior de fascia 52.135; 7/A09.26; CANOPY - North canopy (grid 2->8) fascia: top + bottom de la caja de fascia 2 x 60.51; 7/A09.26 (58.2); CANOPY - North canopy (grid 2->8) soffit: 58.3: track en la linea del muro 57.54 + linea interior de fascia 60.51; 7/A09.26; CANOPY - South canopy (grid A) fascia: top + bottom de la caja de fascia 2 x 23.05; 7/A09.26 (58.2); CANOPY - South canopy (grid A) soffit: 58.3: track en la linea del muro 21.917 + linea interior de fascia 23.05; 7/A09.26
A60: Framed opening for recessed fixture (canopy) | B60: LF | C60: 686.9 | D60: =Inputs!$B$4 -> 0.15 | E60: =C60*D60 -> 103.035 | F60: =C60+E60 -> 789.935 | G60: LF | H60: =ROUNDUP(F60,0) -> 790 | I60: CANOPY - Recessed linear fixtures UU1-UU6 (21): 54.1: 2 x (largo E00.01 + 1/4" 5/A09.33) por fixture; 21 tags E02.01 (ag_mep); ends PENDIENTE cutsheet 4/A09.33
A61: 5/8" gypsum board, ceiling (GWB ceilings + soffits) | B61: SF | C61: 1054.35 | D61: =Inputs!$B$5 -> 0.06 | E61: =C61*D61 -> 63.261 | F61: =C61+E61 -> 1117.611 | G61: 4x12 sheet | H61: =ROUNDUP(F61/48,0) -> 24 | I61: CEILINGS - 24HR Vestibule 101 GB 10'-0": A04.01 GB 10'-0": trapecio bajo el muro F (vector); 6/A09.33; CEILINGS - East aisle ACT-4 11'-6" to 9'-0" transition (y=1110.72): 7/A09.33 transition 5.09 LF (A04.01 x 1530-1622) x 2.5 ft drop (RFI-TR); CEILINGS - Men's 113 GB 8'-6": A04.01 GB 8'-6"; 11'-7 1/2" x 6'-6 3/4" impresos 1/A08.01; 6/A09.33; CEILINGS - Vestibule 100 GB 10'-0": A04.01 GB 10'-0": 16.13 x 7.25 ft (vector); 6/A09.33; CEILINGS - Waiting 104 GB 11'-0": A04.01 GB 11'-0": x 1223.9->1530.4, y 427.44->967.44; 30'-0" impreso; 6/A09.33; CEILINGS - Waiting 104 GB edge to ACT-4 11'-6" (3 sides): 7/A09.33 TYPICAL CEILING TRANSITION 6" impreso: 77.03 LF x 0.5; CEILINGS - Women's 114 GB 8'-6": A04.01 GB 8'-6"; 11'-7 1/2" x 6'-6 3/4" impresos 1/A08.01, A02.01; 6/A09.33; SOFFITS - CSR soffit: fondo 12.0x3.417=41.0 + caras 2x12.0x1.0 = 65.0 SF 9/A12.08
A62: carrying channel 1-1/2" C.R. | B62: LF | C62: 234.55 | D62: =Inputs!$B$4 -> 0.15 | E62: =C62*D62 -> 35.1825 | F62: =C62+E62 -> 269.7325 | G62: piece 16 ft | H62: =ROUNDUP(F62/16,0) -> 17 | I62: CEILINGS - 24HR Vestibule 101 GB 10'-0": A/4 ft (@48" O.C.) ASTM C754 tipico; ningun detalle especifica suspension (ag_mep) RFI-SUSP; 6/A09.33; CEILINGS - Men's 113 GB 8'-6": A/4 ft (@48" O.C.) ASTM C754 tipico; ningun detalle especifica suspension (ag_mep) RFI-SUSP; 6/A09.33; CEILINGS - Vestibule 100 GB 10'-0": A/4 ft (@48" O.C.) ASTM C754 tipico; ningun detalle especifica suspension (ag_mep) RFI-SUSP; 6/A09.33; CEILINGS - Waiting 104 GB 11'-0": A/4 ft (@48" O.C.) ASTM C754 tipico; ningun detalle especifica suspension (ag_mep) RFI-SUSP; 6/A09.33; CEILINGS - Women's 114 GB 8'-6": A/4 ft (@48" O.C.) ASTM C754 tipico; ningun detalle especifica suspension (ag_mep) RFI-SUSP; 6/A09.33
A63: furring channel 7/8" | B63: LF | C63: 703.78 | D63: =Inputs!$B$4 -> 0.15 | E63: =C63*D63 -> 105.567 | F63: =C63+E63 -> 809.347 | G63: piece 16 ft | H63: =ROUNDUP(F63/16,0) -> 51 | I63: CEILINGS - 24HR Vestibule 101 GB 10'-0": A/1.333 (@16" O.C., 6/A09.33 '@ 16" O.C.') RFI-SUSP; CEILINGS - Men's 113 GB 8'-6": A/1.333 (@16" O.C., 6/A09.33 '@ 16" O.C.') RFI-SUSP; CEILINGS - Vestibule 100 GB 10'-0": A/1.333 (@16" O.C., 6/A09.33 '@ 16" O.C.') RFI-SUSP; CEILINGS - Waiting 104 GB 11'-0": A/1.333 (@16" O.C., 6/A09.33 '@ 16" O.C.') RFI-SUSP; CEILINGS - Women's 114 GB 8'-6": A/1.333 (@16" O.C., 6/A09.33 '@ 16" O.C.') RFI-SUSP
A64: hanger wire 12 ga | B64: LF | C64: 341.75 | D64: =Inputs!$B$4 -> 0.15 | E64: =C64*D64 -> 51.2625 | F64: =C64+E64 -> 393.0125 | G64: LF (coil) | H64: =ROUNDUP(F64,0) -> 394 | I64: CEILINGS - 24HR Vestibule 101 GB 10'-0": 10 hangers (@48"x48") x (B.O.D.-ceiling 5.375 + 1.0 vuelta) ; 12 GAUGE HANGER WIRE 3/A09.33; RFI-SUSP; CEILINGS - Men's 113 GB 8'-6": 5 hangers (@48"x48") x (B.O.D.-ceiling 4.5 + 1.0 vuelta) ; 12 GAUGE HANGER WIRE 3/A09.33; RFI-SUSP; CEILINGS - Vestibule 100 GB 10'-0": 8 hangers (@48"x48") x (B.O.D.-ceiling 5.375 + 1.0 vuelta) ; 12 GAUGE HANGER WIRE 3/A09.33; RFI-SUSP; CEILINGS - Waiting 104 GB 11'-0": 32 hangers (@48"x48") x (B.O.D.-ceiling 4.375 + 1.0 vuelta) ; 12 GAUGE HANGER WIRE 3/A09.33; RFI-SUSP; CEILINGS - Women's 114 GB 8'-6": 5 hangers (@48"x48") x (B.O.D.-ceiling 4.5 + 1.0 vuelta) ; 12 GAUGE HANGER WIRE 3/A09.33; RFI-SUSP
A65: Ceiling / soffit track (ceiling perimeter) | B65: LF | C65: 267.28 | D65: =Inputs!$B$4 -> 0.15 | E65: =C65*D65 -> 40.092 | F65: =C65+E65 -> 307.372 | G65: piece 10 ft | H65: =ROUNDUP(F65/10,0) -> 31 | I65: CEILINGS - 24HR Vestibule 101 GB 10'-0": perimetro 53.7 LF ceiling track; 7/A09.33; CEILINGS - Men's 113 GB 8'-6": perimetro 36.38 LF ceiling track; 7/A09.33; CEILINGS - Vestibule 100 GB 10'-0": perimetro 46.76 LF ceiling track; 7/A09.33; CEILINGS - Waiting 104 GB 11'-0": perimetro 94.06 LF ceiling track; 7/A09.33; CEILINGS - Women's 114 GB 8'-6": perimetro 36.38 LF ceiling track; 7/A09.33
A66: Framed opening for recessed fixture (GWB ceiling) | B66: LF | C66: 343.6 | D66: =Inputs!$B$4 -> 0.15 | E66: =C66*D66 -> 51.54 | F66: =C66+E66 -> 395.14 | G66: LF | H66: =ROUNDUP(F66,0) -> 396 | I66: CEILINGS - 24 R-14 downlights en GB (vestibulos + restrooms): 24 x 4 lados x 3.5" (E00.01 R-14 3.5" square) ag_mep; 6/A09.33; CEILINGS - Air devices en GB ceilings (slot diffusers vestibulos + 4 restrooms): 58.5: SD TBDI-10 2 x 53.8 ft (M01.01) + restrooms 4 x 8.0 (A04.01 2'x2', 53.3); ends PENDIENTE; 6/A09.33; CEILINGS - Interior GWB fixtures R-11C/CE (4) + R-11A CSR (2): 54.1/58.5: 4 x 2 x 20'-0" (E00.01 modelo; conflicto con 12' -> 53.3 mas material, RFI-R11C) + 2 x 2 x 4'; ends PENDIENTE; 6/A09.33
A67: metal trim - gypsum edge trim | B67: LF | C67: 176 | D67: =Inputs!$B$4 -> 0.15 | E67: =C67*D67 -> 26.4 | F67: =C67+E67 -> 202.4 | G67: piece 10 ft | H67: =ROUNDUP(F67/10,0) -> 21 | I67: CEILINGS - Interior GWB fixtures: GYPSUM EDGE TRIM 6/A09.33 en los lados de los fixtures lineales
A68: access panel 2'x2' (framed opening) | B68: EA | C68: 1 | D68: 0 | E68: =C68*D68 -> 0 | F68: =C68+E68 -> 1 | G68: EA | H68: =ROUNDUP(F68,0) -> 1 | I68: CEILINGS - Access panel 2x2 Vestibule 100: A04.01 key note 4 2' X 2' LOCKING ACCESS PANEL; 6/A09.33 framing
A69: Ceiling / soffit track (soffit) | B69: LF | C69: 92.12 | D69: =Inputs!$B$4 -> 0.15 | E69: =C69*D69 -> 13.818 | F69: =C69+E69 -> 105.938 | G69: piece 10 ft | H69: =ROUNDUP(F69/10,0) -> 11 | I69: SOFFITS - CSR soffit: 4 corridas x 12.0 ft 9/A12.08, 10/A09.33 (58.2); SOFFITS - Door 100A bulkhead: 5/A12.10 2 x 6'-5" (3'-4"+3'-1" 1/A12.10); SOFFITS - Vestibule head door 101: 6/A12.10 track top+bottom 2 x 15'-7 3/4" (impreso 1/A12.10)
A70: FRT blocking (5/8" FRT plywood) | B70: LF | C70: 12 | D70: =Inputs!$B$5 -> 0.06 | E70: =C70*D70 -> 0.72 | F70: =C70+E70 -> 12.72 | G70: piece 8 ft | H70: =ROUNDUP(F70/8,0) -> 2 | I70: SOFFITS - CSR soffit: 5/8" FRT PLYWOOD BLOCKING 9/A12.08: 12.0 LF x 1 (RFI-CSR cobertura)
A71: Header / box beam - coiling grille 6" CFMF (4/A08.21) | B71: LF | C71: 26.67 | D71: =Inputs!$B$4 -> 0.15 | E71: =C71*D71 -> 4.0005 | F71: =C71+E71 -> 30.6705 | G71: piece 10 ft | H71: =ROUNDUP(F71/10,0) -> 4 | I71: SOFFITS - Coiling grille head bulkhead (4/A08.21): 4/A08.21 6" CFMF BOX BEAM HEADER x2 = 2 x 13'-4"
A72: 2-1/2" metal stud | B72: LF | C72: 7.7 | D72: =Inputs!$B$4 -> 0.15 | E72: =C72*D72 -> 1.155 | F72: =C72+E72 -> 8.855 | G72: stick 20 ft | H72: =ROUNDUP(ROUNDUP(F72/5.375,0)/MAX(1,INT(20/5.375)),0) -> 1 | I72: SOFFITS - Coiling grille head bulkhead: 4/A08.21 2 1/2" CFMF @ 16" O.C. entre box beams: 11 pcs x 0.7 ft dibujado (RFI-GRL)
A73: Ceiling / soffit track (soffit) 2-1/2" | B73: LF | C73: 26.67 | D73: =Inputs!$B$4 -> 0.15 | E73: =C73*D73 -> 4.0005 | F73: =C73+E73 -> 30.6705 | G73: piece 10 ft | H73: =ROUNDUP(F73/10,0) -> 4 | I73: SOFFITS - Coiling grille head bulkhead: 4/A08.21 track arriba y abajo de los 2 1/2" (58.2): 2 x 13'-4"
A74: Header / box header 3-5/8" (A12.10) | B74: LF | C74: 41.71 | D74: =Inputs!$B$4 -> 0.15 | E74: =C74*D74 -> 6.2565 | F74: =C74+E74 -> 47.9665 | G74: piece 10 ft | H74: =ROUNDUP(F74/10,0) -> 5 | I74: SOFFITS - Door 100A bulkhead: 5/A12.10 box header 53.6; SOFFITS - Vestibule head door 101: 6/A12.10 BOX HEADER AS NEEDED 2 members x (15.646 + 1'-4" 53.6) (RFI-VH)
A75: FRP panel | B75: SF | C75: 329.9 | D75: =Inputs!$B$5 -> 0.06 | E75: =C75*D75 -> 19.794 | F75: =C75+E75 -> 349.694 | G75: 4x8 sheet | H75: =ROUNDUP(F75/32,0) -> 11 | I75: WET AREAS - Janitor 112 mop sink FRP 4'-0": A05.01 key note 6 FRP FLOOR TO 4'-0", 5/A08.01 dos caras x 2'-0" (ancho DERIVADO vector) x 4.0; WET AREAS - Men's 113 FRP: A-D/A08.01: 36.39 - doors 113 y 112 6.67 = 29.72 x 5.0 (59.10); WET AREAS - Women's 114 FRP 5'-0" over 6" cove base: A,B,C,D/A08.01: perimetro 36.39 - door 114 3.33 = 33.05 LF x 5.0 (59.10; 53.9.1)
A76: cement board (tile backer) | B76: SF | C76: 31.38 | D76: =Inputs!$B$5 -> 0.06 | E76: =C76*D76 -> 1.8828 | F76: =C76+E76 -> 33.2628 | G76: 3x5 sheet | H76: =ROUNDUP(F76/15,0) -> 3 | I76: WET AREAS - Restrooms tile cove base CT-12C: 58.7: LF cove base (33.05+29.72) x 0.5 ft; A/A08.01
A77: PVC trim (FRP) | B77: LF | C77: 70.77 | D77: =Inputs!$B$5 -> 0.06 | E77: =C77*D77 -> 4.2462 | F77: =C77+E77 -> 75.0162 | G77: piece 10 ft | H77: =ROUNDUP(F77/10,0) -> 8 | I77: WET AREAS - FRP trims: 3/A08.01 PVC EDGE TRIM MOLDING top: 33.05+29.72 + mop sink 2x4.0
A78: FRT blocking (2x FRT wood) | B78: LF | C78: 248.94 | D78: =Inputs!$B$5 -> 0.06 | E78: =C78*D78 -> 14.9364 | F78: =C78+E78 -> 263.8764 | G78: piece 8 ft | H78: =ROUNDUP(F78/8,0) -> 33 | I78: BLOCKING - Coiling grille guides 3/A08.21: 3/A08.21 FRT WOOD BLOCKING (TYP): 4 piezas x 10'-0" (58.6); BLOCKING - Millwork MW01-MW21 (nota D A12.03-A12.06 FRTW): nota D/A12.03 (ag_blocking): MW07 13.25+MW08 7.583+MW11 13.5+MW12 16.8+MW13 7.21+MW21 10.0+MW05 3.5+MW06A 2x3.458 (A06.01 2 tags)+MW18 6.67+MW01 3.125 = 88.6 base + 2a fila en uppers/standards 40.0 (53.3, RFI-MW); 7/A12.04; BLOCKING - Roof ladder Janitor 112: 3/A09.30 2X FRT WOOD BLOCKING BEHIND GWB: 3 brackets x 1.333 (RFI-LAD); BLOCKING - Toilet accessories Men's 113: nota E/A08.01: igual sin TA-9; BLOCKING - Toilet accessories Women's 114 (nota E/A08.01): nota E/A08.01 FRT BLOCKING: TA-3 3.5+TA-5 1.5+TA-4 3.0+TA-10 1.0+TA-9 1.0+TA-17 1.33+TA-7 2x2.0+TA-8 0.67+TA-16 2x2.83 + lav 2.0 (largos minimos, RFI-TA); BLOCKING - Vestibule glass termination 8/A12.10: 8/A12.10 FRT blocking: 2 x 10'-0"; BLOCKING - WH-1 platform Janitor 112
A79: 3/4" FRT plywood blocking (strips) | B79: LF | C79: 96.5 | D79: =Inputs!$B$5 -> 0.06 | E79: =C79*D79 -> 5.79 | F79: =C79+E79 -> 102.29 | G79: piece 8 ft | H79: =ROUNDUP(F79/8,0) -> 13 | I79: BLOCKING - Office front jambs (12) 10/A12.01: 10/A12.01 3/4" FRT PLYWOOD BLOCKING en cada jamb del office front: 12 jambs x HOLD 8'-0 1/2" (7/A11.01)
A80: 3/4" FRT plywood backboard | B80: SF | C80: 243.9 | D80: =Inputs!$B$5 -> 0.06 | E80: =C80*D80 -> 14.634 | F80: =C80+E80 -> 258.534 | G80: 4x8 sheet | H80: =ROUNDUP(F80/32,0) -> 9 | I80: BLOCKING - Electrical 120 / NER 121 plywood backboard (key note 6): A02.01 key note 6; 4/A11.03, 3/A11.03, 2/A11.03, 5/A11.03: 6" AFF a 8'-0" (7'-6") x (9.583+5.833+9.583+7.5)
A81: metal stud blocking 362CR22 | B81: LF | C81: 86.73 | D81: =Inputs!$B$4 -> 0.15 | E81: =C81*D81 -> 13.0095 | F81: =C81+E81 -> 99.7395 | G81: stick 20 ft | H81: =ROUNDUP(ROUNDUP(F81/5.375,0)/MAX(1,INT(20/5.375)),0) -> 7 | I81: BLOCKING - Artwork 6 offices (A11.01-A11.04): 1/A11.01 y elevaciones A11.01-A11.04 artwork 6 x 4'-0"; nota C/A02.01; 4/S5.20 362CR22 (58.6) RFI-BLK; BLOCKING - Lockers CW-16 Break 118 (key note 5): key note 5 A02.01 PROVIDE BLOCKING FOR LOCKERS: 2 runs x 4'-10 3/8" (vector A11.02); 4/S5.20 362CR22; BLOCKING - Wall stops 9 doors (nota D/A00.30): nota D/A00.30 PROVIDE BLOCKING AT EACH WALL STOP: 9 doors (HW groups 04A,08,10,11,11B,12,16) x 2'-0"; sin material -> 362CR22 4/S5.20 (58.6) RFI-BLK; BLOCKING - Wall-mounted equipment A11.02 (cork boards, combo board, coat hooks, phones, sanitizers, clock, FE, security monitor): nota C/A02.01; 5/A11.02, 8/A11.02 etc.: 25.7 LF verificados + 9.5 A11.01 (adv_completitud B8); 4/S5.20 362CR22 RFI-BLK
A82: Header track - recessed accessories (58.4) | B82: LF | C82: 12.2 | D82: =Inputs!$B$4 -> 0.15 | E82: =C82*D82 -> 1.83 | F82: =C82+E82 -> 14.03 | G82: piece 10 ft | H82: =ROUNDUP(F82/10,0) -> 2 | I82: FRAMED OPENINGS - TA-13 hand dryer recess kit (2, chase C1): 58.4: ancho 1.43 ft (A/A08.01) > 14 3/8": header + sill (1.43+1.333) x 2 x 2 restrooms; FRAMED OPENINGS - TA-2 recessed paper towel (Break 118, Wellness 115): 58.4: sin ancho impreso -> 2'-0" x (header+sill) x 2 (RFI-TA2); 8/A11.02, 15/A11.02
A83: Sill track - recessed accessories (58.4) | B83: LF | C83: 12.2 | D83: =Inputs!$B$4 -> 0.15 | E83: =C83*D83 -> 1.83 | F83: =C83+E83 -> 14.03 | G83: piece 10 ft | H83: =ROUNDUP(F83/10,0) -> 2 | I83: FRAMED OPENINGS - TA-13 hand dryer recess kit (2, chase C1): 58.4: ancho 1.43 ft (A/A08.01) > 14 3/8": header + sill (1.43+1.333) x 2 x 2 restrooms; FRAMED OPENINGS - TA-2 recessed paper towel (Break 118, Wellness 115): 58.4: sin ancho impreso -> 2'-0" x (header+sill) x 2 (RFI-TA2); 8/A11.02, 15/A11.02
A84: 7/8" hat channel (furring channel) @16" O.C. | B84: LF | C84: 746 | D84: =Inputs!$B$4 -> 0.15 | E84: =C84*D84 -> 111.9 | F84: =C84+E84 -> 857.9 | G84: piece 16 ft | H84: =ROUNDUP(F84/16,0) -> 54 | I84: EXTERIOR - EPS-5 formed metal panel substrate (4 facades): 3/A09.31, 1/A09.31, 7/A09.26 EPS-5 ON 7/8" HAT CHANNEL @16": ~994 SF EPS-5 (A09.01/A09.02 vector, adv_completitud) / 1.333 (RFI-HAT alcance)
A85: 3/4" FRT plywood (jambs) | B85: SF | C85: 22.8 | D85: =Inputs!$B$5 -> 0.06 | E85: =C85*D85 -> 1.368 | F85: =C85+E85 -> 24.168 | G85: 4x8 sheet | H85: =ROUNDUP(F85/32,0) -> 1 | I85: EXTERIOR - Storefront piers jambs: 1/A09.25, 2/A09.25 3/4" FRT PLYWOOD: 4 jambs x 0.67 x 8.5
A86: Batt insulation (sound batt above ceiling) | B86: SF | C86: 152.6 | D86: =Inputs!$B$5 -> 0.06 | E86: =C86*D86 -> 9.156 | F86: =C86+E86 -> 161.756 | G86: SF | H86: =ROUNDUP(F86,0) -> 162 | I86: CEILINGS - Restrooms 113/114 sound batt above ceiling: A04.01 key note 11 INSTALL SOUND BATT INSULATION ABOVE CEILING: 76.3 + 76.3; 1/A08.01
A87: purlin 1x1x1 16 GA (top track to deck parallel to flute, 10/A09.33) | B87: LF | C87: 167.95 | D87: =Inputs!$B$4 -> 0.15 | E87: =C87*D87 -> 25.1925 | F87: =C87+E87 -> 193.1425 | G87: piece 10 ft | H87: =ROUNDUP(F87/10,0) -> 20 | I87: 59.1: sum LF top track de muros E-W a deck [1, 3, 4, 5, 7, 9, 11, 12, 17, 19, 20, 21, 26, 27, 28, 29, 30, 36, 37, 38, 39, 40, 41, 46] x (1'-6" pieza / 2'-0" PAF 4/A12.01 = 0.75); doble fila = una pieza; flute E-W S2.20 (VIF -> RFI-PUR)
A88: Stud blocking 362CR22 at edge of gypboard (4/S5.20) | B88: LF | C88: 669.84 | D88: =Inputs!$B$4 -> 0.15 | E88: =C88*D88 -> 100.476 | F88: =C88+E88 -> 770.316 | G88: stick 20 ft | H88: =ROUNDUP(ROUNDUP(F88/1.333,0)/MAX(1,INT(20/1.333)),0) -> 39 | I88: 59.14 cifra (b) toda cara con board > 12 ft (hoja 4x12): 669.84 LF; cifra (a) exteriores + doble capa = 405.52 LF (RFI-SB); 4/S5.20 PROVIDE BLOCKING AT THE EDGE OF GYPBOARD
A89: Level 5 finish (wallcovering WC-20 / WC-22 prep) | B89: SF | C89: 304.9 | D89: =Inputs!$B$5 -> 0.06 | E89: =C89*D89 -> 18.294 | F89: =C89+E89 -> 323.194 | G89: SF | H89: =ROUNDUP(F89,0) -> 324 | I89: A05.01 key note 9 (WC-20, 24HR Vestibule 101 F wall: 18.07x10.0-2.25x2.69=174.6) + key note 10 (WC-22 monitor furring 11.333x11.5=130.3); A00.40 LEVEL 5; 12/A12.01 (RFI-L5 extension)

Sheet Pending Items
A1: RFI | B1: Question / condition | C1: Delta of each alternative
A2: RFI-56.2 | B2: Exterior studs: S1.11 LGS note 5 pide 600S162-54 @16" y @12" a 6 ft de esquinas; 7/S5.20 METAL STUD PROPERTIES da 600S137-33 @16". Se carga 600S162-54 (53.3/56.2). | C2: 600S137-33: mismo LF menos ~9 studs de zona de esquina (~135 LF) y calibre 33 mil en ~4,244 LF (3,299 muro + 944 parapet ya es -54 por 11/S5.10)
A3: RFI-SLIP | B3: CONTINUOUS SLIP TRACK (1,3,4/A12.01) sin designacion en ningun schedule. Se carga track del tamano del stud (362T/600T/162T-33). | C3: Alterno deep-leg slip track 2" leg: mismo LF (~617 LF) a mayor precio por LF
A4: RFI-G | B4: Tipos G/G1 y bulkheads de oficina: stud 1-5/8" sin designacion (A12.01, S5.20). Se usa 162S125-33. | C4: Ninguno en LF; cambia precio si es 25 ga o 20 ga
A5: RFI-SUSP | B5: GWB ceilings (A04.01): ningun detalle especifica suspension. Se carga ASTM C754: carrying 1-1/2" @48", furring 7/8" @16", hanger 12 ga @48"x48", track perimetral. | C5: Si el arquitecto pide stud framing 3 5/8" @16" (6/A09.33): ~703 LF de 3-5/8" en vez de furring channel
A6: RFI-PUR | B6: Purlin 1X1X1 16GA (10/A09.33 ALTERNATE CEILING DETAIL, VIF FLUTE DIRECTION). Flute E-W en ambas zonas (S2.20): tracks E-W a deck llevan purlin (59.1). | C6: +196.7 LF purlin si se confirma; 0 si el flute resulta perpendicular
A7: RFI-SB | B7: 4/S5.20 PROVIDE BLOCKING AT THE EDGE OF GYPBOARD sin ubicacion (NTS). Cifra (b) cargada = toda cara con board > 12 ft. | C7: Cifra (a) exteriores + doble capa = 405.52 LF vs (b) 669.84 LF cargada (59.14)
A8: RFI-ELEV | B8: A09.01 'SOUTH ELEVATION' dibuja la fachada norte y A09.02 'NORTH ELEVATION' la sur (orden de grids + contenido). E/W correctos. | C8: Sin delta en cantidades; otros trades leen las mismas hojas
A9: RFI-CAN-SH | B9: Soffit/fascia del canopy: 5/8" EXT. GRADE FRT PLYWOOD (3,7/A09.26; 15,16/A09.27) vs 5/8" EXTERIOR SHEATHING (4,5/A09.33). Se carga FRT plywood. | C9: Si es exterior gyp sheathing: ~2,352 SF pasan de FRT plywood a exterior gyp sheathing
A10: RFI-PAR | B10: Parapet roof side: 5/8" EXTERIOR GYPSUM SHEATHING (secciones A09.21-23) vs 5/8" DENS DECK (4/A09.26, material del roofer). Se carga exterior gyp sheathing. | C10: -986 SF si es del roofer
A11: RFI-PIER | B11: Canopy columns 5/A09.25: altura del stud a B/CANOPY 10'-6" o a T/STEEL 11'-9". | C11: +40 LF 3-5/8" stud y +30 SF FRT plywood si va a 11'-9"
A12: RFI-COL | B12: C1 column furring en vestibulos (4 cajas): se cargan todas las caras a deck. | C12: Solo caras expuestas a 10'-6": -~80 SF board
... A44: RFI-ENDS | B44: Ancho de los ends de los framed openings de fixtures lineales (cutsheet, 4/A09.33). | C44: +~4" x 54 ends

Sheet PARA REVISAR EN LA MANANA
A1: # | B1: Punto | C1: Hoja + detalle | D1: Imagen
A2: 1 | B2: RFI-56.2: Exterior studs: S1.11 LGS note 5 pide 600S162-54 @16" y @12" a 6 ft de esquinas; 7/S5.20 METAL STUD PROPERTIES da 600S137-33 @16". Se carga 600S162-54 (53.3/56.2). | delta: 600S137-33: mismo LF menos ~9 studs de zona de esquina (~135 LF) y calibre 33 mil en ~4,244 LF (3,299 muro + 944 parapet ya es -54 por 11/S5.10) | C2: 7/S5.20 | D2: Planos marcados/
A3: 2 | B3: RFI-SLIP: CONTINUOUS SLIP TRACK (1,3,4/A12.01) sin designacion en ningun schedule. Se carga track del tamano del stud (362T/600T/162T-33). | delta: Alterno deep-leg slip track 2" leg: mismo LF (~617 LF) a mayor precio por LF | C3: 4/A12.01 | D3: Planos marcados/
A4: 3 | B4: RFI-G: Tipos G/G1 y bulkheads de oficina: stud 1-5/8" sin designacion (A12.01, S5.20). Se usa 162S125-33. | delta: Ninguno en LF; cambia precio si es 25 ga o 20 ga | C4: A02.01 | D4: Planos marcados/
A5: 4 | B5: RFI-SUSP: GWB ceilings (A04.01): ningun detalle especifica suspension. Se carga ASTM C754: carrying 1-1/2" @48", furring 7/8" @16", hanger 12 ga @48"x48", track perimetral. | delta: Si el arquitecto pide stud framing 3 5/8" @16" (6/A09.33): ~703 LF de 3-5/8" en vez de furring channel | C5: A02.01 | D5: Planos marcados/
A6: 5 | B6: RFI-PUR: Purlin 1X1X1 16GA (10/A09.33 ALTERNATE CEILING DETAIL, VIF FLUTE DIRECTION). Flute E-W en ambas zonas (S2.20): tracks E-W a deck llevan purlin (59.1). | delta: +196.7 LF purlin si se confirma; 0 si el flute resulta perpendicular | C6: 10/A09.33 | D6: Planos marcados/
A7: 6 | B7: RFI-SB: 4/S5.20 PROVIDE BLOCKING AT THE EDGE OF GYPBOARD sin ubicacion (NTS). Cifra (b) cargada = toda cara con board > 12 ft. | delta: Cifra (a) exteriores + doble capa = 405.52 LF vs (b) 669.84 LF cargada (59.14) | C7: 4/S5.20 | D7: Planos marcados/
A8: 7 | B8: RFI-ELEV: A09.01 'SOUTH ELEVATION' dibuja la fachada norte y A09.02 'NORTH ELEVATION' la sur (orden de grids + contenido). E/W correctos. | delta: Sin delta en cantidades; otros trades leen las mismas hojas | C8: A02.01 | D8: Planos marcados/
A9: 8 | B9: RFI-CAN-SH: Soffit/fascia del canopy: 5/8" EXT. GRADE FRT PLYWOOD (3,7/A09.26; 15,16/A09.27) vs 5/8" EXTERIOR SHEATHING (4,5/A09.33). Se carga FRT plywood. | delta: Si es exterior gyp sheathing: ~2,352 SF pasan de FRT plywood a exterior gyp sheathing | C9: 7/A09.26 | D9: Planos marcados/
A10: 9 | B10: RFI-PAR: Parapet roof side: 5/8" EXTERIOR GYPSUM SHEATHING (secciones A09.21-23) vs 5/8" DENS DECK (4/A09.26, material del roofer). Se carga exterior gyp sheathing. | delta: -986 SF si es del roofer | C10: 4/A09.26 | D10: Planos marcados/
A11: 10 | B11: RFI-PIER: Canopy columns 5/A09.25: altura del stud a B/CANOPY 10'-6" o a T/STEEL 11'-9". | delta: +40 LF 3-5/8" stud y +30 SF FRT plywood si va a 11'-9" | C11: 5/A09.25: | D11: Planos marcados/
A12: 11 | B12: RFI-COL: C1 column furring en vestibulos (4 cajas): se cargan todas las caras a deck. | delta: Solo caras expuestas a 10'-6": -~80 SF board | C12: A02.01 | D12: Planos marcados/
A13: 12 | B13: RFI-CSR: CSR soffit 9/A12.08 = 10/A09.33: studs hasta deck o colgado; cobertura del 5/8" FRT plywood blocking. | delta: Studs a 9'-0" en vez de deck: -~127 LF 3-5/8" | C13: 9/A12.08 | D13: Planos marcados/
... A54: 53 | B54: PROPUESTAS 53.3 NO APLICADAS por no ser medida sino alcance: board sobre ceiling en head de door 101 (RFI-VH +168 SF); blocking continuo 2x6 en toilet accessories (RFI-TA +40 LF). | C54: A02.01 | D54: Planos marcados/BARRIDO_*.png

Sheet Alcances
A1: ALC | B1: Alcance | C1: Estado | D1: Nota (cantidad, NO APLICA + hoja, o RFI)
A2: ALC-01 | B2: ALC-01 | C2: CUANTIFICADO | D2: Partition Takeoff walls #1-#49; 3-5/8", 6", 1-5/8" studs + tracks; A12.01, 7/S5.20
A3: ALC-02 | B3: ALC-02 | C3: CUANTIFICADO | D3: EXT #50-#59: 600S162-54, C/A09.21, S1.11
A4: ALC-03 | B4: ALC-03 | C4: CUANTIFICADO | D4: 6" parapet stud 600S162-54 11/S5.10, 59.4
A5: ALC-04 | B5: ALC-04 | C5: CUANTIFICADO | D5: Bottom / top / deflection tracks por renglon (7/S5.20, 10/S5.10, A12.01)
A6: ALC-05 | B6: ALC-05 | C6: CUANTIFICADO | D6: Header track, sill track, box beams (9/S5.20, 9/A12.01, 6/A08.11, 4/A08.21)
A7: ALC-06 | B7: ALC-06 | C7: CUANTIFICADO | D7: bracing 1-1/2" C.R. channel F/1/S5.20 (53.4)
A8: ALC-07 | B8: ALC-07 | C8: CUANTIFICADO | D8: 5/8" gypsum board por cara A12.01
A9: ALC-08 | B9: ALC-08 | C9: CUANTIFICADO | D9: 5/8" moisture resistant: cara del chase (nota F/A08.01, 59.9)
A10: ALC-09 | B10: ALC-09 | C10: CUANTIFICADO | D10: glass mat base y banda (5/A09.26, 7/A09.26); exterior gyp sheathing parapet (C/A09.21)
A11: ALC-10 | B11: ALC-10 | C11: CUANTIFICADO | D11: FRT plywood nailbase, canopy, backboards, F wall (4/A09.26, 7/A09.26, 12/A12.01)
A12: ALC-11 | B12: ALC-11 | C12: CUANTIFICADO | D12: GWB ceilings A04.01: waiting, vestibules, restrooms
... A25: ALC-24 | B25: ALC-24 | C25: CUANTIFICADO | D25: Level 5 finish A05.01 key notes 9 y 10, A00.40 (RFI-L5)
